Workbook

Sheet 01 DATOS PERSONALES
A1: ORGANIZACION_POLITICA | B1: DNI_CANDIDATO | C1: CANDIDATO | D1: DOCUMENTO_IDENTIDAD | E1: APELLIDO_PATERNO | F1: APELLIDO_MATERNO | G1: NOMBRES | H1: SEXO | I1: FECHA_NACIMIENTO | J1: PAIS_NACIMIENTO | K1: DEPARTAMENTO_NACIMIENTO | L1: PROVINCIA_NACIMIENTO | M1: DISTRITO_NACIMIENTO | N1: PRIMER_CARGO_ELECCION | O1: SEGUNDO_CARGO_ELECION | P1: DISTRITO_ELEC | Q1: INFORMACION_COMPLEMENTARIA | R1: URL_FOTO | S1: TXRUTAVIRTUAL | T1: TXNOMBREDOCUMENTO | U1: EDAD | V1: RANGO_EDAD | W1: PAÍS_LIMPIO | X1: SEXO_LIMPIO | Y1: DEP_NAC_LIMPIO | Z1: DISTRITO_ELEC_LIMPIO
A2: AHORA NACION - AN | B2: 29569533 | C2: ARMINTA VALENCIA, MARLENY BIBIANA | D2: 29569533 | E2: ARMINTA | F2: VALENCIA | G2: MARLENY BIBIANA | H2: FEMENINO | I2: 17/12/1967 | J2: PERÚ | K2: AREQUIPA | L2: AREQUIPA | M2: AREQUIPA | N2: DIPUTADO | P2: AREQUIPA | R2: https://mpesije.jne.gob.pe/apidocs/1d29caa5-9573-43f8-b661-c8bcdcb459d0.jpeg | S2: https://mpesije.jne.gob.pe/apidocs/257db15e-d676-4f48-a881-33b94bc75df8.pdf | T2: =CONCATENATE(A20," - ",B20,".pdf") -> FUERZA POPULAR - 07750373.pdf | U2: =IF(I2="","",DATEDIF(DATE(VALUE(RIGHT(I2,4)),VALUE(MID(I2,4,2)),VALUE(LEFT(I2,2))),TODAY(),"Y")) -> 58 | V2: =IF(U2="","",IF(U2<30,"18-29",IF(U2<40,"30-39",IF(U2<50,"40-49",IF(U2<60,"50-59","60+"))))) -> 50-59 | W2: =IF(UPPER(TRIM(J2))="PERU","PERÚ",UPPER(TRIM(J2))) -> PERÚ | X2: =UPPER(TRIM(H2)) -> FEMENINO | Y2: =UPPER(TRIM(K2)) -> AREQUIPA | Z2: =UPPER(TRIM(P2)) -> AREQUIPA
A3: AHORA NACION - AN | B3: 41618961 | C3: BUITRON MARTINEZ, FRESHMAN | D3: 41618961 | E3: BUITRON | F3: MARTINEZ | G3: FRESHMAN | H3: MASCULINO | I3: 29/09/1982 | J3: PERÚ | K3: AYACUCHO | L3: VILCAS HUAMAN | M3: VILCAS HUAMAN | N3: DIPUTADO | P3: AYACUCHO | R3: https://mpesije.jne.gob.pe/apidocs/54087930-f4c1-4c30-a5ff-c168e7cec980.jpg | S3: https://mpesije.jne.gob.pe/apidocs/a833abe4-70a4-4744-8ca4-794c861b5f05.pdf | T3: =CONCATENATE(A40," - ",B40,".pdf") -> FUERZA POPULAR - 08571708.pdf | U3: =IF(I3="","",DATEDIF(DATE(VALUE(RIGHT(I3,4)),VALUE(MID(I3,4,2)),VALUE(LEFT(I3,2))),TODAY(),"Y")) -> 43 | V3: =IF(U3="","",IF(U3<30,"18-29",IF(U3<40,"30-39",IF(U3<50,"40-49",IF(U3<60,"50-59","60+"))))) -> 40-49 | W3: =IF(UPPER(TRIM(J3))="PERU","PERÚ",UPPER(TRIM(J3))) -> PERÚ | X3: =UPPER(TRIM(H3)) -> MASCULINO | Y3: =UPPER(TRIM(K3)) -> AYACUCHO | Z3: =UPPER(TRIM(P3)) -> AYACUCHO
A4: AHORA NACION - AN | B4: 43592504 | C4: COLCHADO HUAMANI, HARVEY JULIO | D4: 43592504 | E4: COLCHADO | F4: HUAMANI | G4: HARVEY JULIO | H4: MASCULINO | I4: 11/04/1974 | J4: PERÚ | K4: LIMA | L4: LIMA | M4: LIMA | N4: DIPUTADO | P4: LIMA METROPOLITANA | R4: https://mpesije.jne.gob.pe/apidocs/aaf42d15-51c4-42da-970a-27fc9722d258.jpg | S4: https://mpesije.jne.gob.pe/apidocs/c385533c-6800-49cc-a5dd-bc890f9e6f0e.pdf | T4: =CONCATENATE(A72," - ",B72,".pdf") -> PARTIDO CIVICO OBRAS - 17930730.pdf | U4: =IF(I4="","",DATEDIF(DATE(VALUE(RIGHT(I4,4)),VALUE(MID(I4,4,2)),VALUE(LEFT(I4,2))),TODAY(),"Y")) -> 52 | V4: =IF(U4="","",IF(U4<30,"18-29",IF(U4<40,"30-39",IF(U4<50,"40-49",IF(U4<60,"50-59","60+"))))) -> 50-59 | W4: =IF(UPPER(TRIM(J4))="PERU","PERÚ",UPPER(TRIM(J4))) -> PERÚ | X4: =UPPER(TRIM(H4)) -> MASCULINO | Y4: =UPPER(TRIM(K4)) -> LIMA | Z4: =UPPER(TRIM(P4)) -> LIMA METROPOLITANA
A5: AHORA NACION - AN | B5: 43572794 | C5: HOLGUIN LOAIZA, CESAR AUGUSTO | D5: 43572794 | E5: HOLGUIN | F5: LOAIZA | G5: CESAR AUGUSTO | H5: MASCULINO | I5: 27/09/1984 | J5: PERÚ | K5: CUSCO | L5: PARURO | M5: CCAPI | N5: DIPUTADO | P5: CUSCO | R5: https://mpesije.jne.gob.pe/apidocs/20080e01-d77e-4a41-8a34-5e3a55ac4b10.jpg | S5: https://mpesije.jne.gob.pe/apidocs/27f3afef-9c95-4937-93fc-f3b66e2fbe22.pdf | T5: =CONCATENATE(A110," - ",B110,".pdf") -> - .pdf | U5: =IF(I5="","",DATEDIF(DATE(VALUE(RIGHT(I5,4)),VALUE(MID(I5,4,2)),VALUE(LEFT(I5,2))),TODAY(),"Y")) -> 41 | V5: =IF(U5="","",IF(U5<30,"18-29",IF(U5<40,"30-39",IF(U5<50,"40-49",IF(U5<60,"50-59","60+"))))) -> 40-49 | W5: =IF(UPPER(TRIM(J5))="PERU","PERÚ",UPPER(TRIM(J5))) -> PERÚ | X5: =UPPER(TRIM(H5)) -> MASCULINO | Y5: =UPPER(TRIM(K5)) -> CUSCO | Z5: =UPPER(TRIM(P5)) -> CUSCO
A6: AHORA NACION - AN | B6: 45218393 | C6: HUILCA FLORES, INDIRA ISABEL | D6: 45218393 | E6: HUILCA | F6: FLORES | G6: INDIRA ISABEL | H6: FEMENINO | I6: 11/08/1988 | J6: PERÚ | K6: LIMA | L6: LIMA | M6: LA VICTORIA | N6: DIPUTADO | P6: LIMA METROPOLITANA | R6: https://mpesije.jne.gob.pe/apidocs/00a34212-f067-4014-be90-c9a48610b7d1.jpg | S6: https://mpesije.jne.gob.pe/apidocs/df68e47e-04af-4dfe-b08d-ce5fa2659ae8.pdf | T6: =CONCATENATE(A113," - ",B113,".pdf") -> - .pdf | U6: =IF(I6="","",DATEDIF(DATE(VALUE(RIGHT(I6,4)),VALUE(MID(I6,4,2)),VALUE(LEFT(I6,2))),TODAY(),"Y")) -> 37 | V6: =IF(U6="","",IF(U6<30,"18-29",IF(U6<40,"30-39",IF(U6<50,"40-49",IF(U6<60,"50-59","60+"))))) -> 30-39 | W6: =IF(UPPER(TRIM(J6))="PERU","PERÚ",UPPER(TRIM(J6))) -> PERÚ | X6: =UPPER(TRIM(H6)) -> FEMENINO | Y6: =UPPER(TRIM(K6)) -> LIMA | Z6: =UPPER(TRIM(P6)) -> LIMA METROPOLITANA
A7: AHORA NACION - AN | B7: 70665764 | C7: MANRIQUE OLIVERA, BERNARDINO JAIR | D7: 70665764 | E7: MANRIQUE | F7: OLIVERA | G7: BERNARDINO JAIR | H7: MASCULINO | I7: 08/04/1997 | J7: PERÚ | K7: ANCASH | L7: SANTA | M7: CHIMBOTE | N7: DIPUTADO | P7: LIMA METROPOLITANA | R7: https://mpesije.jne.gob.pe/apidocs/7fadb198-1995-459d-b2bb-8111575467a4.jpg | S7: https://mpesije.jne.gob.pe/apidocs/503df6ae-606a-48e9-af8b-ec5e23e520eb.pdf | T7: =CONCATENATE(A146," - ",B146,".pdf") -> - .pdf | U7: =IF(I7="","",DATEDIF(DATE(VALUE(RIGHT(I7,4)),VALUE(MID(I7,4,2)),VALUE(LEFT(I7,2))),TODAY(),"Y")) -> 29 | V7: =IF(U7="","",IF(U7<30,"18-29",IF(U7<40,"30-39",IF(U7<50,"40-49",IF(U7<60,"50-59","60+"))))) -> 18-29 | W7: =IF(UPPER(TRIM(J7))="PERU","PERÚ",UPPER(TRIM(J7))) -> PERÚ | X7: =UPPER(TRIM(H7)) -> MASCULINO | Y7: =UPPER(TRIM(K7)) -> ANCASH | Z7: =UPPER(TRIM(P7)) -> LIMA METROPOLITANA
A8: AHORA NACION - AN | B8: 41840094 | C8: MARCELO SALAZAR, JOSE MIGUEL | D8: 41840094 | E8: MARCELO | F8: SALAZAR | G8: JOSE MIGUEL | H8: MASCULINO | I8: 02/02/1982 | J8: PERÚ | K8: LIMA | L8: LIMA | M8: SAN JUAN DE LURIGANCHO | N8: DIPUTADO | P8: ANCASH | R8: https://mpesije.jne.gob.pe/apidocs/51e57b53-4a9b-411f-b2ba-0b25bfb8aa68.jpg | S8: https://mpesije.jne.gob.pe/apidocs/b40f8d35-dab7-485d-a6af-2434b715bebe.pdf | T8: =CONCATENATE(A149," - ",B149,".pdf") -> - .pdf | U8: =IF(I8="","",DATEDIF(DATE(VALUE(RIGHT(I8,4)),VALUE(MID(I8,4,2)),VALUE(LEFT(I8,2))),TODAY(),"Y")) -> 44 | V8: =IF(U8="","",IF(U8<30,"18-29",IF(U8<40,"30-39",IF(U8<50,"40-49",IF(U8<60,"50-59","60+"))))) -> 40-49 | W8: =IF(UPPER(TRIM(J8))="PERU","PERÚ",UPPER(TRIM(J8))) -> PERÚ | X8: =UPPER(TRIM(H8)) -> MASCULINO | Y8: =UPPER(TRIM(K8)) -> LIMA | Z8: =UPPER(TRIM(P8)) -> ANCASH
A9: AHORA NACION - AN | B9: 42839004 | C9: MUEDAS BALBIESE, CESAR AUGUSTO | D9: 42839004 | E9: MUEDAS | F9: BALBIESE | G9: CESAR AUGUSTO | H9: MASCULINO | I9: 09/08/1976 | J9: PERÚ | K9: JUNIN | L9: CHUPACA | M9: CHONGOS BAJO | N9: DIPUTADO | P9: JUNIN | R9: https://mpesije.jne.gob.pe/apidocs/c0fc0177-68d3-47cf-a9f4-7a0b0edf6c9b.jpg | S9: https://mpesije.jne.gob.pe/apidocs/d9c37dcd-51fe-4c25-8a82-77241e029029.pdf | T9: =CONCATENATE(A163," - ",B163,".pdf") -> - .pdf | U9: =IF(I9="","",DATEDIF(DATE(VALUE(RIGHT(I9,4)),VALUE(MID(I9,4,2)),VALUE(LEFT(I9,2))),TODAY(),"Y")) -> 49 | V9: =IF(U9="","",IF(U9<30,"18-29",IF(U9<40,"30-39",IF(U9<50,"40-49",IF(U9<60,"50-59","60+"))))) -> 40-49 | W9: =IF(UPPER(TRIM(J9))="PERU","PERÚ",UPPER(TRIM(J9))) -> PERÚ | X9: =UPPER(TRIM(H9)) -> MASCULINO | Y9: =UPPER(TRIM(K9)) -> JUNIN | Z9: =UPPER(TRIM(P9)) -> JUNIN
A10: AHORA NACION - AN | B10: 46307918 | C10: SONCO VILLANUEVA, HELARD BLADIMIR | D10: 46307918 | E10: SONCO | F10: VILLANUEVA | G10: HELARD BLADIMIR | H10: MASCULINO | I10: 30/08/1989 | J10: PERÚ | K10: PUNO | L10: SANDIA | M10: LIMBANI | N10: DIPUTADO | P10: PUNO | R10: https://mpesije.jne.gob.pe/apidocs/51e0f0d8-3b5a-4ca2-b969-bc892642c00e.jpg | S10: https://mpesije.jne.gob.pe/apidocs/40974f5b-37d2-427d-b075-de3512eabb23.pdf | T10: =CONCATENATE(A215," - ",B215,".pdf") -> - .pdf | U10: =IF(I10="","",DATEDIF(DATE(VALUE(RIGHT(I10,4)),VALUE(MID(I10,4,2)),VALUE(LEFT(I10,2))),TODAY(),"Y")) -> 36 | V10: =IF(U10="","",IF(U10<30,"18-29",IF(U10<40,"30-39",IF(U10<50,"40-49",IF(U10<60,"50-59","60+"))))) -> 30-39 | W10: =IF(UPPER(TRIM(J10))="PERU","PERÚ",UPPER(TRIM(J10))) -> PERÚ | X10: =UPPER(TRIM(H10)) -> MASCULINO | Y10: =UPPER(TRIM(K10)) -> PUNO | Z10: =UPPER(TRIM(P10)) -> PUNO
A11: FUERZA POPULAR | B11: 09391698 | C11: ABENSUR PINASCO, JAIME AMERICO | D11: 09391698 | E11: ABENSUR | F11: PINASCO | G11: JAIME AMERICO | H11: MASCULINO | I11: 13/04/1971 | J11: PERÚ | K11: UCAYALI | L11: CORONEL PORTILLO | M11: CALLERIA | N11: DIPUTADO | P11: UCAYALI | R11: https://mpesije.jne.gob.pe/apidocs/51fc230d-44ff-4a36-81fd-cdc866d39ffb.jpg | S11: https://mpesije.jne.gob.pe/apidocs/0ffac448-7043-418f-947f-bb410ac077ca.pdf | T11: =CONCATENATE(A1485," - ",B1485,".pdf") -> - .pdf | U11: =IF(I11="","",DATEDIF(DATE(VALUE(RIGHT(I11,4)),VALUE(MID(I11,4,2)),VALUE(LEFT(I11,2))),TODAY(),"Y")) -> 55 | V11: =IF(U11="","",IF(U11<30,"18-29",IF(U11<40,"30-39",IF(U11<50,"40-49",IF(U11<60,"50-59","60+"))))) -> 50-59 | W11: =IF(UPPER(TRIM(J11))="PERU","PERÚ",UPPER(TRIM(J11))) -> PERÚ | X11: =UPPER(TRIM(H11)) -> MASCULINO | Y11: =UPPER(TRIM(K11)) -> UCAYALI | Z11: =UPPER(TRIM(P11)) -> UCAYALI
A12: FUERZA POPULAR | B12: 45382589 | C12: ALEGRIA GARCIA, LUIS ARTURO | D12: 45382589 | E12: ALEGRIA | F12: GARCIA | G12: LUIS ARTURO | H12: MASCULINO | I12: 03/08/1988 | J12: PERÚ | K12: LIMA | L12: LIMA | M12: LIMA | N12: DIPUTADO | P12: SAN MARTIN | R12: https://mpesije.jne.gob.pe/apidocs/0210df51-6f47-4b87-816a-bd7246ac72b9.jpg | S12: https://mpesije.jne.gob.pe/apidocs/450b6742-ef38-45d4-ab3e-56e72e5e2525.pdf | T12: =CONCATENATE(A1494," - ",B1494,".pdf") -> - .pdf | U12: =IF(I12="","",DATEDIF(DATE(VALUE(RIGHT(I12,4)),VALUE(MID(I12,4,2)),VALUE(LEFT(I12,2))),TODAY(),"Y")) -> 37 | V12: =IF(U12="","",IF(U12<30,"18-29",IF(U12<40,"30-39",IF(U12<50,"40-49",IF(U12<60,"50-59","60+"))))) -> 30-39 | W12: =IF(UPPER(TRIM(J12))="PERU","PERÚ",UPPER(TRIM(J12))) -> PERÚ | X12: =UPPER(TRIM(H12)) -> MASCULINO | Y12: =UPPER(TRIM(K12)) -> LIMA | Z12: =UPPER(TRIM(P12)) -> SAN MARTIN
A13: FUERZA POPULAR | B13: 15984771 | C13: ANDRADE SALGUERO DE ALVAREZ, GLADYS GRISELDA | D13: 15984771 | E13: ANDRADE | F13: SALGUERO DE ALVAREZ | G13: GLADYS GRISELDA | H13: FEMENINO | I13: 14/06/1963 | J13: PERÚ | K13: LIMA | L13: HUARAL | M13: CHANCAY | N13: DIPUTADO | P13: LIMA PROVINCIAS | R13: https://mpesije.jne.gob.pe/apidocs/2d022f8e-70ca-4f69-bb66-18caf80c35d1.jpg | S13: https://mpesije.jne.gob.pe/apidocs/be822fbb-498b-4975-8182-7486298e7a22.pdf | T13: =CONCATENATE(A1499," - ",B1499,".pdf") -> - .pdf | U13: =IF(I13="","",DATEDIF(DATE(VALUE(RIGHT(I13,4)),VALUE(MID(I13,4,2)),VALUE(LEFT(I13,2))),TODAY(),"Y")) -> 62 | V13: =IF(U13="","",IF(U13<30,"18-29",IF(U13<40,"30-39",IF(U13<50,"40-49",IF(U13<60,"50-59","60+"))))) -> 60+ | W13: =IF(UPPER(TRIM(J13))="PERU","PERÚ",UPPER(TRIM(J13))) -> PERÚ | X13: =UPPER(TRIM(H13)) -> FEMENINO | Y13: =UPPER(TRIM(K13)) -> LIMA | Z13: =UPPER(TRIM(P13)) -> LIMA PROVINCIAS
A14: FUERZA POPULAR | B14: 76030152 | C14: BARBARAN REYES, ROSANGELLA ANDREA | D14: 76030152 | E14: BARBARAN | F14: REYES | G14: ROSANGELLA ANDREA | H14: FEMENINO | I14: 24/08/1994 | J14: PERÚ | K14: LIMA | L14: LIMA | M14: LIMA | N14: DIPUTADO | P14: LIMA METROPOLITANA | R14: https://mpesije.jne.gob.pe/apidocs/fe41e940-1222-4497-b86f-66bedd7a031d.jpg | S14: https://mpesije.jne.gob.pe/apidocs/0b8d3293-4c04-49d0-9f66-36d9316df1b3.pdf | T14: =CONCATENATE(A1511," - ",B1511,".pdf") -> - .pdf | U14: =IF(I14="","",DATEDIF(DATE(VALUE(RIGHT(I14,4)),VALUE(MID(I14,4,2)),VALUE(LEFT(I14,2))),TODAY(),"Y")) -> 31 | V14: =IF(U14="","",IF(U14<30,"18-29",IF(U14<40,"30-39",IF(U14<50,"40-49",IF(U14<60,"50-59","60+"))))) -> 30-39 | W14: =IF(UPPER(TRIM(J14))="PERU","PERÚ",UPPER(TRIM(J14))) -> PERÚ | X14: =UPPER(TRIM(H14)) -> FEMENINO | Y14: =UPPER(TRIM(K14)) -> LIMA | Z14: =UPPER(TRIM(P14)) -> LIMA METROPOLITANA
A15: FUERZA POPULAR | B15: 22509175 | C15: BETETA RUBIN, KARINA JULIZA | D15: 22509175 | E15: BETETA | F15: RUBIN | G15: KARINA JULIZA | H15: FEMENINO | I15: 18/01/1975 | J15: PERÚ | K15: HUANUCO | L15: HUANUCO | M15: HUANUCO | N15: DIPUTADO | P15: HUANUCO | R15: https://mpesije.jne.gob.pe/apidocs/43176a37-cb6a-4724-be25-93f8b8855a1b.jpg | S15: https://mpesije.jne.gob.pe/apidocs/9798b7a7-1ab2-4804-ad97-510950bd4547.pdf | T15: =CONCATENATE(A1514," - ",B1514,".pdf") -> - .pdf | U15: =IF(I15="","",DATEDIF(DATE(VALUE(RIGHT(I15,4)),VALUE(MID(I15,4,2)),VALUE(LEFT(I15,2))),TODAY(),"Y")) -> 51 | V15: =IF(U15="","",IF(U15<30,"18-29",IF(U15<40,"30-39",IF(U15<50,"40-49",IF(U15<60,"50-59","60+"))))) -> 50-59 | W15: =IF(UPPER(TRIM(J15))="PERU","PERÚ",UPPER(TRIM(J15))) -> PERÚ | X15: =UPPER(TRIM(H15)) -> FEMENINO | Y15: =UPPER(TRIM(K15)) -> HUANUCO | Z15: =UPPER(TRIM(P15)) -> HUANUCO
A16: FUERZA POPULAR | B16: 40224994 | C16: BOBADILLA GALINDO, ANGEL BRUNO | D16: 40224994 | E16: BOBADILLA | F16: GALINDO | G16: ANGEL BRUNO | H16: MASCULINO | I16: 25/11/1976 | J16: PERÚ | K16: LIMA | L16: LIMA | M16: JESUS MARIA | N16: DIPUTADO | P16: CALLAO | R16: https://mpesije.jne.gob.pe/apidocs/4aa19ef9-46f1-4ff4-a11f-55fa2b686023.jpg | S16: https://mpesije.jne.gob.pe/apidocs/d48e8bb9-e8b2-4e42-8637-dab45812eff3.pdf | T16: =CONCATENATE(A1516," - ",B1516,".pdf") -> - .pdf | U16: =IF(I16="","",DATEDIF(DATE(VALUE(RIGHT(I16,4)),VALUE(MID(I16,4,2)),VALUE(LEFT(I16,2))),TODAY(),"Y")) -> 49 | V16: =IF(U16="","",IF(U16<30,"18-29",IF(U16<40,"30-39",IF(U16<50,"40-49",IF(U16<60,"50-59","60+"))))) -> 40-49 | W16: =IF(UPPER(TRIM(J16))="PERU","PERÚ",UPPER(TRIM(J16))) -> PERÚ | X16: =UPPER(TRIM(H16)) -> MASCULINO | Y16: =UPPER(TRIM(K16)) -> LIMA | Z16: =UPPER(TRIM(P16)) -> CALLAO
A17: FUERZA POPULAR | B17: 44807108 | C17: CASTILLO RIVAS, EDUARDO ENRIQUE | D17: 44807108 | E17: CASTILLO | F17: RIVAS | G17: EDUARDO ENRIQUE | H17: MASCULINO | I17: 21/10/1987 | J17: PERÚ | K17: PIURA | L17: PIURA | M17: CASTILLA | N17: DIPUTADO | P17: PIURA | R17: https://mpesije.jne.gob.pe/apidocs/d96b162f-db71-4892-ac4e-829de3492e9d.jpg | S17: https://mpesije.jne.gob.pe/apidocs/1c270718-9c38-47fc-8bf5-48b5f01ca557.pdf | T17: =CONCATENATE(A1534," - ",B1534,".pdf") -> - .pdf | U17: =IF(I17="","",DATEDIF(DATE(VALUE(RIGHT(I17,4)),VALUE(MID(I17,4,2)),VALUE(LEFT(I17,2))),TODAY(),"Y")) -> 38 | V17: =IF(U17="","",IF(U17<30,"18-29",IF(U17<40,"30-39",IF(U17<50,"40-49",IF(U17<60,"50-59","60+"))))) -> 30-39 | W17: =IF(UPPER(TRIM(J17))="PERU","PERÚ",UPPER(TRIM(J17))) -> PERÚ | X17: =UPPER(TRIM(H17)) -> MASCULINO | Y17: =UPPER(TRIM(K17)) -> PIURA | Z17: =UPPER(TRIM(P17)) -> PIURA
A18: FUERZA POPULAR | B18: 16650849 | C18: CASTRO CRUZ, JAVIER ALEJANDRO | D18: 16650849 | E18: CASTRO | F18: CRUZ | G18: JAVIER ALEJANDRO | H18: MASCULINO | I18: 09/09/1966 | J18: PERÚ | K18: LAMBAYEQUE | L18: CHICLAYO | M18: LAGUNAS | N18: DIPUTADO | P18: LAMBAYEQUE | R18: https://mpesije.jne.gob.pe/apidocs/1f66acdf-101e-4b1c-8468-4def175df0f8.jpg | S18: https://mpesije.jne.gob.pe/apidocs/dbc1874a-d204-42ce-9055-a47156e12322.pdf | T18: =CONCATENATE(A1537," - ",B1537,".pdf") -> - .pdf | U18: =IF(I18="","",DATEDIF(DATE(VALUE(RIGHT(I18,4)),VALUE(MID(I18,4,2)),VALUE(LEFT(I18,2))),TODAY(),"Y")) -> 59 | V18: =IF(U18="","",IF(U18<30,"18-29",IF(U18<40,"30-39",IF(U18<50,"40-49",IF(U18<60,"50-59","60+"))))) -> 50-59 | W18: =IF(UPPER(TRIM(J18))="PERU","PERÚ",UPPER(TRIM(J18))) -> PERÚ | X18: =UPPER(TRIM(H18)) -> MASCULINO | Y18: =UPPER(TRIM(K18)) -> LAMBAYEQUE | Z18: =UPPER(TRIM(P18)) -> LAMBAYEQUE
A19: FUERZA POPULAR | B19: 10587515 | C19: CASTRO GRANDEZ, ROYSER | D19: 10587515 | E19: CASTRO | F19: GRANDEZ | G19: ROYSER | H19: MASCULINO | I19: 07/01/1978 | J19: PERÚ | K19: AMAZONAS | L19: RODRIGUEZ DE MENDOZA | M19: SAN NICOLAS | N19: DIPUTADO | P19: AMAZONAS | R19: https://mpesije.jne.gob.pe/apidocs/15b719e1-4b47-4b44-90b3-e7e90d7c9842.jpg | S19: https://mpesije.jne.gob.pe/apidocs/ea82ddc3-c47b-4a6e-94a9-fedf8d602787.pdf | T19: =CONCATENATE(A1538," - ",B1538,".pdf") -> - .pdf | U19: =IF(I19="","",DATEDIF(DATE(VALUE(RIGHT(I19,4)),VALUE(MID(I19,4,2)),VALUE(LEFT(I19,2))),TODAY(),"Y")) -> 48 | V19: =IF(U19="","",IF(U19<30,"18-29",IF(U19<40,"30-39",IF(U19<50,"40-49",IF(U19<60,"50-59","60+"))))) -> 40-49 | W19: =IF(UPPER(TRIM(J19))="PERU","PERÚ",UPPER(TRIM(J19))) -> PERÚ | X19: =UPPER(TRIM(H19)) -> MASCULINO | Y19: =UPPER(TRIM(K19)) -> AMAZONAS | Z19: =UPPER(TRIM(P19)) -> AMAZONAS
A20: FUERZA POPULAR | B20: 07750373 | C20: CELIZ CASTILLO, RAFAEL ALDO | D20: 07750373 | E20: CELIZ | F20: CASTILLO | G20: RAFAEL ALDO | H20: MASCULINO | I20: 08/01/1969 | J20: PERÚ | K20: LIMA | L20: LIMA | M20: JESUS MARIA | N20: DIPUTADO | P20: TUMBES | R20: https://mpesije.jne.gob.pe/apidocs/48700055-eec9-404e-a7ab-37cb70abb653.jpg | S20: https://mpesije.jne.gob.pe/apidocs/cf9cf41d-cbec-433a-a05c-fe5314f2eafe.pdf | T20: =CONCATENATE(A1541," - ",B1541,".pdf") -> - .pdf | U20: =IF(I20="","",DATEDIF(DATE(VALUE(RIGHT(I20,4)),VALUE(MID(I20,4,2)),VALUE(LEFT(I20,2))),TODAY(),"Y")) -> 57 | V20: =IF(U20="","",IF(U20<30,"18-29",IF(U20<40,"30-39",IF(U20<50,"40-49",IF(U20<60,"50-59","60+"))))) -> 50-59 | W20: =IF(UPPER(TRIM(J20))="PERU","PERÚ",UPPER(TRIM(J20))) -> PERÚ | X20: =UPPER(TRIM(H20)) -> MASCULINO | Y20: =UPPER(TRIM(K20)) -> LIMA | Z20: =UPPER(TRIM(P20)) -> TUMBES
A21: FUERZA POPULAR | B21: 09536896 | C21: CHACON DE VETTORI, CECILIA ISABEL | D21: 09536896 | E21: CHACON | F21: DE VETTORI | G21: CECILIA ISABEL | H21: FEMENINO | I21: 03/02/1971 | J21: PERÚ | K21: LAMBAYEQUE | L21: CHICLAYO | M21: CHICLAYO | N21: DIPUTADO | P21: LIMA METROPOLITANA | R21: https://mpesije.jne.gob.pe/apidocs/075f4d47-7bb6-4eea-a441-5e19b60f7b47.jpg | S21: https://mpesije.jne.gob.pe/apidocs/263418a0-327e-47e2-81df-d5e4cbc93bbc.pdf | T21: =CONCATENATE(A1543," - ",B1543,".pdf") -> - .pdf | U21: =IF(I21="","",DATEDIF(DATE(VALUE(RIGHT(I21,4)),VALUE(MID(I21,4,2)),VALUE(LEFT(I21,2))),TODAY(),"Y")) -> 55 | V21: =IF(U21="","",IF(U21<30,"18-29",IF(U21<40,"30-39",IF(U21<50,"40-49",IF(U21<60,"50-59","60+"))))) -> 50-59 | W21: =IF(UPPER(TRIM(J21))="PERU","PERÚ",UPPER(TRIM(J21))) -> PERÚ | X21: =UPPER(TRIM(H21)) -> FEMENINO | Y21: =UPPER(TRIM(K21)) -> LAMBAYEQUE | Z21: =UPPER(TRIM(P21)) -> LIMA METROPOLITANA
A22: FUERZA POPULAR | B22: 40826681 | C22: COLUMBUS MURATA, DIETHELL | D22: 40826681 | E22: COLUMBUS | F22: MURATA | G22: DIETHELL | H22: MASCULINO | I22: 19/03/1981 | J22: PERÚ | K22: LIMA | L22: LIMA | M22: PUEBLO LIBRE | N22: DIPUTADO | P22: LIMA METROPOLITANA | R22: https://mpesije.jne.gob.pe/apidocs/e393717b-8477-43d8-a7a9-f3ce8f09395a.jpg | S22: https://mpesije.jne.gob.pe/apidocs/fb85f7cf-63c2-454a-b8be-caafa9482136.pdf | T22: =CONCATENATE(A1553," - ",B1553,".pdf") -> - .pdf | U22: =IF(I22="","",DATEDIF(DATE(VALUE(RIGHT(I22,4)),VALUE(MID(I22,4,2)),VALUE(LEFT(I22,2))),TODAY(),"Y")) -> 45 | V22: =IF(U22="","",IF(U22<30,"18-29",IF(U22<40,"30-39",IF(U22<50,"40-49",IF(U22<60,"50-59","60+"))))) -> 40-49 | W22: =IF(UPPER(TRIM(J22))="PERU","PERÚ",UPPER(TRIM(J22))) -> PERÚ | X22: =UPPER(TRIM(H22)) -> MASCULINO | Y22: =UPPER(TRIM(K22)) -> LIMA | Z22: =UPPER(TRIM(P22)) -> LIMA METROPOLITANA
A23: FUERZA POPULAR | B23: 42433830 | C23: DODERO JOVICH, PIERANGELI DANIELA | D23: 42433830 | E23: DODERO | F23: JOVICH | G23: PIERANGELI DANIELA | H23: FEMENINO | I23: 09/04/1984 | J23: PERÚ | K23: AREQUIPA | L23: AREQUIPA | M23: AREQUIPA | N23: DIPUTADO | P23: LIMA METROPOLITANA | R23: https://mpesije.jne.gob.pe/apidocs/38b21551-9f9d-4509-8df3-3ff196a3db73.jpg | S23: https://mpesije.jne.gob.pe/apidocs/604a338f-478d-493d-a90f-7914850bb21d.pdf | T23: =CONCATENATE(A1564," - ",B1564,".pdf") -> - .pdf | U23: =IF(I23="","",DATEDIF(DATE(VALUE(RIGHT(I23,4)),VALUE(MID(I23,4,2)),VALUE(LEFT(I23,2))),TODAY(),"Y")) -> 42 | V23: =IF(U23="","",IF(U23<30,"18-29",IF(U23<40,"30-39",IF(U23<50,"40-49",IF(U23<60,"50-59","60+"))))) -> 40-49 | W23: =IF(UPPER(TRIM(J23))="PERU","PERÚ",UPPER(TRIM(J23))) -> PERÚ | X23: =UPPER(TRIM(H23)) -> FEMENINO | Y23: =UPPER(TRIM(K23)) -> AREQUIPA | Z23: =UPPER(TRIM(P23)) -> LIMA METROPOLITANA
A24: FUERZA POPULAR | B24: 07268767 | C24: FIGARI MENDOZA, PIER PAOLO | D24: 07268767 | E24: FIGARI | F24: MENDOZA | G24: PIER PAOLO | H24: MASCULINO | I24: 14/11/1973 | J24: PERÚ | K24: LIMA | L24: LIMA | M24: MIRAFLORES | N24: DIPUTADO | P24: LIMA METROPOLITANA | R24: https://mpesije.jne.gob.pe/apidocs/ac01f508-6d64-4ea5-b2ff-42a47fe0d259.jpg | S24: https://mpesije.jne.gob.pe/apidocs/fd565fc1-e259-4d17-a0be-469e78eef6a5.pdf | T24: =CONCATENATE(A1574," - ",B1574,".pdf") -> - .pdf | U24: =IF(I24="","",DATEDIF(DATE(VALUE(RIGHT(I24,4)),VALUE(MID(I24,4,2)),VALUE(LEFT(I24,2))),TODAY(),"Y")) -> 52 | V24: =IF(U24="","",IF(U24<30,"18-29",IF(U24<40,"30-39",IF(U24<50,"40-49",IF(U24<60,"50-59","60+"))))) -> 50-59 | W24: =IF(UPPER(TRIM(J24))="PERU","PERÚ",UPPER(TRIM(J24))) -> PERÚ | X24: =UPPER(TRIM(H24)) -> MASCULINO | Y24: =UPPER(TRIM(K24)) -> LIMA | Z24: =UPPER(TRIM(P24)) -> LIMA METROPOLITANA
A25: FUERZA POPULAR | B25: 42516751 | C25: GAMARRA PITA, LUZMILA MARIA DEL CARMEN | D25: 42516751 | E25: GAMARRA | F25: PITA | G25: LUZMILA MARIA DEL CARMEN | H25: FEMENINO | I25: 02/07/1984 | J25: PERÚ | K25: LIMA | L25: LIMA | M25: JESUS MARIA | N25: DIPUTADO | P25: ANCASH | R25: https://mpesije.jne.gob.pe/apidocs/799ae78c-4935-458a-aa5c-550ceb4dadf4.jpg | S25: https://mpesije.jne.gob.pe/apidocs/b1cf36db-6a9c-423b-ae82-0a34aae7928c.pdf | T25: =CONCATENATE(A1585," - ",B1585,".pdf") -> - .pdf | U25: =IF(I25="","",DATEDIF(DATE(VALUE(RIGHT(I25,4)),VALUE(MID(I25,4,2)),VALUE(LEFT(I25,2))),TODAY(),"Y")) -> 41 | V25: =IF(U25="","",IF(U25<30,"18-29",IF(U25<40,"30-39",IF(U25<50,"40-49",IF(U25<60,"50-59","60+"))))) -> 40-49 | W25: =IF(UPPER(TRIM(J25))="PERU","PERÚ",UPPER(TRIM(J25))) -> PERÚ | X25: =UPPER(TRIM(H25)) -> FEMENINO | Y25: =UPPER(TRIM(K25)) -> LIMA | Z25: =UPPER(TRIM(P25)) -> ANCASH
A26: FUERZA POPULAR | B26: 16448130 | C26: INFANTES CASTAÑEDA, MERY ELIANA | D26: 16448130 | E26: INFANTES | F26: CASTAÑEDA | G26: MERY ELIANA | H26: FEMENINO | I26: 11/10/1963 | J26: PERÚ | K26: LAMBAYEQUE | L26: CHICLAYO | M26: NUEVA ARICA | N26: DIPUTADO | P26: AMAZONAS | R26: https://mpesije.jne.gob.pe/apidocs/1c7cad1e-55d0-4eaf-a410-3190cc45ccd9.jpg | S26: https://mpesije.jne.gob.pe/apidocs/ff1ca3f2-ec67-4f15-b8ab-a51f00002ed8.pdf | T26: =CONCATENATE(A1600," - ",B1600,".pdf") -> - .pdf | U26: =IF(I26="","",DATEDIF(DATE(VALUE(RIGHT(I26,4)),VALUE(MID(I26,4,2)),VALUE(LEFT(I26,2))),TODAY(),"Y")) -> 62 | V26: =IF(U26="","",IF(U26<30,"18-29",IF(U26<40,"30-39",IF(U26<50,"40-49",IF(U26<60,"50-59","60+"))))) -> 60+ | W26: =IF(UPPER(TRIM(J26))="PERU","PERÚ",UPPER(TRIM(J26))) -> PERÚ | X26: =UPPER(TRIM(H26)) -> FEMENINO | Y26: =UPPER(TRIM(K26)) -> LAMBAYEQUE | Z26: =UPPER(TRIM(P26)) -> AMAZONAS
A27: FUERZA POPULAR | B27: 41919665 | C27: LEIVA BAYLON, LETICIA MARUJA | D27: 41919665 | E27: LEIVA | F27: BAYLON | G27: LETICIA MARUJA | H27: FEMENINO | I27: 21/05/1983 | J27: PERÚ | K27: LIMA | L27: LIMA | M27: LIMA | N27: DIPUTADO | P27: LA LIBERTAD | R27: https://mpesije.jne.gob.pe/apidocs/b00ba9d7-66c7-480f-b8ea-b46904b30968.jpg | S27: https://mpesije.jne.gob.pe/apidocs/c8aad8f9-89d1-4e01-ad7c-eae451c94c24.pdf | T27: =CONCATENATE(A1607," - ",B1607,".pdf") -> - .pdf | U27: =IF(I27="","",DATEDIF(DATE(VALUE(RIGHT(I27,4)),VALUE(MID(I27,4,2)),VALUE(LEFT(I27,2))),TODAY(),"Y")) -> 43 | V27: =IF(U27="","",IF(U27<30,"18-29",IF(U27<40,"30-39",IF(U27<50,"40-49",IF(U27<60,"50-59","60+"))))) -> 40-49 | W27: =IF(UPPER(TRIM(J27))="PERU","PERÚ",UPPER(TRIM(J27))) -> PERÚ | X27: =UPPER(TRIM(H27)) -> FEMENINO | Y27: =UPPER(TRIM(K27)) -> LIMA | Z27: =UPPER(TRIM(P27)) -> LA LIBERTAD
A28: FUERZA POPULAR | B28: 10187011 | C28: MENDOZA BERNEDO, LIZ HULI | D28: 10187011 | E28: MENDOZA | F28: BERNEDO | G28: LIZ HULI | H28: FEMENINO | I28: 04/07/1974 | J28: PERÚ | K28: LIMA | L28: LIMA | M28: ANCON | N28: DIPUTADO | P28: PERUANOS RESIDENTES EN EL EXTRANJERO | R28: https://mpesije.jne.gob.pe/apidocs/8543846b-eaab-4b44-bda0-849122e6f396.jpg | S28: https://mpesije.jne.gob.pe/apidocs/cd39ca14-0159-40c9-843f-17264b0725ee.pdf | T28: =CONCATENATE(A1624," - ",B1624,".pdf") -> - .pdf | U28: =IF(I28="","",DATEDIF(DATE(VALUE(RIGHT(I28,4)),VALUE(MID(I28,4,2)),VALUE(LEFT(I28,2))),TODAY(),"Y")) -> 51 | V28: =IF(U28="","",IF(U28<30,"18-29",IF(U28<40,"30-39",IF(U28<50,"40-49",IF(U28<60,"50-59","60+"))))) -> 50-59 | W28: =IF(UPPER(TRIM(J28))="PERU","PERÚ",UPPER(TRIM(J28))) -> PERÚ | X28: =UPPER(TRIM(H28)) -> FEMENINO | Y28: =UPPER(TRIM(K28)) -> LIMA | Z28: =UPPER(TRIM(P28)) -> PERUANOS RESIDENTES EN EL EXTRANJERO
A29: FUERZA POPULAR | B29: 10028427 | C29: NAVAS SANCHEZ, JESSICA LIZBETH | D29: 10028427 | E29: NAVAS | F29: SANCHEZ | G29: JESSICA LIZBETH | H29: FEMENINO | I29: 09/08/1973 | J29: PERÚ | K29: UCAYALI | L29: CORONEL PORTILLO | M29: CALLERIA | N29: DIPUTADO | P29: UCAYALI | R29: https://mpesije.jne.gob.pe/apidocs/0c036c3c-b21f-4a3c-9aa0-355dc67b9d55.jpg | S29: https://mpesije.jne.gob.pe/apidocs/89f43cc1-8f03-46fa-9b73-d0610df59268.pdf | T29: =CONCATENATE(A1634," - ",B1634,".pdf") -> - .pdf | U29: =IF(I29="","",DATEDIF(DATE(VALUE(RIGHT(I29,4)),VALUE(MID(I29,4,2)),VALUE(LEFT(I29,2))),TODAY(),"Y")) -> 52 | V29: =IF(U29="","",IF(U29<30,"18-29",IF(U29<40,"30-39",IF(U29<50,"40-49",IF(U29<60,"50-59","60+"))))) -> 50-59 | W29: =IF(UPPER(TRIM(J29))="PERU","PERÚ",UPPER(TRIM(J29))) -> PERÚ | X29: =UPPER(TRIM(H29)) -> FEMENINO | Y29: =UPPER(TRIM(K29)) -> UCAYALI | Z29: =UPPER(TRIM(P29)) -> UCAYALI
A30: FUERZA POPULAR | B30: 07737110 | C30: OBANDO MORGAN, AURISTELA ANA | D30: 07737110 | E30: OBANDO | F30: MORGAN | G30: AURISTELA ANA | H30: FEMENINO | I30: 03/08/1953 | J30: PERÚ | K30: LAMBAYEQUE | L30: CHICLAYO | M30: CHICLAYO | N30: DIPUTADO | P30: CALLAO | R30: https://mpesije.jne.gob.pe/apidocs/922d4c25-0617-4447-97d6-8eaf47e4fbf2.jpg | S30: https://mpesije.jne.gob.pe/apidocs/86ed8743-9abe-4eff-9265-e83380b4c05b.pdf | T30: =CONCATENATE(A1637," - ",B1637,".pdf") -> - .pdf | U30: =IF(I30="","",DATEDIF(DATE(VALUE(RIGHT(I30,4)),VALUE(MID(I30,4,2)),VALUE(LEFT(I30,2))),TODAY(),"Y")) -> 72 | V30: =IF(U30="","",IF(U30<30,"18-29",IF(U30<40,"30-39",IF(U30<50,"40-49",IF(U30<60,"50-59","60+"))))) -> 60+ | W30: =IF(UPPER(TRIM(J30))="PERU","PERÚ",UPPER(TRIM(J30))) -> PERÚ | X30: =UPPER(TRIM(H30)) -> FEMENINO | Y30: =UPPER(TRIM(K30)) -> LAMBAYEQUE | Z30: =UPPER(TRIM(P30)) -> CALLAO
A31: FUERZA POPULAR | B31: 47000483 | C31: PACHECO QUISPE, MARCO ANTONIO | D31: 47000483 | E31: PACHECO | F31: QUISPE | G31: MARCO ANTONIO | H31: MASCULINO | I31: 14/03/1992 | J31: PERÚ | K31: LIMA | L31: LIMA | M31: VILLA EL SALVADOR | N31: DIPUTADO | P31: LIMA METROPOLITANA | R31: https://mpesije.jne.gob.pe/apidocs/eeab968c-83e6-41a2-92ec-4dfdcdb0cd7f.jpg | S31: https://mpesije.jne.gob.pe/apidocs/a561a482-3a99-43e4-9314-213f7bb4d7bf.pdf | T31: =CONCATENATE(A1646," - ",B1646,".pdf") -> - .pdf | U31: =IF(I31="","",DATEDIF(DATE(VALUE(RIGHT(I31,4)),VALUE(MID(I31,4,2)),VALUE(LEFT(I31,2))),TODAY(),"Y")) -> 34 | V31: =IF(U31="","",IF(U31<30,"18-29",IF(U31<40,"30-39",IF(U31<50,"40-49",IF(U31<60,"50-59","60+"))))) -> 30-39 | W31: =IF(UPPER(TRIM(J31))="PERU","PERÚ",UPPER(TRIM(J31))) -> PERÚ | X31: =UPPER(TRIM(H31)) -> MASCULINO | Y31: =UPPER(TRIM(K31)) -> LIMA | Z31: =UPPER(TRIM(P31)) -> LIMA METROPOLITANA
A32: FUERZA POPULAR | B32: 45721573 | C32: PALMA MENDOZA, JOSE MARVIN | D32: 45721573 | E32: PALMA | F32: MENDOZA | G32: JOSE MARVIN | H32: MASCULINO | I32: 26/05/1989 | J32: PERÚ | K32: LAMBAYEQUE | L32: CHICLAYO | M32: SANTA ROSA | N32: DIPUTADO | P32: LAMBAYEQUE | R32: https://mpesije.jne.gob.pe/apidocs/f1ccbd31-2838-4168-82d3-eb5b71f519c7.jpg | S32: https://mpesije.jne.gob.pe/apidocs/af5b875e-2cd2-4fa8-82ef-ce3f05284089.pdf | T32: =CONCATENATE(A1647," - ",B1647,".pdf") -> - .pdf | U32: =IF(I32="","",DATEDIF(DATE(VALUE(RIGHT(I32,4)),VALUE(MID(I32,4,2)),VALUE(LEFT(I32,2))),TODAY(),"Y")) -> 37 | V32: =IF(U32="","",IF(U32<30,"18-29",IF(U32<40,"30-39",IF(U32<50,"40-49",IF(U32<60,"50-59","60+"))))) -> 30-39 | W32: =IF(UPPER(TRIM(J32))="PERU","PERÚ",UPPER(TRIM(J32))) -> PERÚ | X32: =UPPER(TRIM(H32)) -> MASCULINO | Y32: =UPPER(TRIM(K32)) -> LAMBAYEQUE | Z32: =UPPER(TRIM(P32)) -> LAMBAYEQUE
A33: FUERZA POPULAR | B33: 10792277 | C33: PATIÑO URCO, ANA BERTHA | D33: 10792277 | E33: PATIÑO | F33: URCO | G33: ANA BERTHA | H33: FEMENINO | I33: 01/05/1967 | J33: PERÚ | K33: JUNIN | L33: HUANCAYO | M33: HUANCAYO | N33: DIPUTADO | P33: JUNIN | R33: https://mpesije.jne.gob.pe/apidocs/1351a920-31c9-42b8-9abc-e65fa1a12dd8.jpg | S33: https://mpesije.jne.gob.pe/apidocs/8cd2976e-3ac9-4cfd-ba3b-2ae21dbdad12.pdf | T33: =CONCATENATE(A1653," - ",B1653,".pdf") -> - .pdf | U33: =IF(I33="","",DATEDIF(DATE(VALUE(RIGHT(I33,4)),VALUE(MID(I33,4,2)),VALUE(LEFT(I33,2))),TODAY(),"Y")) -> 59 | V33: =IF(U33="","",IF(U33<30,"18-29",IF(U33<40,"30-39",IF(U33<50,"40-49",IF(U33<60,"50-59","60+"))))) -> 50-59 | W33: =IF(UPPER(TRIM(J33))="PERU","PERÚ",UPPER(TRIM(J33))) -> PERÚ | X33: =UPPER(TRIM(H33)) -> FEMENINO | Y33: =UPPER(TRIM(K33)) -> JUNIN | Z33: =UPPER(TRIM(P33)) -> JUNIN
A34: FUERZA POPULAR | B34: 41408779 | C34: PAUCARA PAXI, CARMELA | D34: 41408779 | E34: PAUCARA | F34: PAXI | G34: CARMELA | H34: FEMENINO | I34: 18/11/1979 | J34: PERÚ | K34: LIMA | L34: LIMA | M34: VILLA EL SALVADOR | N34: DIPUTADO | P34: PIURA | R34: https://mpesije.jne.gob.pe/apidocs/acf9364c-20ca-403e-bf77-0252c913b060.jpg | S34: https://mpesije.jne.gob.pe/apidocs/aaf53a26-bc0a-41c6-85ba-b6e14514bad4.pdf | T34: =CONCATENATE(A1654," - ",B1654,".pdf") -> - .pdf | U34: =IF(I34="","",DATEDIF(DATE(VALUE(RIGHT(I34,4)),VALUE(MID(I34,4,2)),VALUE(LEFT(I34,2))),TODAY(),"Y")) -> 46 | V34: =IF(U34="","",IF(U34<30,"18-29",IF(U34<40,"30-39",IF(U34<50,"40-49",IF(U34<60,"50-59","60+"))))) -> 40-49 | W34: =IF(UPPER(TRIM(J34))="PERU","PERÚ",UPPER(TRIM(J34))) -> PERÚ | X34: =UPPER(TRIM(H34)) -> FEMENINO | Y34: =UPPER(TRIM(K34)) -> LIMA | Z34: =UPPER(TRIM(P34)) -> PIURA
A35: FUERZA POPULAR | B35: 05414308 | C35: PINASCO MONTENEGRO, NARY BENVINDA | D35: 05414308 | E35: PINASCO | F35: MONTENEGRO | G35: NARY BENVINDA | H35: FEMENINO | I35: 26/10/1977 | J35: PERÚ | K35: LORETO | L35: MAYNAS | M35: IQUITOS | N35: DIPUTADO | P35: LORETO | R35: https://mpesije.jne.gob.pe/apidocs/b177f705-dfd3-4599-a882-ab395bc5346f.jpg | S35: https://mpesije.jne.gob.pe/apidocs/800f7ef6-8de6-4263-9184-22df80bdfc57.pdf | T35: =CONCATENATE(A1658," - ",B1658,".pdf") -> - .pdf | U35: =IF(I35="","",DATEDIF(DATE(VALUE(RIGHT(I35,4)),VALUE(MID(I35,4,2)),VALUE(LEFT(I35,2))),TODAY(),"Y")) -> 48 | V35: =IF(U35="","",IF(U35<30,"18-29",IF(U35<40,"30-39",IF(U35<50,"40-49",IF(U35<60,"50-59","60+"))))) -> 40-49 | W35: =IF(UPPER(TRIM(J35))="PERU","PERÚ",UPPER(TRIM(J35))) -> PERÚ | X35: =UPPER(TRIM(H35)) -> FEMENINO | Y35: =UPPER(TRIM(K35)) -> LORETO | Z35: =UPPER(TRIM(P35)) -> LORETO
A36: FUERZA POPULAR | B36: 44275599 | C36: REVILLA VILLANUEVA, CESAR MANUEL | D36: 44275599 | E36: REVILLA | F36: VILLANUEVA | G36: CESAR MANUEL | H36: MASCULINO | I36: 19/03/1987 | J36: PERÚ | K36: LAMBAYEQUE | L36: CHICLAYO | M36: CHICLAYO | N36: DIPUTADO | P36: PIURA | R36: https://mpesije.jne.gob.pe/apidocs/c239bb01-32d8-47ae-ac26-e62459fe1f18.jpg | S36: https://mpesije.jne.gob.pe/apidocs/994926dc-049b-4590-b5cf-8e1251762deb.pdf | T36: =CONCATENATE(A1671," - ",B1671,".pdf") -> - .pdf | U36: =IF(I36="","",DATEDIF(DATE(VALUE(RIGHT(I36,4)),VALUE(MID(I36,4,2)),VALUE(LEFT(I36,2))),TODAY(),"Y")) -> 39 | V36: =IF(U36="","",IF(U36<30,"18-29",IF(U36<40,"30-39",IF(U36<50,"40-49",IF(U36<60,"50-59","60+"))))) -> 30-39 | W36: =IF(UPPER(TRIM(J36))="PERU","PERÚ",UPPER(TRIM(J36))) -> PERÚ | X36: =UPPER(TRIM(H36)) -> MASCULINO | Y36: =UPPER(TRIM(K36)) -> LAMBAYEQUE | Z36: =UPPER(TRIM(P36)) -> PIURA
A37: FUERZA POPULAR | B37: 80328889 | C37: SALAS RIVERA, ALEXANDER | D37: 80328889 | E37: SALAS | F37: RIVERA | G37: ALEXANDER | H37: MASCULINO | I37: 14/05/1979 | J37: PERÚ | K37: LIMA | L37: CAÑETE | M37: SAN VICENTE DE CAÑETE | N37: DIPUTADO | P37: LIMA PROVINCIAS | R37: https://mpesije.jne.gob.pe/apidocs/2595a793-7375-4430-91d4-9cbc362c884d.jpg | S37: https://mpesije.jne.gob.pe/apidocs/7cf2d539-5f52-4560-8ea2-174a66ade6fe.pdf | T37: =CONCATENATE(A1687," - ",B1687,".pdf") -> - .pdf | U37: =IF(I37="","",DATEDIF(DATE(VALUE(RIGHT(I37,4)),VALUE(MID(I37,4,2)),VALUE(LEFT(I37,2))),TODAY(),"Y")) -> 47 | V37: =IF(U37="","",IF(U37<30,"18-29",IF(U37<40,"30-39",IF(U37<50,"40-49",IF(U37<60,"50-59","60+"))))) -> 40-49 | W37: =IF(UPPER(TRIM(J37))="PERU","PERÚ",UPPER(TRIM(J37))) -> PERÚ | X37: =UPPER(TRIM(H37)) -> MASCULINO | Y37: =UPPER(TRIM(K37)) -> LIMA | Z37: =UPPER(TRIM(P37)) -> LIMA PROVINCIAS
A38: FUERZA POPULAR | B38: 27424381 | C38: TICLLA RAFAEL, SEGUNDO SENOVIO | D38: 27424381 | E38: TICLLA | F38: RAFAEL | G38: SEGUNDO SENOVIO | H38: MASCULINO | I38: 05/09/1973 | J38: PERÚ | K38: CAJAMARCA | L38: CHOTA | M38: CHOTA | N38: DIPUTADO | P38: CAJAMARCA | R38: https://mpesije.jne.gob.pe/apidocs/ea749409-747d-429b-a6ea-fabdb2095247.jpg | S38: https://mpesije.jne.gob.pe/apidocs/afc7375e-ec92-484d-91f2-8092fb1da4af.pdf | T38: =CONCATENATE(A1705," - ",B1705,".pdf") -> - .pdf | U38: =IF(I38="","",DATEDIF(DATE(VALUE(RIGHT(I38,4)),VALUE(MID(I38,4,2)),VALUE(LEFT(I38,2))),TODAY(),"Y")) -> 52 | V38: =IF(U38="","",IF(U38<30,"18-29",IF(U38<40,"30-39",IF(U38<50,"40-49",IF(U38<60,"50-59","60+"))))) -> 50-59 | W38: =IF(UPPER(TRIM(J38))="PERU","PERÚ",UPPER(TRIM(J38))) -> PERÚ | X38: =UPPER(TRIM(H38)) -> MASCULINO | Y38: =UPPER(TRIM(K38)) -> CAJAMARCA | Z38: =UPPER(TRIM(P38)) -> CAJAMARCA
A39: FUERZA POPULAR | B39: 40433187 | C39: TORRES MORALES, MIGUEL ANGEL | D39: 40433187 | E39: TORRES | F39: MORALES | G39: MIGUEL ANGEL | H39: MASCULINO | I39: 18/02/1980 | J39: PERÚ | K39: LIMA | L39: LIMA | M39: LINCE | N39: SEGUNDO VICEPRESIDENTE DE LA REPÚBLICA | O39: SENADOR | P39: ÚNICO NACIONAL | R39: https://mpesije.jne.gob.pe/apidocs/789b7714-8633-4a59-a89b-7fab4646fef1.jpeg | S39: https://mpesije.jne.gob.pe/apidocs/99872797-b3bf-452e-939b-06d1cdeaa917.pdf | T39: =CONCATENATE(A1709," - ",B1709,".pdf") -> - .pdf | U39: =IF(I39="","",DATEDIF(DATE(VALUE(RIGHT(I39,4)),VALUE(MID(I39,4,2)),VALUE(LEFT(I39,2))),TODAY(),"Y")) -> 46 | V39: =IF(U39="","",IF(U39<30,"18-29",IF(U39<40,"30-39",IF(U39<50,"40-49",IF(U39<60,"50-59","60+"))))) -> 40-49 | W39: =IF(UPPER(TRIM(J39))="PERU","PERÚ",UPPER(TRIM(J39))) -> PERÚ | X39: =UPPER(TRIM(H39)) -> MASCULINO | Y39: =UPPER(TRIM(K39)) -> LIMA | Z39: =UPPER(TRIM(P39)) -> ÚNICO NACIONAL
A40: FUERZA POPULAR | B40: 08571708 | C40: TRUJILLO ZEGARRA, GILMER | D40: 08571708 | E40: TRUJILLO | F40: ZEGARRA | G40: GILMER | H40: MASCULINO | I40: 20/06/1966 | J40: PERÚ | K40: LIMA | L40: LIMA | M40: LIMA | N40: DIPUTADO | P40: LA LIBERTAD | R40: https://mpesije.jne.gob.pe/apidocs/4a6db76e-4a02-49f7-8d84-0ad1b851903f.jpg | S40: https://mpesije.jne.gob.pe/apidocs/2520e18a-e627-445c-a066-b83aadc43341.pdf | T40: =CONCATENATE(A1710," - ",B1710,".pdf") -> - .pdf | U40: =IF(I40="","",DATEDIF(DATE(VALUE(RIGHT(I40,4)),VALUE(MID(I40,4,2)),VALUE(LEFT(I40,2))),TODAY(),"Y")) -> 59 | V40: =IF(U40="","",IF(U40<30,"18-29",IF(U40<40,"30-39",IF(U40<50,"40-49",IF(U40<60,"50-59","60+"))))) -> 50-59 | W40: =IF(UPPER(TRIM(J40))="PERU","PERÚ",UPPER(TRIM(J40))) -> PERÚ | X40: =UPPER(TRIM(H40)) -> MASCULINO | Y40: =UPPER(TRIM(K40)) -> LIMA | Z40: =UPPER(TRIM(P40)) -> LA LIBERTAD
A41: FUERZA POPULAR | B41: 47654459 | C41: VALQUI ORDOÑEZ, JHONN BRAYAM | D41: 47654459 | E41: VALQUI | F41: ORDOÑEZ | G41: JHONN BRAYAM | H41: MASCULINO | I41: 14/08/1992 | J41: PERÚ | K41: PASCO | L41: PASCO | M41: CHAUPIMARCA | N41: DIPUTADO | P41: PASCO | R41: https://mpesije.jne.gob.pe/apidocs/5a1d94bc-3050-4a0b-a6e5-35f757b6a559.jpg | S41: https://mpesije.jne.gob.pe/apidocs/d24ab458-8600-4635-95cd-ad3cbd2307a2.pdf | T41: =CONCATENATE(A1717," - ",B1717,".pdf") -> - .pdf | U41: =IF(I41="","",DATEDIF(DATE(VALUE(RIGHT(I41,4)),VALUE(MID(I41,4,2)),VALUE(LEFT(I41,2))),TODAY(),"Y")) -> 33 | V41: =IF(U41="","",IF(U41<30,"18-29",IF(U41<40,"30-39",IF(U41<50,"40-49",IF(U41<60,"50-59","60+"))))) -> 30-39 | W41: =IF(UPPER(TRIM(J41))="PERU","PERÚ",UPPER(TRIM(J41))) -> PERÚ | X41: =UPPER(TRIM(H41)) -> MASCULINO | Y41: =UPPER(TRIM(K41)) -> PASCO | Z41: =UPPER(TRIM(P41)) -> PASCO
A42: FUERZA POPULAR | B42: 42551310 | C42: VIDAURRE FLORIDAS, CESAR MANUEL | D42: 42551310 | E42: VIDAURRE | F42: FLORIDAS | G42: CESAR MANUEL | H42: MASCULINO | I42: 25/08/1984 | J42: PERÚ | K42: LORETO | L42: MAYNAS | M42: IQUITOS | N42: DIPUTADO | P42: LORETO | R42: https://mpesije.jne.gob.pe/apidocs/46ef4d66-b8bf-48b4-aba1-ec2073b8ccf2.jpg | S42: https://mpesije.jne.gob.pe/apidocs/951baeee-fa5f-4a81-b6ca-6b4112606f42.pdf | T42: =CONCATENATE(A1728," - ",B1728,".pdf") -> - .pdf | U42: =IF(I42="","",DATEDIF(DATE(VALUE(RIGHT(I42,4)),VALUE(MID(I42,4,2)),VALUE(LEFT(I42,2))),TODAY(),"Y")) -> 41 | V42: =IF(U42="","",IF(U42<30,"18-29",IF(U42<40,"30-39",IF(U42<50,"40-49",IF(U42<60,"50-59","60+"))))) -> 40-49 | W42: =IF(UPPER(TRIM(J42))="PERU","PERÚ",UPPER(TRIM(J42))) -> PERÚ | X42: =UPPER(TRIM(H42)) -> MASCULINO | Y42: =UPPER(TRIM(K42)) -> LORETO | Z42: =UPPER(TRIM(P42)) -> LORETO
A43: FUERZA POPULAR | B43: 80387180 | C43: ZEGARRA SANCHEZ, CARLOS ALBERTO | D43: 80387180 | E43: ZEGARRA | F43: SANCHEZ | G43: CARLOS ALBERTO | H43: MASCULINO | I43: 19/03/1978 | J43: PERÚ | K43: LIMA | L43: LIMA | M43: LIMA | N43: DIPUTADO | P43: ICA | R43: https://mpesije.jne.gob.pe/apidocs/3684bf3c-4385-430d-bd6e-9d0ac59d4f92.jpg | S43: https://mpesije.jne.gob.pe/apidocs/4819ac33-e7bd-4e67-b67c-9294ca1c08c7.pdf | T43: =CONCATENATE(A1740," - ",B1740,".pdf") -> - .pdf | U43: =IF(I43="","",DATEDIF(DATE(VALUE(RIGHT(I43,4)),VALUE(MID(I43,4,2)),VALUE(LEFT(I43,2))),TODAY(),"Y")) -> 48 | V43: =IF(U43="","",IF(U43<30,"18-29",IF(U43<40,"30-39",IF(U43<50,"40-49",IF(U43<60,"50-59","60+"))))) -> 40-49 | W43: =IF(UPPER(TRIM(J43))="PERU","PERÚ",UPPER(TRIM(J43))) -> PERÚ | X43: =UPPER(TRIM(H43)) -> MASCULINO | Y43: =UPPER(TRIM(K43)) -> LIMA | Z43: =UPPER(TRIM(P43)) -> ICA
A44: JUNTOS POR EL PERU | B44: 46432487 | C44: AGUIRRE RAMOS, MARLON ALBERTO | D44: 46432487 | E44: AGUIRRE | F44: RAMOS | G44: MARLON ALBERTO | H44: MASCULINO | I44: 29/07/1990 | J44: PERÚ | K44: JUNIN | L44: CHANCHAMAYO | M44: PICHANAQUI | N44: DIPUTADO | P44: JUNIN | R44: https://mpesije.jne.gob.pe/apidocs/3cbab5a1-07f1-4378-9838-4d07f4cf0e6f.jpg | S44: https://mpesije.jne.gob.pe/apidocs/2c45f79d-1b6e-43bd-a1d1-f9c05e19286c.pdf | T44: =CONCATENATE(A2006," - ",B2006,".pdf") -> - .pdf | U44: =IF(I44="","",DATEDIF(DATE(VALUE(RIGHT(I44,4)),VALUE(MID(I44,4,2)),VALUE(LEFT(I44,2))),TODAY(),"Y")) -> 35 | V44: =IF(U44="","",IF(U44<30,"18-29",IF(U44<40,"30-39",IF(U44<50,"40-49",IF(U44<60,"50-59","60+"))))) -> 30-39 | W44: =IF(UPPER(TRIM(J44))="PERU","PERÚ",UPPER(TRIM(J44))) -> PERÚ | X44: =UPPER(TRIM(H44)) -> MASCULINO | Y44: =UPPER(TRIM(K44)) -> JUNIN | Z44: =UPPER(TRIM(P44)) -> JUNIN
A45: JUNTOS POR EL PERU | B45: 43845728 | C45: AMBROSIO DOMINGUEZ, YULI LILIANA | D45: 43845728 | E45: AMBROSIO | F45: DOMINGUEZ | G45: YULI LILIANA | H45: FEMENINO | I45: 08/11/1986 | J45: PERÚ | K45: HUANUCO | L45: HUANUCO | M45: HUANUCO | N45: DIPUTADO | P45: HUANUCO | R45: https://mpesije.jne.gob.pe/apidocs/2efb6771-bcb3-4714-b266-fd7c6f05ec2c.jpg | S45: https://mpesije.jne.gob.pe/apidocs/aa42163e-4231-4fc4-b0eb-e834b6b88e5c.pdf | T45: =CONCATENATE(A2009," - ",B2009,".pdf") -> - .pdf | U45: =IF(I45="","",DATEDIF(DATE(VALUE(RIGHT(I45,4)),VALUE(MID(I45,4,2)),VALUE(LEFT(I45,2))),TODAY(),"Y")) -> 39 | V45: =IF(U45="","",IF(U45<30,"18-29",IF(U45<40,"30-39",IF(U45<50,"40-49",IF(U45<60,"50-59","60+"))))) -> 30-39 | W45: =IF(UPPER(TRIM(J45))="PERU","PERÚ",UPPER(TRIM(J45))) -> PERÚ | X45: =UPPER(TRIM(H45)) -> FEMENINO | Y45: =UPPER(TRIM(K45)) -> HUANUCO | Z45: =UPPER(TRIM(P45)) -> HUANUCO
A46: JUNTOS POR EL PERU | B46: 40855980 | C46: AVENDAÑO VILCA, GIANNINA IRIS | D46: 40855980 | E46: AVENDAÑO | F46: VILCA | G46: GIANNINA IRIS | H46: FEMENINO | I46: 06/12/1980 | J46: PERÚ | K46: LIMA | L46: LIMA | M46: JESUS MARIA | N46: DIPUTADO | P46: LIMA METROPOLITANA | R46: https://mpesije.jne.gob.pe/apidocs/5dd5ffdf-a410-49e0-bc70-47b88e90f596.jpg | S46: https://mpesije.jne.gob.pe/apidocs/3eefce9e-5085-439f-ae24-8e4b6df1dacc.pdf | T46: =CONCATENATE(A2019," - ",B2019,".pdf") -> - .pdf | U46: =IF(I46="","",DATEDIF(DATE(VALUE(RIGHT(I46,4)),VALUE(MID(I46,4,2)),VALUE(LEFT(I46,2))),TODAY(),"Y")) -> 45 | V46: =IF(U46="","",IF(U46<30,"18-29",IF(U46<40,"30-39",IF(U46<50,"40-49",IF(U46<60,"50-59","60+"))))) -> 40-49 | W46: =IF(UPPER(TRIM(J46))="PERU","PERÚ",UPPER(TRIM(J46))) -> PERÚ | X46: =UPPER(TRIM(H46)) -> FEMENINO | Y46: =UPPER(TRIM(K46)) -> LIMA | Z46: =UPPER(TRIM(P46)) -> LIMA METROPOLITANA
A47: JUNTOS POR EL PERU | B47: 01223056 | C47: CONDORI FLORES, REMIGIO | D47: 01223056 | E47: CONDORI | F47: FLORES | G47: REMIGIO | H47: MASCULINO | I47: 01/10/1966 | J47: PERÚ | K47: PUNO | L47: PUNO | M47: PUNO | N47: DIPUTADO | P47: PUNO | R47: https://mpesije.jne.gob.pe/apidocs/01517b31-d1ad-46ae-8e61-04d93a3e9c53.jpg | S47: https://mpesije.jne.gob.pe/apidocs/41691d93-23af-4b19-b8a5-a1ad40ec4ea5.pdf | T47: =CONCATENATE(A2051," - ",B2051,".pdf") -> - .pdf | U47: =IF(I47="","",DATEDIF(DATE(VALUE(RIGHT(I47,4)),VALUE(MID(I47,4,2)),VALUE(LEFT(I47,2))),TODAY(),"Y")) -> 59 | V47: =IF(U47="","",IF(U47<30,"18-29",IF(U47<40,"30-39",IF(U47<50,"40-49",IF(U47<60,"50-59","60+"))))) -> 50-59 | W47: =IF(UPPER(TRIM(J47))="PERU","PERÚ",UPPER(TRIM(J47))) -> PERÚ | X47: =UPPER(TRIM(H47)) -> MASCULINO | Y47: =UPPER(TRIM(K47)) -> PUNO | Z47: =UPPER(TRIM(P47)) -> PUNO
A48: JUNTOS POR EL PERU | B48: 41711513 | C48: FLORES VALDIZAN, MARCO ANTONIO | D48: 41711513 | E48: FLORES | F48: VALDIZAN | G48: MARCO ANTONIO | H48: MASCULINO | I48: 04/07/1981 | J48: PERÚ | K48: HUANUCO | L48: LEONCIO PRADO | M48: JOSE CRESPO Y CASTILLO | N48: DIPUTADO | P48: HUANUCO | R48: https://mpesije.jne.gob.pe/apidocs/6870c7f2-a2f8-4370-8dbe-ea07d50b8091.jpg | S48: https://mpesije.jne.gob.pe/apidocs/1fa446e9-a1f6-4eef-adb1-501bc807a80b.pdf | T48: =CONCATENATE(A2071," - ",B2071,".pdf") -> - .pdf | U48: =IF(I48="","",DATEDIF(DATE(VALUE(RIGHT(I48,4)),VALUE(MID(I48,4,2)),VALUE(LEFT(I48,2))),TODAY(),"Y")) -> 44 | V48: =IF(U48="","",IF(U48<30,"18-29",IF(U48<40,"30-39",IF(U48<50,"40-49",IF(U48<60,"50-59","60+"))))) -> 40-49 | W48: =IF(UPPER(TRIM(J48))="PERU","PERÚ",UPPER(TRIM(J48))) -> PERÚ | X48: =UPPER(TRIM(H48)) -> MASCULINO | Y48: =UPPER(TRIM(K48)) -> HUANUCO | Z48: =UPPER(TRIM(P48)) -> HUANUCO
A49: JUNTOS POR EL PERU | B49: 40093361 | C49: GONZALES DELGADO, GABRIEL ROBERTINO | D49: 40093361 | E49: GONZALES | F49: DELGADO | G49: GABRIEL ROBERTINO | H49: MASCULINO | I49: 02/09/1973 | J49: PERÚ | K49: CAJAMARCA | L49: CAJAMARCA | M49: CAJAMARCA | N49: DIPUTADO | P49: CAJAMARCA | R49: https://mpesije.jne.gob.pe/apidocs/098935bc-8d8f-4d90-9ab1-209d38292773.jpg | S49: https://mpesije.jne.gob.pe/apidocs/f71e642d-fec9-4656-bf14-6eb05adea715.pdf | T49: =CONCATENATE(A2075," - ",B2075,".pdf") -> - .pdf | U49: =IF(I49="","",DATEDIF(DATE(VALUE(RIGHT(I49,4)),VALUE(MID(I49,4,2)),VALUE(LEFT(I49,2))),TODAY(),"Y")) -> 52 | V49: =IF(U49="","",IF(U49<30,"18-29",IF(U49<40,"30-39",IF(U49<50,"40-49",IF(U49<60,"50-59","60+"))))) -> 50-59 | W49: =IF(UPPER(TRIM(J49))="PERU","PERÚ",UPPER(TRIM(J49))) -> PERÚ | X49: =UPPER(TRIM(H49)) -> MASCULINO | Y49: =UPPER(TRIM(K49)) -> CAJAMARCA | Z49: =UPPER(TRIM(P49)) -> CAJAMARCA
A50: JUNTOS POR EL PERU | B50: 04810886 | C50: HOLGUIN AGUIRRE, JAMES ARTURO | D50: 04810886 | E50: HOLGUIN | F50: AGUIRRE | G50: JAMES ARTURO | H50: MASCULINO | I50: 03/05/1957 | J50: PERÚ | K50: MADRE DE DIOS | L50: TAMBOPATA | M50: TAMBOPATA | N50: DIPUTADO | P50: MADRE DE DIOS | R50: https://mpesije.jne.gob.pe/apidocs/4234b8c6-6700-4d18-8bc3-3977077d52dc.jpg | S50: https://mpesije.jne.gob.pe/apidocs/f41a93e8-9a85-4ac7-aab4-123530aa6ac0.pdf | T50: =CONCATENATE(A2085," - ",B2085,".pdf") -> - .pdf | U50: =IF(I50="","",DATEDIF(DATE(VALUE(RIGHT(I50,4)),VALUE(MID(I50,4,2)),VALUE(LEFT(I50,2))),TODAY(),"Y")) -> 69 | V50: =IF(U50="","",IF(U50<30,"18-29",IF(U50<40,"30-39",IF(U50<50,"40-49",IF(U50<60,"50-59","60+"))))) -> 60+ | W50: =IF(UPPER(TRIM(J50))="PERU","PERÚ",UPPER(TRIM(J50))) -> PERÚ | X50: =UPPER(TRIM(H50)) -> MASCULINO | Y50: =UPPER(TRIM(K50)) -> MADRE DE DIOS | Z50: =UPPER(TRIM(P50)) -> MADRE DE DIOS
A51: JUNTOS POR EL PERU | B51: 45442927 | C51: MARQUEZ HUANCA, ANALI | D51: 45442927 | E51: MARQUEZ | F51: HUANCA | G51: ANALI | H51: FEMENINO | I51: 10/10/1988 | J51: PERÚ | K51: CUSCO | L51: CHUMBIVILCAS | M51: SANTO TOMAS | N51: PRIMER VICEPRESIDENTE DE LA REPÚBLICA | O51: DIPUTADO | P51: CUSCO | R51: https://mpesije.jne.gob.pe/apidocs/cd236409-a6a7-4b75-8b06-25db73f256bd.jpg | S51: https://mpesije.jne.gob.pe/apidocs/f9b48ebe-feff-4520-8bfd-5779cf2ba37e.pdf | T51: =CONCATENATE(A2106," - ",B2106,".pdf") -> - .pdf | U51: =IF(I51="","",DATEDIF(DATE(VALUE(RIGHT(I51,4)),VALUE(MID(I51,4,2)),VALUE(LEFT(I51,2))),TODAY(),"Y")) -> 37 | V51: =IF(U51="","",IF(U51<30,"18-29",IF(U51<40,"30-39",IF(U51<50,"40-49",IF(U51<60,"50-59","60+"))))) -> 30-39 | W51: =IF(UPPER(TRIM(J51))="PERU","PERÚ",UPPER(TRIM(J51))) -> PERÚ | X51: =UPPER(TRIM(H51)) -> FEMENINO | Y51: =UPPER(TRIM(K51)) -> CUSCO | Z51: =UPPER(TRIM(P51)) -> CUSCO
A52: JUNTOS POR EL PERU | B52: 29313850 | C52: PALOMINO PACHECO, AMALIA EMILIA | D52: 29313850 | E52: PALOMINO | F52: PACHECO | G52: AMALIA EMILIA | H52: FEMENINO | I52: 06/11/1967 | J52: PERÚ | K52: MOQUEGUA | L52: GENERAL SANCHEZ CERRO | M52: QUINISTAQUILLAS | N52: DIPUTADO | P52: AREQUIPA | R52: https://mpesije.jne.gob.pe/apidocs/d05dfeb1-ce90-451c-b614-e00ac68e1077.jpg | S52: https://mpesije.jne.gob.pe/apidocs/8074e846-4b08-4c42-a070-0a9b7c90a685.pdf | T52: =CONCATENATE(A2129," - ",B2129,".pdf") -> - .pdf | U52: =IF(I52="","",DATEDIF(DATE(VALUE(RIGHT(I52,4)),VALUE(MID(I52,4,2)),VALUE(LEFT(I52,2))),TODAY(),"Y")) -> 58 | V52: =IF(U52="","",IF(U52<30,"18-29",IF(U52<40,"30-39",IF(U52<50,"40-49",IF(U52<60,"50-59","60+"))))) -> 50-59 | W52: =IF(UPPER(TRIM(J52))="PERU","PERÚ",UPPER(TRIM(J52))) -> PERÚ | X52: =UPPER(TRIM(H52)) -> FEMENINO | Y52: =UPPER(TRIM(K52)) -> MOQUEGUA | Z52: =UPPER(TRIM(P52)) -> AREQUIPA
A53: JUNTOS POR EL PERU | B53: 74638299 | C53: PAREDES NAVARRO, YENIFER NOELIA | D53: 74638299 | E53: PAREDES | F53: NAVARRO | G53: YENIFER NOELIA | H53: FEMENINO | I53: 05/12/1995 | J53: PERÚ | K53: CAJAMARCA | L53: CHOTA | M53: ANGUIA | N53: DIPUTADO | P53: CAJAMARCA | R53: https://mpesije.jne.gob.pe/apidocs/df807ab2-353c-4d89-8246-1a2b5c04ee5b.jpg | S53: https://mpesije.jne.gob.pe/apidocs/d24eb18d-844a-4c10-9c56-a807b049a338.pdf | T53: =CONCATENATE(A2131," - ",B2131,".pdf") -> - .pdf | U53: =IF(I53="","",DATEDIF(DATE(VALUE(RIGHT(I53,4)),VALUE(MID(I53,4,2)),VALUE(LEFT(I53,2))),TODAY(),"Y")) -> 30 | V53: =IF(U53="","",IF(U53<30,"18-29",IF(U53<40,"30-39",IF(U53<50,"40-49",IF(U53<60,"50-59","60+"))))) -> 30-39 | W53: =IF(UPPER(TRIM(J53))="PERU","PERÚ",UPPER(TRIM(J53))) -> PERÚ | X53: =UPPER(TRIM(H53)) -> FEMENINO | Y53: =UPPER(TRIM(K53)) -> CAJAMARCA | Z53: =UPPER(TRIM(P53)) -> CAJAMARCA
A54: JUNTOS POR EL PERU | B54: 42135939 | C54: PEÑA CORDOVA, OLVER | D54: 42135939 | E54: PEÑA | F54: CORDOVA | G54: OLVER | H54: MASCULINO | I54: 28/03/1983 | J54: PERÚ | K54: SAN MARTIN | L54: RIOJA | M54: YURACYACU | N54: DIPUTADO | P54: SAN MARTIN | R54: https://mpesije.jne.gob.pe/apidocs/46944cd6-4aac-4b6c-9884-64ea79bb4e44.jpg | S54: https://mpesije.jne.gob.pe/apidocs/08490927-9ff4-49e3-ada9-69dcefb0bf23.pdf | T54: =CONCATENATE(A2132," - ",B2132,".pdf") -> - .pdf | U54: =IF(I54="","",DATEDIF(DATE(VALUE(RIGHT(I54,4)),VALUE(MID(I54,4,2)),VALUE(LEFT(I54,2))),TODAY(),"Y")) -> 43 | V54: =IF(U54="","",IF(U54<30,"18-29",IF(U54<40,"30-39",IF(U54<50,"40-49",IF(U54<60,"50-59","60+"))))) -> 40-49 | W54: =IF(UPPER(TRIM(J54))="PERU","PERÚ",UPPER(TRIM(J54))) -> PERÚ | X54: =UPPER(TRIM(H54)) -> MASCULINO | Y54: =UPPER(TRIM(K54)) -> SAN MARTIN | Z54: =UPPER(TRIM(P54)) -> SAN MARTIN
A55: JUNTOS POR EL PERU | B55: 10536312 | C55: PEREZ MALLQUI, JULIAN LUIS | D55: 10536312 | E55: PEREZ | F55: MALLQUI | G55: JULIAN LUIS | H55: MASCULINO | I55: 29/10/1974 | J55: PERÚ | K55: AYACUCHO | L55: LA MAR | M55: TAMBO | N55: DIPUTADO | P55: CUSCO | R55: https://mpesije.jne.gob.pe/apidocs/0fb84197-9795-40fb-98ae-0445dd6de6a6.jpg | S55: https://mpesije.jne.gob.pe/apidocs/341f301e-ede2-414b-a1e0-a40b6cd7917d.pdf | T55: =CONCATENATE(A2133," - ",B2133,".pdf") -> - .pdf | U55: =IF(I55="","",DATEDIF(DATE(VALUE(RIGHT(I55,4)),VALUE(MID(I55,4,2)),VALUE(LEFT(I55,2))),TODAY(),"Y")) -> 51 | V55: =IF(U55="","",IF(U55<30,"18-29",IF(U55<40,"30-39",IF(U55<50,"40-49",IF(U55<60,"50-59","60+"))))) -> 50-59 | W55: =IF(UPPER(TRIM(J55))="PERU","PERÚ",UPPER(TRIM(J55))) -> PERÚ | X55: =UPPER(TRIM(H55)) -> MASCULINO | Y55: =UPPER(TRIM(K55)) -> AYACUCHO | Z55: =UPPER(TRIM(P55)) -> CUSCO
A56: JUNTOS POR EL PERU | B56: 44908591 | C56: PEREZ QUISPE, JESSICA SADITH | D56: 44908591 | E56: PEREZ | F56: QUISPE | G56: JESSICA SADITH | H56: FEMENINO | I56: 22/02/1988 | J56: PERÚ | K56: PUNO | L56: PUNO | M56: PUNO | N56: DIPUTADO | P56: PUNO | R56: https://mpesije.jne.gob.pe/apidocs/8451ecf0-0f0b-4f4c-959e-41a197c80793.jpg | S56: https://mpesije.jne.gob.pe/apidocs/57c139fd-c119-4dc6-8494-430d88ab3b7b.pdf | T56: =CONCATENATE(A2134," - ",B2134,".pdf") -> - .pdf | U56: =IF(I56="","",DATEDIF(DATE(VALUE(RIGHT(I56,4)),VALUE(MID(I56,4,2)),VALUE(LEFT(I56,2))),TODAY(),"Y")) -> 38 | V56: =IF(U56="","",IF(U56<30,"18-29",IF(U56<40,"30-39",IF(U56<50,"40-49",IF(U56<60,"50-59","60+"))))) -> 30-39 | W56: =IF(UPPER(TRIM(J56))="PERU","PERÚ",UPPER(TRIM(J56))) -> PERÚ | X56: =UPPER(TRIM(H56)) -> FEMENINO | Y56: =UPPER(TRIM(K56)) -> PUNO | Z56: =UPPER(TRIM(P56)) -> PUNO
A57: JUNTOS POR EL PERU | B57: 42984568 | C57: POMA HUAMANI, HAYDEE CELINDA | D57: 42984568 | E57: POMA | F57: HUAMANI | G57: HAYDEE CELINDA | H57: FEMENINO | I57: 10/09/1984 | J57: PERÚ | K57: CUSCO | L57: CUSCO | M57: SANTIAGO | N57: DIPUTADO | P57: MADRE DE DIOS | R57: https://mpesije.jne.gob.pe/apidocs/43965a86-c97c-44b8-a5e7-00376bc2c77b.jpg | S57: https://mpesije.jne.gob.pe/apidocs/77daecdd-c6da-4801-b1c5-917f5dc8c6c2.pdf | T57: =CONCATENATE(A2136," - ",B2136,".pdf") -> - .pdf | U57: =IF(I57="","",DATEDIF(DATE(VALUE(RIGHT(I57,4)),VALUE(MID(I57,4,2)),VALUE(LEFT(I57,2))),TODAY(),"Y")) -> 41 | V57: =IF(U57="","",IF(U57<30,"18-29",IF(U57<40,"30-39",IF(U57<50,"40-49",IF(U57<60,"50-59","60+"))))) -> 40-49 | W57: =IF(UPPER(TRIM(J57))="PERU","PERÚ",UPPER(TRIM(J57))) -> PERÚ | X57: =UPPER(TRIM(H57)) -> FEMENINO | Y57: =UPPER(TRIM(K57)) -> CUSCO | Z57: =UPPER(TRIM(P57)) -> MADRE DE DIOS
A58: JUNTOS POR EL PERU | B58: 70163475 | C58: TAPULLIMA INSAPILLO, JACQUELINE VIVIANA | D58: 70163475 | E58: TAPULLIMA | F58: INSAPILLO | G58: JACQUELINE VIVIANA | H58: FEMENINO | I58: 07/06/1989 | J58: PERÚ | K58: SAN MARTIN | L58: SAN MARTIN | M58: TARAPOTO | N58: DIPUTADO | P58: SAN MARTIN | R58: https://mpesije.jne.gob.pe/apidocs/c2d9848e-35f1-4b7c-bac2-15ea99360217.jpg | S58: https://mpesije.jne.gob.pe/apidocs/8e2929eb-243f-4b1a-aa7a-fe19beb67a78.pdf | T58: =CONCATENATE(A2164," - ",B2164,".pdf") -> - .pdf | U58: =IF(I58="","",DATEDIF(DATE(VALUE(RIGHT(I58,4)),VALUE(MID(I58,4,2)),VALUE(LEFT(I58,2))),TODAY(),"Y")) -> 37 | V58: =IF(U58="","",IF(U58<30,"18-29",IF(U58<40,"30-39",IF(U58<50,"40-49",IF(U58<60,"50-59","60+"))))) -> 30-39 | W58: =IF(UPPER(TRIM(J58))="PERU","PERÚ",UPPER(TRIM(J58))) -> PERÚ | X58: =UPPER(TRIM(H58)) -> FEMENINO | Y58: =UPPER(TRIM(K58)) -> SAN MARTIN | Z58: =UPPER(TRIM(P58)) -> SAN MARTIN
A59: JUNTOS POR EL PERU | B59: 01320941 | C59: TITO ROJAS, CESAR HUGO | D59: 01320941 | E59: TITO | F59: ROJAS | G59: CESAR HUGO | H59: MASCULINO | I59: 25/02/1971 | J59: PERÚ | K59: PUNO | L59: PUNO | M59: PAUCARCOLLA | N59: DIPUTADO | P59: PUNO | R59: https://mpesije.jne.gob.pe/apidocs/89ae261a-857b-4969-bad7-55e0ad4efdee.jpg | S59: https://mpesije.jne.gob.pe/apidocs/1181129a-f15c-4438-a615-bb44ad8c2191.pdf | T59: =CONCATENATE(A2167," - ",B2167,".pdf") -> - .pdf | U59: =IF(I59="","",DATEDIF(DATE(VALUE(RIGHT(I59,4)),VALUE(MID(I59,4,2)),VALUE(LEFT(I59,2))),TODAY(),"Y")) -> 55 | V59: =IF(U59="","",IF(U59<30,"18-29",IF(U59<40,"30-39",IF(U59<50,"40-49",IF(U59<60,"50-59","60+"))))) -> 50-59 | W59: =IF(UPPER(TRIM(J59))="PERU","PERÚ",UPPER(TRIM(J59))) -> PERÚ | X59: =UPPER(TRIM(H59)) -> MASCULINO | Y59: =UPPER(TRIM(K59)) -> PUNO | Z59: =UPPER(TRIM(P59)) -> PUNO
A60: JUNTOS POR EL PERU | B60: 45327535 | C60: ZUNINI YERREN, ERNESTO ALONZO | D60: 45327535 | E60: ZUNINI | F60: YERREN | G60: ERNESTO ALONZO | H60: MASCULINO | I60: 27/10/1987 | J60: PERÚ | K60: LAMBAYEQUE | L60: CHICLAYO | M60: CHICLAYO | N60: DIPUTADO | P60: LAMBAYEQUE | R60: https://mpesije.jne.gob.pe/apidocs/41bd9e58-4784-4073-9233-aaec6337b136.jpg | S60: https://mpesije.jne.gob.pe/apidocs/a11b9ee4-9434-49fc-84e2-cf96de2cbadf.pdf | T60: =CONCATENATE(A2187," - ",B2187,".pdf") -> - .pdf | U60: =IF(I60="","",DATEDIF(DATE(VALUE(RIGHT(I60,4)),VALUE(MID(I60,4,2)),VALUE(LEFT(I60,2))),TODAY(),"Y")) -> 38 | V60: =IF(U60="","",IF(U60<30,"18-29",IF(U60<40,"30-39",IF(U60<50,"40-49",IF(U60<60,"50-59","60+"))))) -> 30-39 | W60: =IF(UPPER(TRIM(J60))="PERU","PERÚ",UPPER(TRIM(J60))) -> PERÚ | X60: =UPPER(TRIM(H60)) -> MASCULINO | Y60: =UPPER(TRIM(K60)) -> LAMBAYEQUE | Z60: =UPPER(TRIM(P60)) -> LAMBAYEQUE
A61: PARTIDO CIVICO OBRAS | B61: 46602828 | C61: ALBAÑIL CARMONA, HENRY ANTONIO | D61: 46602828 | E61: ALBAÑIL | F61: CARMONA | G61: HENRY ANTONIO | H61: MASCULINO | I61: 04/11/1990 | J61: PERÚ | K61: PIURA | L61: PIURA | M61: LA UNION | N61: DIPUTADO | P61: PIURA | R61: https://mpesije.jne.gob.pe/apidocs/0db1fcfb-c302-445c-afe1-510fe4bf1f1a.jpg | S61: https://mpesije.jne.gob.pe/apidocs/87d63bc5-2136-4713-8449-b6635be00b8b.pdf | T61: =CONCATENATE(A2792," - ",B2792,".pdf") -> - .pdf | U61: =IF(I61="","",DATEDIF(DATE(VALUE(RIGHT(I61,4)),VALUE(MID(I61,4,2)),VALUE(LEFT(I61,2))),TODAY(),"Y")) -> 35 | V61: =IF(U61="","",IF(U61<30,"18-29",IF(U61<40,"30-39",IF(U61<50,"40-49",IF(U61<60,"50-59","60+"))))) -> 30-39 | W61: =IF(UPPER(TRIM(J61))="PERU","PERÚ",UPPER(TRIM(J61))) -> PERÚ | X61: =UPPER(TRIM(H61)) -> MASCULINO | Y61: =UPPER(TRIM(K61)) -> PIURA | Z61: =UPPER(TRIM(P61)) -> PIURA
A62: PARTIDO CIVICO OBRAS | B62: 43170121 | C62: ALVARON DE LA CRUZ, EDGAR ADRIAN | D62: 43170121 | E62: ALVARON | F62: DE LA CRUZ | G62: EDGAR ADRIAN | H62: MASCULINO | I62: 03/08/1985 | J62: PERÚ | K62: ANCASH | L62: HUARAZ | M62: HUARAZ | N62: DIPUTADO | P62: ANCASH | R62: https://mpesije.jne.gob.pe/apidocs/61529942-8bb4-407c-bc9c-3eb6a34537e6.jpg | S62: https://mpesije.jne.gob.pe/apidocs/bfdf21ad-afa2-449e-bab5-e308cf8b5ebd.pdf | T62: =CONCATENATE(A2796," - ",B2796,".pdf") -> - .pdf | U62: =IF(I62="","",DATEDIF(DATE(VALUE(RIGHT(I62,4)),VALUE(MID(I62,4,2)),VALUE(LEFT(I62,2))),TODAY(),"Y")) -> 40 | V62: =IF(U62="","",IF(U62<30,"18-29",IF(U62<40,"30-39",IF(U62<50,"40-49",IF(U62<60,"50-59","60+"))))) -> 40-49 | W62: =IF(UPPER(TRIM(J62))="PERU","PERÚ",UPPER(TRIM(J62))) -> PERÚ | X62: =UPPER(TRIM(H62)) -> MASCULINO | Y62: =UPPER(TRIM(K62)) -> ANCASH | Z62: =UPPER(TRIM(P62)) -> ANCASH
A63: PARTIDO CIVICO OBRAS | B63: 00482691 | C63: CABRERA NIETO, JUAN CESAR | D63: 00482691 | E63: CABRERA | F63: NIETO | G63: JUAN CESAR | H63: MASCULINO | I63: 18/07/1963 | J63: PERÚ | K63: PUNO | L63: EL COLLAO | M63: ILAVE | N63: DIPUTADO | P63: TACNA | R63: https://mpesije.jne.gob.pe/apidocs/424b0a36-b6b3-4320-9e23-b9875d7fcb48.jpg | S63: https://mpesije.jne.gob.pe/apidocs/36154e90-cf21-4f4c-af27-5bdcc08a0396.pdf | T63: =CONCATENATE(A2819," - ",B2819,".pdf") -> - .pdf | U63: =IF(I63="","",DATEDIF(DATE(VALUE(RIGHT(I63,4)),VALUE(MID(I63,4,2)),VALUE(LEFT(I63,2))),TODAY(),"Y")) -> 62 | V63: =IF(U63="","",IF(U63<30,"18-29",IF(U63<40,"30-39",IF(U63<50,"40-49",IF(U63<60,"50-59","60+"))))) -> 60+ | W63: =IF(UPPER(TRIM(J63))="PERU","PERÚ",UPPER(TRIM(J63))) -> PERÚ | X63: =UPPER(TRIM(H63)) -> MASCULINO | Y63: =UPPER(TRIM(K63)) -> PUNO | Z63: =UPPER(TRIM(P63)) -> TACNA
A64: PARTIDO CIVICO OBRAS | B64: 07654582 | C64: EUSEBIO PADILLA, ARTURO CESAR | D64: 07654582 | E64: EUSEBIO | F64: PADILLA | G64: ARTURO CESAR | H64: MASCULINO | I64: 04/01/1964 | J64: PERÚ | K64: LIMA | L64: LIMA | M64: LURIGANCHO | N64: DIPUTADO | P64: LIMA PROVINCIAS | R64: https://mpesije.jne.gob.pe/apidocs/8d44f945-0c51-4f46-a3e4-44206775973e.jpg | S64: https://mpesije.jne.gob.pe/apidocs/2296a691-3761-471c-bb3b-66bf56d6c564.pdf | T64: =CONCATENATE(A2866," - ",B2866,".pdf") -> - .pdf | U64: =IF(I64="","",DATEDIF(DATE(VALUE(RIGHT(I64,4)),VALUE(MID(I64,4,2)),VALUE(LEFT(I64,2))),TODAY(),"Y")) -> 62 | V64: =IF(U64="","",IF(U64<30,"18-29",IF(U64<40,"30-39",IF(U64<50,"40-49",IF(U64<60,"50-59","60+"))))) -> 60+ | W64: =IF(UPPER(TRIM(J64))="PERU","PERÚ",UPPER(TRIM(J64))) -> PERÚ | X64: =UPPER(TRIM(H64)) -> MASCULINO | Y64: =UPPER(TRIM(K64)) -> LIMA | Z64: =UPPER(TRIM(P64)) -> LIMA PROVINCIAS
A65: PARTIDO CIVICO OBRAS | B65: 01545223 | C65: HANCCO HANCCO, DINA IRENE | D65: 01545223 | E65: HANCCO | F65: HANCCO | G65: DINA IRENE | H65: FEMENINO | I65: 19/03/1970 | J65: PERÚ | K65: PUNO | L65: AZANGARO | M65: AZANGARO | N65: SEGUNDO VICEPRESIDENTE DE LA REPÚBLICA | O65: DIPUTADO | P65: PUNO | R65: https://mpesije.jne.gob.pe/apidocs/fa703877-427f-4312-be04-95b2959bf6d3.jpg | S65: https://mpesije.jne.gob.pe/apidocs/d326664e-0a6e-4e94-9477-cf972ff99bfd.pdf | T65: =CONCATENATE(A2890," - ",B2890,".pdf") -> - .pdf | U65: =IF(I65="","",DATEDIF(DATE(VALUE(RIGHT(I65,4)),VALUE(MID(I65,4,2)),VALUE(LEFT(I65,2))),TODAY(),"Y")) -> 56 | V65: =IF(U65="","",IF(U65<30,"18-29",IF(U65<40,"30-39",IF(U65<50,"40-49",IF(U65<60,"50-59","60+"))))) -> 50-59 | W65: =IF(UPPER(TRIM(J65))="PERU","PERÚ",UPPER(TRIM(J65))) -> PERÚ | X65: =UPPER(TRIM(H65)) -> FEMENINO | Y65: =UPPER(TRIM(K65)) -> PUNO | Z65: =UPPER(TRIM(P65)) -> PUNO
A66: PARTIDO CIVICO OBRAS | B66: 25001331 | C66: LOPEZ LETONA, HEBER | D66: 25001331 | E66: LOPEZ | F66: LETONA | G66: HEBER | H66: MASCULINO | I66: 18/02/1974 | J66: PERÚ | K66: CUSCO | L66: LA CONVENCION | M66: MARANURA | N66: DIPUTADO | P66: CUSCO | R66: https://mpesije.jne.gob.pe/apidocs/142c9ff3-0883-48d4-8fe4-786719c05e9f.jpg | S66: https://mpesije.jne.gob.pe/apidocs/c719ed44-cbe8-4306-81f7-c7ca2a45e10a.pdf | T66: =CONCATENATE(A2915," - ",B2915,".pdf") -> - .pdf | U66: =IF(I66="","",DATEDIF(DATE(VALUE(RIGHT(I66,4)),VALUE(MID(I66,4,2)),VALUE(LEFT(I66,2))),TODAY(),"Y")) -> 52 | V66: =IF(U66="","",IF(U66<30,"18-29",IF(U66<40,"30-39",IF(U66<50,"40-49",IF(U66<60,"50-59","60+"))))) -> 50-59 | W66: =IF(UPPER(TRIM(J66))="PERU","PERÚ",UPPER(TRIM(J66))) -> PERÚ | X66: =UPPER(TRIM(H66)) -> MASCULINO | Y66: =UPPER(TRIM(K66)) -> CUSCO | Z66: =UPPER(TRIM(P66)) -> CUSCO
A67: PARTIDO CIVICO OBRAS | B67: 41242025 | C67: MASCO CACERES, LUIS AURELIO | D67: 41242025 | E67: MASCO | F67: CACERES | G67: LUIS AURELIO | H67: MASCULINO | I67: 11/05/1981 | J67: PERÚ | K67: AREQUIPA | L67: ISLAY | M67: MOLLENDO | N67: DIPUTADO | P67: AREQUIPA | R67: https://mpesije.jne.gob.pe/apidocs/1b6eafdb-2ae0-4e95-ac50-503069a4bae3.jpg | S67: https://mpesije.jne.gob.pe/apidocs/079c12b8-56a0-4b9d-bfc5-555cbb1c35f9.pdf | T67: =CONCATENATE(A2922," - ",B2922,".pdf") -> - .pdf | U67: =IF(I67="","",DATEDIF(DATE(VALUE(RIGHT(I67,4)),VALUE(MID(I67,4,2)),VALUE(LEFT(I67,2))),TODAY(),"Y")) -> 45 | V67: =IF(U67="","",IF(U67<30,"18-29",IF(U67<40,"30-39",IF(U67<50,"40-49",IF(U67<60,"50-59","60+"))))) -> 40-49 | W67: =IF(UPPER(TRIM(J67))="PERU","PERÚ",UPPER(TRIM(J67))) -> PERÚ | X67: =UPPER(TRIM(H67)) -> MASCULINO | Y67: =UPPER(TRIM(K67)) -> AREQUIPA | Z67: =UPPER(TRIM(P67)) -> AREQUIPA
A68: PARTIDO CIVICO OBRAS | B68: 46089177 | C68: MEDINA STEIN, ANDREA DAYNA | D68: 46089177 | E68: MEDINA | F68: STEIN | G68: ANDREA DAYNA | H68: FEMENINO | I68: 24/11/1989 | J68: PERÚ | K68: LIMA | L68: LIMA | M68: SAN BORJA | N68: DIPUTADO | P68: LIMA METROPOLITANA | R68: https://mpesije.jne.gob.pe/apidocs/ce2ebf06-2e90-407f-9981-803107fe0975.jpg | S68: https://mpesije.jne.gob.pe/apidocs/ead020c3-5f53-4462-9013-3960987dba79.pdf | T68: =CONCATENATE(A2923," - ",B2923,".pdf") -> - .pdf | U68: =IF(I68="","",DATEDIF(DATE(VALUE(RIGHT(I68,4)),VALUE(MID(I68,4,2)),VALUE(LEFT(I68,2))),TODAY(),"Y")) -> 36 | V68: =IF(U68="","",IF(U68<30,"18-29",IF(U68<40,"30-39",IF(U68<50,"40-49",IF(U68<60,"50-59","60+"))))) -> 30-39 | W68: =IF(UPPER(TRIM(J68))="PERU","PERÚ",UPPER(TRIM(J68))) -> PERÚ | X68: =UPPER(TRIM(H68)) -> FEMENINO | Y68: =UPPER(TRIM(K68)) -> LIMA | Z68: =UPPER(TRIM(P68)) -> LIMA METROPOLITANA
A69: PARTIDO CIVICO OBRAS | B69: 19995860 | C69: PERALTA JORPA, MAXIMO | D69: 19995860 | E69: PERALTA | F69: JORPA | G69: MAXIMO | H69: MASCULINO | I69: 27/11/1965 | J69: PERÚ | K69: JUNIN | L69: HUANCAYO | M69: HUANCAYO | N69: DIPUTADO | P69: JUNIN | R69: https://mpesije.jne.gob.pe/apidocs/218682eb-a4f1-400c-b05d-637a881181e2.jpg | S69: https://mpesije.jne.gob.pe/apidocs/7c7df6f9-4170-49cc-aec5-0812178fc743.pdf | T69: =CONCATENATE(A2947," - ",B2947,".pdf") -> - .pdf | U69: =IF(I69="","",DATEDIF(DATE(VALUE(RIGHT(I69,4)),VALUE(MID(I69,4,2)),VALUE(LEFT(I69,2))),TODAY(),"Y")) -> 60 | V69: =IF(U69="","",IF(U69<30,"18-29",IF(U69<40,"30-39",IF(U69<50,"40-49",IF(U69<60,"50-59","60+"))))) -> 60+ | W69: =IF(UPPER(TRIM(J69))="PERU","PERÚ",UPPER(TRIM(J69))) -> PERÚ | X69: =UPPER(TRIM(H69)) -> MASCULINO | Y69: =UPPER(TRIM(K69)) -> JUNIN | Z69: =UPPER(TRIM(P69)) -> JUNIN
A70: PARTIDO CIVICO OBRAS | B70: 70074678 | C70: PIÑAN MAMANI, VICTOR EDUARDO | D70: 70074678 | E70: PIÑAN | F70: MAMANI | G70: VICTOR EDUARDO | H70: MASCULINO | I70: 06/05/1992 | J70: PERÚ | K70: LIMA | L70: LIMA | M70: LIMA | N70: DIPUTADO | P70: LIMA METROPOLITANA | R70: https://mpesije.jne.gob.pe/apidocs/af203abd-b7ad-4309-93b0-d86172a4f4e6.jpg | S70: https://mpesije.jne.gob.pe/apidocs/e6ebea0d-f8e3-4938-b5a3-ddaf225901c7.pdf | T70: =CONCATENATE(A2953," - ",B2953,".pdf") -> - .pdf | U70: =IF(I70="","",DATEDIF(DATE(VALUE(RIGHT(I70,4)),VALUE(MID(I70,4,2)),VALUE(LEFT(I70,2))),TODAY(),"Y")) -> 34 | V70: =IF(U70="","",IF(U70<30,"18-29",IF(U70<40,"30-39",IF(U70<50,"40-49",IF(U70<60,"50-59","60+"))))) -> 30-39 | W70: =IF(UPPER(TRIM(J70))="PERU","PERÚ",UPPER(TRIM(J70))) -> PERÚ | X70: =UPPER(TRIM(H70)) -> MASCULINO | Y70: =UPPER(TRIM(K70)) -> LIMA | Z70: =UPPER(TRIM(P70)) -> LIMA METROPOLITANA
A71: PARTIDO CIVICO OBRAS | B71: 07793641 | C71: SAMANEZ GONZALES VIGIL, JEENNY CRISTINA | D71: 07793641 | E71: SAMANEZ | F71: GONZALES VIGIL | G71: JEENNY CRISTINA | H71: FEMENINO | I71: 05/12/1952 | J71: PERÚ | K71: LIMA | L71: LIMA | M71: LIMA | N71: DIPUTADO | P71: LIMA METROPOLITANA | R71: https://mpesije.jne.gob.pe/apidocs/f86a4159-4ef5-4159-99a3-e7ad0f662dea.jpg | S71: https://mpesije.jne.gob.pe/apidocs/296afd5c-70dc-4c2a-ae96-4cf6d3530a49.pdf | T71: =CONCATENATE(A2973," - ",B2973,".pdf") -> - .pdf | U71: =IF(I71="","",DATEDIF(DATE(VALUE(RIGHT(I71,4)),VALUE(MID(I71,4,2)),VALUE(LEFT(I71,2))),TODAY(),"Y")) -> 73 | V71: =IF(U71="","",IF(U71<30,"18-29",IF(U71<40,"30-39",IF(U71<50,"40-49",IF(U71<60,"50-59","60+"))))) -> 60+ | W71: =IF(UPPER(TRIM(J71))="PERU","PERÚ",UPPER(TRIM(J71))) -> PERÚ | X71: =UPPER(TRIM(H71)) -> FEMENINO | Y71: =UPPER(TRIM(K71)) -> LIMA | Z71: =UPPER(TRIM(P71)) -> LIMA METROPOLITANA
A72: PARTIDO CIVICO OBRAS | B72: 17930730 | C72: VALQUI CALDERON, DEMETRIO FLAVIO | D72: 17930730 | E72: VALQUI | F72: CALDERON | G72: DEMETRIO FLAVIO | H72: MASCULINO | I72: 22/12/1955 | J72: PERÚ | K72: LA LIBERTAD | L72: TRUJILLO | M72: TRUJILLO | N72: DIPUTADO | P72: LA LIBERTAD | R72: https://mpesije.jne.gob.pe/apidocs/ab981458-cca9-4216-891a-c01371fa4609.jpg | S72: https://mpesije.jne.gob.pe/apidocs/815d153b-346a-47e2-8e3c-0eac0e1a58e3.pdf | T72: =CONCATENATE(A3001," - ",B3001,".pdf") -> - .pdf | U72: =IF(I72="","",DATEDIF(DATE(VALUE(RIGHT(I72,4)),VALUE(MID(I72,4,2)),VALUE(LEFT(I72,2))),TODAY(),"Y")) -> 70 | V72: =IF(U72="","",IF(U72<30,"18-29",IF(U72<40,"30-39",IF(U72<50,"40-49",IF(U72<60,"50-59","60+"))))) -> 60+ | W72: =IF(UPPER(TRIM(J72))="PERU","PERÚ",UPPER(TRIM(J72))) -> PERÚ | X72: =UPPER(TRIM(H72)) -> MASCULINO | Y72: =UPPER(TRIM(K72)) -> LA LIBERTAD | Z72: =UPPER(TRIM(P72)) -> LA LIBERTAD
A73: PARTIDO CIVICO OBRAS | B73: 42188288 | C73: YATACO TORREALVA, JOSE RICARDO | D73: 42188288 | E73: YATACO | F73: TORREALVA | G73: JOSE RICARDO | H73: MASCULINO | I73: 06/04/1982 | J73: PERÚ | K73: ICA | L73: ICA | M73: ICA | N73: DIPUTADO | P73: ICA | R73: https://mpesije.jne.gob.pe/apidocs/b4199bc6-2a02-456e-ba65-3d397f8acb9d.jpg | S73: https://mpesije.jne.gob.pe/apidocs/784d9274-98ac-405b-84a3-ff7786b655ff.pdf | T73: =CONCATENATE(A3014," - ",B3014,".pdf") -> - .pdf | U73: =IF(I73="","",DATEDIF(DATE(VALUE(RIGHT(I73,4)),VALUE(MID(I73,4,2)),VALUE(LEFT(I73,2))),TODAY(),"Y")) -> 44 | V73: =IF(U73="","",IF(U73<30,"18-29",IF(U73<40,"30-39",IF(U73<50,"40-49",IF(U73<60,"50-59","60+"))))) -> 40-49 | W73: =IF(UPPER(TRIM(J73))="PERU","PERÚ",UPPER(TRIM(J73))) -> PERÚ | X73: =UPPER(TRIM(H73)) -> MASCULINO | Y73: =UPPER(TRIM(K73)) -> ICA | Z73: =UPPER(TRIM(P73)) -> ICA
A74: PARTIDO DEL BUEN GOBIERNO | B74: 43478989 | C74: ALAYZA MACCERA, ROSSANA HERMINIA | D74: 43478989 | E74: ALAYZA | F74: MACCERA | G74: ROSSANA HERMINIA | H74: FEMENINO | I74: 16/03/1986 | J74: PERÚ | K74: LIMA | L74: LIMA | M74: MIRAFLORES | N74: DIPUTADO | P74: LIMA METROPOLITANA | R74: https://mpesije.jne.gob.pe/apidocs/c0aa7fd0-a9f9-4350-925f-0182ae996c3f.jpg | S74: https://mpesije.jne.gob.pe/apidocs/c96cec4d-1e58-481c-b421-0f38cb368efe.pdf | T74: =CONCATENATE(A3228," - ",B3228,".pdf") -> - .pdf | U74: =IF(I74="","",DATEDIF(DATE(VALUE(RIGHT(I74,4)),VALUE(MID(I74,4,2)),VALUE(LEFT(I74,2))),TODAY(),"Y")) -> 40 | V74: =IF(U74="","",IF(U74<30,"18-29",IF(U74<40,"30-39",IF(U74<50,"40-49",IF(U74<60,"50-59","60+"))))) -> 40-49 | W74: =IF(UPPER(TRIM(J74))="PERU","PERÚ",UPPER(TRIM(J74))) -> PERÚ | X74: =UPPER(TRIM(H74)) -> FEMENINO | Y74: =UPPER(TRIM(K74)) -> LIMA | Z74: =UPPER(TRIM(P74)) -> LIMA METROPOLITANA
A75: PARTIDO DEL BUEN GOBIERNO | B75: 41356710 | C75: BENITEZ BARRIONUEVO, JESSICA | D75: 41356710 | E75: BENITEZ | F75: BARRIONUEVO | G75: JESSICA | H75: FEMENINO | I75: 28/11/1981 | J75: PERÚ | K75: LIMA | L75: LIMA | M75: PUEBLO LIBRE | N75: DIPUTADO | P75: LIMA METROPOLITANA | R75: https://mpesije.jne.gob.pe/apidocs/79cec618-7fb8-406a-bb30-481e575dd8aa.jpg | S75: https://mpesije.jne.gob.pe/apidocs/8b00771a-f8e6-4ccd-8a35-81365583e9fa.pdf | T75: =CONCATENATE(A3252," - ",B3252,".pdf") -> - .pdf | U75: =IF(I75="","",DATEDIF(DATE(VALUE(RIGHT(I75,4)),VALUE(MID(I75,4,2)),VALUE(LEFT(I75,2))),TODAY(),"Y")) -> 44 | V75: =IF(U75="","",IF(U75<30,"18-29",IF(U75<40,"30-39",IF(U75<50,"40-49",IF(U75<60,"50-59","60+"))))) -> 40-49 | W75: =IF(UPPER(TRIM(J75))="PERU","PERÚ",UPPER(TRIM(J75))) -> PERÚ | X75: =UPPER(TRIM(H75)) -> FEMENINO | Y75: =UPPER(TRIM(K75)) -> LIMA | Z75: =UPPER(TRIM(P75)) -> LIMA METROPOLITANA
A76: PARTIDO DEL BUEN GOBIERNO | B76: 16629849 | C76: CASTREJON FERNANDEZ, SEGUNDO JUAN | D76: 16629849 | E76: CASTREJON | F76: FERNANDEZ | G76: SEGUNDO JUAN | H76: MASCULINO | I76: 28/08/1971 | J76: PERÚ | K76: LAMBAYEQUE | L76: CHICLAYO | M76: CHICLAYO | N76: DIPUTADO | P76: LAMBAYEQUE | R76: https://mpesije.jne.gob.pe/apidocs/31d49098-516e-4c03-8a17-a7b02572d1c1.jpg | S76: https://mpesije.jne.gob.pe/apidocs/1a054092-049b-4abe-8f27-266acf357dbe.pdf | T76: =CONCATENATE(A3268," - ",B3268,".pdf") -> - .pdf | U76: =IF(I76="","",DATEDIF(DATE(VALUE(RIGHT(I76,4)),VALUE(MID(I76,4,2)),VALUE(LEFT(I76,2))),TODAY(),"Y")) -> 54 | V76: =IF(U76="","",IF(U76<30,"18-29",IF(U76<40,"30-39",IF(U76<50,"40-49",IF(U76<60,"50-59","60+"))))) -> 50-59 | W76: =IF(UPPER(TRIM(J76))="PERU","PERÚ",UPPER(TRIM(J76))) -> PERÚ | X76: =UPPER(TRIM(H76)) -> MASCULINO | Y76: =UPPER(TRIM(K76)) -> LAMBAYEQUE | Z76: =UPPER(TRIM(P76)) -> LAMBAYEQUE
A77: PARTIDO DEL BUEN GOBIERNO | B77: 10277219 | C77: DUARTE PATIÑO DE PEZET, CARMEN GEORGINA | D77: 10277219 | E77: DUARTE | F77: PATIÑO DE PEZET | G77: CARMEN GEORGINA | H77: FEMENINO | I77: 06/05/1957 | J77: PERÚ | K77: JUNIN | L77: HUANCAYO | M77: HUANCAYO | N77: DIPUTADO | P77: JUNIN | R77: https://mpesije.jne.gob.pe/apidocs/96e1f352-3fca-4573-8959-94b731cb2082.jpg | S77: https://mpesije.jne.gob.pe/apidocs/e7628ce5-1d58-4b2c-91e9-f8fd0edf0a90.pdf | T77: =CONCATENATE(A3299," - ",B3299,".pdf") -> - .pdf | U77: =IF(I77="","",DATEDIF(DATE(VALUE(RIGHT(I77,4)),VALUE(MID(I77,4,2)),VALUE(LEFT(I77,2))),TODAY(),"Y")) -> 69 | V77: =IF(U77="","",IF(U77<30,"18-29",IF(U77<40,"30-39",IF(U77<50,"40-49",IF(U77<60,"50-59","60+"))))) -> 60+ | W77: =IF(UPPER(TRIM(J77))="PERU","PERÚ",UPPER(TRIM(J77))) -> PERÚ | X77: =UPPER(TRIM(H77)) -> FEMENINO | Y77: =UPPER(TRIM(K77)) -> JUNIN | Z77: =UPPER(TRIM(P77)) -> JUNIN
A78: PARTIDO DEL BUEN GOBIERNO | B78: 31038213 | C78: FERNANDEZ DE LA TORRE, HILDA JUDIT | D78: 31038213 | E78: FERNANDEZ | F78: DE LA TORRE | G78: HILDA JUDIT | H78: FEMENINO | I78: 04/08/1973 | J78: PERÚ | K78: APURIMAC | L78: AYMARAES | M78: CHALHUANCA | N78: DIPUTADO | P78: LIMA METROPOLITANA | R78: https://mpesije.jne.gob.pe/apidocs/4e96cee3-276f-4dd5-87fb-be716ede1954.jpg | S78: https://mpesije.jne.gob.pe/apidocs/2db4aed5-9530-48d1-9972-08a4d19eb45c.pdf | T78: =CONCATENATE(A3307," - ",B3307,".pdf") -> - .pdf | U78: =IF(I78="","",DATEDIF(DATE(VALUE(RIGHT(I78,4)),VALUE(MID(I78,4,2)),VALUE(LEFT(I78,2))),TODAY(),"Y")) -> 52 | V78: =IF(U78="","",IF(U78<30,"18-29",IF(U78<40,"30-39",IF(U78<50,"40-49",IF(U78<60,"50-59","60+"))))) -> 50-59 | W78: =IF(UPPER(TRIM(J78))="PERU","PERÚ",UPPER(TRIM(J78))) -> PERÚ | X78: =UPPER(TRIM(H78)) -> FEMENINO | Y78: =UPPER(TRIM(K78)) -> APURIMAC | Z78: =UPPER(TRIM(P78)) -> LIMA METROPOLITANA
A79: PARTIDO DEL BUEN GOBIERNO | B79: 08573694 | C79: GARCIA HUBY, FERNANDO ALBERTO | D79: 08573694 | E79: GARCIA | F79: HUBY | G79: FERNANDO ALBERTO | H79: MASCULINO | I79: 12/03/1961 | J79: PERÚ | K79: LIMA | L79: LIMA | M79: LIMA | N79: DIPUTADO | P79: CALLAO | R79: https://mpesije.jne.gob.pe/apidocs/a03eee72-dcb6-4ae2-9b09-f203c0289b9c.jpg | S79: https://mpesije.jne.gob.pe/apidocs/05b150e1-09be-42fd-b8e6-11e2ee76ad58.pdf | T79: =CONCATENATE(A3319," - ",B3319,".pdf") -> - .pdf | U79: =IF(I79="","",DATEDIF(DATE(VALUE(RIGHT(I79,4)),VALUE(MID(I79,4,2)),VALUE(LEFT(I79,2))),TODAY(),"Y")) -> 65 | V79: =IF(U79="","",IF(U79<30,"18-29",IF(U79<40,"30-39",IF(U79<50,"40-49",IF(U79<60,"50-59","60+"))))) -> 60+ | W79: =IF(UPPER(TRIM(J79))="PERU","PERÚ",UPPER(TRIM(J79))) -> PERÚ | X79: =UPPER(TRIM(H79)) -> MASCULINO | Y79: =UPPER(TRIM(K79)) -> LIMA | Z79: =UPPER(TRIM(P79)) -> CALLAO
A80: PARTIDO DEL BUEN GOBIERNO | B80: 29715400 | C80: GONZALES POLAR, EDGAR DEMBER | D80: 29715400 | E80: GONZALES | F80: POLAR | G80: EDGAR DEMBER | H80: MASCULINO | I80: 06/09/1963 | J80: PERÚ | K80: AREQUIPA | L80: AREQUIPA | M80: AREQUIPA | N80: DIPUTADO | P80: AREQUIPA | R80: https://mpesije.jne.gob.pe/apidocs/f17364a8-2519-4d38-8f99-bd6c610c1ae7.jpg | S80: https://mpesije.jne.gob.pe/apidocs/455b153e-0c98-4a98-b0a0-d366e8524f3e.pdf | T80: =CONCATENATE(A3326," - ",B3326,".pdf") -> - .pdf | U80: =IF(I80="","",DATEDIF(DATE(VALUE(RIGHT(I80,4)),VALUE(MID(I80,4,2)),VALUE(LEFT(I80,2))),TODAY(),"Y")) -> 62 | V80: =IF(U80="","",IF(U80<30,"18-29",IF(U80<40,"30-39",IF(U80<50,"40-49",IF(U80<60,"50-59","60+"))))) -> 60+ | W80: =IF(UPPER(TRIM(J80))="PERU","PERÚ",UPPER(TRIM(J80))) -> PERÚ | X80: =UPPER(TRIM(H80)) -> MASCULINO | Y80: =UPPER(TRIM(K80)) -> AREQUIPA | Z80: =UPPER(TRIM(P80)) -> AREQUIPA
A81: PARTIDO DEL BUEN GOBIERNO | B81: 29311981 | C81: HIRACHE PIZARRO, GLORIA CHARITO | D81: 29311981 | E81: HIRACHE | F81: PIZARRO | G81: GLORIA CHARITO | H81: FEMENINO | I81: 02/01/1967 | J81: PERÚ | K81: AREQUIPA | L81: CONDESUYOS | M81: CHICHAS | N81: DIPUTADO | P81: AREQUIPA | R81: https://mpesije.jne.gob.pe/apidocs/b0b0414c-e256-403d-a125-f0a5634e8d31.jpg | S81: https://mpesije.jne.gob.pe/apidocs/62a21092-cc55-4650-bc4d-1bdd8881a12c.pdf | T81: =CONCATENATE(A3333," - ",B3333,".pdf") -> - .pdf | U81: =IF(I81="","",DATEDIF(DATE(VALUE(RIGHT(I81,4)),VALUE(MID(I81,4,2)),VALUE(LEFT(I81,2))),TODAY(),"Y")) -> 59 | V81: =IF(U81="","",IF(U81<30,"18-29",IF(U81<40,"30-39",IF(U81<50,"40-49",IF(U81<60,"50-59","60+"))))) -> 50-59 | W81: =IF(UPPER(TRIM(J81))="PERU","PERÚ",UPPER(TRIM(J81))) -> PERÚ | X81: =UPPER(TRIM(H81)) -> FEMENINO | Y81: =UPPER(TRIM(K81)) -> AREQUIPA | Z81: =UPPER(TRIM(P81)) -> AREQUIPA
A82: PARTIDO DEL BUEN GOBIERNO | B82: 02819812 | C82: HUAMAN CORNEJO, MIGUEL FELIX | D82: 02819812 | E82: HUAMAN | F82: CORNEJO | G82: MIGUEL FELIX | H82: MASCULINO | I82: 23/07/1969 | J82: PERÚ | K82: PIURA | L82: PIURA | M82: PIURA | N82: DIPUTADO | P82: PIURA | R82: https://mpesije.jne.gob.pe/apidocs/d2f6880b-86eb-4e5e-a1a3-3474f35e6b0d.jpg | S82: https://mpesije.jne.gob.pe/apidocs/41f91401-16a2-4b40-8a73-f982e16b33a1.pdf | T82: =CONCATENATE(A3336," - ",B3336,".pdf") -> - .pdf | U82: =IF(I82="","",DATEDIF(DATE(VALUE(RIGHT(I82,4)),VALUE(MID(I82,4,2)),VALUE(LEFT(I82,2))),TODAY(),"Y")) -> 56 | V82: =IF(U82="","",IF(U82<30,"18-29",IF(U82<40,"30-39",IF(U82<50,"40-49",IF(U82<60,"50-59","60+"))))) -> 50-59 | W82: =IF(UPPER(TRIM(J82))="PERU","PERÚ",UPPER(TRIM(J82))) -> PERÚ | X82: =UPPER(TRIM(H82)) -> MASCULINO | Y82: =UPPER(TRIM(K82)) -> PIURA | Z82: =UPPER(TRIM(P82)) -> PIURA
A83: PARTIDO DEL BUEN GOBIERNO | B83: 06296745 | C83: LLAQUE LINARES, NORA MARIA | D83: 06296745 | E83: LLAQUE | F83: LINARES | G83: NORA MARIA | H83: FEMENINO | I83: 20/05/1955 | J83: PERÚ | K83: LIMA | L83: LIMA | M83: PUEBLO LIBRE | N83: DIPUTADO | P83: LA LIBERTAD | R83: https://mpesije.jne.gob.pe/apidocs/77d2ff11-97f6-4d87-966b-2206b6073627.jpg | S83: https://mpesije.jne.gob.pe/apidocs/5c297464-cc25-4d7e-922e-61a9d88943d1.pdf | T83: =CONCATENATE(A3344," - ",B3344,".pdf") -> - .pdf | U83: =IF(I83="","",DATEDIF(DATE(VALUE(RIGHT(I83,4)),VALUE(MID(I83,4,2)),VALUE(LEFT(I83,2))),TODAY(),"Y")) -> 71 | V83: =IF(U83="","",IF(U83<30,"18-29",IF(U83<40,"30-39",IF(U83<50,"40-49",IF(U83<60,"50-59","60+"))))) -> 60+ | W83: =IF(UPPER(TRIM(J83))="PERU","PERÚ",UPPER(TRIM(J83))) -> PERÚ | X83: =UPPER(TRIM(H83)) -> FEMENINO | Y83: =UPPER(TRIM(K83)) -> LIMA | Z83: =UPPER(TRIM(P83)) -> LA LIBERTAD
A84: PARTIDO DEL BUEN GOBIERNO | B84: 76871362 | C84: MOLINA SOTO, NATHALY MILAGROS | D84: 76871362 | E84: MOLINA | F84: SOTO | G84: NATHALY MILAGROS | H84: FEMENINO | I84: 15/10/1996 | J84: PERÚ | K84: LIMA | L84: LIMA | M84: SAN JUAN DE LURIGANCHO | N84: DIPUTADO | P84: LIMA METROPOLITANA | R84: https://mpesije.jne.gob.pe/apidocs/85df76a1-f01a-4e24-8b72-a80dadb1ee0a.jpg | S84: https://mpesije.jne.gob.pe/apidocs/c709b840-8691-4d90-9c8d-3119423e76d8.pdf | T84: =CONCATENATE(A3361," - ",B3361,".pdf") -> - .pdf | U84: =IF(I84="","",DATEDIF(DATE(VALUE(RIGHT(I84,4)),VALUE(MID(I84,4,2)),VALUE(LEFT(I84,2))),TODAY(),"Y")) -> 29 | V84: =IF(U84="","",IF(U84<30,"18-29",IF(U84<40,"30-39",IF(U84<50,"40-49",IF(U84<60,"50-59","60+"))))) -> 18-29 | W84: =IF(UPPER(TRIM(J84))="PERU","PERÚ",UPPER(TRIM(J84))) -> PERÚ | X84: =UPPER(TRIM(H84)) -> FEMENINO | Y84: =UPPER(TRIM(K84)) -> LIMA | Z84: =UPPER(TRIM(P84)) -> LIMA METROPOLITANA
A85: PARTIDO DEL BUEN GOBIERNO | B85: 45741388 | C85: PRADO VALLEJOS, LILA MARIANELA | D85: 45741388 | E85: PRADO | F85: VALLEJOS | G85: LILA MARIANELA | H85: FEMENINO | I85: 12/05/1989 | J85: PERÚ | K85: ICA | L85: ICA | M85: ICA | N85: DIPUTADO | P85: ICA | Q85: Contadora pública colegiada | R85: https://mpesije.jne.gob.pe/apidocs/63bf2e32-eea7-4bc0-b6d0-2ab775ee4843.jpg | S85: https://mpesije.jne.gob.pe/apidocs/c78fdbbe-1fd7-43a2-97e1-58773c00f24e.pdf | T85: =CONCATENATE(A3403," - ",B3403,".pdf") -> - .pdf | U85: =IF(I85="","",DATEDIF(DATE(VALUE(RIGHT(I85,4)),VALUE(MID(I85,4,2)),VALUE(LEFT(I85,2))),TODAY(),"Y")) -> 37 | V85: =IF(U85="","",IF(U85<30,"18-29",IF(U85<40,"30-39",IF(U85<50,"40-49",IF(U85<60,"50-59","60+"))))) -> 30-39 | W85: =IF(UPPER(TRIM(J85))="PERU","PERÚ",UPPER(TRIM(J85))) -> PERÚ | X85: =UPPER(TRIM(H85)) -> FEMENINO | Y85: =UPPER(TRIM(K85)) -> ICA | Z85: =UPPER(TRIM(P85)) -> ICA
A86: PARTIDO DEL BUEN GOBIERNO | B86: 40067839 | C86: QUISPE CANDIA, LUIS ELISEO | D86: 40067839 | E86: QUISPE | F86: CANDIA | G86: LUIS ELISEO | H86: MASCULINO | I86: 18/08/1948 | J86: PERÚ | K86: CUSCO | L86: QUISPICANCHI | M86: QUIQUIJANA | N86: DIPUTADO | P86: LIMA METROPOLITANA | R86: https://mpesije.jne.gob.pe/apidocs/93bd1fb5-a0ee-4900-b08b-36a0071a8d02.jpg | S86: https://mpesije.jne.gob.pe/apidocs/e993201b-7cef-4a0f-a4eb-73252cf33ffc.pdf | T86: =CONCATENATE(A3407," - ",B3407,".pdf") -> - .pdf | U86: =IF(I86="","",DATEDIF(DATE(VALUE(RIGHT(I86,4)),VALUE(MID(I86,4,2)),VALUE(LEFT(I86,2))),TODAY(),"Y")) -> 77 | V86: =IF(U86="","",IF(U86<30,"18-29",IF(U86<40,"30-39",IF(U86<50,"40-49",IF(U86<60,"50-59","60+"))))) -> 60+ | W86: =IF(UPPER(TRIM(J86))="PERU","PERÚ",UPPER(TRIM(J86))) -> PERÚ | X86: =UPPER(TRIM(H86)) -> MASCULINO | Y86: =UPPER(TRIM(K86)) -> CUSCO | Z86: =UPPER(TRIM(P86)) -> LIMA METROPOLITANA
A87: PARTIDO DEL BUEN GOBIERNO | B87: 43348625 | C87: RETO OTERO, OSCAR DE JESUS | D87: 43348625 | E87: RETO | F87: OTERO | G87: OSCAR DE JESUS | H87: MASCULINO | I87: 28/04/1962 | J87: PERÚ | K87: TUMBES | L87: CONTRALMIRANTE VILLAR | M87: ZORRITOS | N87: DIPUTADO | P87: LIMA METROPOLITANA | R87: https://mpesije.jne.gob.pe/apidocs/bf8f66d1-eceb-4872-b784-b17b419d8f33.jpg | S87: https://mpesije.jne.gob.pe/apidocs/88c12820-5e45-42c4-ae0c-a4e70f54e695.pdf | T87: =CONCATENATE(A3418," - ",B3418,".pdf") -> - .pdf | U87: =IF(I87="","",DATEDIF(DATE(VALUE(RIGHT(I87,4)),VALUE(MID(I87,4,2)),VALUE(LEFT(I87,2))),TODAY(),"Y")) -> 64 | V87: =IF(U87="","",IF(U87<30,"18-29",IF(U87<40,"30-39",IF(U87<50,"40-49",IF(U87<60,"50-59","60+"))))) -> 60+ | W87: =IF(UPPER(TRIM(J87))="PERU","PERÚ",UPPER(TRIM(J87))) -> PERÚ | X87: =UPPER(TRIM(H87)) -> MASCULINO | Y87: =UPPER(TRIM(K87)) -> TUMBES | Z87: =UPPER(TRIM(P87)) -> LIMA METROPOLITANA
A88: RENOVACION POPULAR | B88: 70747151 | C88: ARANDA VASQUEZ, CHRISTIAN | D88: 70747151 | E88: ARANDA | F88: VASQUEZ | G88: CHRISTIAN | H88: MASCULINO | I88: 26/06/1991 | J88: PERÚ | K88: AREQUIPA | L88: AREQUIPA | M88: AREQUIPA | N88: DIPUTADO | P88: AREQUIPA | R88: https://mpesije.jne.gob.pe/apidocs/d70f438b-eda1-464c-8674-72cac0bacde7.jpg | S88: https://mpesije.jne.gob.pe/apidocs/20a3a65b-0460-4a06-bcee-505c19fcc859.pdf | T88: =CONCATENATE(A7760," - ",B7760,".pdf") -> - .pdf | U88: =IF(I88="","",DATEDIF(DATE(VALUE(RIGHT(I88,4)),VALUE(MID(I88,4,2)),VALUE(LEFT(I88,2))),TODAY(),"Y")) -> 34 | V88: =IF(U88="","",IF(U88<30,"18-29",IF(U88<40,"30-39",IF(U88<50,"40-49",IF(U88<60,"50-59","60+"))))) -> 30-39 | W88: =IF(UPPER(TRIM(J88))="PERU","PERÚ",UPPER(TRIM(J88))) -> PERÚ | X88: =UPPER(TRIM(H88)) -> MASCULINO | Y88: =UPPER(TRIM(K88)) -> AREQUIPA | Z88: =UPPER(TRIM(P88)) -> AREQUIPA
A89: RENOVACION POPULAR | B89: 09937296 | C89: BAELLA MALCA, JOSE ISIDRO | D89: 09937296 | E89: BAELLA | F89: MALCA | G89: JOSE ISIDRO | H89: MASCULINO | I89: 11/08/1960 | J89: PERÚ | K89: CALLAO | L89: CALLAO | M89: CALLAO | N89: DIPUTADO | P89: LIMA METROPOLITANA | R89: https://mpesije.jne.gob.pe/apidocs/40d1c4f0-80ca-4308-9956-39825342cc72.jpg | S89: https://mpesije.jne.gob.pe/apidocs/c5435b9e-d8c7-48d7-88f7-17de4e8128a3.pdf | T89: =CONCATENATE(A7768," - ",B7768,".pdf") -> - .pdf | U89: =IF(I89="","",DATEDIF(DATE(VALUE(RIGHT(I89,4)),VALUE(MID(I89,4,2)),VALUE(LEFT(I89,2))),TODAY(),"Y")) -> 65 | V89: =IF(U89="","",IF(U89<30,"18-29",IF(U89<40,"30-39",IF(U89<50,"40-49",IF(U89<60,"50-59","60+"))))) -> 60+ | W89: =IF(UPPER(TRIM(J89))="PERU","PERÚ",UPPER(TRIM(J89))) -> PERÚ | X89: =UPPER(TRIM(H89)) -> MASCULINO | Y89: =UPPER(TRIM(K89)) -> CALLAO | Z89: =UPPER(TRIM(P89)) -> LIMA METROPOLITANA
A90: RENOVACION POPULAR | B90: 46847115 | C90: BAZAN CALDERON, DIEGO ALONSO FERNANDO | D90: 46847115 | E90: BAZAN | F90: CALDERON | G90: DIEGO ALONSO FERNANDO | H90: MASCULINO | I90: 12/02/1991 | J90: PERÚ | K90: LA LIBERTAD | L90: TRUJILLO | M90: LAREDO | N90: DIPUTADO | P90: LA LIBERTAD | R90: https://mpesije.jne.gob.pe/apidocs/bff26ae0-3fe2-4ed8-9782-3b6450bdd88f.jpg | S90: https://mpesije.jne.gob.pe/apidocs/3aef188a-2b78-47e9-954a-7ce011e081a1.pdf | T90: =CONCATENATE(A7771," - ",B7771,".pdf") -> - .pdf | U90: =IF(I90="","",DATEDIF(DATE(VALUE(RIGHT(I90,4)),VALUE(MID(I90,4,2)),VALUE(LEFT(I90,2))),TODAY(),"Y")) -> 35 | V90: =IF(U90="","",IF(U90<30,"18-29",IF(U90<40,"30-39",IF(U90<50,"40-49",IF(U90<60,"50-59","60+"))))) -> 30-39 | W90: =IF(UPPER(TRIM(J90))="PERU","PERÚ",UPPER(TRIM(J90))) -> PERÚ | X90: =UPPER(TRIM(H90)) -> MASCULINO | Y90: =UPPER(TRIM(K90)) -> LA LIBERTAD | Z90: =UPPER(TRIM(P90)) -> LA LIBERTAD
A91: RENOVACION POPULAR | B91: 07974594 | C91: CHANG APUY, FELIX SEE HUNG | D91: 07974594 | E91: CHANG | F91: APUY | G91: FELIX SEE HUNG | H91: MASCULINO | I91: 10/11/1970 | J91: ESTADOS UNIDOS DE AMERICA | K91: HONOLULU | N91: DIPUTADO | P91: PIURA | R91: https://mpesije.jne.gob.pe/apidocs/eb0f38dd-1396-4901-94e7-b32e9c61a978.jpg | S91: https://mpesije.jne.gob.pe/apidocs/811824b7-1dc0-4038-8ec9-6bc810d66b63.pdf | T91: =CONCATENATE(A7796," - ",B7796,".pdf") -> - .pdf | U91: =IF(I91="","",DATEDIF(DATE(VALUE(RIGHT(I91,4)),VALUE(MID(I91,4,2)),VALUE(LEFT(I91,2))),TODAY(),"Y")) -> 55 | V91: =IF(U91="","",IF(U91<30,"18-29",IF(U91<40,"30-39",IF(U91<50,"40-49",IF(U91<60,"50-59","60+"))))) -> 50-59 | W91: =IF(UPPER(TRIM(J91))="PERU","PERÚ",UPPER(TRIM(J91))) -> ESTADOS UNIDOS DE AMERICA | X91: =UPPER(TRIM(H91)) -> MASCULINO | Y91: =UPPER(TRIM(K91)) -> HONOLULU | Z91: =UPPER(TRIM(P91)) -> PIURA
A92: RENOVACION POPULAR | B92: 07744156 | C92: CIPRIANI THORNE, JAVIER JOSE MARIA | D92: 07744156 | E92: CIPRIANI | F92: THORNE | G92: JAVIER JOSE MARIA | H92: MASCULINO | I92: 12/10/1955 | J92: PERÚ | K92: LIMA | L92: LIMA | M92: LINCE | N92: DIPUTADO | P92: LIMA METROPOLITANA | R92: https://mpesije.jne.gob.pe/apidocs/5c003520-8824-4be8-958c-b1df3c8f9a6b.jpg | S92: https://mpesije.jne.gob.pe/apidocs/50847803-d4db-4c55-83cf-c259cb9e73f7.pdf | T92: =CONCATENATE(A7804," - ",B7804,".pdf") -> - .pdf | U92: =IF(I92="","",DATEDIF(DATE(VALUE(RIGHT(I92,4)),VALUE(MID(I92,4,2)),VALUE(LEFT(I92,2))),TODAY(),"Y")) -> 70 | V92: =IF(U92="","",IF(U92<30,"18-29",IF(U92<40,"30-39",IF(U92<50,"40-49",IF(U92<60,"50-59","60+"))))) -> 60+ | W92: =IF(UPPER(TRIM(J92))="PERU","PERÚ",UPPER(TRIM(J92))) -> PERÚ | X92: =UPPER(TRIM(H92)) -> MASCULINO | Y92: =UPPER(TRIM(K92)) -> LIMA | Z92: =UPPER(TRIM(P92)) -> LIMA METROPOLITANA
A93: RENOVACION POPULAR | B93: 43401219 | C93: DE PAZ LANCHO, LEO MIGUEL | D93: 43401219 | E93: DE PAZ | F93: LANCHO | G93: LEO MIGUEL | H93: MASCULINO | I93: 01/03/1985 | J93: PERÚ | K93: LIMA | L93: CAÑETE | M93: SAN LUIS | N93: DIPUTADO | P93: LIMA METROPOLITANA | R93: https://mpesije.jne.gob.pe/apidocs/3c15f97e-30d2-4d67-9170-3e68af9281ce.jpg | S93: https://mpesije.jne.gob.pe/apidocs/c03536e0-392f-478d-9dfc-ef19c457f090.pdf | T93: =CONCATENATE(A7817," - ",B7817,".pdf") -> - .pdf | U93: =IF(I93="","",DATEDIF(DATE(VALUE(RIGHT(I93,4)),VALUE(MID(I93,4,2)),VALUE(LEFT(I93,2))),TODAY(),"Y")) -> 41 | V93: =IF(U93="","",IF(U93<30,"18-29",IF(U93<40,"30-39",IF(U93<50,"40-49",IF(U93<60,"50-59","60+"))))) -> 40-49 | W93: =IF(UPPER(TRIM(J93))="PERU","PERÚ",UPPER(TRIM(J93))) -> PERÚ | X93: =UPPER(TRIM(H93)) -> MASCULINO | Y93: =UPPER(TRIM(K93)) -> LIMA | Z93: =UPPER(TRIM(P93)) -> LIMA METROPOLITANA
A94: RENOVACION POPULAR | B94: 46548697 | C94: KRKLEC TORRES, FRANK | D94: 46548697 | E94: KRKLEC | F94: TORRES | G94: FRANK | H94: MASCULINO | I94: 12/07/1990 | J94: PERÚ | K94: LAMBAYEQUE | L94: CHICLAYO | M94: CHICLAYO | N94: DIPUTADO | P94: LIMA METROPOLITANA | R94: https://mpesije.jne.gob.pe/apidocs/45d1c562-f232-4b64-bc2c-6c8c0f0ba33a.jpg | S94: https://mpesije.jne.gob.pe/apidocs/8bcee026-27d0-4f75-a598-489ac1865236.pdf | T94: =CONCATENATE(A7866," - ",B7866,".pdf") -> - .pdf | U94: =IF(I94="","",DATEDIF(DATE(VALUE(RIGHT(I94,4)),VALUE(MID(I94,4,2)),VALUE(LEFT(I94,2))),TODAY(),"Y")) -> 35 | V94: =IF(U94="","",IF(U94<30,"18-29",IF(U94<40,"30-39",IF(U94<50,"40-49",IF(U94<60,"50-59","60+"))))) -> 30-39 | W94: =IF(UPPER(TRIM(J94))="PERU","PERÚ",UPPER(TRIM(J94))) -> PERÚ | X94: =UPPER(TRIM(H94)) -> MASCULINO | Y94: =UPPER(TRIM(K94)) -> LAMBAYEQUE | Z94: =UPPER(TRIM(P94)) -> LIMA METROPOLITANA
A95: RENOVACION POPULAR | B95: 45363882 | C95: MARTINEZ PAITAN, PAOLA ISABEL | D95: 45363882 | E95: MARTINEZ | F95: PAITAN | G95: PAOLA ISABEL | H95: FEMENINO | I95: 23/03/1988 | J95: PERÚ | K95: LIMA | L95: LIMA | M95: LIMA | N95: DIPUTADO | P95: LIMA METROPOLITANA | R95: https://mpesije.jne.gob.pe/apidocs/cb2c329e-da2f-4c05-8cbe-86dc48f97529.jpg | S95: https://mpesije.jne.gob.pe/apidocs/da6774e7-e804-4f18-9833-92a96dd8327c.pdf | T95: =CONCATENATE(A7884," - ",B7884,".pdf") -> - .pdf | U95: =IF(I95="","",DATEDIF(DATE(VALUE(RIGHT(I95,4)),VALUE(MID(I95,4,2)),VALUE(LEFT(I95,2))),TODAY(),"Y")) -> 38 | V95: =IF(U95="","",IF(U95<30,"18-29",IF(U95<40,"30-39",IF(U95<50,"40-49",IF(U95<60,"50-59","60+"))))) -> 30-39 | W95: =IF(UPPER(TRIM(J95))="PERU","PERÚ",UPPER(TRIM(J95))) -> PERÚ | X95: =UPPER(TRIM(H95)) -> FEMENINO | Y95: =UPPER(TRIM(K95)) -> LIMA | Z95: =UPPER(TRIM(P95)) -> LIMA METROPOLITANA
A96: RENOVACION POPULAR | B96: 10275564 | C96: ROCHA GALLEGOS, ROXANA MARIA | D96: 10275564 | E96: ROCHA | F96: GALLEGOS | G96: ROXANA MARIA | H96: FEMENINO | I96: 30/11/1964 | J96: PERÚ | K96: LIMA | L96: LIMA | M96: LINCE | N96: DIPUTADO | P96: LIMA METROPOLITANA | R96: https://mpesije.jne.gob.pe/apidocs/86b38aa1-2f58-4a5f-b0f9-4a7d8368659b.jpg | S96: https://mpesije.jne.gob.pe/apidocs/2694f248-1961-4fba-ad56-4e1ec8c7036d.pdf | T96: =CONCATENATE(A7951," - ",B7951,".pdf") -> - .pdf | U96: =IF(I96="","",DATEDIF(DATE(VALUE(RIGHT(I96,4)),VALUE(MID(I96,4,2)),VALUE(LEFT(I96,2))),TODAY(),"Y")) -> 61 | V96: =IF(U96="","",IF(U96<30,"18-29",IF(U96<40,"30-39",IF(U96<50,"40-49",IF(U96<60,"50-59","60+"))))) -> 60+ | W96: =IF(UPPER(TRIM(J96))="PERU","PERÚ",UPPER(TRIM(J96))) -> PERÚ | X96: =UPPER(TRIM(H96)) -> FEMENINO | Y96: =UPPER(TRIM(K96)) -> LIMA | Z96: =UPPER(TRIM(P96)) -> LIMA METROPOLITANA
A97: RENOVACION POPULAR | B97: 41010370 | C97: SEGURA FIGUEROA, GUSTAVO ALEXANDER | D97: 41010370 | E97: SEGURA | F97: FIGUEROA | G97: GUSTAVO ALEXANDER | H97: MASCULINO | I97: 26/02/1970 | J97: PERÚ | K97: LIMA | L97: LIMA | M97: JESUS MARIA | N97: DIPUTADO | P97: LIMA METROPOLITANA | R97: https://mpesije.jne.gob.pe/apidocs/e1aea3a3-5ab0-43e8-b91b-052215702d28.jpg | S97: https://mpesije.jne.gob.pe/apidocs/8bab1060-4b59-4554-8594-417e77642abc.pdf | T97: =CONCATENATE(A7963," - ",B7963,".pdf") -> - .pdf | U97: =IF(I97="","",DATEDIF(DATE(VALUE(RIGHT(I97,4)),VALUE(MID(I97,4,2)),VALUE(LEFT(I97,2))),TODAY(),"Y")) -> 56 | V97: =IF(U97="","",IF(U97<30,"18-29",IF(U97<40,"30-39",IF(U97<50,"40-49",IF(U97<60,"50-59","60+"))))) -> 50-59 | W97: =IF(UPPER(TRIM(J97))="PERU","PERÚ",UPPER(TRIM(J97))) -> PERÚ | X97: =UPPER(TRIM(H97)) -> MASCULINO | Y97: =UPPER(TRIM(K97)) -> LIMA | Z97: =UPPER(TRIM(P97)) -> LIMA METROPOLITANA
A98: RENOVACION POPULAR | B98: 08878867 | C98: YALTA SOTELO, CARLOS ALBERTO | D98: 08878867 | E98: YALTA | F98: SOTELO | G98: CARLOS ALBERTO | H98: MASCULINO | I98: 10/10/1970 | J98: PERÚ | K98: LIMA | L98: LIMA | M98: JESUS MARIA | N98: DIPUTADO | P98: CALLAO | R98: https://mpesije.jne.gob.pe/apidocs/1f3cf0a8-3e7e-4509-9b05-821faca27afa.jpg | S98: https://mpesije.jne.gob.pe/apidocs/9a572382-76b7-4e3a-b18c-42910b21e3a8.pdf | T98: =CONCATENATE(A8005," - ",B8005,".pdf") -> - .pdf | U98: =IF(I98="","",DATEDIF(DATE(VALUE(RIGHT(I98,4)),VALUE(MID(I98,4,2)),VALUE(LEFT(I98,2))),TODAY(),"Y")) -> 55 | V98: =IF(U98="","",IF(U98<30,"18-29",IF(U98<40,"30-39",IF(U98<50,"40-49",IF(U98<60,"50-59","60+"))))) -> 50-59 | W98: =IF(UPPER(TRIM(J98))="PERU","PERÚ",UPPER(TRIM(J98))) -> PERÚ | X98: =UPPER(TRIM(H98)) -> MASCULINO | Y98: =UPPER(TRIM(K98)) -> LIMA | Z98: =UPPER(TRIM(P98)) -> CALLAO
A99: RENOVACION POPULAR | B99: 10806296 | C99: YARROW LUMBRERAS, NORMA MARTINA | D99: 10806296 | E99: YARROW | F99: LUMBRERAS | G99: NORMA MARTINA | H99: FEMENINO | I99: 29/07/1963 | J99: PERÚ | K99: LAMBAYEQUE | L99: CHICLAYO | M99: CHICLAYO | N99: PRIMER VICEPRESIDENTE DE LA REPÚBLICA | O99: DIPUTADO | P99: LIMA METROPOLITANA | R99: https://mpesije.jne.gob.pe/apidocs/90b8a957-0b76-41a0-b2a0-62ad6e328327.jpg | S99: https://mpesije.jne.gob.pe/apidocs/36ac23b8-d38e-4adc-82dd-7d7482e07946.pdf | T99: =CONCATENATE(A8006," - ",B8006,".pdf") -> - .pdf | U99: =IF(I99="","",DATEDIF(DATE(VALUE(RIGHT(I99,4)),VALUE(MID(I99,4,2)),VALUE(LEFT(I99,2))),TODAY(),"Y")) -> 62 | V99: =IF(U99="","",IF(U99<30,"18-29",IF(U99<40,"30-39",IF(U99<50,"40-49",IF(U99<60,"50-59","60+"))))) -> 60+ | W99: =IF(UPPER(TRIM(J99))="PERU","PERÚ",UPPER(TRIM(J99))) -> PERÚ | X99: =UPPER(TRIM(H99)) -> FEMENINO | Y99: =UPPER(TRIM(K99)) -> LAMBAYEQUE | Z99: =UPPER(TRIM(P99)) -> LIMA METROPOLITANA
A100: RENOVACION POPULAR | B100: 44689086 | C100: YONZ NUÑEZ, MADY VERONICA | D100: 44689086 | E100: YONZ | F100: NUÑEZ | G100: MADY VERONICA | H100: FEMENINO | I100: 22/08/1987 | J100: PERÚ | K100: ICA | L100: ICA | M100: ICA | N100: DIPUTADO | P100: ICA | R100: https://mpesije.jne.gob.pe/apidocs/36da1705-188b-41bc-98e4-1c18c05612d5.jpg | S100: https://mpesije.jne.gob.pe/apidocs/68a4c40f-86ec-4607-ba75-3f4d641885b1.pdf | T100: =CONCATENATE(A8007," - ",B8007,".pdf") -> - .pdf | U100: =IF(I100="","",DATEDIF(DATE(VALUE(RIGHT(I100,4)),VALUE(MID(I100,4,2)),VALUE(LEFT(I100,2))),TODAY(),"Y")) -> 38 | V100: =IF(U100="","",IF(U100<30,"18-29",IF(U100<40,"30-39",IF(U100<50,"40-49",IF(U100<60,"50-59","60+"))))) -> 30-39 | W100: =IF(UPPER(TRIM(J100))="PERU","PERÚ",UPPER(TRIM(J100))) -> PERÚ | X100: =UPPER(TRIM(H100)) -> FEMENINO | Y100: =UPPER(TRIM(K100)) -> ICA | Z100: =UPPER(TRIM(P100)) -> ICA
...

Sheet RESUMEN_DP
A1: Total candidatos | B1: Mujeres | C1: Hombres | D1: Edad promedio | E1: Edad mediana | F1: Edad mínima | G1: Edad máxima
A2: =COUNTA('01 DATOS PERSONALES'!B2:B1000) -> 100 | B2: =COUNTIF('01 DATOS PERSONALES'!X2:Y1000,"FEMENINO") -> 39 | C2: =COUNTIF('01 DATOS PERSONALES'!X2:Y1000,"MASCULINO") -> 61 | D2: =AVERAGE('01 DATOS PERSONALES'!U2:U1000) -> 49.18 | E2: =MEDIAN('01 DATOS PERSONALES'!U2:U1000) -> 48 | F2: =MIN('01 DATOS PERSONALES'!U2:U1000) -> 29 | G2: =MAX('01 DATOS PERSONALES'!U2:U1000) -> 77

Sheet PIVOT_DP_ORG
F1: PARIDAD
F2: % mujeres | G2: % hombres
F3: =B3/D3 -> 0.22222222 | G3: =C3/D3 -> 0.77777778
F4: =B4/D4 -> 0.42424242 | G4: =C4/D4 -> 0.57575758
F5: =B5/D5 -> 0.47058824 | G5: =C5/D5 -> 0.52941176
F6: =B6/D6 -> 0.23076923 | G6: =C6/D6 -> 0.76923077
F7: =B7/D7 -> 0.57142857 | G7: =C7/D7 -> 0.42857143
F8: =B8/D8 -> 0.28571429 | G8: =C8/D8 -> 0.71428571

Sheet 02 EXPERIENCIA LABORAL
A1: ORGANIZACION_POLITICA | B1: DNI_CANDIDATO | C1: CANDIDATO | D1: TIENE_EXPERIENCIA_LABORAL | E1: CENTRO_TRABAJO | F1: PROFESION_OCUPACION | G1: RUC | H1: DIRECCION | I1: AÑO_DESDE | J1: AÑO_HASTA | K1: PAIS | L1: DEPARTAMENTO | M1: PROVINCIA | N1: DISTRITO | O1: INFORMACION_ADICIONAL | P1: TRABAJO_CONGRESO
A2: AHORA NACION - AN | B2: 29569533 | C2: ARMINTA VALENCIA, MARLENY BIBIANA | D2: SI | E2: Inversiones Plus EIRL | F2: Asesora Gerencial Externa | G2: 20498689877 | H2: MZA. F LOTE. 13 DPTO. 102 URB. LA ESPERANZA (COSTADO COLEGIO ESTELA MARIS) AREQUIPA - AREQUIPA - JOS | I2: 2018 | J2: 2022 | K2: PERU | L2: AREQUIPA | M2: AREQUIPA | N2: JOSE LUIS BUSTAMANTE Y RIVERO | P2: =IFERROR(__xludf.DUMMYFUNCTION("IF(REGEXMATCH(UPPER(E2),""CONGRESO""),1,0)"),0.0) -> 0
A3: AHORA NACION - AN | B3: 29569533 | C3: ARMINTA VALENCIA, MARLENY BIBIANA | D3: SI | E3: Gobierno Regional de Arequipa | F3: Consejera Regional de Arequipa | G3: 20498390570 | H3: Calle Bolívar N° 206 Cercado | I3: 2023 | J3: 2025 | K3: PERU | L3: AREQUIPA | M3: AREQUIPA | N3: AREQUIPA | P3: =IFERROR(__xludf.DUMMYFUNCTION("IF(REGEXMATCH(UPPER(E3),""CONGRESO""),1,0)"),0.0) -> 0
A4: AHORA NACION - AN | B4: 41618961 | C4: BUITRON MARTINEZ, FRESHMAN | D4: SI | E4: Servicios Falcons EIRL | F4: Gerente | G4: 20602115349 | H4: Av. Ramón Castilla N° 406 | I4: 2018 | J4: 2025 | K4: PERU | L4: AYACUCHO | M4: HUAMANGA | N4: SAN JUAN BAUTISTA | O4: Sigo laborando y registrado en la planilla de la institución hasta la actualidad en Servicios Falcons EIRL | P4: =IFERROR(__xludf.DUMMYFUNCTION("IF(REGEXMATCH(UPPER(E4),""CONGRESO""),1,0)"),0.0) -> 0
A5: AHORA NACION - AN | B5: 43592504 | C5: COLCHADO HUAMANI, HARVEY JULIO | D5: SI | E5: División de Investigaciones de Alta Complejidad (DIVIAC) | F5: Jefe de División | H5: Av. Pedro Venturo Nro 403 - Urb Higuereta | I5: 2023 | J5: 2024 | K5: PERU | L5: LIMA | M5: LIMA | N5: SANTIAGO DE SURCO | O5: Cargo desempeñado desde el 31 Oct 2023 hasta el 13 Abr 2024, dependiente de la DIRNIC PNP | P5: =IFERROR(__xludf.DUMMYFUNCTION("IF(REGEXMATCH(UPPER(E5),""CONGRESO""),1,0)"),0.0) -> 0
A6: AHORA NACION - AN | B6: 43592504 | C6: COLCHADO HUAMANI, HARVEY JULIO | D6: SI | E6: II MACREPOL Lambayeque | F6: Jefe de la Región Policial Lambayeque | H6: Av. José Balta - Complejo Policial 07 de Agosto | I6: 2021 | J6: 2022 | K6: PERU | L6: LAMBAYEQUE | M6: CHICLAYO | N6: CHICLAYO | O6: Mayo 2021 a Feb 2022 | P6: =IFERROR(__xludf.DUMMYFUNCTION("IF(REGEXMATCH(UPPER(E6),""CONGRESO""),1,0)"),0.0) -> 0
A7: AHORA NACION - AN | B7: 43592504 | C7: COLCHADO HUAMANI, HARVEY JULIO | D7: SI | E7: Dirección de Medioambiente - PNP | F7: Jefe de Secretaría | H7: Calle Rivero de Ustaris 251 | I7: 2022 | J7: 2022 | K7: PERU | L7: LIMA | M7: LIMA | N7: JESUS MARIA | O7: Cargo desempeñado desde febrero del 2022 a Julio del 2022, primero como Jefe de la División contra la Tala Ilegal y Protección de Recursos Naturales de la DIRMEAMB | P7: =IFERROR(__xludf.DUMMYFUNCTION("IF(REGEXMATCH(UPPER(E7),""CONGRESO""),1,0)"),0.0) -> 0
A8: AHORA NACION - AN | B8: 43592504 | C8: COLCHADO HUAMANI, HARVEY JULIO | D8: SI | E8: Observatorio del Delito y la Criminalidad - DIRNIC PNP | F8: Jefe de Unidad | H8: Plaza 30 de Agosto S/N, Urb. Corpac - MININTER | I8: 2024 | J8: 2024 | K8: PERU | L8: LIMA | M8: LIMA | N8: SAN ISIDRO | O8: Prestó servicios del 15 Abr al 31 Dic 2024 | P8: =IFERROR(__xludf.DUMMYFUNCTION("IF(REGEXMATCH(UPPER(E8),""CONGRESO""),1,0)"),0.0) -> 0
A9: AHORA NACION - AN | B9: 43592504 | C9: COLCHADO HUAMANI, HARVEY JULIO | D9: SI | E9: Dirección General de Inteligencia - MININTER | F9: Jefe de División de Búsqueda | H9: Casa de Seguridad (dir. reservada) | I9: 2022 | J9: 2023 | K9: PERU | L9: LIMA | M9: LIMA | N9: LIMA | O9: Con RM Nro. 903-2022 del 18JUL2022, fue designado como coordinador general del Equipo Especial de Apoyo al Equipo Especial de Fiscales Contra la Corrupción en el Poder - EFICCOP. | P9: =IFERROR(__xludf.DUMMYFUNCTION("IF(REGEXMATCH(UPPER(E9),""CONGRESO""),1,0)"),0.0) -> 0
A10: AHORA NACION - AN | B10: 43572794 | C10: HOLGUIN LOAIZA, CESAR AUGUSTO | D10: SI | E10: Universidad Andina del Cusco | F10: Docente | G10: 20177395227 | H10: Urb. Ingeniería Larapa Grande A-7, San Jerónimo | I10: 2023 | J10: 2024 | K10: PERU | L10: CUSCO | M10: CUSCO | N10: SAN JERONIMO | O10: Docente en la escuela profesional de economía | P10: =IFERROR(__xludf.DUMMYFUNCTION("IF(REGEXMATCH(UPPER(E10),""CONGRESO""),1,0)"),0.0) -> 0
A11: AHORA NACION - AN | B11: 43572794 | C11: HOLGUIN LOAIZA, CESAR AUGUSTO | D11: SI | E11: Ministerio de Economía y Finanzas | F11: Consultor / Inversión privada | G11: 20131370645 | H11: Jr. Lampa 594 | I11: 2021 | J11: 2022 | K11: PERU | L11: LIMA | M11: LIMA | N11: LIMA | O11: Temas: Políticas de Promoción de la Inversión Privada. | P11: =IFERROR(__xludf.DUMMYFUNCTION("IF(REGEXMATCH(UPPER(E11),""CONGRESO""),1,0)"),0.0) -> 0
A12: AHORA NACION - AN | B12: 43572794 | C12: HOLGUIN LOAIZA, CESAR AUGUSTO | D12: SI | E12: Consultoría Independiente | F12: Consultor / Inversión privada | H12: Av Grau 4-5 Apu Zarzuela Baja | I12: 2021 | J12: 2022 | K12: PERU | L12: CUSCO | M12: CUSCO | N12: CUSCO | O12: En los municipios distritales de OMACHA, CHALLABAMBA y VILLCABAMBA | P12: =IFERROR(__xludf.DUMMYFUNCTION("IF(REGEXMATCH(UPPER(E12),""CONGRESO""),1,0)"),0.0) -> 0
A13: AHORA NACION - AN | B13: 43572794 | C13: HOLGUIN LOAIZA, CESAR AUGUSTO | D13: SI | E13: Apu Millenium SAC | F13: Docente | G13: 20602298214 | H13: Av. La Cultura N° 1008 | I13: 2019 | J13: 2025 | K13: PERU | L13: CUSCO | M13: PARURO | N13: OMACHA | O13: Elaboración de material educativo. | P13: =IFERROR(__xludf.DUMMYFUNCTION("IF(REGEXMATCH(UPPER(E13),""CONGRESO""),1,0)"),0.0) -> 0
A14: AHORA NACION - AN | B14: 43572794 | C14: HOLGUIN LOAIZA, CESAR AUGUSTO | D14: SI | E14: Municipalidad Distrital de San Sebastián | F14: Consultor - Gestión Pública | G14: 20159308961 | H14: Plaza de Armas San Sebastián S/N | I14: 2023 | J14: 2023 | K14: PERU | L14: CUSCO | M14: CUSCO | N14: SAN SEBASTIAN | O14: Especialista en Gobernanza e infraestructura | P14: =IFERROR(__xludf.DUMMYFUNCTION("IF(REGEXMATCH(UPPER(E14),""CONGRESO""),1,0)"),0.0) -> 0
A15: AHORA NACION - AN | B15: 45218393 | C15: HUILCA FLORES, INDIRA ISABEL | D15: SI | E15: Asociación Pro Derechos Humanos | F15: Socióloga | H15: Calle Pachacutec 980 | I15: 2024 | J15: 2025 | K15: PERU | L15: LIMA | M15: LIMA | N15: JESUS MARIA | P15: =IFERROR(__xludf.DUMMYFUNCTION("IF(REGEXMATCH(UPPER(E15),""CONGRESO""),1,0)"),0.0) -> 0
A16: AHORA NACION - AN | B16: 45218393 | C16: HUILCA FLORES, INDIRA ISABEL | D16: SI | E16: Centro de la Mujer Peruana Flora Tristán | F16: Consultora Socióloga | H16: Parque Hernán Velarde N° 42 Lima | I16: 2025 | J16: 2025 | K16: PERU | L16: LIMA | M16: LIMA | N16: LIMA | P16: =IFERROR(__xludf.DUMMYFUNCTION("IF(REGEXMATCH(UPPER(E16),""CONGRESO""),1,0)"),0.0) -> 0
A17: AHORA NACION - AN | B17: 45218393 | C17: HUILCA FLORES, INDIRA ISABEL | D17: SI | E17: Servicios Educativos El Agustino SEA | F17: Sociologa | H17: Jr Renan Elias Olivera 249 | I17: 2025 | J17: 2025 | K17: PERU | L17: LIMA | M17: LIMA | N17: EL AGUSTINO | P17: =IFERROR(__xludf.DUMMYFUNCTION("IF(REGEXMATCH(UPPER(E17),""CONGRESO""),1,0)"),0.0) -> 0
A18: AHORA NACION - AN | B18: 45218393 | C18: HUILCA FLORES, INDIRA ISABEL | D18: SI | E18: Centro de Estudios y Promoción del Desarrollo Ciudadano - DESCO Ciudadano | F18: Consultora Sociologa | H18: Mz G Lt 10 Sector 2, Grupo 5, Villa el Salvador | I18: 2025 | J18: 2025 | K18: PERU | L18: LIMA | M18: LIMA | N18: VILLA EL SALVADOR | P18: =IFERROR(__xludf.DUMMYFUNCTION("IF(REGEXMATCH(UPPER(E18),""CONGRESO""),1,0)"),0.0) -> 0
A19: AHORA NACION - AN | B19: 45218393 | C19: HUILCA FLORES, INDIRA ISABEL | D19: SI | E19: Fundación Friedrich Egert | F19: Sociologa | H19: Av Camino Real No 492 | I19: 2025 | J19: 2025 | K19: PERU | L19: LIMA | M19: LIMA | N19: SAN ISIDRO | P19: =IFERROR(__xludf.DUMMYFUNCTION("IF(REGEXMATCH(UPPER(E19),""CONGRESO""),1,0)"),0.0) -> 0
A20: AHORA NACION - AN | B20: 70665764 | C20: MANRIQUE OLIVERA, BERNARDINO JAIR | D20: SI | E20: Tectopia Perú | F20: AI Developer | H20: Calle Berlin 438 | I20: 2023 | J20: 2025 | K20: PERU | L20: LIMA | M20: LIMA | N20: MIRAFLORES | P20: =IFERROR(__xludf.DUMMYFUNCTION("IF(REGEXMATCH(UPPER(E20),""CONGRESO""),1,0)"),0.0) -> 0
A21: AHORA NACION - AN | B21: 70665764 | C21: MANRIQUE OLIVERA, BERNARDINO JAIR | D21: SI | E21: Divelia SAC | F21: CEO & Digital Transformator | G21: 20607140686 | H21: Calle Berlin 438 | I21: 2020 | J21: 2024 | K21: PERU | L21: LIMA | M21: LIMA | N21: MIRAFLORES | P21: =IFERROR(__xludf.DUMMYFUNCTION("IF(REGEXMATCH(UPPER(E21),""CONGRESO""),1,0)"),0.0) -> 0
A22: AHORA NACION - AN | B22: 70665764 | C22: MANRIQUE OLIVERA, BERNARDINO JAIR | D22: SI | E22: INICTEL UNI | F22: Docente Blockchain | G22: 20514761826 | H22: Av San Luis 1771 | I22: 2023 | J22: 2023 | K22: PERU | L22: LIMA | M22: LIMA | N22: SAN BORJA | O22: Servicios por honorarios | P22: =IFERROR(__xludf.DUMMYFUNCTION("IF(REGEXMATCH(UPPER(E22),""CONGRESO""),1,0)"),0.0) -> 0
A23: AHORA NACION - AN | B23: 70665764 | C23: MANRIQUE OLIVERA, BERNARDINO JAIR | D23: SI | E23: Marina de Guerra del Perú | F23: Programador de Parámetros Meteorológicos | G23: 20153408191 | H23: Calle Roca 118 | I23: 2025 | J23: 2025 | K23: PERU | L23: CALLAO | M23: CALLAO | N23: CALLAO | O23: Prestación de servicios | P23: =IFERROR(__xludf.DUMMYFUNCTION("IF(REGEXMATCH(UPPER(E23),""CONGRESO""),1,0)"),0.0) -> 0
A24: AHORA NACION - AN | B24: 70665764 | C24: MANRIQUE OLIVERA, BERNARDINO JAIR | D24: SI | E24: Fdex Asesores SAC | F24: CEO & Full Stack Developer | G24: 20603216700 | H24: Blvd. Plaza Mantaro 102 | I24: 2018 | J24: 2020 | K24: PERU | L24: LIMA | M24: LIMA | N24: SAN MIGUEL | P24: =IFERROR(__xludf.DUMMYFUNCTION("IF(REGEXMATCH(UPPER(E24),""CONGRESO""),1,0)"),0.0) -> 0
A25: AHORA NACION - AN | B25: 41840094 | C25: MARCELO SALAZAR, JOSE MIGUEL | D25: SI | E25: Banco BBVA | F25: Gerente de Oficina | G25: 20100130204 | H25: Av. Republica de Panamá 3055 | I25: 2016 | J25: 2019 | K25: PERU | L25: LIMA | M25: LIMA | N25: SAN ISIDRO | P25: =IFERROR(__xludf.DUMMYFUNCTION("IF(REGEXMATCH(UPPER(E25),""CONGRESO""),1,0)"),0.0) -> 0
A26: AHORA NACION - AN | B26: 41840094 | C26: MARCELO SALAZAR, JOSE MIGUEL | D26: SI | E26: Autoridad de Transporte Urbano (ATU) | F26: Especialista económico Financiero | G26: 20604932964 | H26: Calle Jose Galvez N° 550 | I26: 2024 | J26: 2025 | K26: PERU | L26: LIMA | M26: LIMA | N26: MIRAFLORES | O26: Locador | P26: =IFERROR(__xludf.DUMMYFUNCTION("IF(REGEXMATCH(UPPER(E26),""CONGRESO""),1,0)"),0.0) -> 0
A27: AHORA NACION - AN | B27: 41840094 | C27: MARCELO SALAZAR, JOSE MIGUEL | D27: SI | E27: Municipalidad Metropolitana de Lima | F27: Especialista Económico Financiero | G27: 20131380951 | H27: Rufino Torrico 1778- Cercado de Lima | I27: 2025 | J27: 2025 | K27: PERU | L27: LIMA | M27: LIMA | N27: LIMA | O27: Locador. | P27: =IFERROR(__xludf.DUMMYFUNCTION("IF(REGEXMATCH(UPPER(E27),""CONGRESO""),1,0)"),0.0) -> 0
A28: AHORA NACION - AN | B28: 41840094 | C28: MARCELO SALAZAR, JOSE MIGUEL | D28: SI | E28: Municipalidad Distrital De San Marcos | F28: Gerente de Administración | G28: 20166544000 | H28: jiron progreso n° 332 | I28: 2021 | J28: 2022 | K28: PERU | L28: ANCASH | M28: HUARI | N28: SAN MARCOS | P28: =IFERROR(__xludf.DUMMYFUNCTION("IF(REGEXMATCH(UPPER(E28),""CONGRESO""),1,0)"),0.0) -> 0
A29: AHORA NACION - AN | B29: 42839004 | C29: MUEDAS BALBIESE, CESAR AUGUSTO | D29: SI | E29: Centro de Conciliación "Conciliación del Centro" | F29: Conciliador | H29: Jr. Julio C. Tello N° 766 | I29: 2024 | J29: 2025 | K29: PERU | L29: JUNIN | M29: HUANCAYO | N29: EL TAMBO | O29: Director y conciliador con especialización en familia. | P29: =IFERROR(__xludf.DUMMYFUNCTION("IF(REGEXMATCH(UPPER(E29),""CONGRESO""),1,0)"),0.0) -> 0
A30: AHORA NACION - AN | B30: 42839004 | C30: MUEDAS BALBIESE, CESAR AUGUSTO | D30: SI | E30: Inmobiliaria y Constructora Techo Seguro Perú EIRL | F30: Gerente - Titular | G30: 20610120301 | H30: Jr. Julio C. Tello 766 | I30: 2022 | J30: 2025 | K30: PERU | L30: JUNIN | M30: HUANCAYO | N30: EL TAMBO | P30: =IFERROR(__xludf.DUMMYFUNCTION("IF(REGEXMATCH(UPPER(E30),""CONGRESO""),1,0)"),0.0) -> 0
A31: AHORA NACION - AN | B31: 42839004 | C31: MUEDAS BALBIESE, CESAR AUGUSTO | D31: SI | E31: Radiodifusora Huancayo SAC | F31: Director - conductor | G31: 20112257994 | H31: Calle Real N° 577 Of. 403 | I31: 1998 | J31: 2025 | K31: PERU | L31: JUNIN | M31: HUANCAYO | N31: HUANCAYO | O31: Director y conductor del programa informativo Huancayo Noticias. | P31: =IFERROR(__xludf.DUMMYFUNCTION("IF(REGEXMATCH(UPPER(E31),""CONGRESO""),1,0)"),0.0) -> 0
A32: AHORA NACION - AN | B32: 42839004 | C32: MUEDAS BALBIESE, CESAR AUGUSTO | D32: SI | E32: Instituto de Investigación Peruana de Política Social y Derecho Constitucional | F32: Presidente- Fundador | G32: 20610233008 | H32: Jr. Julio C. Tello N° 766 | I32: 2022 | J32: 2025 | K32: PERU | L32: JUNIN | M32: HUANCAYO | N32: EL TAMBO | P32: =IFERROR(__xludf.DUMMYFUNCTION("IF(REGEXMATCH(UPPER(E32),""CONGRESO""),1,0)"),0.0) -> 0
A33: AHORA NACION - AN | B33: 46307918 | C33: SONCO VILLANUEVA, HELARD BLADIMIR | D33: SI | E33: Trabajador independiente | F33: Comerciante | H33: Interior del mercado Pedro Vilcapoza | I33: 2014 | J33: 2025 | K33: PERU | L33: PUNO | M33: SAN ROMAN | N33: JULIACA | O33: Puesto de venta N° 35 pabellón 3 de la sección carnes. | P33: =IFERROR(__xludf.DUMMYFUNCTION("IF(REGEXMATCH(UPPER(E33),""CONGRESO""),1,0)"),0.0) -> 0
A34: FUERZA POPULAR | B34: 09391698 | C34: ABENSUR PINASCO, JAIME AMERICO | D34: SI | E34: CONGRESO DE LA REPUBLICA | F34: ESPECIALISTA PARLAMENTARIO | G34: 20161749126 | H34: PLAZA BOLIVAR - AV. ABANCAY S/N | I34: 2004 | J34: 2025 | K34: PERU | L34: LIMA | M34: LIMA | N34: LIMA | O34: * DESDE 2004 HASTA 19-06-2025 *DIRECTOR GENERAL PARLAMENTARIO DEL CONGRESO DE LA REPÚBLICA ( 2023 - 2025) | P34: =IFERROR(__xludf.DUMMYFUNCTION("IF(REGEXMATCH(UPPER(E34),""CONGRESO""),1,0)"),1.0) -> 1
A35: FUERZA POPULAR | B35: 09391698 | C35: ABENSUR PINASCO, JAIME AMERICO | D35: SI | E35: CONGRESO DE LA REPUBLICA | F35: ASESOR PARLAMENTARIO | G35: 20161749126 | H35: PLAZA BOLÍVAR - AV.ABANCAY S/N | I35: 2025 | J35: 2025 | K35: PERU | L35: LIMA | M35: LIMA | N35: LIMA | O35: *DESDE 20-06-2025 HASTA LA ACTUALIDAD *ACTUALMENTE DIRECTOR GENERAL PARLAMENTARIO DEL CONGRESO DE LA REPUBLICA | P35: =IFERROR(__xludf.DUMMYFUNCTION("IF(REGEXMATCH(UPPER(E35),""CONGRESO""),1,0)"),1.0) -> 1
A36: FUERZA POPULAR | B36: 45382589 | C36: ALEGRIA GARCIA, LUIS ARTURO | D36: SI | E36: CONGRESO DE LA REPÚBLICA | F36: ASISTENTE NIVEL SA-2 EN EL DESPACHO DEL EX CONGRESISTA LUIS GALARRETA | G36: 20161749126 | H36: Jr. Azángaro 468 | I36: 2011 | J36: 2013 | K36: PERU | L36: LIMA | M36: LIMA | N36: LIMA | O36: desde el 28 de julio de 2011 hasta el 12 de agosto de 2013 en el cargo de Asistente Nivel SA-2 en el despacho del ex Congresista Luis Galarreta | P36: =IFERROR(__xludf.DUMMYFUNCTION("IF(REGEXMATCH(UPPER(E36),""CONGRESO""),1,0)"),1.0) -> 1
A37: FUERZA POPULAR | B37: 45382589 | C37: ALEGRIA GARCIA, LUIS ARTURO | D37: SI | E37: CONGRESO DE LA REPÚBLICA | F37: ASISTENTE NIVEL SA-2 EN EL DESPACHO DEL EX CONGRESISTA LUIS GALARRETA | G37: 20161749126 | H37: Jr. Azángaro 468 | I37: 2009 | J37: 2011 | K37: PERU | L37: LIMA | M37: LIMA | N37: LIMA | O37: desde el 3 de agosto de 2009 hasta el 26 de julio de 2011, en el cargo de asistente nivel SA-2, en el Despacho del ex Congresista Luis Fernando Galarreta Velarde. | P37: =IFERROR(__xludf.DUMMYFUNCTION("IF(REGEXMATCH(UPPER(E37),""CONGRESO""),1,0)"),1.0) -> 1
A38: FUERZA POPULAR | B38: 45382589 | C38: ALEGRIA GARCIA, LUIS ARTURO | D38: SI | E38: CONGRESO DE LA REPÚBLICA | F38: ASISTENTE NIVEL SA-2 y TÉCNICO NIVEL ST-6 EN EL DESPACHO DEL EX CONGRESISTA LUIS GALARRETA | H38: Jr. Azángaro 468 | I38: 2013 | J38: 2016 | K38: PERU | L38: LIMA | M38: LIMA | N38: LIMA | O38: desde el 28 de agosto de 2013 en el cargo de Asistente Nivel SA-2. A partir del 1 de julio de 2014 en el cargo de técnico nivel st-6 en el Despacho del ex Congresista Luis Galarreta, cesando el 26 de julio de 2016 | P38: =IFERROR(__xludf.DUMMYFUNCTION("IF(REGEXMATCH(UPPER(E38),""CONGRESO""),1,0)"),1.0) -> 1
A39: FUERZA POPULAR | B39: 45382589 | C39: ALEGRIA GARCIA, LUIS ARTURO | D39: SI | E39: CONGRESO DE LA REPÚBLICA | F39: TECNICO NIVEL ST-6 y ASESOR NIVEL SP-9 EN EL DESPACHO DEL EX CONGRESISTA LUIS GALARRETA | H39: Jr. Azángaro 468 | I39: 2016 | J39: 2020 | K39: PERU | L39: LIMA | M39: LIMA | N39: LIMA | O39: desde el 27 de julio de 2016 en el cargo de técnico nivel st-6 en el despacho del ex Congresista Luis Galarreta. A partir del 6 de octubre de 2016 en el cargo de asesor nivel sp-9 en el despacho del ex Congresista Luis Galarreta, cesando el 6 de agosto de 2018. desde el 29 de agosto de 2018 hasta el 15 de marzo de 2020 en el cargo de asesor nivel sp-9 en el despacho del ex congresista Luis Galarreta. | P39: =IFERROR(__xludf.DUMMYFUNCTION("IF(REGEXMATCH(UPPER(E39),""CONGRESO""),1,0)"),1.0) -> 1
A40: FUERZA POPULAR | B40: 45382589 | C40: ALEGRIA GARCIA, LUIS ARTURO | D40: SI | E40: CONGRESO DE LA REPÚBLICA | F40: CONGRESISTA | G40: 20161749126 | H40: Jr. Azángaro 468 | I40: 2021 | J40: 2025 | K40: PERU | L40: LIMA | M40: LIMA | N40: LIMA | O40: periodo 2021-2026 | P40: =IFERROR(__xludf.DUMMYFUNCTION("IF(REGEXMATCH(UPPER(E40),""CONGRESO""),1,0)"),1.0) -> 1
A41: FUERZA POPULAR | B41: 15984771 | C41: ANDRADE SALGUERO DE ALVAREZ, GLADYS GRISELDA | D41: SI | E41: Carofi Bienes Raíces EIRL | F41: Apoyo Administrativo | G41: 20504749097 | H41: Calle López de Zúñiga 527 | I41: 2024 | J41: 2024 | K41: PERU | L41: LIMA | M41: HUARAL | N41: CHANCAY | O41: Meses de setiembre a diciembre de 2024. | P41: =IFERROR(__xludf.DUMMYFUNCTION("IF(REGEXMATCH(UPPER(E41),""CONGRESO""),1,0)"),0.0) -> 0
A42: FUERZA POPULAR | B42: 15984771 | C42: ANDRADE SALGUERO DE ALVAREZ, GLADYS GRISELDA | D42: SI | E42: Trece SAC | F42: Apoyo Administrativo | H42: Calle Luis Felipe del Solar N 205 | I42: 2015 | J42: 2016 | K42: PERU | L42: LIMA | M42: HUARAL | N42: CHANCAY | P42: =IFERROR(__xludf.DUMMYFUNCTION("IF(REGEXMATCH(UPPER(E42),""CONGRESO""),1,0)"),0.0) -> 0
A43: FUERZA POPULAR | B43: 15984771 | C43: ANDRADE SALGUERO DE ALVAREZ, GLADYS GRISELDA | D43: SI | E43: Congreso de la República | F43: Congresista de la República | H43: Plaza Bolivar con AV. Abancay S/N | I43: 2016 | J43: 2020 | K43: PERU | L43: LIMA | M43: LIMA | N43: LIMA | P43: =IFERROR(__xludf.DUMMYFUNCTION("IF(REGEXMATCH(UPPER(E43),""CONGRESO""),1,0)"),1.0) -> 1
A44: FUERZA POPULAR | B44: 15984771 | C44: ANDRADE SALGUERO DE ALVAREZ, GLADYS GRISELDA | D44: SI | E44: Notaría Villavicencio | F44: Asistente Legal | H44: Av. Primero de Mayo N 160 | I44: 2022 | J44: 2023 | K44: PERU | L44: CALLAO | M44: CALLAO | N44: CARMEN DE LA LEGUA-REYNOSO | P44: =IFERROR(__xludf.DUMMYFUNCTION("IF(REGEXMATCH(UPPER(E44),""CONGRESO""),1,0)"),0.0) -> 0
A45: FUERZA POPULAR | B45: 15984771 | C45: ANDRADE SALGUERO DE ALVAREZ, GLADYS GRISELDA | D45: SI | E45: Carmen Rodriguez Figueroa | F45: Apoyo Administrativo | G45: 10159816261 | H45: Calle López de Zúñiga # 527 | I45: 2024 | J45: 2024 | K45: PERU | L45: LIMA | M45: HUARAL | N45: CHANCAY | O45: Se trabajo en los meses de febrero a marzo y de mayo a agosto de 2024 | P45: =IFERROR(__xludf.DUMMYFUNCTION("IF(REGEXMATCH(UPPER(E45),""CONGRESO""),1,0)"),0.0) -> 0
A46: FUERZA POPULAR | B46: 76030152 | C46: BARBARAN REYES, ROSANGELLA ANDREA | D46: SI | E46: OTASS | F46: APOYO ADM. EN GOBIERNO CORPORATIVO | H46: CALLE GERMÁN SCHEREIBER GULSMANCO 210 | I46: 2019 | J46: 2019 | K46: PERU | L46: LIMA | M46: LIMA | N46: LIMA | P46: =IFERROR(__xludf.DUMMYFUNCTION("IF(REGEXMATCH(UPPER(E46),""CONGRESO""),1,0)"),0.0) -> 0
A47: FUERZA POPULAR | B47: 76030152 | C47: BARBARAN REYES, ROSANGELLA ANDREA | D47: SI | E47: CONGRESO DE LA REPÚBLICA | F47: CONGRESISTA | H47: JIRÓN HUALLAGA 358 | I47: 2021 | J47: 2025 | K47: PERU | L47: LIMA | M47: LIMA | N47: LIMA | P47: =IFERROR(__xludf.DUMMYFUNCTION("IF(REGEXMATCH(UPPER(E47),""CONGRESO""),1,0)"),1.0) -> 1
A48: FUERZA POPULAR | B48: 76030152 | C48: BARBARAN REYES, ROSANGELLA ANDREA | D48: SI | E48: CONGRESO DE LA REPÚBLICA | F48: TÉCNICO | H48: JIRÓN HUALLAGA 358 | I48: 2017 | J48: 2019 | K48: PERU | L48: LIMA | M48: LIMA | N48: LIMA | P48: =IFERROR(__xludf.DUMMYFUNCTION("IF(REGEXMATCH(UPPER(E48),""CONGRESO""),1,0)"),1.0) -> 1
A49: FUERZA POPULAR | B49: 76030152 | C49: BARBARAN REYES, ROSANGELLA ANDREA | D49: SI | E49: EPS SEDA HUÁNUCO | F49: ASESORA | H49: JIRÓN DAMASO BEARÚN 545 | I49: 2019 | J49: 2020 | K49: PERU | L49: HUANUCO | M49: HUANUCO | N49: HUANUCO | P49: =IFERROR(__xludf.DUMMYFUNCTION("IF(REGEXMATCH(UPPER(E49),""CONGRESO""),1,0)"),0.0) -> 0
A50: FUERZA POPULAR | B50: 76030152 | C50: BARBARAN REYES, ROSANGELLA ANDREA | D50: SI | E50: CONGRESO DE LA REPÚBLICA | F50: TÉCNICO | H50: JIRÓN HUALLAGA 358 | I50: 2020 | J50: 2021 | K50: PERU | L50: LIMA | M50: LIMA | N50: LIMA | P50: =IFERROR(__xludf.DUMMYFUNCTION("IF(REGEXMATCH(UPPER(E50),""CONGRESO""),1,0)"),1.0) -> 1
A51: FUERZA POPULAR | B51: 22509175 | C51: BETETA RUBIN, KARINA JULIZA | D51: SI | E51: Congreso de la República | F51: Congresista | G51: 20161749126 | H51: AV. ABANCAY S/N PLAZA BOLIVAR | I51: 2016 | J51: 2020 | K51: PERU | L51: LIMA | M51: LIMA | N51: LIMA | O51: Fui elegida congresista por el periodo parlamentario 2016-2021; sin embargo, por el cierre inconstitucional del Parlamento el 30 de setiembre de 2019, mi periodo parlamentario se recortó hasta el 15 de marzo de 2020. | P51: =IFERROR(__xludf.DUMMYFUNCTION("IF(REGEXMATCH(UPPER(E51),""CONGRESO""),1,0)"),1.0) -> 1
A52: FUERZA POPULAR | B52: 22509175 | C52: BETETA RUBIN, KARINA JULIZA | D52: SI | E52: CONGRESO DE LA REPUBLICA | F52: FUNCIONARIA | G52: 20161749126 | H52: JIRON HUALLAGA 330 | I52: 2024 | J52: 2025 | K52: PERU | L52: LIMA | M52: LIMA | N52: LIMA | O52: JEFE DEL FONDO EDITORIAL | P52: =IFERROR(__xludf.DUMMYFUNCTION("IF(REGEXMATCH(UPPER(E52),""CONGRESO""),1,0)"),1.0) -> 1
A53: FUERZA POPULAR | B53: 22509175 | C53: BETETA RUBIN, KARINA JULIZA | D53: SI | E53: CONGRESO DE LA REPUBLICA | F53: FUNCIONARIA | G53: 20161749126 | H53: JIRON HUALLAGA 330 | I53: 2022 | J53: 2024 | K53: PERU | L53: LIMA | M53: LIMA | N53: LIMA | O53: JEFE DE LA OFICINA DE PARTICIPACIÓN CIUDADANA | P53: =IFERROR(__xludf.DUMMYFUNCTION("IF(REGEXMATCH(UPPER(E53),""CONGRESO""),1,0)"),1.0) -> 1
A54: FUERZA POPULAR | B54: 22509175 | C54: BETETA RUBIN, KARINA JULIZA | D54: SI | E54: CONGRESO DE LA REPÚBLICA | F54: FUNCIONARIA | G54: 20161749126 | H54: AV. ABANCAY S/N PLAZA BOLIVAR | I54: 2021 | J54: 2022 | K54: PERU | L54: LIMA | M54: LIMA | N54: LIMA | O54: ASESORA DE LA COMISIÓN DE FISCALIZACIÓN Y CONTRALORIA | P54: =IFERROR(__xludf.DUMMYFUNCTION("IF(REGEXMATCH(UPPER(E54),""CONGRESO""),1,0)"),1.0) -> 1
A55: FUERZA POPULAR | B55: 22509175 | C55: BETETA RUBIN, KARINA JULIZA | D55: SI | E55: CONGRESO DE LA REPÚBLICA | F55: FUNCIONARIA | G55: 20161749126 | H55: AV. ABANCAY S/N PLAZA BOLIVAR | I55: 2020 | J55: 2021 | K55: PERU | L55: LIMA | M55: LIMA | N55: LIMA | O55: ASESORA DE LA COMISIÓN DE INTELIGENCIA | P55: =IFERROR(__xludf.DUMMYFUNCTION("IF(REGEXMATCH(UPPER(E55),""CONGRESO""),1,0)"),1.0) -> 1
A56: FUERZA POPULAR | B56: 40224994 | C56: BOBADILLA GALINDO, ANGEL BRUNO | D56: SI | E56: Abogado independiente | F56: Abogado | G56: 10402249949 | H56: Lima | I56: 2021 | J56: 2024 | K56: PERU | L56: LIMA | M56: LIMA | N56: LIMA | O56: Labore en el sector público contratado con Orden de Servicio | P56: =IFERROR(__xludf.DUMMYFUNCTION("IF(REGEXMATCH(UPPER(E56),""CONGRESO""),1,0)"),0.0) -> 0
A57: FUERZA POPULAR | B57: 40224994 | C57: BOBADILLA GALINDO, ANGEL BRUNO | D57: SI | E57: Congreso de la República | F57: Asesor | G57: 20161749126 | H57: Pasaje Simón Rodriguez 615 - Cercado de Lima - Lima - Lima | I57: 2017 | J57: 2018 | K57: PERU | L57: LIMA | M57: LIMA | N57: LIMA | P57: =IFERROR(__xludf.DUMMYFUNCTION("IF(REGEXMATCH(UPPER(E57),""CONGRESO""),1,0)"),1.0) -> 1
A58: FUERZA POPULAR | B58: 40224994 | C58: BOBADILLA GALINDO, ANGEL BRUNO | D58: SI | E58: Universidad de San Martín de Porres | F58: Profesor | G58: 20138149022 | H58: Alameda del Corregidor 1865 - La Molina - Lima - Lima | I58: 2019 | J58: 2021 | K58: PERU | L58: LIMA | M58: LIMA | N58: LA MOLINA | P58: =IFERROR(__xludf.DUMMYFUNCTION("IF(REGEXMATCH(UPPER(E58),""CONGRESO""),1,0)"),0.0) -> 0
A59: FUERZA POPULAR | B59: 40224994 | C59: BOBADILLA GALINDO, ANGEL BRUNO | D59: SI | E59: Congreso de la República | F59: Profesional | G59: 20161749126 | H59: Pasaje Simón Rodriguez 615 | I59: 2018 | J59: 2020 | K59: PERU | L59: LIMA | M59: LIMA | N59: LIMA | P59: =IFERROR(__xludf.DUMMYFUNCTION("IF(REGEXMATCH(UPPER(E59),""CONGRESO""),1,0)"),1.0) -> 1
A60: FUERZA POPULAR | B60: 40224994 | C60: BOBADILLA GALINDO, ANGEL BRUNO | D60: SI | E60: Congreso de la República | F60: Profesional en el Servicio Parlamentario | G60: 20161749126 | H60: Pasaje Simón Rodriguez 615 | I60: 2025 | J60: 2025 | K60: PERU | L60: LIMA | M60: LIMA | N60: LIMA | O60: Hasta la actualidad | P60: =IFERROR(__xludf.DUMMYFUNCTION("IF(REGEXMATCH(UPPER(E60),""CONGRESO""),1,0)"),1.0) -> 1
A61: FUERZA POPULAR | B61: 44807108 | C61: CASTILLO RIVAS, EDUARDO ENRIQUE | D61: SI | E61: CONGRESO DE LA REPUBLICA | F61: TECNICO | G61: 20161749126 | H61: JR. HUALLAGA 358 | I61: 2016 | J61: 2019 | K61: PERU | L61: LIMA | M61: LIMA | N61: LIMA | P61: =IFERROR(__xludf.DUMMYFUNCTION("IF(REGEXMATCH(UPPER(E61),""CONGRESO""),1,0)"),1.0) -> 1
A62: FUERZA POPULAR | B62: 44807108 | C62: CASTILLO RIVAS, EDUARDO ENRIQUE | D62: SI | E62: CONGRESO DE LA REPUBLICA | F62: CONGRESISTA DE LA REPUBLICA | G62: 20161749126 | H62: JR. HUALLAGA 358 | I62: 2021 | J62: 2025 | K62: PERU | L62: LIMA | M62: LIMA | N62: LIMA | O62: CONGRESISTA HASTA LA ACTUALIDAD. ELEGIDO CONGRESISTA POR EL PERIODO 2021- 2026. | P62: =IFERROR(__xludf.DUMMYFUNCTION("IF(REGEXMATCH(UPPER(E62),""CONGRESO""),1,0)"),1.0) -> 1
A63: FUERZA POPULAR | B63: 44807108 | C63: CASTILLO RIVAS, EDUARDO ENRIQUE | D63: SI | E63: CONGRESO DE LA REPUBLICA | F63: AUXILIAR | G63: 20161749126 | H63: JR. HUALLAGA 358 | I63: 2020 | J63: 2021 | K63: PERU | L63: LIMA | M63: LIMA | N63: LIMA | P63: =IFERROR(__xludf.DUMMYFUNCTION("IF(REGEXMATCH(UPPER(E63),""CONGRESO""),1,0)"),1.0) -> 1
A64: FUERZA POPULAR | B64: 44807108 | C64: CASTILLO RIVAS, EDUARDO ENRIQUE | D64: SI | E64: CONGRESO DE LA REPUBLICA | F64: AUXILIAR | G64: 20161749126 | H64: JR. HUALLAGA 358 | I64: 2014 | J64: 2015 | K64: PERU | L64: LIMA | M64: LIMA | N64: LIMA | P64: =IFERROR(__xludf.DUMMYFUNCTION("IF(REGEXMATCH(UPPER(E64),""CONGRESO""),1,0)"),1.0) -> 1
A65: FUERZA POPULAR | B65: 16650849 | C65: CASTRO CRUZ, JAVIER ALEJANDRO | D65: SI | E65: TELEJAC SAC. | F65: COMUNICADOR | G65: 20612763519 | H65: SAN JOSÉ 759 OF. 049 | I65: 2024 | J65: 2025 | K65: PERU | L65: LAMBAYEQUE | M65: CHICLAYO | N65: CHICLAYO | O65: HASTA LA ACTUALIDAD | P65: =IFERROR(__xludf.DUMMYFUNCTION("IF(REGEXMATCH(UPPER(E65),""CONGRESO""),1,0)"),0.0) -> 0
A66: FUERZA POPULAR | B66: 16650849 | C66: CASTRO CRUZ, JAVIER ALEJANDRO | D66: SI | E66: ROSA DEL CARMEN TOCTO MONTALVO | F66: COMUNICADOR | G66: 10164919728 | H66: SAN JOSÉ 759 OF. 049 | I66: 2015 | J66: 2023 | K66: PERU | L66: LAMBAYEQUE | M66: CHICLAYO | N66: CHICLAYO | P66: =IFERROR(__xludf.DUMMYFUNCTION("IF(REGEXMATCH(UPPER(E66),""CONGRESO""),1,0)"),0.0) -> 0
A67: FUERZA POPULAR | B67: 10587515 | C67: CASTRO GRANDEZ, ROYSER | D67: SI | E67: NEGOCIACIONES TAFUR E.I.R.L. | F67: Asesor legal | G67: 20479749176 | H67: Jr. Amazonas 101 | I67: 2020 | J67: 2024 | K67: PERU | L67: AMAZONAS | M67: RODRIGUEZ DE MENDOZA | N67: SAN NICOLAS | P67: =IFERROR(__xludf.DUMMYFUNCTION("IF(REGEXMATCH(UPPER(E67),""CONGRESO""),1,0)"),0.0) -> 0
A68: FUERZA POPULAR | B68: 10587515 | C68: CASTRO GRANDEZ, ROYSER | D68: SI | E68: AMAZONAS COFFEE FRIENDS S.A.C. | F68: Asesor legal | G68: 20604498091 | H68: Av. Chachapoyas 3509 sector san luis | I68: 2024 | J68: 2024 | K68: PERU | L68: AMAZONAS | M68: UTCUBAMBA | N68: BAGUA GRANDE | P68: =IFERROR(__xludf.DUMMYFUNCTION("IF(REGEXMATCH(UPPER(E68),""CONGRESO""),1,0)"),0.0) -> 0
A69: FUERZA POPULAR | B69: 10587515 | C69: CASTRO GRANDEZ, ROYSER | D69: SI | E69: Estudio Contable K'PITAL E.I.R.L. | F69: Asesor legal | G69: 20607364771 | H69: Jr. Kuelap N.° 131 | I69: 2024 | J69: 2025 | K69: PERU | L69: AMAZONAS | M69: CHACHAPOYAS | N69: CHACHAPOYAS | O69: Hasta la actualidad. | P69: =IFERROR(__xludf.DUMMYFUNCTION("IF(REGEXMATCH(UPPER(E69),""CONGRESO""),1,0)"),0.0) -> 0
A70: FUERZA POPULAR | B70: 10587515 | C70: CASTRO GRANDEZ, ROYSER | D70: SI | E70: Estudio jurídico contable CRECECONT'S E. I. R. L. | F70: Asesor legal | G70: 20610688404 | H70: Jr. Kuelap N.° 135 | I70: 2024 | J70: 2025 | K70: PERU | L70: AMAZONAS | M70: CHACHAPOYAS | N70: CHACHAPOYAS | O70: Hasta la actualidad. | P70: =IFERROR(__xludf.DUMMYFUNCTION("IF(REGEXMATCH(UPPER(E70),""CONGRESO""),1,0)"),0.0) -> 0
A71: FUERZA POPULAR | B71: 07750373 | C71: CELIZ CASTILLO, RAFAEL ALDO | D71: SI | E71: Congreso de la República | F71: Especialista | H71: Av. Abancay cuadra 2 S/N | I71: 2019 | J71: 2019 | K71: PERU | L71: LIMA | M71: LIMA | N71: LIMA | O71: Especialista del Área de Despacho Parlamentario. | P71: =IFERROR(__xludf.DUMMYFUNCTION("IF(REGEXMATCH(UPPER(E71),""CONGRESO""),1,0)"),1.0) -> 1
A72: FUERZA POPULAR | B72: 07750373 | C72: CELIZ CASTILLO, RAFAEL ALDO | D72: SI | E72: Congreso de la República | F72: Profesional | H72: Av. Abancay cuadra 2 S/N | I72: 2022 | J72: 2025 | K72: PERU | L72: LIMA | M72: LIMA | N72: LIMA | O72: Centro de Estudios Constitucionales y Parlamentarios. Actualmente viene ejerciendo funciones. | P72: =IFERROR(__xludf.DUMMYFUNCTION("IF(REGEXMATCH(UPPER(E72),""CONGRESO""),1,0)"),1.0) -> 1
A73: FUERZA POPULAR | B73: 07750373 | C73: CELIZ CASTILLO, RAFAEL ALDO | D73: SI | E73: Congreso de la República | F73: Profesional | H73: Av. Abancay cuadra 2 S/N | I73: 2022 | J73: 2022 | K73: PERU | L73: LIMA | M73: LIMA | N73: LIMA | O73: Fondo Editorial del Congreso de la República. | P73: =IFERROR(__xludf.DUMMYFUNCTION("IF(REGEXMATCH(UPPER(E73),""CONGRESO""),1,0)"),1.0) -> 1
A74: FUERZA POPULAR | B74: 07750373 | C74: CELIZ CASTILLO, RAFAEL ALDO | D74: SI | E74: Congreso de la República | F74: Asesor | H74: Av. Abancay cuadra 2 S/N | I74: 2021 | J74: 2022 | K74: PERU | L74: LIMA | M74: LIMA | N74: LIMA | O74: Asesor I del Despacho del congresista Arturo Alegría. | P74: =IFERROR(__xludf.DUMMYFUNCTION("IF(REGEXMATCH(UPPER(E74),""CONGRESO""),1,0)"),1.0) -> 1
A75: FUERZA POPULAR | B75: 07750373 | C75: CELIZ CASTILLO, RAFAEL ALDO | D75: SI | E75: Congreso de la República | F75: Asesor | H75: Av. Abancay cuadra 2 S/N | I75: 2020 | J75: 2021 | K75: PERU | L75: LIMA | M75: LIMA | N75: LIMA | O75: Asesor II del Despacho del congresista Erwin Tito. | P75: =IFERROR(__xludf.DUMMYFUNCTION("IF(REGEXMATCH(UPPER(E75),""CONGRESO""),1,0)"),1.0) -> 1
A76: FUERZA POPULAR | B76: 09536896 | C76: CHACON DE VETTORI, CECILIA ISABEL | D76: SI | E76: MINKAMAR S.A.C | F76: ADMINISTRADORA | G76: 20604844593 | H76: CALLE ARICA 171 URBANIZACIÓN SURQUILLO | I76: 2019 | J76: 2025 | K76: PERU | L76: LIMA | M76: LIMA | N76: MIRAFLORES | O76: HASTA LA ACTUALIDAD | P76: =IFERROR(__xludf.DUMMYFUNCTION("IF(REGEXMATCH(UPPER(E76),""CONGRESO""),1,0)"),0.0) -> 0
A77: FUERZA POPULAR | B77: 09536896 | C77: CHACON DE VETTORI, CECILIA ISABEL | D77: SI | E77: MARSALA SAC | F77: GESTIÓN DE MARKETING | G77: 20604652201 | H77: AV. MIGUEL DASSO 160 INT. 801 | I77: 2024 | J77: 2025 | K77: PERU | L77: LIMA | M77: LIMA | N77: SAN ISIDRO | O77: HASTA LA ACTUALIDAD. | P77: =IFERROR(__xludf.DUMMYFUNCTION("IF(REGEXMATCH(UPPER(E77),""CONGRESO""),1,0)"),0.0) -> 0
A78: FUERZA POPULAR | B78: 09536896 | C78: CHACON DE VETTORI, CECILIA ISABEL | D78: SI | E78: CONGRESO DE LA REPUBLICA | F78: CONGRESISTA | G78: 20161749126 | H78: AV. HUALLAGA 358 | I78: 2006 | J78: 2019 | K78: PERU | L78: LIMA | M78: LIMA | N78: LIMA | P78: =IFERROR(__xludf.DUMMYFUNCTION("IF(REGEXMATCH(UPPER(E78),""CONGRESO""),1,0)"),1.0) -> 1
A79: FUERZA POPULAR | B79: 09536896 | C79: CHACON DE VETTORI, CECILIA ISABEL | D79: SI | E79: DIMOL S.A.C | F79: GERENTE GENERAL | G79: 20605048057 | H79: CALLE 2 DE MAYO 701 - URB. SURQUILLO | I79: 2024 | J79: 2025 | K79: PERU | L79: LIMA | M79: LIMA | N79: MIRAFLORES | O79: HASTA LA ACTUALIDAD | P79: =IFERROR(__xludf.DUMMYFUNCTION("IF(REGEXMATCH(UPPER(E79),""CONGRESO""),1,0)"),0.0) -> 0
A80: FUERZA POPULAR | B80: 40826681 | C80: COLUMBUS MURATA, DIETHELL | D80: SI | E80: CONGRESO DE LA REPÚBLICA | F80: ASESOR DE GRUPO PARLAMENTARIO FP | H80: AV. ABANCAY S/N PLAZA BOLIVAR | I80: 2025 | J80: 2025 | K80: PERU | L80: LIMA | M80: LIMA | N80: LIMA | O80: HASTA LA ACTUALIDAD | P80: =IFERROR(__xludf.DUMMYFUNCTION("IF(REGEXMATCH(UPPER(E80),""CONGRESO""),1,0)"),1.0) -> 1
A81: FUERZA POPULAR | B81: 40826681 | C81: COLUMBUS MURATA, DIETHELL | D81: SI | E81: FACULTAD DE DERECHO USMP | F81: DOCENTE | H81: ALAMEDA DEL CORREGIDOR 1865 - LA MOLINA | I81: 2016 | J81: 2025 | K81: PERU | L81: LIMA | M81: LIMA | N81: LA MOLINA | P81: =IFERROR(__xludf.DUMMYFUNCTION("IF(REGEXMATCH(UPPER(E81),""CONGRESO""),1,0)"),0.0) -> 0
A82: FUERZA POPULAR | B82: 40826681 | C82: COLUMBUS MURATA, DIETHELL | D82: SI | E82: CONGRESO DE LA REPUBLICA | F82: ASESOR | H82: AV. ABANCAY S/N - PLAZA BOLIVAR | I82: 2021 | J82: 2024 | K82: PERU | L82: LIMA | M82: LIMA | N82: LIMA | P82: =IFERROR(__xludf.DUMMYFUNCTION("IF(REGEXMATCH(UPPER(E82),""CONGRESO""),1,0)"),1.0) -> 1
A83: FUERZA POPULAR | B83: 40826681 | C83: COLUMBUS MURATA, DIETHELL | D83: SI | E83: CONGRESO DE LA REPÚBLICA | F83: CONGRESISTA | H83: AV. ABANCAY S/N PLAZA BOLIVAR | I83: 2020 | J83: 2021 | K83: PERU | L83: LIMA | M83: LIMA | N83: LIMA | P83: =IFERROR(__xludf.DUMMYFUNCTION("IF(REGEXMATCH(UPPER(E83),""CONGRESO""),1,0)"),1.0) -> 1
A84: FUERZA POPULAR | B84: 40826681 | C84: COLUMBUS MURATA, DIETHELL | D84: SI | E84: CONGRESO DE LA REPÚBLICA | F84: JEFE DE DEPARTAMENTO | H84: AV. ABANCAY S/N PLAZA BOLIVAR | I84: 2024 | J84: 2025 | K84: PERU | L84: LIMA | M84: LIMA | N84: LIMA | P84: =IFERROR(__xludf.DUMMYFUNCTION("IF(REGEXMATCH(UPPER(E84),""CONGRESO""),1,0)"),1.0) -> 1
A85: FUERZA POPULAR | B85: 42433830 | C85: DODERO JOVICH, PIERANGELI DANIELA | D85: SI | E85: AVIANCA PERÚ S.A. | F85: TRIPULANTE DE CABINA | H85: CALLE CORPAC 152, FUNDO BOCANEGRA, CALLAO | I85: 2010 | J85: 2020 | K85: PERU | L85: CALLAO | M85: CALLAO | N85: CALLAO | P85: =IFERROR(__xludf.DUMMYFUNCTION("IF(REGEXMATCH(UPPER(E85),""CONGRESO""),1,0)"),0.0) -> 0
A86: FUERZA POPULAR | B86: 42433830 | C86: DODERO JOVICH, PIERANGELI DANIELA | D86: SI | E86: PD PRODUCTORA E.I.R.L. | F86: GERENTE GENERAL | H86: AV. 28 DE JULIO 345, DPTO. 1004C, MIRAFLORES | I86: 2022 | J86: 2025 | K86: PERU | L86: LIMA | M86: LIMA | N86: MIRAFLORES | P86: =IFERROR(__xludf.DUMMYFUNCTION("IF(REGEXMATCH(UPPER(E86),""CONGRESO""),1,0)"),0.0) -> 0
A87: FUERZA POPULAR | B87: 07268767 | C87: FIGARI MENDOZA, PIER PAOLO | D87: SI | E87: INMOBILIARIA E INVERSIONES RB S.A.C | F87: ASESOR LEGAL | H87: AV. TOMAS MARSANO N° 1981 DPTO 301 | I87: 2022 | J87: 2025 | K87: PERU | L87: LIMA | M87: LIMA | N87: SURQUILLO | O87: ACTUALMENTE | P87: =IFERROR(__xludf.DUMMYFUNCTION("IF(REGEXMATCH(UPPER(E87),""CONGRESO""),1,0)"),0.0) -> 0
A88: FUERZA POPULAR | B88: 07268767 | C88: FIGARI MENDOZA, PIER PAOLO | D88: SI | E88: UNIVERSIDAD PRIVADA DE HUANCAYO FRANKLIN ROOSEVELT S.A.C | F88: ASESOR EXTERNO | H88: AV. GIRÁLDEZ 542 | I88: 2024 | J88: 2024 | K88: PERU | L88: JUNIN | M88: HUANCAYO | N88: HUANCAYO | P88: =IFERROR(__xludf.DUMMYFUNCTION("IF(REGEXMATCH(UPPER(E88),""CONGRESO""),1,0)"),0.0) -> 0
A89: FUERZA POPULAR | B89: 07268767 | C89: FIGARI MENDOZA, PIER PAOLO | D89: SI | E89: FUERZA POPULAR | F89: ASESOR | H89: AV. 9 DE DICIEMBRE 422 | I89: 2015 | J89: 2021 | K89: PERU | L89: LIMA | M89: LIMA | N89: LIMA | P89: =IFERROR(__xludf.DUMMYFUNCTION("IF(REGEXMATCH(UPPER(E89),""CONGRESO""),1,0)"),0.0) -> 0
A90: FUERZA POPULAR | B90: 07268767 | C90: FIGARI MENDOZA, PIER PAOLO | D90: SI | E90: ALIEM PERU S.A.C | F90: ASESOR COMERCIAL | H90: AV. JACARANDA MZ. K LT. 9 -A | I90: 2023 | J90: 2025 | K90: PERU | L90: LIMA | M90: LIMA | N90: SAN JUAN DE LURIGANCHO | O90: ACTUALMENTE | P90: =IFERROR(__xludf.DUMMYFUNCTION("IF(REGEXMATCH(UPPER(E90),""CONGRESO""),1,0)"),0.0) -> 0
A91: FUERZA POPULAR | B91: 42516751 | C91: GAMARRA PITA, LUZMILA MARIA DEL CARMEN | D91: SI | E91: SERVICIOS GENERALES JACKSON SAC | F91: ADMINISTRADOR | H91: AV. CIRCUNVALACIÓN 415 | I91: 2017 | J91: 2025 | K91: PERU | L91: LIMA | M91: LIMA | N91: SANTIAGO DE SURCO | P91: =IFERROR(__xludf.DUMMYFUNCTION("IF(REGEXMATCH(UPPER(E91),""CONGRESO""),1,0)"),0.0) -> 0
A92: FUERZA POPULAR | B92: 16448130 | C92: INFANTES CASTAÑEDA, MERY ELIANA | D92: SI | E92: Botica Mery E. I. R. L. | F92: Obstetriz | G92: 20480791992 | H92: Av. Chachapoyas 2218 | I92: 2001 | J92: 2021 | K92: PERU | L92: AMAZONAS | M92: UTCUBAMBA | N92: BAGUA GRANDE | P92: =IFERROR(__xludf.DUMMYFUNCTION("IF(REGEXMATCH(UPPER(E92),""CONGRESO""),1,0)"),0.0) -> 0
A93: FUERZA POPULAR | B93: 16448130 | C93: INFANTES CASTAÑEDA, MERY ELIANA | D93: SI | E93: Congreso de la República del Perú | F93: Congresista | G93: 20161749126 | H93: Jr. Huallaga 358 | I93: 2021 | J93: 2025 | K93: PERU | L93: LIMA | M93: LIMA | N93: LIMA | P93: =IFERROR(__xludf.DUMMYFUNCTION("IF(REGEXMATCH(UPPER(E93),""CONGRESO""),1,0)"),1.0) -> 1
A94: FUERZA POPULAR | B94: 41919665 | C94: LEIVA BAYLON, LETICIA MARUJA | D94: SI | E94: CAFÉ DEL MUSEO | F94: ASISTENTE | G94: 20513257610 | H94: AV. BOLIVAR N°1515 | I94: 2010 | J94: 2013 | K94: PERU | L94: LIMA | M94: LIMA | N94: PUEBLO LIBRE | P94: =IFERROR(__xludf.DUMMYFUNCTION("IF(REGEXMATCH(UPPER(E94),""CONGRESO""),1,0)"),0.0) -> 0
A95: FUERZA POPULAR | B95: 41919665 | C95: LEIVA BAYLON, LETICIA MARUJA | D95: SI | E95: CONGRESO DE LA REPÚBLICA | F95: TÉCNICO | G95: 20161749126 | H95: AV. ABANCAY S/N | I95: 2021 | J95: 2025 | K95: PERU | L95: LIMA | M95: LIMA | N95: LIMA | P95: =IFERROR(__xludf.DUMMYFUNCTION("IF(REGEXMATCH(UPPER(E95),""CONGRESO""),1,0)"),1.0) -> 1
A96: FUERZA POPULAR | B96: 41919665 | C96: LEIVA BAYLON, LETICIA MARUJA | D96: SI | E96: CONGRESO DE LA REPÚBLICA | F96: ASESOR | G96: 20161749126 | H96: AV. ABANCAY S/N | I96: 2025 | J96: 2025 | K96: PERU | L96: LIMA | M96: LIMA | N96: LIMA | O96: Viene desempeñando funciones hasta la actualidad | P96: =IFERROR(__xludf.DUMMYFUNCTION("IF(REGEXMATCH(UPPER(E96),""CONGRESO""),1,0)"),1.0) -> 1
A97: FUERZA POPULAR | B97: 41919665 | C97: LEIVA BAYLON, LETICIA MARUJA | D97: SI | E97: FUERZA POPULAR | F97: AUXILIAR | G97: 20535603261 | H97: PARQUE HERNAN VELARDE NRO. 38, SANTA BEATRIZ | I97: 2016 | J97: 2018 | K97: PERU | L97: LIMA | M97: LIMA | N97: LIMA | P97: =IFERROR(__xludf.DUMMYFUNCTION("IF(REGEXMATCH(UPPER(E97),""CONGRESO""),1,0)"),0.0) -> 0
A98: FUERZA POPULAR | B98: 41919665 | C98: LEIVA BAYLON, LETICIA MARUJA | D98: SI | E98: FUERZA POPULAR | F98: ADMINISTRADORA | G98: 20535603261 | H98: PQ. PARQUE HERNAN VELARDE NRO. 38 | I98: 2018 | J98: 2021 | K98: PERU | L98: LIMA | M98: LIMA | N98: LIMA | P98: =IFERROR(__xludf.DUMMYFUNCTION("IF(REGEXMATCH(UPPER(E98),""CONGRESO""),1,0)"),0.0) -> 0
A99: FUERZA POPULAR | B99: 10187011 | C99: MENDOZA BERNEDO, LIZ HULI | D99: SI | E99: EXPERTOS EN ODONTOLOGÍA, IMPLANTOLOGIA Y ORTODONCIA SLP. | F99: ODONTÓLOGA | H99: CALLE CLARA JANES 9 LOCAL | I99: 2013 | J99: 2019 | K99: ESPANA | O99: RUC EMPRESA B87687422 DIRECCIÓN: LEGANES/ MADRID/ ESPAÑA | P99: =IFERROR(__xludf.DUMMYFUNCTION("IF(REGEXMATCH(UPPER(E99),""CONGRESO""),1,0)"),0.0) -> 0
A100: FUERZA POPULAR | B100: 10187011 | C100: MENDOZA BERNEDO, LIZ HULI | D100: SI | E100: CENTRO DE ESPECIALIDADES DENTALES Y DE SALUD S.L. | F100: ODONTÓLOGA | H100: AVENIDA REINA SOFIA 14 LOCAL | I100: 2019 | J100: 2025 | K100: ESPANA | O100: RUC EMPRESA B88324447 DIRECCIÓN: LEGANES / MADRID/ESPAÑA | P100: =IFERROR(__xludf.DUMMYFUNCTION("IF(REGEXMATCH(UPPER(E100),""CONGRESO""),1,0)"),0.0) -> 0
...

Sheet PIVOT_EXPERIENCIA
A1: DNI_CANDIDATO | B1: TRABAJO ALGUNA VEZ EN CONGRESO | C1: REGISTROS CONGRESO
A2: {=UNIQUE('02 EXPERIENCIA LABORAL'!B2:B1000)} -> 29569533 | B2: =IF(SUMIF('02 EXPERIENCIA LABORAL'!B:B,A2,'02 EXPERIENCIA LABORAL'!P:P)>0,1,0) -> 0 | C2: =SUMIF('02 EXPERIENCIA LABORAL'!B:B,A2,'02 EXPERIENCIA LABORAL'!P:P) -> 0
A3: 41618961 | B3: =IF(SUMIF('02 EXPERIENCIA LABORAL'!B:B,A3,'02 EXPERIENCIA LABORAL'!P:P)>0,1,0) -> 0 | C3: =SUMIF('02 EXPERIENCIA LABORAL'!B:B,A3,'02 EXPERIENCIA LABORAL'!P:P) -> 0
A4: 43592504 | B4: =IF(SUMIF('02 EXPERIENCIA LABORAL'!B:B,A4,'02 EXPERIENCIA LABORAL'!P:P)>0,1,0) -> 0 | C4: =SUMIF('02 EXPERIENCIA LABORAL'!B:B,A4,'02 EXPERIENCIA LABORAL'!P:P) -> 0
A5: 43572794 | B5: =IF(SUMIF('02 EXPERIENCIA LABORAL'!B:B,A5,'02 EXPERIENCIA LABORAL'!P:P)>0,1,0) -> 0 | C5: =SUMIF('02 EXPERIENCIA LABORAL'!B:B,A5,'02 EXPERIENCIA LABORAL'!P:P) -> 0
A6: 45218393 | B6: =IF(SUMIF('02 EXPERIENCIA LABORAL'!B:B,A6,'02 EXPERIENCIA LABORAL'!P:P)>0,1,0) -> 0 | C6: =SUMIF('02 EXPERIENCIA LABORAL'!B:B,A6,'02 EXPERIENCIA LABORAL'!P:P) -> 0
A7: 70665764 | B7: =IF(SUMIF('02 EXPERIENCIA LABORAL'!B:B,A7,'02 EXPERIENCIA LABORAL'!P:P)>0,1,0) -> 0 | C7: =SUMIF('02 EXPERIENCIA LABORAL'!B:B,A7,'02 EXPERIENCIA LABORAL'!P:P) -> 0
A8: 41840094 | B8: =IF(SUMIF('02 EXPERIENCIA LABORAL'!B:B,A8,'02 EXPERIENCIA LABORAL'!P:P)>0,1,0) -> 0 | C8: =SUMIF('02 EXPERIENCIA LABORAL'!B:B,A8,'02 EXPERIENCIA LABORAL'!P:P) -> 0
A9: 42839004 | B9: =IF(SUMIF('02 EXPERIENCIA LABORAL'!B:B,A9,'02 EXPERIENCIA LABORAL'!P:P)>0,1,0) -> 0 | C9: =SUMIF('02 EXPERIENCIA LABORAL'!B:B,A9,'02 EXPERIENCIA LABORAL'!P:P) -> 0
A10: 46307918 | B10: =IF(SUMIF('02 EXPERIENCIA LABORAL'!B:B,A10,'02 EXPERIENCIA LABORAL'!P:P)>0,1,0) -> 0 | C10: =SUMIF('02 EXPERIENCIA LABORAL'!B:B,A10,'02 EXPERIENCIA LABORAL'!P:P) -> 0
A11: 09391698 | B11: =IF(SUMIF('02 EXPERIENCIA LABORAL'!B:B,A11,'02 EXPERIENCIA LABORAL'!P:P)>0,1,0) -> 1 | C11: =SUMIF('02 EXPERIENCIA LABORAL'!B:B,A11,'02 EXPERIENCIA LABORAL'!P:P) -> 2
A12: 45382589 | B12: =IF(SUMIF('02 EXPERIENCIA LABORAL'!B:B,A12,'02 EXPERIENCIA LABORAL'!P:P)>0,1,0) -> 1 | C12: =SUMIF('02 EXPERIENCIA LABORAL'!B:B,A12,'02 EXPERIENCIA LABORAL'!P:P) -> 5
A13: 15984771 | B13: =IF(SUMIF('02 EXPERIENCIA LABORAL'!B:B,A13,'02 EXPERIENCIA LABORAL'!P:P)>0,1,0) -> 1 | C13: =SUMIF('02 EXPERIENCIA LABORAL'!B:B,A13,'02 EXPERIENCIA LABORAL'!P:P) -> 1
A14: 76030152 | B14: =IF(SUMIF('02 EXPERIENCIA LABORAL'!B:B,A14,'02 EXPERIENCIA LABORAL'!P:P)>0,1,0) -> 1 | C14: =SUMIF('02 EXPERIENCIA LABORAL'!B:B,A14,'02 EXPERIENCIA LABORAL'!P:P) -> 3
... A101: 07026029 | B101: =IF(SUMIF('02 EXPERIENCIA LABORAL'!B:B,A101,'02 EXPERIENCIA LABORAL'!P:P)>0,1,0) -> 1 | C101: =SUMIF('02 EXPERIENCIA LABORAL'!B:B,A101,'02 EXPERIENCIA LABORAL'!P:P) -> 1
B103: =SUM(B2:B101) -> 29 | C103: =SUM(C2:C101) -> 62

Sheet 03 FORM ACADEM. - EDUC. BASICA
A1: ORGANIZACION_POLITICA | B1: DNI_CANDIDATO | C1: CANDIDATO | D1: TIENE_EDUCACION_BASICA | E1: EDUC_PRIMARIA | F1: EDUC_PRIMARIA_CONCLUIDA | G1: EDUC_SECUNDARIA | H1: EDUC_SECUNDARIA_CONCLUIDA
A2: AHORA NACION - AN | B2: 29569533 | C2: ARMINTA VALENCIA, MARLENY BIBIANA | D2: SI | E2: SI | F2: SI | G2: SI | H2: SI
A3: AHORA NACION - AN | B3: 41618961 | C3: BUITRON MARTINEZ, FRESHMAN | D3: SI | E3: SI | F3: SI | G3: SI | H3: SI
A4: AHORA NACION - AN | B4: 43592504 | C4: COLCHADO HUAMANI, HARVEY JULIO | D4: SI | E4: SI | F4: SI | G4: SI | H4: SI
A5: AHORA NACION - AN | B5: 43572794 | C5: HOLGUIN LOAIZA, CESAR AUGUSTO | D5: SI | E5: SI | F5: SI | G5: SI | H5: SI
A6: AHORA NACION - AN | B6: 45218393 | C6: HUILCA FLORES, INDIRA ISABEL | D6: SI | E6: SI | F6: SI | G6: SI | H6: SI
A7: AHORA NACION - AN | B7: 70665764 | C7: MANRIQUE OLIVERA, BERNARDINO JAIR | D7: SI | E7: SI | F7: SI | G7: SI | H7: SI
A8: AHORA NACION - AN | B8: 41840094 | C8: MARCELO SALAZAR, JOSE MIGUEL | D8: SI | E8: SI | F8: SI | G8: SI | H8: SI
A9: AHORA NACION - AN | B9: 42839004 | C9: MUEDAS BALBIESE, CESAR AUGUSTO | D9: SI | E9: SI | F9: SI | G9: SI | H9: SI
A10: AHORA NACION - AN | B10: 46307918 | C10: SONCO VILLANUEVA, HELARD BLADIMIR | D10: SI | E10: SI | F10: SI | G10: SI | H10: SI
A11: FUERZA POPULAR | B11: 09391698 | C11: ABENSUR PINASCO, JAIME AMERICO | D11: SI | E11: SI | F11: SI | G11: SI | H11: SI
A12: FUERZA POPULAR | B12: 45382589 | C12: ALEGRIA GARCIA, LUIS ARTURO | D12: SI | E12: SI | F12: SI | G12: SI | H12: SI
... A55: JUNTOS POR EL PERU | B55: 74638299 | C55: PAREDES NAVARRO, YENIFER NOELIA | D55: SI | E55: SI | F55: SI | G55: SI | H55: SI
A56: JUNTOS POR EL PERU | B56: 42135939 | C56: PEÑA CORDOVA, OLVER | D56: SI | E56: SI | G56: SI
A57: JUNTOS POR EL PERU | B57: 10536312 | C57: PEREZ MALLQUI, JULIAN LUIS | D57: SI | E57: SI | F57: SI | G57: SI | H57: SI
A58: JUNTOS POR EL PERU | B58: 44908591 | C58: PEREZ QUISPE, JESSICA SADITH | D58: SI | E58: SI | F58: SI | G58: SI | H58: SI
A59: JUNTOS POR EL PERU | B59: 42984568 | C59: POMA HUAMANI, HAYDEE CELINDA | D59: SI | E59: SI | F59: SI | G59: SI | H59: SI
A60: JUNTOS POR EL PERU | B60: 70163475 | C60: TAPULLIMA INSAPILLO, JACQUELINE VIVIANA | D60: NO
A61: JUNTOS POR EL PERU | B61: 01320941 | C61: TITO ROJAS, CESAR HUGO | D61: SI | E61: SI | F61: SI | G61: SI | H61: SI
A62: JUNTOS POR EL PERU | B62: 45327535 | C62: ZUNINI YERREN, ERNESTO ALONZO | D62: SI | E62: SI | F62: SI | G62: SI | H62: SI
A63: PARTIDO CIVICO OBRAS | B63: 46602828 | C63: ALBAÑIL CARMONA, HENRY ANTONIO | D63: SI | E63: SI | F63: SI | G63: SI | H63: SI
A64: PARTIDO CIVICO OBRAS | B64: 43170121 | C64: ALVARON DE LA CRUZ, EDGAR ADRIAN | D64: SI | E64: SI | F64: SI | G64: SI | H64: SI
A65: PARTIDO CIVICO OBRAS | B65: 00482691 | C65: CABRERA NIETO, JUAN CESAR | D65: SI | E65: SI | F65: SI | G65: SI | H65: SI
A66: PARTIDO CIVICO OBRAS | B66: 07654582 | C66: EUSEBIO PADILLA, ARTURO CESAR | D66: SI | E66: SI | F66: SI | G66: SI | H66: SI
A67: PARTIDO CIVICO OBRAS | B67: 01545223 | C67: HANCCO HANCCO, DINA IRENE | D67: SI | E67: SI | F67: SI | G67: SI | H67: SI
A68: PARTIDO CIVICO OBRAS | B68: 01545223 | C68: HANCCO HANCCO, DINA IRENE | D68: SI | E68: SI | F68: SI | G68: SI | H68: SI
A69: PARTIDO CIVICO OBRAS | B69: 25001331 | C69: LOPEZ LETONA, HEBER | D69: SI | E69: SI | F69: SI | G69: SI | H69: SI
A70: PARTIDO CIVICO OBRAS | B70: 41242025 | C70: MASCO CACERES, LUIS AURELIO | D70: SI | E70: SI | F70: SI | G70: SI | H70: SI
A71: PARTIDO CIVICO OBRAS | B71: 46089177 | C71: MEDINA STEIN, ANDREA DAYNA | D71: SI | E71: SI | F71: SI | G71: SI | H71: SI
A72: PARTIDO CIVICO OBRAS | B72: 19995860 | C72: PERALTA JORPA, MAXIMO | D72: SI | E72: SI | F72: SI | G72: SI | H72: SI
A73: PARTIDO CIVICO OBRAS | B73: 70074678 | C73: PIÑAN MAMANI, VICTOR EDUARDO | D73: SI | E73: SI | F73: SI | G73: SI | H73: SI
A74: PARTIDO CIVICO OBRAS | B74: 07793641 | C74: SAMANEZ GONZALES VIGIL, JEENNY CRISTINA | D74: SI | E74: SI | F74: SI
A75: PARTIDO CIVICO OBRAS | B75: 17930730 | C75: VALQUI CALDERON, DEMETRIO FLAVIO | D75: SI | E75: SI | F75: SI | G75: SI | H75: No
A76: PARTIDO CIVICO OBRAS | B76: 42188288 | C76: YATACO TORREALVA, JOSE RICARDO | D76: SI | E76: SI | F76: SI | G76: SI | H76: SI
A77: PARTIDO DEL BUEN GOBIERNO | B77: 43478989 | C77: ALAYZA MACCERA, ROSSANA HERMINIA | D77: SI | E77: SI | F77: SI
A78: PARTIDO DEL BUEN GOBIERNO | B78: 41356710 | C78: BENITEZ BARRIONUEVO, JESSICA | D78: SI | E78: SI | F78: SI | G78: SI | H78: SI
A79: PARTIDO DEL BUEN GOBIERNO | B79: 16629849 | C79: CASTREJON FERNANDEZ, SEGUNDO JUAN | D79: SI | E79: SI | F79: SI | G79: SI | H79: SI
A80: PARTIDO DEL BUEN GOBIERNO | B80: 10277219 | C80: DUARTE PATIÑO DE PEZET, CARMEN GEORGINA | D80: SI | E80: SI | F80: SI | G80: SI | H80: SI
A81: PARTIDO DEL BUEN GOBIERNO | B81: 31038213 | C81: FERNANDEZ DE LA TORRE, HILDA JUDIT | D81: SI | E81: SI | F81: SI | G81: SI | H81: SI
A82: PARTIDO DEL BUEN GOBIERNO | B82: 08573694 | C82: GARCIA HUBY, FERNANDO ALBERTO | D82: SI | E82: SI | F82: SI | G82: SI | H82: SI
A83: PARTIDO DEL BUEN GOBIERNO | B83: 29715400 | C83: GONZALES POLAR, EDGAR DEMBER | D83: SI | E83: SI | F83: SI | G83: SI | H83: SI
A84: PARTIDO DEL BUEN GOBIERNO | B84: 29311981 | C84: HIRACHE PIZARRO, GLORIA CHARITO | D84: NO
A85: PARTIDO DEL BUEN GOBIERNO | B85: 02819812 | C85: HUAMAN CORNEJO, MIGUEL FELIX | D85: SI | E85: SI | F85: SI | G85: SI | H85: SI
A86: PARTIDO DEL BUEN GOBIERNO | B86: 06296745 | C86: LLAQUE LINARES, NORA MARIA | D86: SI | E86: SI | F86: SI | G86: SI | H86: SI
A87: PARTIDO DEL BUEN GOBIERNO | B87: 76871362 | C87: MOLINA SOTO, NATHALY MILAGROS | D87: SI | E87: SI | F87: SI | G87: SI | H87: SI
A88: PARTIDO DEL BUEN GOBIERNO | B88: 45741388 | C88: PRADO VALLEJOS, LILA MARIANELA | D88: SI | E88: SI | G88: SI
A89: PARTIDO DEL BUEN GOBIERNO | B89: 40067839 | C89: QUISPE CANDIA, LUIS ELISEO | D89: SI | E89: SI | F89: SI | G89: SI | H89: SI
A90: PARTIDO DEL BUEN GOBIERNO | B90: 43348625 | C90: RETO OTERO, OSCAR DE JESUS | D90: SI | E90: SI | F90: SI | G90: SI | H90: SI
A91: RENOVACION POPULAR | B91: 70747151 | C91: ARANDA VASQUEZ, CHRISTIAN | D91: SI
A92: RENOVACION POPULAR | B92: 09937296 | C92: BAELLA MALCA, JOSE ISIDRO | D92: SI | E92: SI | F92: SI | G92: SI | H92: SI
A93: RENOVACION POPULAR | B93: 46847115 | C93: BAZAN CALDERON, DIEGO ALONSO FERNANDO | D93: SI | E93: SI | G93: SI
A94: RENOVACION POPULAR | B94: 07974594 | C94: CHANG APUY, FELIX SEE HUNG | D94: SI | E94: SI | F94: SI | G94: SI | H94: SI
A95: RENOVACION POPULAR | B95: 07744156 | C95: CIPRIANI THORNE, JAVIER JOSE MARIA | D95: SI | E95: SI | F95: SI | G95: SI | H95: SI
A96: RENOVACION POPULAR | B96: 43401219 | C96: DE PAZ LANCHO, LEO MIGUEL | D96: SI | E96: SI | F96: SI | G96: SI | H96: SI
A97: RENOVACION POPULAR | B97: 46548697 | C97: KRKLEC TORRES, FRANK | D97: SI | E97: SI | F97: SI | G97: SI | H97: SI
A98: RENOVACION POPULAR | B98: 45363882 | C98: MARTINEZ PAITAN, PAOLA ISABEL | D98: SI | E98: SI | F98: SI | G98: SI | H98: SI
A99: RENOVACION POPULAR | B99: 10275564 | C99: ROCHA GALLEGOS, ROXANA MARIA | D99: SI | E99: SI | F99: SI | G99: SI | H99: SI
A100: RENOVACION POPULAR | B100: 41010370 | C100: SEGURA FIGUEROA, GUSTAVO ALEXANDER | D100: SI | E100: SI | F100: SI | G100: SI | H100: SI
A101: RENOVACION POPULAR | B101: 08878867 | C101: YALTA SOTELO, CARLOS ALBERTO | D101: SI | E101: SI | F101: SI | G101: SI | H101: SI
A102: RENOVACION POPULAR | B102: 10806296 | C102: YARROW LUMBRERAS, NORMA MARTINA | D102: SI | E102: SI | F102: SI | G102: SI | H102: SI
A103: RENOVACION POPULAR | B103: 10806296 | C103: YARROW LUMBRERAS, NORMA MARTINA | D103: SI | E103: SI | F103: SI | G103: SI | H103: SI
A104: RENOVACION POPULAR | B104: 44689086 | C104: YONZ NUÑEZ, MADY VERONICA | D104: SI | E104: SI | F104: SI | G104: SI | H104: SI
A105: RENOVACION POPULAR | B105: 07026029 | C105: ZEBALLOS APONTE, JORGE ARTURO | D105: SI | E105: SI | F105: SI | G105: SI | H105: SI

Sheet 03 FORM. ACADEM. - EDUC TECNICA
A1: ORGANIZACION_POLITICA | B1: DNI_CANDIDATO | C1: CANDIDATO | D1: TIENE_EDUC_TECNICO | E1: CENTRO_ESTUDIOS | F1: CARRERA | G1: CONCLUIDO | H1: INFORMACION_ADICIONAL
A2: AHORA NACION - AN | B2: 29569533 | C2: ARMINTA VALENCIA, MARLENY BIBIANA | D2: NO
A3: AHORA NACION - AN | B3: 41618961 | C3: BUITRON MARTINEZ, FRESHMAN | D3: NO
A4: AHORA NACION - AN | B4: 43592504 | C4: COLCHADO HUAMANI, HARVEY JULIO | D4: NO
A5: AHORA NACION - AN | B5: 43572794 | C5: HOLGUIN LOAIZA, CESAR AUGUSTO | D5: NO
A6: AHORA NACION - AN | B6: 45218393 | C6: HUILCA FLORES, INDIRA ISABEL | D6: NO
A7: AHORA NACION - AN | B7: 70665764 | C7: MANRIQUE OLIVERA, BERNARDINO JAIR | D7: NO
A8: AHORA NACION - AN | B8: 41840094 | C8: MARCELO SALAZAR, JOSE MIGUEL | D8: NO
A9: AHORA NACION - AN | B9: 42839004 | C9: MUEDAS BALBIESE, CESAR AUGUSTO | D9: NO
A10: AHORA NACION - AN | B10: 46307918 | C10: SONCO VILLANUEVA, HELARD BLADIMIR | D10: NO
A11: FUERZA POPULAR | B11: 09391698 | C11: ABENSUR PINASCO, JAIME AMERICO | D11: NO
A12: FUERZA POPULAR | B12: 45382589 | C12: ALEGRIA GARCIA, LUIS ARTURO | D12: NO
A13: FUERZA POPULAR | B13: 15984771 | C13: ANDRADE SALGUERO DE ALVAREZ, GLADYS GRISELDA | D13: NO
... A17: FUERZA POPULAR | B17: 44807108 | C17: CASTILLO RIVAS, EDUARDO ENRIQUE | D17: NO
A18: FUERZA POPULAR | B18: 16650849 | C18: CASTRO CRUZ, JAVIER ALEJANDRO | D18: SI | E18: BERTRAND RUSSEL | F18: CONTABILIDAD | G18: NO
A19: FUERZA POPULAR | B19: 10587515 | C19: CASTRO GRANDEZ, ROYSER | D19: SI | E19: IDAT | F19: Título en Mercadotecnia | G19: SI | H19: Título a nombre de la Nación, 20 de junio de 2002.
A20: FUERZA POPULAR | B20: 07750373 | C20: CELIZ CASTILLO, RAFAEL ALDO | D20: NO
A21: FUERZA POPULAR | B21: 09536896 | C21: CHACON DE VETTORI, CECILIA ISABEL | D21: NO
A22: FUERZA POPULAR | B22: 40826681 | C22: COLUMBUS MURATA, DIETHELL | D22: NO
A23: FUERZA POPULAR | B23: 42433830 | C23: DODERO JOVICH, PIERANGELI DANIELA | D23: NO
A24: FUERZA POPULAR | B24: 07268767 | C24: FIGARI MENDOZA, PIER PAOLO | D24: NO
A25: FUERZA POPULAR | B25: 42516751 | C25: GAMARRA PITA, LUZMILA MARIA DEL CARMEN | D25: NO
A26: FUERZA POPULAR | B26: 16448130 | C26: INFANTES CASTAÑEDA, MERY ELIANA | D26: NO
A27: FUERZA POPULAR | B27: 41919665 | C27: LEIVA BAYLON, LETICIA MARUJA | D27: NO
A28: FUERZA POPULAR | B28: 10187011 | C28: MENDOZA BERNEDO, LIZ HULI | D28: NO
A29: FUERZA POPULAR | B29: 10028427 | C29: NAVAS SANCHEZ, JESSICA LIZBETH | D29: NO
A30: FUERZA POPULAR | B30: 07737110 | C30: OBANDO MORGAN, AURISTELA ANA | D30: NO
A31: FUERZA POPULAR | B31: 47000483 | C31: PACHECO QUISPE, MARCO ANTONIO | D31: SI | E31: SAN IGNACIO DE LOYOLA | F31: PROFESIONAL TÉCNICO EN COMUNICACIÓN INTEGRAL | G31: SI
A32: FUERZA POPULAR | B32: 45721573 | C32: PALMA MENDOZA, JOSE MARVIN | D32: NO
A33: FUERZA POPULAR | B33: 10792277 | C33: PATIÑO URCO, ANA BERTHA | D33: NO
A34: FUERZA POPULAR | B34: 41408779 | C34: PAUCARA PAXI, CARMELA | D34: SI | E34: ELA | F34: PROFESIONAL TÉCNICO EN SECRETARIADO EJECUTIVO | G34: SI
A35: FUERZA POPULAR | B35: 05414308 | C35: PINASCO MONTENEGRO, NARY BENVINDA | D35: NO
A36: FUERZA POPULAR | B36: 44275599 | C36: REVILLA VILLANUEVA, CESAR MANUEL | D36: NO
A37: FUERZA POPULAR | B37: 80328889 | C37: SALAS RIVERA, ALEXANDER | D37: SI | E37: IEST Valle Grande | F37: Técnico de Producción Agraria | G37: SI
A38: FUERZA POPULAR | B38: 27424381 | C38: TICLLA RAFAEL, SEGUNDO SENOVIO | D38: SI | E38: INSTITUTO SUPERIOR TECNOLOGICO PUBLICO CHOTA | F38: COMPUTACIÓN E INFORMATICA | G38: SI
A39: FUERZA POPULAR | B39: 40433187 | C39: TORRES MORALES, MIGUEL ANGEL | D39: NO
A40: FUERZA POPULAR | B40: 40433187 | C40: TORRES MORALES, MIGUEL ANGEL | D40: NO
A41: FUERZA POPULAR | B41: 08571708 | C41: TRUJILLO ZEGARRA, GILMER | D41: NO
A42: FUERZA POPULAR | B42: 47654459 | C42: VALQUI ORDOÑEZ, JHONN BRAYAM | D42: NO
A43: FUERZA POPULAR | B43: 42551310 | C43: VIDAURRE FLORIDAS, CESAR MANUEL | D43: SI | E43: CEO DE GESTIÓN NO ESTATAL "INFORMÁTICA 2000" | F43: OPERADOR DE WINDOWS | G43: SI
A44: FUERZA POPULAR | B44: 80387180 | C44: ZEGARRA SANCHEZ, CARLOS ALBERTO | D44: NO
A45: JUNTOS POR EL PERU | B45: 46432487 | C45: AGUIRRE RAMOS, MARLON ALBERTO | D45: NO
A46: JUNTOS POR EL PERU | B46: 43845728 | C46: AMBROSIO DOMINGUEZ, YULI LILIANA | D46: NO
A47: JUNTOS POR EL PERU | B47: 40855980 | C47: AVENDAÑO VILCA, GIANNINA IRIS | D47: NO
A48: JUNTOS POR EL PERU | B48: 01223056 | C48: CONDORI FLORES, REMIGIO | D48: NO
A49: JUNTOS POR EL PERU | B49: 41711513 | C49: FLORES VALDIZAN, MARCO ANTONIO | D49: NO
A50: JUNTOS POR EL PERU | B50: 40093361 | C50: GONZALES DELGADO, GABRIEL ROBERTINO | D50: NO
A51: JUNTOS POR EL PERU | B51: 04810886 | C51: HOLGUIN AGUIRRE, JAMES ARTURO | D51: SI | E51: INSTITUTO SUPERIOR NSR | F51: EDUCACION PRIMARIA | G51: SI
A52: JUNTOS POR EL PERU | B52: 45442927 | C52: MARQUEZ HUANCA, ANALI | D52: NO
A53: JUNTOS POR EL PERU | B53: 45442927 | C53: MARQUEZ HUANCA, ANALI | D53: NO
A54: JUNTOS POR EL PERU | B54: 29313850 | C54: PALOMINO PACHECO, AMALIA EMILIA | D54: NO
A55: JUNTOS POR EL PERU | B55: 74638299 | C55: PAREDES NAVARRO, YENIFER NOELIA | D55: NO
A56: JUNTOS POR EL PERU | B56: 42135939 | C56: PEÑA CORDOVA, OLVER | D56: NO
A57: JUNTOS POR EL PERU | B57: 10536312 | C57: PEREZ MALLQUI, JULIAN LUIS | D57: NO
A58: JUNTOS POR EL PERU | B58: 44908591 | C58: PEREZ QUISPE, JESSICA SADITH | D58: NO
A59: JUNTOS POR EL PERU | B59: 42984568 | C59: POMA HUAMANI, HAYDEE CELINDA | D59: SI | E59: ISTP Antonio Lorena | F59: Técnico en Farmacia | G59: SI
A60: JUNTOS POR EL PERU | B60: 70163475 | C60: TAPULLIMA INSAPILLO, JACQUELINE VIVIANA | D60: NO
A61: JUNTOS POR EL PERU | B61: 01320941 | C61: TITO ROJAS, CESAR HUGO | D61: NO
A62: JUNTOS POR EL PERU | B62: 45327535 | C62: ZUNINI YERREN, ERNESTO ALONZO | D62: NO
A63: PARTIDO CIVICO OBRAS | B63: 46602828 | C63: ALBAÑIL CARMONA, HENRY ANTONIO | D63: NO
A64: PARTIDO CIVICO OBRAS | B64: 43170121 | C64: ALVARON DE LA CRUZ, EDGAR ADRIAN | D64: NO
A65: PARTIDO CIVICO OBRAS | B65: 00482691 | C65: CABRERA NIETO, JUAN CESAR | D65: SI | E65: IESTP “Francisco de Paula Gonzáles Vigil” | F65: MECANICA AUTOMOTRIZ | G65: SI
A66: PARTIDO CIVICO OBRAS | B66: 07654582 | C66: EUSEBIO PADILLA, ARTURO CESAR | D66: NO
A67: PARTIDO CIVICO OBRAS | B67: 01545223 | C67: HANCCO HANCCO, DINA IRENE | D67: NO
A68: PARTIDO CIVICO OBRAS | B68: 01545223 | C68: HANCCO HANCCO, DINA IRENE | D68: NO
A69: PARTIDO CIVICO OBRAS | B69: 25001331 | C69: LOPEZ LETONA, HEBER | D69: NO
A70: PARTIDO CIVICO OBRAS | B70: 41242025 | C70: MASCO CACERES, LUIS AURELIO | D70: SI | E70: SENATI | F70: MECANICA AUTOMOTRIZ | G70: SI
A71: PARTIDO CIVICO OBRAS | B71: 46089177 | C71: MEDINA STEIN, ANDREA DAYNA | D71: NO
A72: PARTIDO CIVICO OBRAS | B72: 19995860 | C72: PERALTA JORPA, MAXIMO | D72: SI | E72: I.S.T PUBLICO ANDRES AVELINO CACERES | F72: TECNICO MECANICO AUTOMOTRIZ | G72: SI
A73: PARTIDO CIVICO OBRAS | B73: 70074678 | C73: PIÑAN MAMANI, VICTOR EDUARDO | D73: NO
A74: PARTIDO CIVICO OBRAS | B74: 07793641 | C74: SAMANEZ GONZALES VIGIL, JEENNY CRISTINA | D74: SI | E74: INSTITUTO EUROPEO DE ESTUDIOS EMPRESARIALES | F74: CURSO EN MOVILIDAD URBANA SOSTENIBLE Y TRANSPORTE INTELIGENTE | G74: SI | H74: CERTIFICADA EN CURSOS DE MOVILIDAD URBANA EN BICICLETA OTORGADO EN EL COLEGIO DE ARQUITECTOS DEL PERU-REGION LIMA. CERTIFICADO DE PARTICIPACION EN CONNECTIVE CITIES TALLER DE PROYECTOS.
A75: PARTIDO CIVICO OBRAS | B75: 17930730 | C75: VALQUI CALDERON, DEMETRIO FLAVIO | D75: SI | E75: UNIVERSIDAD NACIONAL MAYOR DE SAN MARCOS | F75: REALIDAD Y PERSPECTIVAS DE LA INDUSTRIA AZUCARERA EN EL PERU | G75: SI | H75: CERTIFICADO EN FRENTE NACIONAL DE DEFENSA DE LA INDUSTRIA AZUCARERA DEL PERU, 2DO CONGRESO DE AZUCAREROS DEL PERU. DIPLOMADO EN UNIVERSIDAD NACIONAL DE TRUJILLO.
A76: PARTIDO CIVICO OBRAS | B76: 42188288 | C76: YATACO TORREALVA, JOSE RICARDO | D76: NO
A77: PARTIDO DEL BUEN GOBIERNO | B77: 43478989 | C77: ALAYZA MACCERA, ROSSANA HERMINIA | D77: NO
A78: PARTIDO DEL BUEN GOBIERNO | B78: 41356710 | C78: BENITEZ BARRIONUEVO, JESSICA | D78: NO
A79: PARTIDO DEL BUEN GOBIERNO | B79: 16629849 | C79: CASTREJON FERNANDEZ, SEGUNDO JUAN | D79: NO
A80: PARTIDO DEL BUEN GOBIERNO | B80: 10277219 | C80: DUARTE PATIÑO DE PEZET, CARMEN GEORGINA | D80: NO
A81: PARTIDO DEL BUEN GOBIERNO | B81: 31038213 | C81: FERNANDEZ DE LA TORRE, HILDA JUDIT | D81: SI | E81: Instituto Pedagogico La Salle | F81: Fisica Química | G81: SI | H81: Con licenciatura en la Universidad Mayor de San Marcos
A82: PARTIDO DEL BUEN GOBIERNO | B82: 08573694 | C82: GARCIA HUBY, FERNANDO ALBERTO | D82: NO
A83: PARTIDO DEL BUEN GOBIERNO | B83: 29715400 | C83: GONZALES POLAR, EDGAR DEMBER | D83: NO
A84: PARTIDO DEL BUEN GOBIERNO | B84: 29311981 | C84: HIRACHE PIZARRO, GLORIA CHARITO | D84: NO
A85: PARTIDO DEL BUEN GOBIERNO | B85: 02819812 | C85: HUAMAN CORNEJO, MIGUEL FELIX | D85: NO
A86: PARTIDO DEL BUEN GOBIERNO | B86: 06296745 | C86: LLAQUE LINARES, NORA MARIA | D86: SI | E86: Escuela de Filosofía Nueva Acrópolis | F86: Filosofía clásica y pedagogia | G86: SI
A87: PARTIDO DEL BUEN GOBIERNO | B87: 76871362 | C87: MOLINA SOTO, NATHALY MILAGROS | D87: NO
A88: PARTIDO DEL BUEN GOBIERNO | B88: 45741388 | C88: PRADO VALLEJOS, LILA MARIANELA | D88: NO
A89: PARTIDO DEL BUEN GOBIERNO | B89: 40067839 | C89: QUISPE CANDIA, LUIS ELISEO | D89: NO
A90: PARTIDO DEL BUEN GOBIERNO | B90: 43348625 | C90: RETO OTERO, OSCAR DE JESUS | D90: NO
A91: RENOVACION POPULAR | B91: 70747151 | C91: ARANDA VASQUEZ, CHRISTIAN | D91: NO
A92: RENOVACION POPULAR | B92: 09937296 | C92: BAELLA MALCA, JOSE ISIDRO | D92: NO
A93: RENOVACION POPULAR | B93: 46847115 | C93: BAZAN CALDERON, DIEGO ALONSO FERNANDO | D93: NO
A94: RENOVACION POPULAR | B94: 07974594 | C94: CHANG APUY, FELIX SEE HUNG | D94: NO
A95: RENOVACION POPULAR | B95: 07744156 | C95: CIPRIANI THORNE, JAVIER JOSE MARIA | D95: NO
A96: RENOVACION POPULAR | B96: 43401219 | C96: DE PAZ LANCHO, LEO MIGUEL | D96: SI | E96: IDAT | F96: BACHILLER TÉCNICO EN CIENCIAS PUBLICITARIAS | G96: SI
A97: RENOVACION POPULAR | B97: 46548697 | C97: KRKLEC TORRES, FRANK | D97: NO
A98: RENOVACION POPULAR | B98: 45363882 | C98: MARTINEZ PAITAN, PAOLA ISABEL | D98: NO
A99: RENOVACION POPULAR | B99: 10275564 | C99: ROCHA GALLEGOS, ROXANA MARIA | D99: NO
A100: RENOVACION POPULAR | B100: 41010370 | C100: SEGURA FIGUEROA, GUSTAVO ALEXANDER | D100: NO
A101: RENOVACION POPULAR | B101: 08878867 | C101: YALTA SOTELO, CARLOS ALBERTO | D101: NO
A102: RENOVACION POPULAR | B102: 10806296 | C102: YARROW LUMBRERAS, NORMA MARTINA | D102: NO
A103: RENOVACION POPULAR | B103: 10806296 | C103: YARROW LUMBRERAS, NORMA MARTINA | D103: NO
...

Sheet 03 FORM. ACADEM. - EDUC. NO UNI
A1: ORGANIZACION_POLITICA | B1: DNI_CANDIDATO | C1: CANDIDATO | D1: TIENE_EDUC_NO_UNIVERSITARIA | E1: EDUC_NO_UNIVERSITARIA | F1: CENTRO_ESTUDIOS | G1: CARRERA | H1: CONCLUIDO
A2: AHORA NACION - AN | B2: 29569533 | C2: ARMINTA VALENCIA, MARLENY BIBIANA | D2: NO
A3: AHORA NACION - AN | B3: 41618961 | C3: BUITRON MARTINEZ, FRESHMAN | D3: NO
A4: AHORA NACION - AN | B4: 43592504 | C4: COLCHADO HUAMANI, HARVEY JULIO | D4: NO
A5: AHORA NACION - AN | B5: 43572794 | C5: HOLGUIN LOAIZA, CESAR AUGUSTO | D5: NO
A6: AHORA NACION - AN | B6: 45218393 | C6: HUILCA FLORES, INDIRA ISABEL | D6: NO
A7: AHORA NACION - AN | B7: 70665764 | C7: MANRIQUE OLIVERA, BERNARDINO JAIR | D7: NO
A8: AHORA NACION - AN | B8: 41840094 | C8: MARCELO SALAZAR, JOSE MIGUEL | D8: NO
A9: AHORA NACION - AN | B9: 42839004 | C9: MUEDAS BALBIESE, CESAR AUGUSTO | D9: NO
A10: AHORA NACION - AN | B10: 46307918 | C10: SONCO VILLANUEVA, HELARD BLADIMIR | D10: NO
A11: FUERZA POPULAR | B11: 09391698 | C11: ABENSUR PINASCO, JAIME AMERICO | D11: NO
A12: FUERZA POPULAR | B12: 45382589 | C12: ALEGRIA GARCIA, LUIS ARTURO | D12: NO
A13: FUERZA POPULAR | B13: 15984771 | C13: ANDRADE SALGUERO DE ALVAREZ, GLADYS GRISELDA | D13: NO
... A17: FUERZA POPULAR | B17: 44807108 | C17: CASTILLO RIVAS, EDUARDO ENRIQUE | D17: NO
A18: FUERZA POPULAR | B18: 16650849 | C18: CASTRO CRUZ, JAVIER ALEJANDRO | D18: SI | E18: NO
A19: FUERZA POPULAR | B19: 10587515 | C19: CASTRO GRANDEZ, ROYSER | D19: SI | E19: NO
A20: FUERZA POPULAR | B20: 07750373 | C20: CELIZ CASTILLO, RAFAEL ALDO | D20: NO
A21: FUERZA POPULAR | B21: 09536896 | C21: CHACON DE VETTORI, CECILIA ISABEL | D21: NO
A22: FUERZA POPULAR | B22: 40826681 | C22: COLUMBUS MURATA, DIETHELL | D22: NO
A23: FUERZA POPULAR | B23: 42433830 | C23: DODERO JOVICH, PIERANGELI DANIELA | D23: NO
A24: FUERZA POPULAR | B24: 07268767 | C24: FIGARI MENDOZA, PIER PAOLO | D24: NO
A25: FUERZA POPULAR | B25: 42516751 | C25: GAMARRA PITA, LUZMILA MARIA DEL CARMEN | D25: NO
A26: FUERZA POPULAR | B26: 16448130 | C26: INFANTES CASTAÑEDA, MERY ELIANA | D26: NO
A27: FUERZA POPULAR | B27: 41919665 | C27: LEIVA BAYLON, LETICIA MARUJA | D27: NO
A28: FUERZA POPULAR | B28: 10187011 | C28: MENDOZA BERNEDO, LIZ HULI | D28: NO
A29: FUERZA POPULAR | B29: 10028427 | C29: NAVAS SANCHEZ, JESSICA LIZBETH | D29: NO
A30: FUERZA POPULAR | B30: 07737110 | C30: OBANDO MORGAN, AURISTELA ANA | D30: NO
A31: FUERZA POPULAR | B31: 47000483 | C31: PACHECO QUISPE, MARCO ANTONIO | D31: SI | E31: NO
A32: FUERZA POPULAR | B32: 45721573 | C32: PALMA MENDOZA, JOSE MARVIN | D32: NO
A33: FUERZA POPULAR | B33: 10792277 | C33: PATIÑO URCO, ANA BERTHA | D33: NO
A34: FUERZA POPULAR | B34: 41408779 | C34: PAUCARA PAXI, CARMELA | D34: SI | E34: SI | F34: UNIVERSIDAD CESAR VALLEJO | G34: ADMINISTRACION DE EMPRESAS | H34: NO
A35: FUERZA POPULAR | B35: 05414308 | C35: PINASCO MONTENEGRO, NARY BENVINDA | D35: NO
A36: FUERZA POPULAR | B36: 44275599 | C36: REVILLA VILLANUEVA, CESAR MANUEL | D36: SI | E36: NO
A37: FUERZA POPULAR | B37: 80328889 | C37: SALAS RIVERA, ALEXANDER | D37: SI | E37: NO
A38: FUERZA POPULAR | B38: 27424381 | C38: TICLLA RAFAEL, SEGUNDO SENOVIO | D38: SI | E38: SI | F38: INSTITUTO SUPERIOR PEDAGOGICO PRIVADO AKUNTA | G38: LENGUAJE Y LITERATURA | H38: NO
A39: FUERZA POPULAR | B39: 40433187 | C39: TORRES MORALES, MIGUEL ANGEL | D39: NO
A40: FUERZA POPULAR | B40: 40433187 | C40: TORRES MORALES, MIGUEL ANGEL | D40: NO
A41: FUERZA POPULAR | B41: 08571708 | C41: TRUJILLO ZEGARRA, GILMER | D41: NO
A42: FUERZA POPULAR | B42: 47654459 | C42: VALQUI ORDOÑEZ, JHONN BRAYAM | D42: NO
A43: FUERZA POPULAR | B43: 42551310 | C43: VIDAURRE FLORIDAS, CESAR MANUEL | D43: SI | E43: NO
A44: FUERZA POPULAR | B44: 80387180 | C44: ZEGARRA SANCHEZ, CARLOS ALBERTO | D44: NO
A45: JUNTOS POR EL PERU | B45: 46432487 | C45: AGUIRRE RAMOS, MARLON ALBERTO | D45: NO
A46: JUNTOS POR EL PERU | B46: 43845728 | C46: AMBROSIO DOMINGUEZ, YULI LILIANA | D46: NO
A47: JUNTOS POR EL PERU | B47: 40855980 | C47: AVENDAÑO VILCA, GIANNINA IRIS | D47: NO
A48: JUNTOS POR EL PERU | B48: 01223056 | C48: CONDORI FLORES, REMIGIO | D48: NO
A49: JUNTOS POR EL PERU | B49: 41711513 | C49: FLORES VALDIZAN, MARCO ANTONIO | D49: NO
A50: JUNTOS POR EL PERU | B50: 40093361 | C50: GONZALES DELGADO, GABRIEL ROBERTINO | D50: NO
A51: JUNTOS POR EL PERU | B51: 04810886 | C51: HOLGUIN AGUIRRE, JAMES ARTURO | D51: SI | E51: NO
A52: JUNTOS POR EL PERU | B52: 45442927 | C52: MARQUEZ HUANCA, ANALI | D52: NO
A53: JUNTOS POR EL PERU | B53: 45442927 | C53: MARQUEZ HUANCA, ANALI | D53: NO
A54: JUNTOS POR EL PERU | B54: 29313850 | C54: PALOMINO PACHECO, AMALIA EMILIA | D54: NO
A55: JUNTOS POR EL PERU | B55: 74638299 | C55: PAREDES NAVARRO, YENIFER NOELIA | D55: NO
A56: JUNTOS POR EL PERU | B56: 42135939 | C56: PEÑA CORDOVA, OLVER | D56: SI | E56: SI | F56: GRUPO HORIZONTE EDUCA PERU | G56: CURSO DE ESPECIALIZACION | H56: SI
A57: JUNTOS POR EL PERU | B57: 10536312 | C57: PEREZ MALLQUI, JULIAN LUIS | D57: NO
A58: JUNTOS POR EL PERU | B58: 44908591 | C58: PEREZ QUISPE, JESSICA SADITH | D58: NO
A59: JUNTOS POR EL PERU | B59: 42984568 | C59: POMA HUAMANI, HAYDEE CELINDA | D59: SI | E59: NO
A60: JUNTOS POR EL PERU | B60: 70163475 | C60: TAPULLIMA INSAPILLO, JACQUELINE VIVIANA | D60: NO
A61: JUNTOS POR EL PERU | B61: 01320941 | C61: TITO ROJAS, CESAR HUGO | D61: SI | E61: SI | F61: ISP Puno | G61: Educación Primaria | H61: SI
A62: JUNTOS POR EL PERU | B62: 45327535 | C62: ZUNINI YERREN, ERNESTO ALONZO | D62: NO
A63: PARTIDO CIVICO OBRAS | B63: 46602828 | C63: ALBAÑIL CARMONA, HENRY ANTONIO | D63: NO
A64: PARTIDO CIVICO OBRAS | B64: 43170121 | C64: ALVARON DE LA CRUZ, EDGAR ADRIAN | D64: NO
A65: PARTIDO CIVICO OBRAS | B65: 00482691 | C65: CABRERA NIETO, JUAN CESAR | D65: SI | E65: SI | F65: berlitz school of languages | G65: Curso Intensivo de Ingles | H65: SI
A66: PARTIDO CIVICO OBRAS | B66: 07654582 | C66: EUSEBIO PADILLA, ARTURO CESAR | D66: SI | E66: NO
A67: PARTIDO CIVICO OBRAS | B67: 01545223 | C67: HANCCO HANCCO, DINA IRENE | D67: NO
A68: PARTIDO CIVICO OBRAS | B68: 01545223 | C68: HANCCO HANCCO, DINA IRENE | D68: NO
A69: PARTIDO CIVICO OBRAS | B69: 25001331 | C69: LOPEZ LETONA, HEBER | D69: NO
A70: PARTIDO CIVICO OBRAS | B70: 41242025 | C70: MASCO CACERES, LUIS AURELIO | D70: SI | E70: SI | F70: ASOCIACION DE SERVICIOS Y CAPACITACION ASERCAP | G70: OPERADOR MULTIPLE DE MAQUINARIA PESADA | H70: SI
A71: PARTIDO CIVICO OBRAS | B71: 46089177 | C71: MEDINA STEIN, ANDREA DAYNA | D71: NO
A72: PARTIDO CIVICO OBRAS | B72: 19995860 | C72: PERALTA JORPA, MAXIMO | D72: SI | E72: SI | F72: I.S.P PUBLICO JOSE ANTONIO ENCINAS | G72: PROFESOR | H72: SI
A73: PARTIDO CIVICO OBRAS | B73: 70074678 | C73: PIÑAN MAMANI, VICTOR EDUARDO | D73: NO
A74: PARTIDO CIVICO OBRAS | B74: 07793641 | C74: SAMANEZ GONZALES VIGIL, JEENNY CRISTINA | D74: SI | E74: NO
A75: PARTIDO CIVICO OBRAS | B75: 17930730 | C75: VALQUI CALDERON, DEMETRIO FLAVIO | D75: SI | E75: NO
A76: PARTIDO CIVICO OBRAS | B76: 42188288 | C76: YATACO TORREALVA, JOSE RICARDO | D76: NO
A77: PARTIDO DEL BUEN GOBIERNO | B77: 43478989 | C77: ALAYZA MACCERA, ROSSANA HERMINIA | D77: NO
A78: PARTIDO DEL BUEN GOBIERNO | B78: 41356710 | C78: BENITEZ BARRIONUEVO, JESSICA | D78: NO
A79: PARTIDO DEL BUEN GOBIERNO | B79: 16629849 | C79: CASTREJON FERNANDEZ, SEGUNDO JUAN | D79: NO
A80: PARTIDO DEL BUEN GOBIERNO | B80: 10277219 | C80: DUARTE PATIÑO DE PEZET, CARMEN GEORGINA | D80: NO
A81: PARTIDO DEL BUEN GOBIERNO | B81: 31038213 | C81: FERNANDEZ DE LA TORRE, HILDA JUDIT | D81: SI | E81: NO
A82: PARTIDO DEL BUEN GOBIERNO | B82: 08573694 | C82: GARCIA HUBY, FERNANDO ALBERTO | D82: NO
A83: PARTIDO DEL BUEN GOBIERNO | B83: 29715400 | C83: GONZALES POLAR, EDGAR DEMBER | D83: NO
A84: PARTIDO DEL BUEN GOBIERNO | B84: 29311981 | C84: HIRACHE PIZARRO, GLORIA CHARITO | D84: NO
A85: PARTIDO DEL BUEN GOBIERNO | B85: 02819812 | C85: HUAMAN CORNEJO, MIGUEL FELIX | D85: NO
A86: PARTIDO DEL BUEN GOBIERNO | B86: 06296745 | C86: LLAQUE LINARES, NORA MARIA | D86: SI | E86: NO
A87: PARTIDO DEL BUEN GOBIERNO | B87: 76871362 | C87: MOLINA SOTO, NATHALY MILAGROS | D87: NO
A88: PARTIDO DEL BUEN GOBIERNO | B88: 45741388 | C88: PRADO VALLEJOS, LILA MARIANELA | D88: NO
A89: PARTIDO DEL BUEN GOBIERNO | B89: 40067839 | C89: QUISPE CANDIA, LUIS ELISEO | D89: NO
A90: PARTIDO DEL BUEN GOBIERNO | B90: 43348625 | C90: RETO OTERO, OSCAR DE JESUS | D90: NO
A91: RENOVACION POPULAR | B91: 70747151 | C91: ARANDA VASQUEZ, CHRISTIAN | D91: NO
A92: RENOVACION POPULAR | B92: 09937296 | C92: BAELLA MALCA, JOSE ISIDRO | D92: NO
A93: RENOVACION POPULAR | B93: 46847115 | C93: BAZAN CALDERON, DIEGO ALONSO FERNANDO | D93: NO
A94: RENOVACION POPULAR | B94: 07974594 | C94: CHANG APUY, FELIX SEE HUNG | D94: NO
A95: RENOVACION POPULAR | B95: 07744156 | C95: CIPRIANI THORNE, JAVIER JOSE MARIA | D95: NO
A96: RENOVACION POPULAR | B96: 43401219 | C96: DE PAZ LANCHO, LEO MIGUEL | D96: SI | E96: NO
A97: RENOVACION POPULAR | B97: 46548697 | C97: KRKLEC TORRES, FRANK | D97: NO
A98: RENOVACION POPULAR | B98: 45363882 | C98: MARTINEZ PAITAN, PAOLA ISABEL | D98: NO
A99: RENOVACION POPULAR | B99: 10275564 | C99: ROCHA GALLEGOS, ROXANA MARIA | D99: NO
A100: RENOVACION POPULAR | B100: 41010370 | C100: SEGURA FIGUEROA, GUSTAVO ALEXANDER | D100: NO
A101: RENOVACION POPULAR | B101: 08878867 | C101: YALTA SOTELO, CARLOS ALBERTO | D101: NO
A102: RENOVACION POPULAR | B102: 10806296 | C102: YARROW LUMBRERAS, NORMA MARTINA | D102: SI | E102: NO
A103: RENOVACION POPULAR | B103: 10806296 | C103: YARROW LUMBRERAS, NORMA MARTINA | D103: SI | E103: NO
...

Sheet 03 FORM. ACADEM. - EDUC. UNIV
A1: ORGANIZACION_POLITICA | B1: DNI_CANDIDATO | C1: CANDIDATO | D1: TIENE_EDUC_UNIV | E1: EDUC_UNIV | F1: UNIVERSIDAD | G1: CARRERA | H1: CONCLUIDO | I1: EGRESADO | J1: INFORMACION_COMPLEMENTARIA
A2: AHORA NACION - AN | B2: 29569533 | C2: ARMINTA VALENCIA, MARLENY BIBIANA | D2: SI | E2: SI | F2: Universidad Nacional de San Agustín de Arequipa | G2: BACHILLER EN CONTABILIDAD | H2: SI | I2: SI
A3: AHORA NACION - AN | B3: 29569533 | C3: ARMINTA VALENCIA, MARLENY BIBIANA | D3: SI | E3: SI | F3: Universidad Nacional de San Agustín de Arequipa | G3: CONTADOR PUBLICO | H3: SI | I3: SI
A4: AHORA NACION - AN | B4: 41618961 | C4: BUITRON MARTINEZ, FRESHMAN | D4: SI | E4: SI | F4: Universidad Nacional de San Cristóbal de Huamanga | G4: LICENCIADO EN EDUCACION SECUNDARIA | H4: SI | I4: SI
A5: AHORA NACION - AN | B5: 41618961 | C5: BUITRON MARTINEZ, FRESHMAN | D5: SI | E5: SI | F5: Universidad Nacional de San Cristóbal de Huamanga | G5: BACHILLER EN DERECHO | H5: SI | I5: SI
A6: AHORA NACION - AN | B6: 41618961 | C6: BUITRON MARTINEZ, FRESHMAN | D6: SI | E6: SI | F6: Universidad Nacional de San Cristóbal de Huamanga | G6: BACHILLER EN CIENCIAS DE LA EDUCACION | H6: SI | I6: SI
A7: AHORA NACION - AN | B7: 41618961 | C7: BUITRON MARTINEZ, FRESHMAN | D7: SI | E7: SI | F7: Universidad Nacional de San Cristóbal de Huamanga | G7: TITULO PROFESIONAL DE ABOGADO | H7: SI | I7: SI
A8: AHORA NACION - AN | B8: 43592504 | C8: COLCHADO HUAMANI, HARVEY JULIO | D8: SI | E8: SI | F8: Universidad Nacional Federico Villarreal | G8: BACHILLER EN DERECHO | H8: SI | I8: SI
A9: AHORA NACION - AN | B9: 43592504 | C9: COLCHADO HUAMANI, HARVEY JULIO | D9: SI | E9: SI | F9: Universidad de Huánuco | G9: TITULO PROFESIONAL DE ABOGADO | H9: SI | I9: SI
A10: AHORA NACION - AN | B10: 43592504 | C10: COLCHADO HUAMANI, HARVEY JULIO | D10: SI | E10: SI | F10: Escuela de Oficiales de la Policía Nacional del Perú | G10: LICENCIADO EN ADMINISTRACION Y CIENCIAS POLICIALES | H10: SI | I10: SI
A11: AHORA NACION - AN | B11: 43592504 | C11: COLCHADO HUAMANI, HARVEY JULIO | D11: SI | E11: SI | F11: Escuela de Oficiales de la Policía Nacional del Perú | G11: BACHILLER EN ADMINISTRACION Y CIENCIAS POLICIALES | H11: SI | I11: SI
A12: AHORA NACION - AN | B12: 43572794 | C12: HOLGUIN LOAIZA, CESAR AUGUSTO | D12: SI | E12: SI | F12: Universidad Nacional de San Antonio Abad del Cusco | G12: ECONOMISTA | H12: SI | I12: SI
A13: AHORA NACION - AN | B13: 43572794 | C13: HOLGUIN LOAIZA, CESAR AUGUSTO | D13: SI | E13: SI | F13: Universidad Nacional de San Antonio Abad del Cusco | G13: BACHILLER EN ECONOMIA | H13: SI | I13: SI
... A19: AHORA NACION - AN | B19: 42839004 | C19: MUEDAS BALBIESE, CESAR AUGUSTO | D19: SI | E19: SI | F19: Universidad Peruana Los Andes | G19: Bachiller en Derecho y Ciencias Políticas | H19: SI | I19: SI
A20: AHORA NACION - AN | B20: 46307918 | C20: SONCO VILLANUEVA, HELARD BLADIMIR | D20: SI | E20: SI | F20: Universidad Nacional del Altiplano-Puno | G20: Egresado | H20: SI | I20: SI | J20: Egresado E.P Ingeniería de minas
A21: FUERZA POPULAR | B21: 09391698 | C21: ABENSUR PINASCO, JAIME AMERICO | D21: SI | E21: SI | F21: Universidad de San Martín de Porres | G21: BACHILLER EN DERECHO Y CIENCIAS POLITICAS | H21: SI | I21: SI
A22: FUERZA POPULAR | B22: 09391698 | C22: ABENSUR PINASCO, JAIME AMERICO | D22: SI | E22: SI | F22: Universidad de San Martín de Porres | G22: ABOGADO | H22: SI | I22: SI
A23: FUERZA POPULAR | B23: 45382589 | C23: ALEGRIA GARCIA, LUIS ARTURO | D23: SI | E23: SI | F23: UNIVERSIDAD SAN IGNACIO DE LOYOLA | G23: NO CONCLUIDO | H23: NO | J23: estudios no concluidos en marketing
A24: FUERZA POPULAR | B24: 15984771 | C24: ANDRADE SALGUERO DE ALVAREZ, GLADYS GRISELDA | D24: SI | E24: SI | F24: Universidad Continental S.A.C. | G24: ABOGADA | H24: SI | I24: SI
A25: FUERZA POPULAR | B25: 15984771 | C25: ANDRADE SALGUERO DE ALVAREZ, GLADYS GRISELDA | D25: SI | E25: SI | F25: Universidad Continental S.A.C. | G25: BACHILLER EN DERECHO | H25: SI | I25: SI
A26: FUERZA POPULAR | B26: 76030152 | C26: BARBARAN REYES, ROSANGELLA ANDREA | D26: SI | E26: SI | F26: Universidad Científica del Sur S.A.C. | G26: INGENIERA ECONOMISTA | H26: SI | I26: SI
A27: FUERZA POPULAR | B27: 76030152 | C27: BARBARAN REYES, ROSANGELLA ANDREA | D27: SI | E27: SI | F27: Universidad Científica del Sur S.A.C. | G27: BACHILLER EN INGENIERIA ECONOMICA Y DE NEGOCIOS | H27: SI | I27: SI
A28: FUERZA POPULAR | B28: 22509175 | C28: BETETA RUBIN, KARINA JULIZA | D28: SI | E28: SI | F28: Universidad de Huánuco | G28: ABOGADA | H28: SI | I28: SI
A29: FUERZA POPULAR | B29: 22509175 | C29: BETETA RUBIN, KARINA JULIZA | D29: SI | E29: SI | F29: Universidad de Huánuco | G29: BACHILLER EN DERECHO Y CIENCIAS POLITICAS | H29: SI | I29: SI
A30: FUERZA POPULAR | B30: 40224994 | C30: BOBADILLA GALINDO, ANGEL BRUNO | D30: SI | E30: SI | F30: Universidad de San Martín de Porres | G30: BACHILLER EN DERECHO Y CIENCIA POLITICA | H30: SI | I30: SI
A31: FUERZA POPULAR | B31: 40224994 | C31: BOBADILLA GALINDO, ANGEL BRUNO | D31: SI | E31: SI | F31: Universidad de San Martín de Porres | G31: ABOGADO | H31: SI | I31: SI
A32: FUERZA POPULAR | B32: 44807108 | C32: CASTILLO RIVAS, EDUARDO ENRIQUE | D32: SI | E32: SI | F32: UNIVERSIDAD CATOLICA LOS ANGELES DE CHIMBOTE | G32: DERECHO | H32: NO
A33: FUERZA POPULAR | B33: 44807108 | C33: CASTILLO RIVAS, EDUARDO ENRIQUE | D33: SI | E33: SI | F33: UNIVERSIDAD CONTINENTAL | G33: DERECHO | H33: SI | I33: NO
A34: FUERZA POPULAR | B34: 16650849 | C34: CASTRO CRUZ, JAVIER ALEJANDRO | D34: SI | E34: SI | F34: Universidad Particular de Chiclayo | G34: ABOGADO | H34: SI | I34: SI
A35: FUERZA POPULAR | B35: 16650849 | C35: CASTRO CRUZ, JAVIER ALEJANDRO | D35: SI | E35: SI | F35: Universidad Particular de Chiclayo | G35: - | H35: SI | I35: SI
A36: FUERZA POPULAR | B36: 10587515 | C36: CASTRO GRANDEZ, ROYSER | D36: SI | E36: SI | F36: Universidad Inca Garcilaso de la Vega Asociación Civil | G36: BACHILLER EN DERECHO Y CIENCIAS POLITICAS | H36: SI | I36: SI
A37: FUERZA POPULAR | B37: 10587515 | C37: CASTRO GRANDEZ, ROYSER | D37: SI | E37: SI | F37: Universidad Inca Garcilaso de la Vega Asociación Civil | G37: ABOGADO | H37: SI | I37: SI
A38: FUERZA POPULAR | B38: 07750373 | C38: CELIZ CASTILLO, RAFAEL ALDO | D38: SI | E38: SI | F38: Universidad de San Martín de Porres | G38: ABOGADO | H38: SI | I38: SI
A39: FUERZA POPULAR | B39: 07750373 | C39: CELIZ CASTILLO, RAFAEL ALDO | D39: SI | E39: SI | F39: Universidad de San Martín de Porres | G39: BACHILLER EN DERECHO | H39: SI | I39: SI
A40: FUERZA POPULAR | B40: 09536896 | C40: CHACON DE VETTORI, CECILIA ISABEL | D40: SI | E40: SI | F40: UNIVERSIDAD RICARDO PALMA | G40: ADMINISTRACIÓN Y GERENCIA | H40: NO
A41: FUERZA POPULAR | B41: 40826681 | C41: COLUMBUS MURATA, DIETHELL | D41: SI | E41: SI | F41: Universidad Nacional Federico Villarreal | G41: TÍTULO DE ABOGADO | H41: SI | I41: SI
A42: FUERZA POPULAR | B42: 40826681 | C42: COLUMBUS MURATA, DIETHELL | D42: SI | E42: SI | F42: Universidad Nacional Federico Villarreal | G42: BACHILLER EN DERECHO | H42: SI | I42: SI
A43: FUERZA POPULAR | B43: 42433830 | C43: DODERO JOVICH, PIERANGELI DANIELA | D43: SI | E43: SI | F43: Universidad Católica de Santa María | G43: BACHILLER EN TURISMO Y HOTELERÍA | H43: SI | I43: SI
A44: FUERZA POPULAR | B44: 07268767 | C44: FIGARI MENDOZA, PIER PAOLO | D44: SI | E44: SI | F44: Universidad de Lima | G44: BACHILLER EN DERECHO | H44: SI | I44: SI
A45: FUERZA POPULAR | B45: 07268767 | C45: FIGARI MENDOZA, PIER PAOLO | D45: SI | E45: SI | F45: Universidad de Lima | G45: ABOGADO | H45: SI | I45: SI
A46: FUERZA POPULAR | B46: 07268767 | C46: FIGARI MENDOZA, PIER PAOLO | D46: SI | E46: SI | F46: Universidad de Lima | G46: BACHILLER EN CIENCIAS DE LA COMUNICACIÓN | H46: SI | I46: SI
A47: FUERZA POPULAR | B47: 42516751 | C47: GAMARRA PITA, LUZMILA MARIA DEL CARMEN | D47: SI | E47: SI | F47: Universidad Privada San Pedro | G47: BACHILLER EN DERECHO | H47: SI | I47: SI
A48: FUERZA POPULAR | B48: 16448130 | C48: INFANTES CASTAÑEDA, MERY ELIANA | D48: SI | E48: SI | F48: Universidad Particular de Chiclayo | G48: LICENCIADA EN OBSTETRICIA | H48: SI | I48: SI
A49: FUERZA POPULAR | B49: 16448130 | C49: INFANTES CASTAÑEDA, MERY ELIANA | D49: SI | E49: SI | F49: Universidad Particular de Chiclayo | G49: BACHILLER EN OBSTETRICIA | H49: SI | I49: SI
A50: FUERZA POPULAR | B50: 41919665 | C50: LEIVA BAYLON, LETICIA MARUJA | D50: SI | E50: SI | F50: Universidad San Ignacio de Loyola S.A. | G50: Bachiller en Administración de Empresas | H50: SI | I50: SI
A51: FUERZA POPULAR | B51: 41919665 | C51: LEIVA BAYLON, LETICIA MARUJA | D51: SI | E51: SI | F51: Universidad San Ignacio de Loyola S.R.L. | G51: LICENCIADO EN ADMINISTRACIÓN DE EMPRESAS | H51: SI | I51: SI
A52: FUERZA POPULAR | B52: 10187011 | C52: MENDOZA BERNEDO, LIZ HULI | D52: SI | E52: SI | F52: Universidad de San Martín de Porres | G52: BACHILLER EN ODONTOLOGIA | H52: SI | I52: SI
... A64: FUERZA POPULAR | B64: 10792277 | C64: PATIÑO URCO, ANA BERTHA | D64: SI | E64: SI | F64: Universidad de San Martín de Porres | G64: BACHILLER EN DERECHO | H64: SI | I64: SI
A65: FUERZA POPULAR | B65: 41408779 | C65: PAUCARA PAXI, CARMELA | D65: NO
A66: FUERZA POPULAR | B66: 05414308 | C66: PINASCO MONTENEGRO, NARY BENVINDA | D66: SI | E66: SI | F66: Universidad Científica del Perú | G66: BACHILLER EN ADMINISTRACION DE EMPRESAS | H66: SI | I66: SI
A67: FUERZA POPULAR | B67: 05414308 | C67: PINASCO MONTENEGRO, NARY BENVINDA | D67: SI | E67: SI | F67: Universidad Científica del Perú | G67: LICENCIADA EN ADMINISTRACION DE EMPRESAS | H67: SI | I67: SI
A68: FUERZA POPULAR | B68: 44275599 | C68: REVILLA VILLANUEVA, CESAR MANUEL | D68: SI | E68: SI | F68: Universidad Inca Garcilaso de la Vega Asociación Civil | G68: CIRUJANO DENTISTA | H68: SI | I68: SI
A69: FUERZA POPULAR | B69: 44275599 | C69: REVILLA VILLANUEVA, CESAR MANUEL | D69: SI | E69: SI | F69: Universidad César Vallejo S.A.C. | G69: BACHILLER EN ESTOMATOLOGIA | H69: SI | I69: SI
A70: FUERZA POPULAR | B70: 80328889 | C70: SALAS RIVERA, ALEXANDER | D70: NO
A71: FUERZA POPULAR | B71: 27424381 | C71: TICLLA RAFAEL, SEGUNDO SENOVIO | D71: NO
A72: FUERZA POPULAR | B72: 40433187 | C72: TORRES MORALES, MIGUEL ANGEL | D72: SI | E72: SI | F72: Universidad de Lima | G72: BACHILLER EN DERECHO | H72: SI | I72: SI | J72: Año de obtención del bachiller: 2003.
A73: FUERZA POPULAR | B73: 40433187 | C73: TORRES MORALES, MIGUEL ANGEL | D73: SI | E73: SI | F73: Universidad de Lima | G73: ABOGADO | H73: SI | I73: SI | J73: Año de obtención del título: 2003.
A74: FUERZA POPULAR | B74: 40433187 | C74: TORRES MORALES, MIGUEL ANGEL | D74: SI | E74: SI | F74: Universidad de Lima | G74: ABOGADO | H74: SI | I74: SI | J74: Año de obtención del título: 2003.
A75: FUERZA POPULAR | B75: 40433187 | C75: TORRES MORALES, MIGUEL ANGEL | D75: SI | E75: SI | F75: Universidad de Lima | G75: BACHILLER EN DERECHO | H75: SI | I75: SI | J75: Año de obtención del bachiller: 2003.
A76: FUERZA POPULAR | B76: 08571708 | C76: TRUJILLO ZEGARRA, GILMER | D76: SI | E76: SI | F76: Universidad de San Martín de Porres | G76: BACHILLER EN DERECHO | H76: SI | I76: SI
A77: FUERZA POPULAR | B77: 08571708 | C77: TRUJILLO ZEGARRA, GILMER | D77: SI | E77: SI | F77: Universidad de San Martín de Porres | G77: ABOGADO | H77: SI | I77: SI
A78: FUERZA POPULAR | B78: 47654459 | C78: VALQUI ORDOÑEZ, JHONN BRAYAM | D78: SI | E78: SI | F78: Pontificia Universidad Católica del Perú | G78: INGENIERO CIVIL | H78: SI | I78: SI
A79: FUERZA POPULAR | B79: 47654459 | C79: VALQUI ORDOÑEZ, JHONN BRAYAM | D79: SI | E79: SI | F79: Pontificia Universidad Católica del Perú | G79: BACHILLER EN CIENCIAS CON MENCIÓN EN INGENIERÍA CIVIL | H79: SI | I79: SI
A80: FUERZA POPULAR | B80: 42551310 | C80: VIDAURRE FLORIDAS, CESAR MANUEL | D80: SI | E80: SI | F80: Universidad Científica del Perú | G80: BACHILLER EN CONTABILIDAD | H80: SI | I80: SI
A81: FUERZA POPULAR | B81: 42551310 | C81: VIDAURRE FLORIDAS, CESAR MANUEL | D81: SI | E81: SI | F81: Universidad Particular de Iquitos | G81: CONTADOR PUBLICO | H81: SI | I81: SI
A82: FUERZA POPULAR | B82: 80387180 | C82: ZEGARRA SANCHEZ, CARLOS ALBERTO | D82: SI | E82: SI | F82: Universidad Alas Peruanas S.A. | G82: INGENIERO DE SISTEMAS E INFORMATICA | H82: SI | I82: SI
A83: FUERZA POPULAR | B83: 80387180 | C83: ZEGARRA SANCHEZ, CARLOS ALBERTO | D83: SI | E83: SI | F83: Universidad Alas Peruanas S.A. | G83: BACHILLER EN INGENIERIA DE SISTEMAS E INFORMATICA | H83: SI | I83: SI
A84: JUNTOS POR EL PERU | B84: 46432487 | C84: AGUIRRE RAMOS, MARLON ALBERTO | D84: SI | E84: SI | F84: Universidad Peruana Los Andes | G84: BACHILLER EN INGENIERÍA CIVIL | H84: SI | I84: SI
A85: JUNTOS POR EL PERU | B85: 46432487 | C85: AGUIRRE RAMOS, MARLON ALBERTO | D85: SI | E85: SI | F85: Universidad Continental S.A.C. | G85: BACHILLER EN INGENIERÍA ELÉCTRICA | H85: SI | I85: SI
A86: JUNTOS POR EL PERU | B86: 46432487 | C86: AGUIRRE RAMOS, MARLON ALBERTO | D86: SI | E86: SI | F86: Universidad Peruana Los Andes | G86: Ingeniero Civil | H86: SI | I86: SI
A87: JUNTOS POR EL PERU | B87: 43845728 | C87: AMBROSIO DOMINGUEZ, YULI LILIANA | D87: SI | E87: SI | F87: Universidad de Huánuco | G87: TITULO PROFESIONAL DE LICENCIADA EN ENFERMERIA | H87: SI | I87: SI
... A110: JUNTOS POR EL PERU | B110: 42135939 | C110: PEÑA CORDOVA, OLVER | D110: SI | E110: SI | F110: Universidad José Carlos Mariátegui | G110: BACHILLER EN EDUCACION | H110: SI | I110: SI
A111: JUNTOS POR EL PERU | B111: 10536312 | C111: PEREZ MALLQUI, JULIAN LUIS | D111: SI | E111: SI | F111: UNIVERSIDAD CONTINENTAL | G111: DERECHO | H111: NO
A112: JUNTOS POR EL PERU | B112: 44908591 | C112: PEREZ QUISPE, JESSICA SADITH | D112: SI | E112: SI | F112: Universidad Andina Néstor Cáceres Velásquez | G112: BACHILLER EN DERECHO | H112: SI | I112: SI
A113: JUNTOS POR EL PERU | B113: 44908591 | C113: PEREZ QUISPE, JESSICA SADITH | D113: SI | E113: SI | F113: Universidad Andina Néstor Cáceres Velásquez | G113: CONTADOR PUBLICO | H113: SI | I113: SI
A114: JUNTOS POR EL PERU | B114: 44908591 | C114: PEREZ QUISPE, JESSICA SADITH | D114: SI | E114: SI | F114: Universidad Andina Néstor Cáceres Velásquez | G114: ABOGADA | H114: SI | I114: SI
A115: JUNTOS POR EL PERU | B115: 44908591 | C115: PEREZ QUISPE, JESSICA SADITH | D115: SI | E115: SI | F115: Universidad Andina Néstor Cáceres Velásquez | G115: BACHILLER EN CIENCIAS CONTABLES | H115: SI | I115: SI
A116: JUNTOS POR EL PERU | B116: 42984568 | C116: POMA HUAMANI, HAYDEE CELINDA | D116: NO
A117: JUNTOS POR EL PERU | B117: 70163475 | C117: TAPULLIMA INSAPILLO, JACQUELINE VIVIANA | D117: NO
A118: JUNTOS POR EL PERU | B118: 01320941 | C118: TITO ROJAS, CESAR HUGO | D118: SI | E118: SI | F118: Universidad José Carlos Mariátegui | G118: BACHILLER EN DERECHO | H118: SI | I118: SI
A119: JUNTOS POR EL PERU | B119: 01320941 | C119: TITO ROJAS, CESAR HUGO | D119: SI | E119: SI | F119: Universidad José Carlos Mariátegui | G119: ABOGADO | H119: SI | I119: SI
A120: JUNTOS POR EL PERU | B120: 45327535 | C120: ZUNINI YERREN, ERNESTO ALONZO | D120: SI | E120: SI | F120: Universidad Nacional Pedro Ruiz Gallo | G120: LICENCIADO EN SOCIOLOGIA | H120: SI | I120: SI
A121: JUNTOS POR EL PERU | B121: 45327535 | C121: ZUNINI YERREN, ERNESTO ALONZO | D121: SI | E121: SI | F121: Universidad Nacional Pedro Ruiz Gallo | G121: BACHILLER EN SOCIOLOGIA | H121: SI | I121: SI
A122: PARTIDO CIVICO OBRAS | B122: 46602828 | C122: ALBAÑIL CARMONA, HENRY ANTONIO | D122: SI | E122: SI | F122: Universidad Nacional de Piura | G122: BACHILLER EN ARQUITECTURA Y URBANISMO | H122: SI | I122: SI
A123: PARTIDO CIVICO OBRAS | B123: 46602828 | C123: ALBAÑIL CARMONA, HENRY ANTONIO | D123: SI | E123: SI | F123: Universidad Nacional de Piura | G123: ARQUITECTO | H123: SI | I123: SI
A124: PARTIDO CIVICO OBRAS | B124: 43170121 | C124: ALVARON DE LA CRUZ, EDGAR ADRIAN | D124: SI | E124: SI | F124: Universidad Nacional Santiago Antúnez de Mayolo | G124: BACHILLER EN CIENCIAS AGRONOMIA | H124: SI | I124: SI
A125: PARTIDO CIVICO OBRAS | B125: 43170121 | C125: ALVARON DE LA CRUZ, EDGAR ADRIAN | D125: SI | E125: SI | F125: Universidad Nacional Santiago Antúnez de Mayolo | G125: INGENIERO AGRONOMO | H125: SI | I125: SI
A126: PARTIDO CIVICO OBRAS | B126: 00482691 | C126: CABRERA NIETO, JUAN CESAR | D126: NO
A127: PARTIDO CIVICO OBRAS | B127: 07654582 | C127: EUSEBIO PADILLA, ARTURO CESAR | D127: SI | E127: SI | F127: Universidad Nacional de Educación Enrique Guzmán y Valle | G127: BACHILLER EN EDUCACION | H127: SI | I127: SI
A128: PARTIDO CIVICO OBRAS | B128: 07654582 | C128: EUSEBIO PADILLA, ARTURO CESAR | D128: SI | E128: SI | F128: Universidad Nacional de Educación Enrique Guzmán y Valle | G128: LICENCIADO EN EDUCACION | H128: SI | I128: SI
A129: PARTIDO CIVICO OBRAS | B129: 01545223 | C129: HANCCO HANCCO, DINA IRENE | D129: SI | E129: SI | F129: Universidad Nacional Federico Villarreal | G129: BACHILLER EN EDUCACIÓN | H129: SI | I129: SI
A130: PARTIDO CIVICO OBRAS | B130: 01545223 | C130: HANCCO HANCCO, DINA IRENE | D130: SI | E130: SI | F130: Universidad Nacional Federico Villarreal | G130: BACHILLER EN EDUCACIÓN | H130: SI | I130: SI
A131: PARTIDO CIVICO OBRAS | B131: 25001331 | C131: LOPEZ LETONA, HEBER | D131: SI | E131: SI | F131: Universidad Privada Telesup S.A.C. | G131: BACHILLER EN DERECHO CORPORATIVO | H131: SI | I131: SI
A132: PARTIDO CIVICO OBRAS | B132: 25001331 | C132: LOPEZ LETONA, HEBER | D132: SI | E132: SI | F132: Universidad Privada Telesup S.A.C. | G132: ABOGADO | H132: SI | I132: SI
A133: PARTIDO CIVICO OBRAS | B133: 41242025 | C133: MASCO CACERES, LUIS AURELIO | D133: NO
A134: PARTIDO CIVICO OBRAS | B134: 46089177 | C134: MEDINA STEIN, ANDREA DAYNA | D134: SI | E134: SI | F134: Universidad ESAN | G134: BACHILLER EN ADMINISTRACIÓN Y MARKETING | H134: SI | I134: SI
A135: PARTIDO CIVICO OBRAS | B135: 46089177 | C135: MEDINA STEIN, ANDREA DAYNA | D135: SI | E135: SI | F135: Universidad ESAN | G135: LICENCIADA EN ADMINISTRACIÓN Y MARKETING | H135: SI | I135: SI
A136: PARTIDO CIVICO OBRAS | B136: 19995860 | C136: PERALTA JORPA, MAXIMO | D136: SI | E136: SI | F136: universidad ALCIDES CARRIÓN | G136: BACHILLER | H136: SI | I136: SI
A137: PARTIDO CIVICO OBRAS | B137: 70074678 | C137: PIÑAN MAMANI, VICTOR EDUARDO | D137: SI | E137: SI | F137: Universidad Nacional Mayor de San Marcos | G137: BACHILLER EN CIENCIA POLITICA | H137: SI | I137: SI
A138: PARTIDO CIVICO OBRAS | B138: 07793641 | C138: SAMANEZ GONZALES VIGIL, JEENNY CRISTINA | D138: NO
...

Sheet 03 FORM. ACADEM. - POSGRADO
A1: ORGANIZACION_POLITICA | B1: DNI_CANDIDATO | C1: CANDIDATO | D1: TIENE_POSGRADO | E1: POSGRADO | F1: CENTRO_ESTUDIOS | G1: ESPECIALIDAD_GRADO | H1: CONCLUIDO | I1: EGRESADO | J1: ES_MAESTRO | K1: ES_DOCTOR | L1: AÑO | M1: INFORMACION_COMPLEMENTARIA
A2: AHORA NACION - AN | B2: 29569533 | C2: ARMINTA VALENCIA, MARLENY BIBIANA | D2: SI | E2: SI | F2: Universidad Nacional de San Agustín | G2: Maestría en Psicología Clínica Educativa Infantil y Adolescencial | H2: SI | I2: SI | J2: NO | K2: NO | M2: Estudios concluidos, mas no obtuve el grado.
A3: AHORA NACION - AN | B3: 29569533 | C3: ARMINTA VALENCIA, MARLENY BIBIANA | D3: SI | E3: SI | F3: Universidad Nacional de San Agustín de Arequipa | G3: MAESTRO EN CIENCIAS: CONTABLES Y ADMINISTRATIVAS | H3: SI | I3: SI | J3: SI | L3: 2013
A4: AHORA NACION - AN | B4: 29569533 | C4: ARMINTA VALENCIA, MARLENY BIBIANA | D4: SI | E4: SI | F4: Universidad Nacional de San Agustín de Arequipa | G4: DOCTORA EN CIENCIAS EMPRESARIALES | H4: SI | I4: SI | K4: SI | L4: 2017
A5: AHORA NACION - AN | B5: 41618961 | C5: BUITRON MARTINEZ, FRESHMAN | D5: NO
A6: AHORA NACION - AN | B6: 43592504 | C6: COLCHADO HUAMANI, HARVEY JULIO | D6: SI | E6: SI | F6: Pontificia Universidad Católica del Perú | G6: MAGÍSTER EN GOBIERNO Y POLÍTICAS PÚBLICAS | H6: SI | I6: SI | J6: SI | L6: 2022
A7: AHORA NACION - AN | B7: 43572794 | C7: HOLGUIN LOAIZA, CESAR AUGUSTO | D7: SI | E7: SI | F7: Universidad Nacional de San Antonio Abad del Cusco | G7: MAESTRO EN ECONOMÍA MENCIÓN GESTIÓN PÚBLICA Y DESARROLLO REGIONAL | H7: SI | I7: SI | J7: SI | L7: 2024
A8: AHORA NACION - AN | B8: 43572794 | C8: HOLGUIN LOAIZA, CESAR AUGUSTO | D8: SI | E8: SI | F8: Universidad Nacional San Antonio Abad del Cusco | G8: Doctorado en Economía | H8: NO | M8: Desde 2024
A9: AHORA NACION - AN | B9: 45218393 | C9: HUILCA FLORES, INDIRA ISABEL | D9: SI | E9: SI | F9: Pontificia Universidad Católica del Perú | G9: Maestría en Ciencia Política y Gobierno | H9: NO
A10: AHORA NACION - AN | B10: 70665764 | C10: MANRIQUE OLIVERA, BERNARDINO JAIR | D10: NO
A11: AHORA NACION - AN | B11: 41840094 | C11: MARCELO SALAZAR, JOSE MIGUEL | D11: SI | E11: SI | F11: Universidad Del Pacifico | G11: Maestría en Finanzas Corporativas | H11: SI | I11: NO | M11: Con fecha 30/07/2019 se emitió constancia de notas con créditos culminados, a la fecha categoría egresado.
A12: AHORA NACION - AN | B12: 42839004 | C12: MUEDAS BALBIESE, CESAR AUGUSTO | D12: SI | E12: SI | F12: Universidad Peruana Los Andes UPLA | G12: Gestión Pública | H12: NO | M12: Se concluye la maestría el 21/12/25
A13: AHORA NACION - AN | B13: 46307918 | C13: SONCO VILLANUEVA, HELARD BLADIMIR | D13: NO
A14: FUERZA POPULAR | B14: 09391698 | C14: ABENSUR PINASCO, JAIME AMERICO | D14: SI | E14: SI | F14: Universidad de San Martín de Porres | G14: MAESTRO EN GESTIÓN PÚBLICA | H14: SI | I14: SI | J14: SI | L14: 2025
A15: FUERZA POPULAR | B15: 45382589 | C15: ALEGRIA GARCIA, LUIS ARTURO | D15: NO
A16: FUERZA POPULAR | B16: 15984771 | C16: ANDRADE SALGUERO DE ALVAREZ, GLADYS GRISELDA | D16: SI | E16: SI | F16: Universidad San Ignacio de Loyola | G16: Gestión Pública | H16: NO
A17: FUERZA POPULAR | B17: 76030152 | C17: BARBARAN REYES, ROSANGELLA ANDREA | D17: SI | E17: SI | F17: UNIVERSIDAD REY JUAN CARLOS | G17: TÍTULO OFICIAL DE MÁSTER UNIVERSITARIO EN CIENCIA POLÍTICA Y GESTIÓN PÚBLICA (GRADO DE MAESTRO) | H17: SI | I17: SI | J17: SI | L17: 2025
A18: FUERZA POPULAR | B18: 22509175 | C18: BETETA RUBIN, KARINA JULIZA | D18: SI | E18: SI | F18: Universidad Nacional Mayor de San Marcos | G18: Maestría en Derecho Civil y Comercial | H18: SI | I18: SI | J18: NO | K18: NO
A19: FUERZA POPULAR | B19: 22509175 | C19: BETETA RUBIN, KARINA JULIZA | D19: SI | E19: SI | F19: Universidad de la Rioja - España | G19: Maestría en Comunicación y Marketing Político | H19: SI | I19: SI | J19: NO | K19: NO
A20: FUERZA POPULAR | B20: 40224994 | C20: BOBADILLA GALINDO, ANGEL BRUNO | D20: SI | E20: SI | F20: Universidad Peruana de Ciencias Aplicadas S.A.C. | G20: MAESTRO EN DERECHO DE LA EMPRESA | H20: SI | I20: SI | J20: SI | L20: 2018
A21: FUERZA POPULAR | B21: 44807108 | C21: CASTILLO RIVAS, EDUARDO ENRIQUE | D21: NO
A22: FUERZA POPULAR | B22: 16650849 | C22: CASTRO CRUZ, JAVIER ALEJANDRO | D22: NO
A23: FUERZA POPULAR | B23: 10587515 | C23: CASTRO GRANDEZ, ROYSER | D23: NO
A24: FUERZA POPULAR | B24: 07750373 | C24: CELIZ CASTILLO, RAFAEL ALDO | D24: SI | E24: SI | F24: Universidad Particular Ricardo Palma | G24: Ciencias Políticas | H24: SI | I24: SI | J24: NO | K24: NO | M24: Maestría concluida y aprobada con situación de egresado.
A25: FUERZA POPULAR | B25: 09536896 | C25: CHACON DE VETTORI, CECILIA ISABEL | D25: NO
A26: FUERZA POPULAR | B26: 40826681 | C26: COLUMBUS MURATA, DIETHELL | D26: SI | E26: SI | F26: Universidad de San Martín de Porres | G26: MAESTRO EN SOLUCIÓN DE CONFLICTOS | H26: SI | I26: SI | J26: SI | L26: 2022
A27: FUERZA POPULAR | B27: 42433830 | C27: DODERO JOVICH, PIERANGELI DANIELA | D27: NO
A28: FUERZA POPULAR | B28: 07268767 | C28: FIGARI MENDOZA, PIER PAOLO | D28: NO
A29: FUERZA POPULAR | B29: 42516751 | C29: GAMARRA PITA, LUZMILA MARIA DEL CARMEN | D29: NO
A30: FUERZA POPULAR | B30: 16448130 | C30: INFANTES CASTAÑEDA, MERY ELIANA | D30: NO
A31: FUERZA POPULAR | B31: 41919665 | C31: LEIVA BAYLON, LETICIA MARUJA | D31: SI | E31: SI | F31: UNIVERSIDAD INTERNACIONAL DE LA RIOJA | G31: TÍTULO OFICIAL DE MÁSTER UNIVERSITARIO EN COMUNICACIÓN Y MARKETING POLÍTICO (GRADO DE MAESTRO) | H31: SI | I31: SI | J31: SI | L31: 2023
A32: FUERZA POPULAR | B32: 10187011 | C32: MENDOZA BERNEDO, LIZ HULI | D32: SI | E32: SI | F32: UNIVERSIDAD DE SEVILLA | G32: TITULO DE MASTER EN IMPLANTOLOGÍA ORAL | H32: SI | I32: SI | J32: SI | L32: 2013 | M32: TITULO PROPIO (SEVILLA - ESPAÑA)
A33: FUERZA POPULAR | B33: 10028427 | C33: NAVAS SANCHEZ, JESSICA LIZBETH | D33: NO | E33: SI
A34: FUERZA POPULAR | B34: 07737110 | C34: OBANDO MORGAN, AURISTELA ANA | D34: NO
A35: FUERZA POPULAR | B35: 47000483 | C35: PACHECO QUISPE, MARCO ANTONIO | D35: SI | E35: SI | F35: UNIVERSITAT POMPEU FABRA | G35: TÍTULO UNIVERSITARIO OFICIAL DE MÁSTER EN GOBIERNO Y GESTIÓN PÚBLICA EN AMÉRICA LATINA (GRADO DE MAESTRO) | H35: SI | I35: SI | J35: SI | L35: 2025
A36: FUERZA POPULAR | B36: 45721573 | C36: PALMA MENDOZA, JOSE MARVIN | D36: NO
A37: FUERZA POPULAR | B37: 10792277 | C37: PATIÑO URCO, ANA BERTHA | D37: SI | E37: SI | F37: UNIVERSIDAD SAN MARTIN DE PORRES | G37: GESTIÓN PÚBLICA | H37: SI | I37: SI | J37: NO | K37: NO | M37: Estudié la citada maestría en el periodo 2014-2015.
A38: FUERZA POPULAR | B38: 41408779 | C38: PAUCARA PAXI, CARMELA | D38: NO
A39: FUERZA POPULAR | B39: 05414308 | C39: PINASCO MONTENEGRO, NARY BENVINDA | D39: SI | E39: SI | F39: Universidad Científica del Perú | G39: Magíster en Gestión, mención en Finanzas Públicas | H39: SI | I39: SI | J39: SI | L39: 2022
A40: FUERZA POPULAR | B40: 44275599 | C40: REVILLA VILLANUEVA, CESAR MANUEL | D40: SI | E40: SI | F40: Universidad Privada César Vallejo | G40: MAGISTER EN GESTION DE LOS SERVICIOS DE LA SALUD | H40: SI | I40: SI | J40: SI | L40: 2014
A41: FUERZA POPULAR | B41: 44275599 | C41: REVILLA VILLANUEVA, CESAR MANUEL | D41: SI | E41: SI | F41: Universidad César Vallejo S.A.C. | G41: DOCTOR EN GESTIÓN PÚBLICA Y GOBERNABILIDAD | H41: SI | I41: SI | K41: SI | L41: 2021
A42: FUERZA POPULAR | B42: 80328889 | C42: SALAS RIVERA, ALEXANDER | D42: NO
A43: FUERZA POPULAR | B43: 27424381 | C43: TICLLA RAFAEL, SEGUNDO SENOVIO | D43: NO
A44: FUERZA POPULAR | B44: 40433187 | C44: TORRES MORALES, MIGUEL ANGEL | D44: SI | E44: SI | F44: Universidad de Piura | G44: MAGISTER EN GOBIERNO DE LAS ORGANIZACIONES | H44: SI | I44: SI | J44: SI | L44: 2020 | M44: Mi fecha de egreso es el 21/08/2020. Y, la obtención del título es el 29/01/21.
A45: FUERZA POPULAR | B45: 40433187 | C45: TORRES MORALES, MIGUEL ANGEL | D45: SI | E45: SI | F45: Universidad de Piura | G45: MAGISTER EN GOBIERNO DE LAS ORGANIZACIONES | H45: SI | I45: SI | J45: SI | L45: 2020 | M45: Mi fecha de egreso es el 21/08/2020. Y, la obtención del título es el 29/01/21.
A46: FUERZA POPULAR | B46: 08571708 | C46: TRUJILLO ZEGARRA, GILMER | D46: SI | E46: SI | F46: Universidad Privada César Vallejo | G46: MAGISTER EN GESTION PUBLICA | H46: SI | I46: SI | J46: SI | L46: 2016
A47: FUERZA POPULAR | B47: 47654459 | C47: VALQUI ORDOÑEZ, JHONN BRAYAM | D47: NO
A48: FUERZA POPULAR | B48: 42551310 | C48: VIDAURRE FLORIDAS, CESAR MANUEL | D48: SI | E48: SI | F48: Universidad Nacional de la Amazonía Peruana | G48: MAGISTER EN GESTION EMPRESARIAL | H48: SI | I48: SI | J48: SI | L48: 2013
A49: FUERZA POPULAR | B49: 80387180 | C49: ZEGARRA SANCHEZ, CARLOS ALBERTO | D49: SI | E49: SI | F49: Universidad Peruana de Ciencias e Informática S.A.C. | G49: MAESTRO EN INVESTIGACIÓN Y DOCENCIA UNIVERSITARIA | H49: SI | I49: SI | J49: SI | L49: 2019
A50: FUERZA POPULAR | B50: 80387180 | C50: ZEGARRA SANCHEZ, CARLOS ALBERTO | D50: SI | E50: SI | F50: Universidad Nacional Santiago Antúnez de Mayolo | G50: DOCTOR EN EDUCACIÓN | H50: SI | I50: SI | K50: SI | L50: 2025
A51: JUNTOS POR EL PERU | B51: 46432487 | C51: AGUIRRE RAMOS, MARLON ALBERTO | D51: NO
A52: JUNTOS POR EL PERU | B52: 43845728 | C52: AMBROSIO DOMINGUEZ, YULI LILIANA | D52: NO
A53: JUNTOS POR EL PERU | B53: 40855980 | C53: AVENDAÑO VILCA, GIANNINA IRIS | D53: SI | E53: SI | F53: Universitat Pompeu Fabra | G53: Ciencias Políticas | H53: SI | I53: SI | J53: SI | L53: 2010 | M53: Registro NRO.067 - SERVIR 2019
A54: JUNTOS POR EL PERU | B54: 01223056 | C54: CONDORI FLORES, REMIGIO | D54: SI | E54: SI | F54: Universidad Andina Ne`stor Càceres Velasquez | G54: Derecho Constitucional | H54: SI | I54: SI | J54: NO | K54: NO
A55: JUNTOS POR EL PERU | B55: 41711513 | C55: FLORES VALDIZAN, MARCO ANTONIO | D55: NO
A56: JUNTOS POR EL PERU | B56: 40093361 | C56: GONZALES DELGADO, GABRIEL ROBERTINO | D56: NO
A57: JUNTOS POR EL PERU | B57: 04810886 | C57: HOLGUIN AGUIRRE, JAMES ARTURO | D57: NO
A58: JUNTOS POR EL PERU | B58: 45442927 | C58: MARQUEZ HUANCA, ANALI | D58: SI | E58: SI | F58: Universidad César Vallejo S.A.C. | G58: MAESTRA EN GESTIÓN PÚBLICA | H58: SI | I58: SI | J58: SI | L58: 2021
A59: JUNTOS POR EL PERU | B59: 45442927 | C59: MARQUEZ HUANCA, ANALI | D59: SI | E59: SI | F59: Universidad César Vallejo S.A.C. | G59: MAESTRA EN GESTIÓN PÚBLICA | H59: SI | I59: SI | J59: SI | L59: 2021
A60: JUNTOS POR EL PERU | B60: 29313850 | C60: PALOMINO PACHECO, AMALIA EMILIA | D60: NO
A61: JUNTOS POR EL PERU | B61: 74638299 | C61: PAREDES NAVARRO, YENIFER NOELIA | D61: NO
A62: JUNTOS POR EL PERU | B62: 42135939 | C62: PEÑA CORDOVA, OLVER | D62: NO
A63: JUNTOS POR EL PERU | B63: 10536312 | C63: PEREZ MALLQUI, JULIAN LUIS | D63: NO
A64: JUNTOS POR EL PERU | B64: 44908591 | C64: PEREZ QUISPE, JESSICA SADITH | D64: SI | E64: SI | F64: Universidad Nacional del Altiplano | G64: Magíster Scientiae en Contabilidad y Administración Mención en Administración y Finanzas | H64: SI | I64: SI | J64: SI | L64: 2020
A65: JUNTOS POR EL PERU | B65: 42984568 | C65: POMA HUAMANI, HAYDEE CELINDA | D65: NO
A66: JUNTOS POR EL PERU | B66: 70163475 | C66: TAPULLIMA INSAPILLO, JACQUELINE VIVIANA | D66: NO
A67: JUNTOS POR EL PERU | B67: 01320941 | C67: TITO ROJAS, CESAR HUGO | D67: SI | E67: SI | F67: Universidad Cesar Vallejo | G67: Gestión Pública | H67: SI | I67: SI | J67: NO | K67: NO
A68: JUNTOS POR EL PERU | B68: 45327535 | C68: ZUNINI YERREN, ERNESTO ALONZO | D68: SI | E68: SI | F68: UNIVERSIDAD DE SAN MARTÍN DE PORRES | G68: GESTIÓN PÚBLICA | H68: SI | I68: SI | J68: NO | K68: NO | M68: EN SUSTENTACIÓN DE TESIS
A69: PARTIDO CIVICO OBRAS | B69: 46602828 | C69: ALBAÑIL CARMONA, HENRY ANTONIO | D69: NO
A70: PARTIDO CIVICO OBRAS | B70: 43170121 | C70: ALVARON DE LA CRUZ, EDGAR ADRIAN | D70: NO
A71: PARTIDO CIVICO OBRAS | B71: 00482691 | C71: CABRERA NIETO, JUAN CESAR | D71: NO
A72: PARTIDO CIVICO OBRAS | B72: 07654582 | C72: EUSEBIO PADILLA, ARTURO CESAR | D72: SI | E72: SI | F72: Universidad Nacional de Educación Enrique Guzmán y Valle | G72: MAESTRO EN CIENCIAS DE LA EDUCACIÓN CON MENCIÓN EN GESTIÓN EDUCACIONAL | H72: SI | I72: SI | J72: SI | L72: 2022
A73: PARTIDO CIVICO OBRAS | B73: 01545223 | C73: HANCCO HANCCO, DINA IRENE | D73: SI | E73: SI | F73: UNIVERSIDAD INCA GARCILAZO DE LA VEGA | G73: MAESTRIA EN INVESTIGACIÓN Y DOCENCIA UNIVERSITARIA | H73: SI | I73: SI | J73: NO | K73: NO
A74: PARTIDO CIVICO OBRAS | B74: 01545223 | C74: HANCCO HANCCO, DINA IRENE | D74: SI | E74: SI | F74: UNIVERSIDAD INCA GARCILAZO DE LA VEGA | G74: MAESTRIA EN INVESTIGACIÓN Y DOCENCIA UNIVERSITARIA | H74: SI | I74: SI | J74: NO | K74: NO
A75: PARTIDO CIVICO OBRAS | B75: 25001331 | C75: LOPEZ LETONA, HEBER | D75: SI | E75: SI | F75: UNIVERSIDAD AUTONOMA DEL PERÚ | G75: MAESTRIA EN DERECHO PENAL | H75: NO
A76: PARTIDO CIVICO OBRAS | B76: 41242025 | C76: MASCO CACERES, LUIS AURELIO | D76: NO
A77: PARTIDO CIVICO OBRAS | B77: 46089177 | C77: MEDINA STEIN, ANDREA DAYNA | D77: NO
A78: PARTIDO CIVICO OBRAS | B78: 19995860 | C78: PERALTA JORPA, MAXIMO | D78: NO
A79: PARTIDO CIVICO OBRAS | B79: 70074678 | C79: PIÑAN MAMANI, VICTOR EDUARDO | D79: NO
A80: PARTIDO CIVICO OBRAS | B80: 07793641 | C80: SAMANEZ GONZALES VIGIL, JEENNY CRISTINA | D80: NO
A81: PARTIDO CIVICO OBRAS | B81: 17930730 | C81: VALQUI CALDERON, DEMETRIO FLAVIO | D81: NO
A82: PARTIDO CIVICO OBRAS | B82: 42188288 | C82: YATACO TORREALVA, JOSE RICARDO | D82: SI | E82: SI | F82: Universidad Nacional San Luis Gonzaga | G82: MAESTRO EN INGENIERÍA DE SISTEMAS - MENCIÓN GESTIÓN DE LA TECNOLOGÍA DE LA INFORMACIÓN | H82: SI | I82: SI | J82: SI | L82: 2023
A83: PARTIDO DEL BUEN GOBIERNO | B83: 43478989 | C83: ALAYZA MACCERA, ROSSANA HERMINIA | D83: SI | E83: SI | F83: Tecnológico de Monterrey | G83: Diplomado en Inversión Social Privada | H83: SI | I83: SI | J83: NO | K83: NO
A84: PARTIDO DEL BUEN GOBIERNO | B84: 41356710 | C84: BENITEZ BARRIONUEVO, JESSICA | D84: SI | E84: SI | F84: Universidad José Carlos Mariátegui | G84: Docencia e investigación universitaria | H84: SI | I84: SI | J84: NO | K84: NO | M84: Me encuentro como egresada de la maestría.
A85: PARTIDO DEL BUEN GOBIERNO | B85: 41356710 | C85: BENITEZ BARRIONUEVO, JESSICA | D85: SI | E85: SI | F85: Universidad César Vallejo S.A.C. | G85: Maestra en Gestión Pública | H85: SI | I85: SI | J85: SI | L85: 2023
A86: PARTIDO DEL BUEN GOBIERNO | B86: 16629849 | C86: CASTREJON FERNANDEZ, SEGUNDO JUAN | D86: SI | E86: SI | F86: Universidad Nacional Pedro Ruiz Gallo | G86: MAESTRO EN CIENCIAS DE LA EDUCACION CON MENCION EN INVESTIGACION Y DOCENCIA | H86: SI | I86: SI | J86: SI | L86: 2021
A87: PARTIDO DEL BUEN GOBIERNO | B87: 10277219 | C87: DUARTE PATIÑO DE PEZET, CARMEN GEORGINA | D87: SI | E87: SI | F87: UNIVERSIDAD RICARDO PALMA | G87: Maestría en Ciencias Políticas | H87: SI | I87: SI | J87: NO | K87: NO
A88: PARTIDO DEL BUEN GOBIERNO | B88: 31038213 | C88: FERNANDEZ DE LA TORRE, HILDA JUDIT | D88: NO
A89: PARTIDO DEL BUEN GOBIERNO | B89: 08573694 | C89: GARCIA HUBY, FERNANDO ALBERTO | D89: NO
A90: PARTIDO DEL BUEN GOBIERNO | B90: 29715400 | C90: GONZALES POLAR, EDGAR DEMBER | D90: SI | E90: SI | F90: Universidad Nacional San Agustin | G90: Magister en Gestión Pública | H90: NO
A91: PARTIDO DEL BUEN GOBIERNO | B91: 29311981 | C91: HIRACHE PIZARRO, GLORIA CHARITO | D91: NO
A92: PARTIDO DEL BUEN GOBIERNO | B92: 02819812 | C92: HUAMAN CORNEJO, MIGUEL FELIX | D92: NO
A93: PARTIDO DEL BUEN GOBIERNO | B93: 06296745 | C93: LLAQUE LINARES, NORA MARIA | D93: NO
A94: PARTIDO DEL BUEN GOBIERNO | B94: 76871362 | C94: MOLINA SOTO, NATHALY MILAGROS | D94: NO
A95: PARTIDO DEL BUEN GOBIERNO | B95: 45741388 | C95: PRADO VALLEJOS, LILA MARIANELA | D95: NO
A96: PARTIDO DEL BUEN GOBIERNO | B96: 40067839 | C96: QUISPE CANDIA, LUIS ELISEO | D96: SI | E96: SI | F96: Universidad Inca Garcilaso de la Vega Asociación Civil | G96: Doctorado en Derecho | H96: NO | M96: Me encuentro en el tercer ciclo del doctorado y con miras a retornarlo
A97: PARTIDO DEL BUEN GOBIERNO | B97: 40067839 | C97: QUISPE CANDIA, LUIS ELISEO | D97: SI | E97: SI | F97: Universidad Inca Garcilaso de la Vega Asociación Civil | G97: Maestría en Nuevo Código Procesal Penal con mención en Litigación Oral | H97: SI | I97: SI | J97: NO | K97: NO
A98: PARTIDO DEL BUEN GOBIERNO | B98: 43348625 | C98: RETO OTERO, OSCAR DE JESUS | D98: SI | E98: SI | F98: Universidad Alas Peruanas S.A. | G98: MAESTRO EN ADMINISTRACION | H98: SI | I98: SI | J98: SI | L98: 2013
A99: PARTIDO DEL BUEN GOBIERNO | B99: 43348625 | C99: RETO OTERO, OSCAR DE JESUS | D99: SI | E99: SI | F99: Escuela Superior de Guerra del Ejército | G99: MAESTRO EN CIENCIAS MILITARES | H99: SI | I99: SI | J99: SI | L99: 2015
A100: RENOVACION POPULAR | B100: 70747151 | C100: ARANDA VASQUEZ, CHRISTIAN | D100: SI | E100: SI | F100: UNIVERSIDAD CATÓLICA SAN PABLO | G100: GESTIÓN PÚBLICA Y POLÍTICAS PÚBLICAS | H100: SI | I100: SI | J100: NO | K100: NO | M100: ESTUDIOS CONCLUIDOS EN EL AÑO 2024
...

Sheet 03 FORM. ACADEM. - OTRO POSGRAD
A1: ORGANIZACION_POLITICA | B1: DNI_CANDIDATO | C1: CANDIDATO | D1: TIENE_OTRO_POSGRADO | E1: POSGRADO_OTRO | F1: CENTRO_ESTUDIOS | G1: ESPECIALIDAD | H1: CONCLUIDO | I1: EGRESADO | J1: GRADO | K1: AÑO | L1: INFORMACION_COMPLEMENTARIA
A2: AHORA NACION - AN | B2: 29569533 | C2: ARMINTA VALENCIA, MARLENY BIBIANA | D2: NO
A3: AHORA NACION - AN | B3: 41618961 | C3: BUITRON MARTINEZ, FRESHMAN | D3: NO
A4: AHORA NACION - AN | B4: 43592504 | C4: COLCHADO HUAMANI, HARVEY JULIO | D4: NO
A5: AHORA NACION - AN | B5: 43572794 | C5: HOLGUIN LOAIZA, CESAR AUGUSTO | D5: NO
A6: AHORA NACION - AN | B6: 45218393 | C6: HUILCA FLORES, INDIRA ISABEL | D6: NO
A7: AHORA NACION - AN | B7: 70665764 | C7: MANRIQUE OLIVERA, BERNARDINO JAIR | D7: SI | E7: SI | F7: Massachussetts Institute of Technology | G7: Digital Transformator | H7: SI | I7: SI | J7: Digital Transformator | K7: 2021 | L7: No está Inscrito en SUNEDU
A8: AHORA NACION - AN | B8: 41840094 | C8: MARCELO SALAZAR, JOSE MIGUEL | D8: NO
A9: AHORA NACION - AN | B9: 42839004 | C9: MUEDAS BALBIESE, CESAR AUGUSTO | D9: SI | E9: SI | F9: European Open Business School | G9: Master en Innovación Digital y Excelencia Empresarial | H9: NO | L9: En proceso de estudio
A10: AHORA NACION - AN | B10: 46307918 | C10: SONCO VILLANUEVA, HELARD BLADIMIR | D10: NO
A11: FUERZA POPULAR | B11: 09391698 | C11: ABENSUR PINASCO, JAIME AMERICO | D11: SI | E11: SI | F11: Universidad de San Martín de Porres | G11: MAESTRIA EN DERECHO CIVIL Y COMERCIAL | H11: SI | I11: SI | L11: SOLO EGRESADO
A12: FUERZA POPULAR | B12: 45382589 | C12: ALEGRIA GARCIA, LUIS ARTURO | D12: NO
A13: FUERZA POPULAR | B13: 15984771 | C13: ANDRADE SALGUERO DE ALVAREZ, GLADYS GRISELDA | D13: NO
A14: FUERZA POPULAR | B14: 76030152 | C14: BARBARAN REYES, ROSANGELLA ANDREA | D14: NO
A15: FUERZA POPULAR | B15: 22509175 | C15: BETETA RUBIN, KARINA JULIZA | D15: NO | E15: SI
A16: FUERZA POPULAR | B16: 40224994 | C16: BOBADILLA GALINDO, ANGEL BRUNO | D16: NO
A17: FUERZA POPULAR | B17: 44807108 | C17: CASTILLO RIVAS, EDUARDO ENRIQUE | D17: NO
A18: FUERZA POPULAR | B18: 16650849 | C18: CASTRO CRUZ, JAVIER ALEJANDRO | D18: NO
A19: FUERZA POPULAR | B19: 10587515 | C19: CASTRO GRANDEZ, ROYSER | D19: NO
A20: FUERZA POPULAR | B20: 07750373 | C20: CELIZ CASTILLO, RAFAEL ALDO | D20: NO
A21: FUERZA POPULAR | B21: 09536896 | C21: CHACON DE VETTORI, CECILIA ISABEL | D21: NO
A22: FUERZA POPULAR | B22: 40826681 | C22: COLUMBUS MURATA, DIETHELL | D22: NO
A23: FUERZA POPULAR | B23: 42433830 | C23: DODERO JOVICH, PIERANGELI DANIELA | D23: NO
A24: FUERZA POPULAR | B24: 07268767 | C24: FIGARI MENDOZA, PIER PAOLO | D24: NO
A25: FUERZA POPULAR | B25: 42516751 | C25: GAMARRA PITA, LUZMILA MARIA DEL CARMEN | D25: NO
A26: FUERZA POPULAR | B26: 16448130 | C26: INFANTES CASTAÑEDA, MERY ELIANA | D26: NO
A27: FUERZA POPULAR | B27: 41919665 | C27: LEIVA BAYLON, LETICIA MARUJA | D27: NO
