Workbook

Sheet 01 DATOS PERSONALES
A1: ORGANIZACION_POLITICA | B1: DNI_CANDIDATO | C1: CANDIDATO | D1: DOCUMENTO_IDENTIDAD | E1: APELLIDO_PATERNO | F1: APELLIDO_MATERNO | G1: NOMBRES | H1: SEXO | I1: FECHA_NACIMIENTO | J1: PAIS_NACIMIENTO | K1: DEPARTAMENTO_NACIMIENTO | L1: PROVINCIA_NACIMIENTO | M1: DISTRITO_NACIMIENTO | N1: PRIMER_CARGO_ELECCION | O1: SEGUNDO_CARGO_ELECION | P1: DISTRITO_ELEC | Q1: INFORMACION_COMPLEMENTARIA | R1: URL_FOTO | S1: TXRUTAVIRTUAL | T1: TXNOMBREDOCUMENTO | U1: EDAD | V1: RANGO_EDAD | W1: PAÍS_LIMPIO | X1: SEXO_LIMPIO | Y1: DEP_NAC_LIMPIO | Z1: DISTRITO_ELEC_LIMPIO
A2: AHORA NACION - AN | B2: 07755878 | C2: DELGADO ZEGARRA, JAIME RICARDO | D2: 07755878 | E2: DELGADO | F2: ZEGARRA | G2: JAIME RICARDO | H2: MASCULINO | I2: 17/11/1956 | J2: PERÚ | K2: AREQUIPA | L2: AREQUIPA | M2: AREQUIPA | N2: SENADOR | P2: ÚNICO NACIONAL | R2: https://mpesije.jne.gob.pe/apidocs/9aee4b33-103e-4327-9038-3618515d950d.jpg | S2: https://mpesije.jne.gob.pe/apidocs/bec6fc78-6285-4522-a02e-2730994b7ca8.pdf | T2: =CONCATENATE(A2," - ",B2,".pdf") -> AHORA NACION - AN - 07755878.pdf | U2: =IF(I2="","",DATEDIF(DATE(VALUE(RIGHT(I2,4)),VALUE(MID(I2,4,2)),VALUE(LEFT(I2,2))),TODAY(),"Y")) -> 69 | V2: =IF(U2="","",IF(U2<30,"18-29",IF(U2<40,"30-39",IF(U2<50,"40-49",IF(U2<60,"50-59","60+"))))) -> 60+ | W2: =IF(UPPER(TRIM(J2))="PERU","PERÚ",UPPER(TRIM(J2))) -> PERÚ | X2: =UPPER(TRIM(H2)) -> MASCULINO | Y2: =UPPER(TRIM(K2)) -> AREQUIPA | Z2: =UPPER(TRIM(P2)) -> ÚNICO NACIONAL
A3: AHORA NACION - AN | B3: 25331980 | C3: LOPEZ CHAU NAVA, PABLO ALFONSO | D3: 25331980 | E3: LOPEZ CHAU | F3: NAVA | G3: PABLO ALFONSO | H3: MASCULINO | I3: 17/07/1950 | J3: PERÚ | K3: LIMA | L3: LIMA | M3: LIMA | N3: PRESIDENTE DE LA REPÚBLICA | O3: SENADOR | P3: ÚNICO NACIONAL | R3: https://mpesije.jne.gob.pe/apidocs/ddfa74eb-cae3-401c-a34c-35543ae83c57.jpg | S3: https://mpesije.jne.gob.pe/apidocs/4ba2cdce-703e-421b-8b75-746b4dd21439.pdf | T3: =CONCATENATE(A3," - ",B3,".pdf") -> AHORA NACION - AN - 25331980.pdf | U3: =IF(I3="","",DATEDIF(DATE(VALUE(RIGHT(I3,4)),VALUE(MID(I3,4,2)),VALUE(LEFT(I3,2))),TODAY(),"Y")) -> 75 | V3: =IF(U3="","",IF(U3<30,"18-29",IF(U3<40,"30-39",IF(U3<50,"40-49",IF(U3<60,"50-59","60+"))))) -> 60+ | W3: =IF(UPPER(TRIM(J3))="PERU","PERÚ",UPPER(TRIM(J3))) -> PERÚ | X3: =UPPER(TRIM(H3)) -> MASCULINO | Y3: =UPPER(TRIM(K3)) -> LIMA | Z3: =UPPER(TRIM(P3)) -> ÚNICO NACIONAL
A4: AHORA NACION - AN | B4: 40204874 | C4: LUQUE IBARRA, RUTH | D4: 40204874 | E4: LUQUE | F4: IBARRA | G4: RUTH | H4: FEMENINO | I4: 19/06/1979 | J4: PERÚ | K4: CUSCO | L4: CUSCO | M4: SANTIAGO | N4: SENADOR | P4: ÚNICO NACIONAL | R4: https://mpesije.jne.gob.pe/apidocs/428c14a1-1be6-477e-b02a-f0dec2dc8e65.jpg | S4: https://mpesije.jne.gob.pe/apidocs/ed569772-6440-41f6-a1ad-b62d373d92ef.pdf | T4: =CONCATENATE(A4," - ",B4,".pdf") -> AHORA NACION - AN - 40204874.pdf | U4: =IF(I4="","",DATEDIF(DATE(VALUE(RIGHT(I4,4)),VALUE(MID(I4,4,2)),VALUE(LEFT(I4,2))),TODAY(),"Y")) -> 46 | V4: =IF(U4="","",IF(U4<30,"18-29",IF(U4<40,"30-39",IF(U4<50,"40-49",IF(U4<60,"50-59","60+"))))) -> 40-49 | W4: =IF(UPPER(TRIM(J4))="PERU","PERÚ",UPPER(TRIM(J4))) -> PERÚ | X4: =UPPER(TRIM(H4)) -> FEMENINO | Y4: =UPPER(TRIM(K4)) -> CUSCO | Z4: =UPPER(TRIM(P4)) -> ÚNICO NACIONAL
A5: AHORA NACION - AN | B5: 26705695 | C5: VASQUEZ CHUQUILIN, MIRTHA ESTHER | D5: 26705695 | E5: VASQUEZ | F5: CHUQUILIN | G5: MIRTHA ESTHER | H5: FEMENINO | I5: 31/03/1975 | J5: PERÚ | K5: CAJAMARCA | L5: CAJAMARCA | M5: CAJAMARCA | N5: SENADOR | P5: ÚNICO NACIONAL | R5: https://mpesije.jne.gob.pe/apidocs/83aa4be4-54a0-4f96-874a-96ec34678843.jpg | S5: https://mpesije.jne.gob.pe/apidocs/26df0361-db17-47af-85bf-fc1e8ae1329b.pdf | T5: =CONCATENATE(A5," - ",B5,".pdf") -> AHORA NACION - AN - 26705695.pdf | U5: =IF(I5="","",DATEDIF(DATE(VALUE(RIGHT(I5,4)),VALUE(MID(I5,4,2)),VALUE(LEFT(I5,2))),TODAY(),"Y")) -> 51 | V5: =IF(U5="","",IF(U5<30,"18-29",IF(U5<40,"30-39",IF(U5<50,"40-49",IF(U5<60,"50-59","60+"))))) -> 50-59 | W5: =IF(UPPER(TRIM(J5))="PERU","PERÚ",UPPER(TRIM(J5))) -> PERÚ | X5: =UPPER(TRIM(H5)) -> FEMENINO | Y5: =UPPER(TRIM(K5)) -> CAJAMARCA | Z5: =UPPER(TRIM(P5)) -> ÚNICO NACIONAL
A6: FUERZA POPULAR | B6: 08236035 | C6: AGUINAGA RECUENCO, ALEJANDRO AURELIO | D6: 08236035 | E6: AGUINAGA | F6: RECUENCO | G6: ALEJANDRO AURELIO | H6: MASCULINO | I6: 28/01/1950 | J6: PERÚ | K6: LA LIBERTAD | L6: TRUJILLO | M6: TRUJILLO | N6: SENADOR | P6: LAMBAYEQUE | R6: https://mpesije.jne.gob.pe/apidocs/ec0a8246-1b06-4e2b-8037-a71cfce09cf5.jpg | S6: https://mpesije.jne.gob.pe/apidocs/6b4456ea-6731-4925-a6e7-056a36b87156.pdf | T6: =CONCATENATE(A6," - ",B6,".pdf") -> FUERZA POPULAR - 08236035.pdf | U6: =IF(I6="","",DATEDIF(DATE(VALUE(RIGHT(I6,4)),VALUE(MID(I6,4,2)),VALUE(LEFT(I6,2))),TODAY(),"Y")) -> 76 | V6: =IF(U6="","",IF(U6<30,"18-29",IF(U6<40,"30-39",IF(U6<50,"40-49",IF(U6<60,"50-59","60+"))))) -> 60+ | W6: =IF(UPPER(TRIM(J6))="PERU","PERÚ",UPPER(TRIM(J6))) -> PERÚ | X6: =UPPER(TRIM(H6)) -> MASCULINO | Y6: =UPPER(TRIM(K6)) -> LA LIBERTAD | Z6: =UPPER(TRIM(P6)) -> LAMBAYEQUE
A7: FUERZA POPULAR | B7: 06717199 | C7: ARISTA ARBILDO, JOSE BERLEY | D7: 06717199 | E7: ARISTA | F7: ARBILDO | G7: JOSE BERLEY | H7: MASCULINO | I7: 18/08/1959 | J7: PERÚ | K7: AMAZONAS | L7: RODRIGUEZ DE MENDOZA | M7: HUAMBO | N7: SENADOR | P7: AMAZONAS | R7: https://mpesije.jne.gob.pe/apidocs/d70fc358-ff34-4dfb-99fc-2cdcbb77ff83.jpg | S7: https://mpesije.jne.gob.pe/apidocs/4239a3ba-9445-4c88-a74d-d0d798857d45.pdf | T7: =CONCATENATE(A7," - ",B7,".pdf") -> FUERZA POPULAR - 06717199.pdf | U7: =IF(I7="","",DATEDIF(DATE(VALUE(RIGHT(I7,4)),VALUE(MID(I7,4,2)),VALUE(LEFT(I7,2))),TODAY(),"Y")) -> 66 | V7: =IF(U7="","",IF(U7<30,"18-29",IF(U7<40,"30-39",IF(U7<50,"40-49",IF(U7<60,"50-59","60+"))))) -> 60+ | W7: =IF(UPPER(TRIM(J7))="PERU","PERÚ",UPPER(TRIM(J7))) -> PERÚ | X7: =UPPER(TRIM(H7)) -> MASCULINO | Y7: =UPPER(TRIM(K7)) -> AMAZONAS | Z7: =UPPER(TRIM(P7)) -> AMAZONAS
A8: FUERZA POPULAR | B8: 10307948 | C8: ASTUDILLO SALCEDO, CESAR AUGUSTO | D8: 10307948 | E8: ASTUDILLO | F8: SALCEDO | G8: CESAR AUGUSTO | H8: MASCULINO | I8: 30/09/1960 | J8: PERÚ | K8: LIMA | L8: LIMA | M8: MIRAFLORES | N8: SENADOR | P8: ÚNICO NACIONAL | R8: https://mpesije.jne.gob.pe/apidocs/e4aee02d-e85d-44f7-aaca-9eb286ee132f.jpg | S8: https://mpesije.jne.gob.pe/apidocs/c3804a57-68ff-450f-b6d6-edd5fa532e44.pdf | T8: =CONCATENATE(A8," - ",B8,".pdf") -> FUERZA POPULAR - 10307948.pdf | U8: =IF(I8="","",DATEDIF(DATE(VALUE(RIGHT(I8,4)),VALUE(MID(I8,4,2)),VALUE(LEFT(I8,2))),TODAY(),"Y")) -> 65 | V8: =IF(U8="","",IF(U8<30,"18-29",IF(U8<40,"30-39",IF(U8<50,"40-49",IF(U8<60,"50-59","60+"))))) -> 60+ | W8: =IF(UPPER(TRIM(J8))="PERU","PERÚ",UPPER(TRIM(J8))) -> PERÚ | X8: =UPPER(TRIM(H8)) -> MASCULINO | Y8: =UPPER(TRIM(K8)) -> LIMA | Z8: =UPPER(TRIM(P8)) -> ÚNICO NACIONAL
A9: FUERZA POPULAR | B9: 32971154 | C9: CHACON TRUJILLO, NILZA MERLY | D9: 32971154 | E9: CHACON | F9: TRUJILLO | G9: NILZA MERLY | H9: FEMENINO | I9: 15/12/1975 | J9: PERÚ | K9: ANCASH | L9: SANTA | M9: CHIMBOTE | N9: SENADOR | P9: ANCASH | R9: https://mpesije.jne.gob.pe/apidocs/133f5d7c-5498-4a5e-81e2-a7c2f3f53d0c.jpg | S9: https://mpesije.jne.gob.pe/apidocs/647e50c4-80ae-491f-9f49-ead290ebba04.pdf | T9: =CONCATENATE(A9," - ",B9,".pdf") -> FUERZA POPULAR - 32971154.pdf | U9: =IF(I9="","",DATEDIF(DATE(VALUE(RIGHT(I9,4)),VALUE(MID(I9,4,2)),VALUE(LEFT(I9,2))),TODAY(),"Y")) -> 50 | V9: =IF(U9="","",IF(U9<30,"18-29",IF(U9<40,"30-39",IF(U9<50,"40-49",IF(U9<60,"50-59","60+"))))) -> 50-59 | W9: =IF(UPPER(TRIM(J9))="PERU","PERÚ",UPPER(TRIM(J9))) -> PERÚ | X9: =UPPER(TRIM(H9)) -> FEMENINO | Y9: =UPPER(TRIM(K9)) -> ANCASH | Z9: =UPPER(TRIM(P9)) -> ANCASH
A10: FUERZA POPULAR | B10: 07960843 | C10: CHAVEZ COSSIO, MARTHA GLADYS | D10: 07960843 | E10: CHAVEZ | F10: COSSIO | G10: MARTHA GLADYS | H10: FEMENINO | I10: 12/01/1953 | J10: PERÚ | K10: CALLAO | L10: CALLAO | M10: BELLAVISTA | N10: SENADOR | P10: ÚNICO NACIONAL | Q10: Callao no es departamento. Debería figurar como "provincia constitucional del Callao". | R10: https://mpesije.jne.gob.pe/apidocs/b3b29de8-c5bd-4b73-b34b-29c48267363a.jpg | S10: https://mpesije.jne.gob.pe/apidocs/cd58063a-eafa-4e92-b04e-267a33eda88b.pdf | T10: =CONCATENATE(A10," - ",B10,".pdf") -> FUERZA POPULAR - 07960843.pdf | U10: =IF(I10="","",DATEDIF(DATE(VALUE(RIGHT(I10,4)),VALUE(MID(I10,4,2)),VALUE(LEFT(I10,2))),TODAY(),"Y")) -> 73 | V10: =IF(U10="","",IF(U10<30,"18-29",IF(U10<40,"30-39",IF(U10<50,"40-49",IF(U10<60,"50-59","60+"))))) -> 60+ | W10: =IF(UPPER(TRIM(J10))="PERU","PERÚ",UPPER(TRIM(J10))) -> PERÚ | X10: =UPPER(TRIM(H10)) -> FEMENINO | Y10: =UPPER(TRIM(K10)) -> CALLAO | Z10: =UPPER(TRIM(P10)) -> ÚNICO NACIONAL
A11: FUERZA POPULAR | B11: 05227631 | C11: DEL AGUILA CARDENAS, JUAN CARLOS | D11: 05227631 | E11: DEL AGUILA | F11: CARDENAS | G11: JUAN CARLOS | H11: MASCULINO | I11: 09/01/1962 | J11: PERÚ | K11: LORETO | L11: MAYNAS | M11: IQUITOS | N11: SENADOR | P11: LORETO | R11: https://mpesije.jne.gob.pe/apidocs/39addd4e-6c93-405b-9e93-56a0892eae72.jpg | S11: https://mpesije.jne.gob.pe/apidocs/f2c9c961-f74a-45e8-8790-d864e7893093.pdf | T11: =CONCATENATE(A11," - ",B11,".pdf") -> FUERZA POPULAR - 05227631.pdf | U11: =IF(I11="","",DATEDIF(DATE(VALUE(RIGHT(I11,4)),VALUE(MID(I11,4,2)),VALUE(LEFT(I11,2))),TODAY(),"Y")) -> 64 | V11: =IF(U11="","",IF(U11<30,"18-29",IF(U11<40,"30-39",IF(U11<50,"40-49",IF(U11<60,"50-59","60+"))))) -> 60+ | W11: =IF(UPPER(TRIM(J11))="PERU","PERÚ",UPPER(TRIM(J11))) -> PERÚ | X11: =UPPER(TRIM(H11)) -> MASCULINO | Y11: =UPPER(TRIM(K11)) -> LORETO | Z11: =UPPER(TRIM(P11)) -> LORETO
A12: FUERZA POPULAR | B12: 17896798 | C12: FLORES RUIZ, VICTOR SEFERINO | D12: 17896798 | E12: FLORES | F12: RUIZ | G12: VICTOR SEFERINO | H12: MASCULINO | I12: 24/08/1957 | J12: PERÚ | K12: LA LIBERTAD | L12: SANCHEZ CARRION | M12: HUAMACHUCO | N12: SENADOR | P12: LA LIBERTAD | R12: https://mpesije.jne.gob.pe/apidocs/8022ae32-73db-492b-9442-9ab351cf4ac6.jpg | S12: https://mpesije.jne.gob.pe/apidocs/c913c7f0-9803-46c8-8b69-d37a3f7b5206.pdf | T12: =CONCATENATE(A12," - ",B12,".pdf") -> FUERZA POPULAR - 17896798.pdf | U12: =IF(I12="","",DATEDIF(DATE(VALUE(RIGHT(I12,4)),VALUE(MID(I12,4,2)),VALUE(LEFT(I12,2))),TODAY(),"Y")) -> 68 | V12: =IF(U12="","",IF(U12<30,"18-29",IF(U12<40,"30-39",IF(U12<50,"40-49",IF(U12<60,"50-59","60+"))))) -> 60+ | W12: =IF(UPPER(TRIM(J12))="PERU","PERÚ",UPPER(TRIM(J12))) -> PERÚ | X12: =UPPER(TRIM(H12)) -> MASCULINO | Y12: =UPPER(TRIM(K12)) -> LA LIBERTAD | Z12: =UPPER(TRIM(P12)) -> LA LIBERTAD
A13: FUERZA POPULAR | B13: 19994639 | C13: JIMENEZ HEREDIA, DAVID JULIO | D13: 19994639 | E13: JIMENEZ | F13: HEREDIA | G13: DAVID JULIO | H13: MASCULINO | I13: 01/09/1955 | J13: PERÚ | K13: JUNIN | L13: HUANCAYO | M13: HUANCAYO | N13: SENADOR | P13: JUNIN | R13: https://mpesije.jne.gob.pe/apidocs/2856fdf9-9f1e-4e3e-857e-0b998e066e36.jpg | S13: https://mpesije.jne.gob.pe/apidocs/e234be5e-855f-4d56-9ed4-0849690ccbf5.pdf | T13: =CONCATENATE(A13," - ",B13,".pdf") -> FUERZA POPULAR - 19994639.pdf | U13: =IF(I13="","",DATEDIF(DATE(VALUE(RIGHT(I13,4)),VALUE(MID(I13,4,2)),VALUE(LEFT(I13,2))),TODAY(),"Y")) -> 70 | V13: =IF(U13="","",IF(U13<30,"18-29",IF(U13<40,"30-39",IF(U13<50,"40-49",IF(U13<60,"50-59","60+"))))) -> 60+ | W13: =IF(UPPER(TRIM(J13))="PERU","PERÚ",UPPER(TRIM(J13))) -> PERÚ | X13: =UPPER(TRIM(H13)) -> MASCULINO | Y13: =UPPER(TRIM(K13)) -> JUNIN | Z13: =UPPER(TRIM(P13)) -> JUNIN
A14: FUERZA POPULAR | B14: 07831436 | C14: JUAREZ GALLEGOS, CARMEN PATRICIA | D14: 07831436 | E14: JUAREZ | F14: GALLEGOS | G14: CARMEN PATRICIA | H14: FEMENINO | I14: 16/07/1960 | J14: PERÚ | K14: ICA | L14: NASCA | M14: MARCONA | N14: SENADOR | P14: ÚNICO NACIONAL | R14: https://mpesije.jne.gob.pe/apidocs/1dc6fbdd-d970-4fa3-9195-cf0492bc11d2.jpg | S14: https://mpesije.jne.gob.pe/apidocs/f7c8bd65-b17e-4266-845d-b045a55d492a.pdf | T14: =CONCATENATE(A14," - ",B14,".pdf") -> FUERZA POPULAR - 07831436.pdf | U14: =IF(I14="","",DATEDIF(DATE(VALUE(RIGHT(I14,4)),VALUE(MID(I14,4,2)),VALUE(LEFT(I14,2))),TODAY(),"Y")) -> 65 | V14: =IF(U14="","",IF(U14<30,"18-29",IF(U14<40,"30-39",IF(U14<50,"40-49",IF(U14<60,"50-59","60+"))))) -> 60+ | W14: =IF(UPPER(TRIM(J14))="PERU","PERÚ",UPPER(TRIM(J14))) -> PERÚ | X14: =UPPER(TRIM(H14)) -> FEMENINO | Y14: =UPPER(TRIM(K14)) -> ICA | Z14: =UPPER(TRIM(P14)) -> ÚNICO NACIONAL
A15: FUERZA POPULAR | B15: 09884301 | C15: MELGAR VALDEZ, ELARD GALO | D15: 09884301 | E15: MELGAR | F15: VALDEZ | G15: ELARD GALO | H15: MASCULINO | I15: 15/10/1956 | J15: PERÚ | K15: AREQUIPA | L15: CASTILLA | M15: APLAO | N15: SENADOR | P15: LIMA PROVINCIAS | R15: https://mpesije.jne.gob.pe/apidocs/2d527059-8586-4a8d-9224-a08d4d3dc223.jpg | S15: https://mpesije.jne.gob.pe/apidocs/a0e3bdcd-8a71-4f70-a1d5-aebd9d0c263a.pdf | T15: =CONCATENATE(A15," - ",B15,".pdf") -> FUERZA POPULAR - 09884301.pdf | U15: =IF(I15="","",DATEDIF(DATE(VALUE(RIGHT(I15,4)),VALUE(MID(I15,4,2)),VALUE(LEFT(I15,2))),TODAY(),"Y")) -> 69 | V15: =IF(U15="","",IF(U15<30,"18-29",IF(U15<40,"30-39",IF(U15<50,"40-49",IF(U15<60,"50-59","60+"))))) -> 60+ | W15: =IF(UPPER(TRIM(J15))="PERU","PERÚ",UPPER(TRIM(J15))) -> PERÚ | X15: =UPPER(TRIM(H15)) -> MASCULINO | Y15: =UPPER(TRIM(K15)) -> AREQUIPA | Z15: =UPPER(TRIM(P15)) -> LIMA PROVINCIAS
A16: FUERZA POPULAR | B16: 08266314 | C16: MESIA RAMIREZ, CARLOS FERNANDO | D16: 08266314 | E16: MESIA | F16: RAMIREZ | G16: CARLOS FERNANDO | H16: MASCULINO | I16: 08/12/1959 | J16: PERÚ | K16: LORETO | L16: MAYNAS | M16: IQUITOS | N16: SENADOR | P16: ÚNICO NACIONAL | R16: https://mpesije.jne.gob.pe/apidocs/8b5d10f4-a0ec-4744-b29f-59271274b78c.jpg | S16: https://mpesije.jne.gob.pe/apidocs/986de612-7510-4a49-bbd3-8d3ff2e98d15.pdf | T16: =CONCATENATE(A16," - ",B16,".pdf") -> FUERZA POPULAR - 08266314.pdf | U16: =IF(I16="","",DATEDIF(DATE(VALUE(RIGHT(I16,4)),VALUE(MID(I16,4,2)),VALUE(LEFT(I16,2))),TODAY(),"Y")) -> 66 | V16: =IF(U16="","",IF(U16<30,"18-29",IF(U16<40,"30-39",IF(U16<50,"40-49",IF(U16<60,"50-59","60+"))))) -> 60+ | W16: =IF(UPPER(TRIM(J16))="PERU","PERÚ",UPPER(TRIM(J16))) -> PERÚ | X16: =UPPER(TRIM(H16)) -> MASCULINO | Y16: =UPPER(TRIM(K16)) -> LORETO | Z16: =UPPER(TRIM(P16)) -> ÚNICO NACIONAL
A17: FUERZA POPULAR | B17: 22974228 | C17: MIYASHIRO ARASHIRO, MARCO ENRIQUE | D17: 22974228 | E17: MIYASHIRO | F17: ARASHIRO | G17: MARCO ENRIQUE | H17: MASCULINO | I17: 25/04/1953 | J17: PERÚ | K17: LIMA | L17: LIMA | M17: LIMA | N17: SENADOR | P17: LIMA METROPOLITANA | R17: https://mpesije.jne.gob.pe/apidocs/8388c289-7fce-48e9-91f9-732565b127c7.jpg | S17: https://mpesije.jne.gob.pe/apidocs/a49ce4d3-07d3-4728-a386-78e3a7696cd2.pdf | T17: =CONCATENATE(A17," - ",B17,".pdf") -> FUERZA POPULAR - 22974228.pdf | U17: =IF(I17="","",DATEDIF(DATE(VALUE(RIGHT(I17,4)),VALUE(MID(I17,4,2)),VALUE(LEFT(I17,2))),TODAY(),"Y")) -> 73 | V17: =IF(U17="","",IF(U17<30,"18-29",IF(U17<40,"30-39",IF(U17<50,"40-49",IF(U17<60,"50-59","60+"))))) -> 60+ | W17: =IF(UPPER(TRIM(J17))="PERU","PERÚ",UPPER(TRIM(J17))) -> PERÚ | X17: =UPPER(TRIM(H17)) -> MASCULINO | Y17: =UPPER(TRIM(K17)) -> LIMA | Z17: =UPPER(TRIM(P17)) -> LIMA METROPOLITANA
A18: FUERZA POPULAR | B18: 08911520 | C18: MOYANO DELGADO, MARTHA LUPE | D18: 08911520 | E18: MOYANO | F18: DELGADO | G18: MARTHA LUPE | H18: FEMENINO | I18: 14/10/1964 | J18: PERÚ | K18: CALLAO | L18: CALLAO | M18: BELLAVISTA | N18: SENADOR | P18: ÚNICO NACIONAL | R18: https://mpesije.jne.gob.pe/apidocs/e1193269-c9d9-48c8-9ff2-4fa1317c49cf.jpg | S18: https://mpesije.jne.gob.pe/apidocs/68a5f54c-a9f2-41e8-915f-4b14a17dc3a3.pdf | T18: =CONCATENATE(A18," - ",B18,".pdf") -> FUERZA POPULAR - 08911520.pdf | U18: =IF(I18="","",DATEDIF(DATE(VALUE(RIGHT(I18,4)),VALUE(MID(I18,4,2)),VALUE(LEFT(I18,2))),TODAY(),"Y")) -> 61 | V18: =IF(U18="","",IF(U18<30,"18-29",IF(U18<40,"30-39",IF(U18<50,"40-49",IF(U18<60,"50-59","60+"))))) -> 60+ | W18: =IF(UPPER(TRIM(J18))="PERU","PERÚ",UPPER(TRIM(J18))) -> PERÚ | X18: =UPPER(TRIM(H18)) -> FEMENINO | Y18: =UPPER(TRIM(K18)) -> CALLAO | Z18: =UPPER(TRIM(P18)) -> ÚNICO NACIONAL
A19: FUERZA POPULAR | B19: 17806760 | C19: NORIEGA REATEGUI, VICTOR MANUEL | D19: 17806760 | E19: NORIEGA | F19: REATEGUI | G19: VICTOR MANUEL | H19: MASCULINO | I19: 14/05/1962 | J19: PERÚ | K19: SAN MARTIN | L19: EL DORADO | M19: SAN JOSE DE SISA | N19: SENADOR | P19: SAN MARTIN | R19: https://mpesije.jne.gob.pe/apidocs/84f8ce01-b3ad-4d93-bbe2-79314b572334.jpg | S19: https://mpesije.jne.gob.pe/apidocs/f4f1e141-61f6-4499-bf91-10e28fe56db1.pdf | T19: =CONCATENATE(A19," - ",B19,".pdf") -> FUERZA POPULAR - 17806760.pdf | U19: =IF(I19="","",DATEDIF(DATE(VALUE(RIGHT(I19,4)),VALUE(MID(I19,4,2)),VALUE(LEFT(I19,2))),TODAY(),"Y")) -> 64 | V19: =IF(U19="","",IF(U19<30,"18-29",IF(U19<40,"30-39",IF(U19<50,"40-49",IF(U19<60,"50-59","60+"))))) -> 60+ | W19: =IF(UPPER(TRIM(J19))="PERU","PERÚ",UPPER(TRIM(J19))) -> PERÚ | X19: =UPPER(TRIM(H19)) -> MASCULINO | Y19: =UPPER(TRIM(K19)) -> SAN MARTIN | Z19: =UPPER(TRIM(P19)) -> SAN MARTIN
A20: FUERZA POPULAR | B20: 08234063 | C20: RODRICH ACKERMAN, JACQUES SALOMON | D20: 08234063 | E20: RODRICH | F20: ACKERMAN | G20: JACQUES SALOMON | H20: MASCULINO | I20: 14/08/1961 | J20: PERÚ | K20: LIMA | L20: LIMA | M20: SAN ISIDRO | N20: SENADOR | P20: CALLAO | Q20: El candidato actualmente consigna en su Documento Nacional de Identidad como domicilio calle Alberto Secada N° 315 - Callao | R20: https://mpesije.jne.gob.pe/apidocs/04696b3b-471f-462a-b3c2-84726b866a6f.jpg | S20: https://mpesije.jne.gob.pe/apidocs/b368d19a-c667-4b25-9d4f-8e5048887a4f.pdf | T20: =CONCATENATE(A20," - ",B20,".pdf") -> FUERZA POPULAR - 08234063.pdf | U20: =IF(I20="","",DATEDIF(DATE(VALUE(RIGHT(I20,4)),VALUE(MID(I20,4,2)),VALUE(LEFT(I20,2))),TODAY(),"Y")) -> 64 | V20: =IF(U20="","",IF(U20<30,"18-29",IF(U20<40,"30-39",IF(U20<50,"40-49",IF(U20<60,"50-59","60+"))))) -> 60+ | W20: =IF(UPPER(TRIM(J20))="PERU","PERÚ",UPPER(TRIM(J20))) -> PERÚ | X20: =UPPER(TRIM(H20)) -> MASCULINO | Y20: =UPPER(TRIM(K20)) -> LIMA | Z20: =UPPER(TRIM(P20)) -> CALLAO
A21: FUERZA POPULAR | B21: 07704730 | C21: ROSPIGLIOSI CAPURRO, FERNANDO MIGUEL | D21: 07704730 | E21: ROSPIGLIOSI | F21: CAPURRO | G21: FERNANDO MIGUEL | H21: MASCULINO | I21: 25/02/1947 | J21: PERÚ | K21: LIMA | L21: LIMA | M21: MIRAFLORES | N21: SENADOR | P21: ÚNICO NACIONAL | R21: https://mpesije.jne.gob.pe/apidocs/4e1024fa-a2ee-4b49-8563-7484061f3763.jpg | S21: https://mpesije.jne.gob.pe/apidocs/e088f78d-87d9-4d2c-a3a9-d348a26419b4.pdf | T21: =CONCATENATE(A21," - ",B21,".pdf") -> FUERZA POPULAR - 07704730.pdf | U21: =IF(I21="","",DATEDIF(DATE(VALUE(RIGHT(I21,4)),VALUE(MID(I21,4,2)),VALUE(LEFT(I21,2))),TODAY(),"Y")) -> 79 | V21: =IF(U21="","",IF(U21<30,"18-29",IF(U21<40,"30-39",IF(U21<50,"40-49",IF(U21<60,"50-59","60+"))))) -> 60+ | W21: =IF(UPPER(TRIM(J21))="PERU","PERÚ",UPPER(TRIM(J21))) -> PERÚ | X21: =UPPER(TRIM(H21)) -> MASCULINO | Y21: =UPPER(TRIM(K21)) -> LIMA | Z21: =UPPER(TRIM(P21)) -> ÚNICO NACIONAL
A22: FUERZA POPULAR | B22: 10638205 | C22: SCHAEFER CUCULIZA, KARLA MELISSA | D22: 10638205 | E22: SCHAEFER | F22: CUCULIZA | G22: KARLA MELISSA | H22: FEMENINO | I22: 14/03/1966 | J22: PERÚ | K22: PIURA | L22: PIURA | M22: PIURA | N22: SENADOR | P22: PIURA | R22: https://mpesije.jne.gob.pe/apidocs/8484cd8e-5f0a-48d3-ba54-be7120b1107f.jpg | S22: https://mpesije.jne.gob.pe/apidocs/82e3af5f-ed4b-423d-bba6-e9de26662f1a.pdf | T22: =CONCATENATE(A22," - ",B22,".pdf") -> FUERZA POPULAR - 10638205.pdf | U22: =IF(I22="","",DATEDIF(DATE(VALUE(RIGHT(I22,4)),VALUE(MID(I22,4,2)),VALUE(LEFT(I22,2))),TODAY(),"Y")) -> 60 | V22: =IF(U22="","",IF(U22<30,"18-29",IF(U22<40,"30-39",IF(U22<50,"40-49",IF(U22<60,"50-59","60+"))))) -> 60+ | W22: =IF(UPPER(TRIM(J22))="PERU","PERÚ",UPPER(TRIM(J22))) -> PERÚ | X22: =UPPER(TRIM(H22)) -> FEMENINO | Y22: =UPPER(TRIM(K22)) -> PIURA | Z22: =UPPER(TRIM(P22)) -> PIURA
A23: FUERZA POPULAR | B23: 16657841 | C23: TAPIA BERNAL, SEGUNDO LEOCADIO | D23: 16657841 | E23: TAPIA | F23: BERNAL | G23: SEGUNDO LEOCADIO | H23: MASCULINO | I23: 12/02/1968 | J23: PERÚ | K23: CAJAMARCA | L23: CHOTA | M23: CHOTA | N23: SENADOR | P23: CAJAMARCA | R23: https://mpesije.jne.gob.pe/apidocs/09f4526f-7117-476b-9499-38179dd8ef02.jpg | S23: https://mpesije.jne.gob.pe/apidocs/3f910188-c6ed-44e3-93a5-a8fdeb7a3531.pdf | T23: =CONCATENATE(A23," - ",B23,".pdf") -> FUERZA POPULAR - 16657841.pdf | U23: =IF(I23="","",DATEDIF(DATE(VALUE(RIGHT(I23,4)),VALUE(MID(I23,4,2)),VALUE(LEFT(I23,2))),TODAY(),"Y")) -> 58 | V23: =IF(U23="","",IF(U23<30,"18-29",IF(U23<40,"30-39",IF(U23<50,"40-49",IF(U23<60,"50-59","60+"))))) -> 50-59 | W23: =IF(UPPER(TRIM(J23))="PERU","PERÚ",UPPER(TRIM(J23))) -> PERÚ | X23: =UPPER(TRIM(H23)) -> MASCULINO | Y23: =UPPER(TRIM(K23)) -> CAJAMARCA | Z23: =UPPER(TRIM(P23)) -> CAJAMARCA
A24: FUERZA POPULAR | B24: 21143880 | C24: VELASQUEZ PORTOCARRERO, JORGE | D24: 21143880 | E24: VELASQUEZ | F24: PORTOCARRERO | G24: JORGE | H24: MASCULINO | I24: 14/01/1966 | J24: PERÚ | K24: SAN MARTIN | L24: RIOJA | M24: RIOJA | N24: SENADOR | P24: UCAYALI | R24: https://mpesije.jne.gob.pe/apidocs/043cb739-9e01-4351-88d8-c0a5979b4884.jpg | S24: https://mpesije.jne.gob.pe/apidocs/764aa850-dece-4ab5-8956-4420b2717ec3.pdf | T24: =CONCATENATE(A24," - ",B24,".pdf") -> FUERZA POPULAR - 21143880.pdf | U24: =IF(I24="","",DATEDIF(DATE(VALUE(RIGHT(I24,4)),VALUE(MID(I24,4,2)),VALUE(LEFT(I24,2))),TODAY(),"Y")) -> 60 | V24: =IF(U24="","",IF(U24<30,"18-29",IF(U24<40,"30-39",IF(U24<50,"40-49",IF(U24<60,"50-59","60+"))))) -> 60+ | W24: =IF(UPPER(TRIM(J24))="PERU","PERÚ",UPPER(TRIM(J24))) -> PERÚ | X24: =UPPER(TRIM(H24)) -> MASCULINO | Y24: =UPPER(TRIM(K24)) -> SAN MARTIN | Z24: =UPPER(TRIM(P24)) -> UCAYALI
A25: FUERZA POPULAR | B25: 40242430 | C25: VENTURA ANGEL, HECTOR JOSE | D25: 40242430 | E25: VENTURA | F25: ANGEL | G25: HECTOR JOSE | H25: MASCULINO | I25: 24/07/1979 | J25: PERÚ | K25: PASCO | L25: PASCO | M25: HUARIACA | N25: SENADOR | P25: TUMBES | R25: https://mpesije.jne.gob.pe/apidocs/bcf4cec7-d78a-4d75-a07c-d6ecf3f9322e.jpg | S25: https://mpesije.jne.gob.pe/apidocs/b003710f-1e5d-4c02-bbca-7b10f0cca71a.pdf | T25: =CONCATENATE(A25," - ",B25,".pdf") -> FUERZA POPULAR - 40242430.pdf | U25: =IF(I25="","",DATEDIF(DATE(VALUE(RIGHT(I25,4)),VALUE(MID(I25,4,2)),VALUE(LEFT(I25,2))),TODAY(),"Y")) -> 46 | V25: =IF(U25="","",IF(U25<30,"18-29",IF(U25<40,"30-39",IF(U25<50,"40-49",IF(U25<60,"50-59","60+"))))) -> 40-49 | W25: =IF(UPPER(TRIM(J25))="PERU","PERÚ",UPPER(TRIM(J25))) -> PERÚ | X25: =UPPER(TRIM(H25)) -> MASCULINO | Y25: =UPPER(TRIM(K25)) -> PASCO | Z25: =UPPER(TRIM(P25)) -> TUMBES
A26: FUERZA POPULAR | B26: 21414172 | C26: YAMASHIRO ORE, RAFAEL GUSTAVO | D26: 21414172 | E26: YAMASHIRO | F26: ORE | G26: RAFAEL GUSTAVO | H26: MASCULINO | I26: 25/06/1963 | J26: PERÚ | K26: ICA | L26: ICA | M26: ICA | N26: SENADOR | P26: ICA | R26: https://mpesije.jne.gob.pe/apidocs/54b17e85-5ae3-4825-85d3-be4a29802a84.jpg | S26: https://mpesije.jne.gob.pe/apidocs/dd0973d2-282d-4388-8bf1-5f081177d22a.pdf | T26: =CONCATENATE(A26," - ",B26,".pdf") -> FUERZA POPULAR - 21414172.pdf | U26: =IF(I26="","",DATEDIF(DATE(VALUE(RIGHT(I26,4)),VALUE(MID(I26,4,2)),VALUE(LEFT(I26,2))),TODAY(),"Y")) -> 62 | V26: =IF(U26="","",IF(U26<30,"18-29",IF(U26<40,"30-39",IF(U26<50,"40-49",IF(U26<60,"50-59","60+"))))) -> 60+ | W26: =IF(UPPER(TRIM(J26))="PERU","PERÚ",UPPER(TRIM(J26))) -> PERÚ | X26: =UPPER(TRIM(H26)) -> MASCULINO | Y26: =UPPER(TRIM(K26)) -> ICA | Z26: =UPPER(TRIM(P26)) -> ICA
A27: JUNTOS POR EL PERU | B27: 22482738 | C27: ANDRES LUJAN, SERAFIN | D27: 22482738 | E27: ANDRES | F27: LUJAN | G27: SERAFIN | H27: MASCULINO | I27: 12/10/1966 | J27: PERÚ | K27: HUANUCO | L27: YAROWILCA | M27: APARICIO POMARES | N27: SENADOR | P27: HUANUCO | R27: https://mpesije.jne.gob.pe/apidocs/28f4e30f-f8c9-4a48-b698-94f4480bd3fe.jpg | S27: https://mpesije.jne.gob.pe/apidocs/5110bbb9-f342-40ef-8b4b-e6beb36c0f94.pdf | T27: =CONCATENATE(A27," - ",B27,".pdf") -> JUNTOS POR EL PERU - 22482738.pdf | U27: =IF(I27="","",DATEDIF(DATE(VALUE(RIGHT(I27,4)),VALUE(MID(I27,4,2)),VALUE(LEFT(I27,2))),TODAY(),"Y")) -> 59 | V27: =IF(U27="","",IF(U27<30,"18-29",IF(U27<40,"30-39",IF(U27<50,"40-49",IF(U27<60,"50-59","60+"))))) -> 50-59 | W27: =IF(UPPER(TRIM(J27))="PERU","PERÚ",UPPER(TRIM(J27))) -> PERÚ | X27: =UPPER(TRIM(H27)) -> MASCULINO | Y27: =UPPER(TRIM(K27)) -> HUANUCO | Z27: =UPPER(TRIM(P27)) -> HUANUCO
A28: JUNTOS POR EL PERU | B28: 21487528 | C28: ARMACANQUI MORALES, SAUL ANDRES | D28: 21487528 | E28: ARMACANQUI | F28: MORALES | G28: SAUL ANDRES | H28: MASCULINO | I28: 30/11/1953 | J28: PERÚ | K28: ICA | L28: ICA | M28: ICA | N28: SENADOR | P28: ÚNICO NACIONAL | R28: https://mpesije.jne.gob.pe/apidocs/1baf3ce6-bf7f-4f48-90af-7df69ba21d70.jpg | S28: https://mpesije.jne.gob.pe/apidocs/fba5c0e0-c3b9-4c85-b049-58a2a0771bf0.pdf | T28: =CONCATENATE(A28," - ",B28,".pdf") -> JUNTOS POR EL PERU - 21487528.pdf | U28: =IF(I28="","",DATEDIF(DATE(VALUE(RIGHT(I28,4)),VALUE(MID(I28,4,2)),VALUE(LEFT(I28,2))),TODAY(),"Y")) -> 72 | V28: =IF(U28="","",IF(U28<30,"18-29",IF(U28<40,"30-39",IF(U28<50,"40-49",IF(U28<60,"50-59","60+"))))) -> 60+ | W28: =IF(UPPER(TRIM(J28))="PERU","PERÚ",UPPER(TRIM(J28))) -> PERÚ | X28: =UPPER(TRIM(H28)) -> MASCULINO | Y28: =UPPER(TRIM(K28)) -> ICA | Z28: =UPPER(TRIM(P28)) -> ÚNICO NACIONAL
A29: JUNTOS POR EL PERU | B29: 27409088 | C29: CASTILLO TERRONES, JOSE MERCEDES | D29: 27409088 | E29: CASTILLO | F29: TERRONES | G29: JOSE MERCEDES | H29: MASCULINO | I29: 24/09/1964 | J29: PERÚ | K29: CAJAMARCA | L29: CHOTA | M29: TACABAMBA | N29: SENADOR | P29: ÚNICO NACIONAL | R29: https://mpesije.jne.gob.pe/apidocs/0e2b05c2-c95a-4599-bc78-56584d571b51.jpg | S29: https://mpesije.jne.gob.pe/apidocs/61933e79-79be-45fb-9b0f-11be2bf70d02.pdf | T29: =CONCATENATE(A29," - ",B29,".pdf") -> JUNTOS POR EL PERU - 27409088.pdf | U29: =IF(I29="","",DATEDIF(DATE(VALUE(RIGHT(I29,4)),VALUE(MID(I29,4,2)),VALUE(LEFT(I29,2))),TODAY(),"Y")) -> 61 | V29: =IF(U29="","",IF(U29<30,"18-29",IF(U29<40,"30-39",IF(U29<50,"40-49",IF(U29<60,"50-59","60+"))))) -> 60+ | W29: =IF(UPPER(TRIM(J29))="PERU","PERÚ",UPPER(TRIM(J29))) -> PERÚ | X29: =UPPER(TRIM(H29)) -> MASCULINO | Y29: =UPPER(TRIM(K29)) -> CAJAMARCA | Z29: =UPPER(TRIM(P29)) -> ÚNICO NACIONAL
A30: JUNTOS POR EL PERU | B30: 40669342 | C30: CCAHUANA AYMACHOQUE, HUGO ISAAC | D30: 40669342 | E30: CCAHUANA | F30: AYMACHOQUE | G30: HUGO ISAAC | H30: MASCULINO | I30: 08/07/1978 | J30: PERÚ | K30: CUSCO | L30: CANCHIS | M30: SAN PEDRO | N30: SENADOR | P30: MADRE DE DIOS | R30: https://mpesije.jne.gob.pe/apidocs/ffc812a5-4689-4912-831a-cb0ab734f078.jpg | S30: https://mpesije.jne.gob.pe/apidocs/bbc0ceed-8cb9-4859-b242-24ff0547c996.pdf | T30: =CONCATENATE(A30," - ",B30,".pdf") -> JUNTOS POR EL PERU - 40669342.pdf | U30: =IF(I30="","",DATEDIF(DATE(VALUE(RIGHT(I30,4)),VALUE(MID(I30,4,2)),VALUE(LEFT(I30,2))),TODAY(),"Y")) -> 47 | V30: =IF(U30="","",IF(U30<30,"18-29",IF(U30<40,"30-39",IF(U30<50,"40-49",IF(U30<60,"50-59","60+"))))) -> 40-49 | W30: =IF(UPPER(TRIM(J30))="PERU","PERÚ",UPPER(TRIM(J30))) -> PERÚ | X30: =UPPER(TRIM(H30)) -> MASCULINO | Y30: =UPPER(TRIM(K30)) -> CUSCO | Z30: =UPPER(TRIM(P30)) -> MADRE DE DIOS
A31: JUNTOS POR EL PERU | B31: 04647085 | C31: CUTIPA CCAMA, VICTOR RAUL | D31: 04647085 | E31: CUTIPA | F31: CCAMA | G31: VICTOR RAUL | H31: MASCULINO | I31: 14/09/1972 | J31: PERÚ | K31: PUNO | L31: PUNO | M31: ACORA | N31: SENADOR | P31: MOQUEGUA | R31: https://mpesije.jne.gob.pe/apidocs/8a462ad7-557a-40c5-80af-4f87c81544ea.jpg | S31: https://mpesije.jne.gob.pe/apidocs/df837d7a-d815-4f7a-b9f2-39edb294f267.pdf | T31: =CONCATENATE(A31," - ",B31,".pdf") -> JUNTOS POR EL PERU - 04647085.pdf | U31: =IF(I31="","",DATEDIF(DATE(VALUE(RIGHT(I31,4)),VALUE(MID(I31,4,2)),VALUE(LEFT(I31,2))),TODAY(),"Y")) -> 53 | V31: =IF(U31="","",IF(U31<30,"18-29",IF(U31<40,"30-39",IF(U31<50,"40-49",IF(U31<60,"50-59","60+"))))) -> 50-59 | W31: =IF(UPPER(TRIM(J31))="PERU","PERÚ",UPPER(TRIM(J31))) -> PERÚ | X31: =UPPER(TRIM(H31)) -> MASCULINO | Y31: =UPPER(TRIM(K31)) -> PUNO | Z31: =UPPER(TRIM(P31)) -> MOQUEGUA
A32: JUNTOS POR EL PERU | B32: 21453924 | C32: MARAVI OLARTE, IBER ANTENOR | D32: 21453924 | E32: MARAVI | F32: OLARTE | G32: IBER ANTENOR | H32: MASCULINO | I32: 15/05/1961 | J32: PERÚ | K32: AYACUCHO | L32: HUAMANGA | M32: AYACUCHO | N32: SENADOR | P32: ÚNICO NACIONAL | R32: https://mpesije.jne.gob.pe/apidocs/9ff4f8d0-cff1-429b-b3b9-a2c9baf178cf.jpg | S32: https://mpesije.jne.gob.pe/apidocs/4080756a-aa47-451c-9ae6-ea726f4dbf37.pdf | T32: =CONCATENATE(A32," - ",B32,".pdf") -> JUNTOS POR EL PERU - 21453924.pdf | U32: =IF(I32="","",DATEDIF(DATE(VALUE(RIGHT(I32,4)),VALUE(MID(I32,4,2)),VALUE(LEFT(I32,2))),TODAY(),"Y")) -> 65 | V32: =IF(U32="","",IF(U32<30,"18-29",IF(U32<40,"30-39",IF(U32<50,"40-49",IF(U32<60,"50-59","60+"))))) -> 60+ | W32: =IF(UPPER(TRIM(J32))="PERU","PERÚ",UPPER(TRIM(J32))) -> PERÚ | X32: =UPPER(TRIM(H32)) -> MASCULINO | Y32: =UPPER(TRIM(K32)) -> AYACUCHO | Z32: =UPPER(TRIM(P32)) -> ÚNICO NACIONAL
... A38: PARTIDO CIVICO OBRAS | B38: 07651031 | C38: ASTUCURI LAURA, ROGER MIGUEL | D38: 07651031 | E38: ASTUCURI | F38: LAURA | G38: ROGER MIGUEL | H38: MASCULINO | I38: 03/09/1960 | J38: PERÚ | K38: LIMA | L38: LIMA | M38: LURIGANCHO | N38: SENADOR | P38: ÚNICO NACIONAL | R38: https://mpesije.jne.gob.pe/apidocs/ca28ff0a-b929-4dae-87b6-d49dc63f75ac.jpg | S38: https://mpesije.jne.gob.pe/apidocs/1ae39a6e-ce49-4e8d-9354-e609b53c2d20.pdf | T38: =CONCATENATE(A38," - ",B38,".pdf") -> PARTIDO CIVICO OBRAS - 07651031.pdf | U38: =IF(I38="","",DATEDIF(DATE(VALUE(RIGHT(I38,4)),VALUE(MID(I38,4,2)),VALUE(LEFT(I38,2))),TODAY(),"Y")) -> 65 | V38: =IF(U38="","",IF(U38<30,"18-29",IF(U38<40,"30-39",IF(U38<50,"40-49",IF(U38<60,"50-59","60+"))))) -> 60+ | W38: =IF(UPPER(TRIM(J38))="PERU","PERÚ",UPPER(TRIM(J38))) -> PERÚ | X38: =UPPER(TRIM(H38)) -> MASCULINO | Y38: =UPPER(TRIM(K38)) -> LIMA | Z38: =UPPER(TRIM(P38)) -> ÚNICO NACIONAL
A39: PARTIDO CIVICO OBRAS | B39: 10063223 | C39: BARRAGAN COLOMA, DANIEL HUGO | D39: 10063223 | E39: BARRAGAN | F39: COLOMA | G39: DANIEL HUGO | H39: MASCULINO | I39: 21/08/1961 | J39: PERÚ | K39: LIMA | L39: LIMA | M39: LIMA | N39: PRIMER VICEPRESIDENTE DE LA REPÚBLICA | O39: SENADOR | P39: ÚNICO NACIONAL | R39: https://mpesije.jne.gob.pe/apidocs/15595890-de24-4f14-b4f6-bd9b5e10372a.jpg | S39: https://mpesije.jne.gob.pe/apidocs/6a216000-4a97-4d48-94f0-5ac8d5186e12.pdf | T39: =CONCATENATE(A39," - ",B39,".pdf") -> PARTIDO CIVICO OBRAS - 10063223.pdf | U39: =IF(I39="","",DATEDIF(DATE(VALUE(RIGHT(I39,4)),VALUE(MID(I39,4,2)),VALUE(LEFT(I39,2))),TODAY(),"Y")) -> 64 | V39: =IF(U39="","",IF(U39<30,"18-29",IF(U39<40,"30-39",IF(U39<50,"40-49",IF(U39<60,"50-59","60+"))))) -> 60+ | W39: =IF(UPPER(TRIM(J39))="PERU","PERÚ",UPPER(TRIM(J39))) -> PERÚ | X39: =UPPER(TRIM(H39)) -> MASCULINO | Y39: =UPPER(TRIM(K39)) -> LIMA | Z39: =UPPER(TRIM(P39)) -> ÚNICO NACIONAL
A40: PARTIDO CIVICO OBRAS | B40: 07250032 | C40: FLORES CORDOVA, AGRIPINA MARIA DEL PILAR | D40: 07250032 | E40: FLORES | F40: CORDOVA | G40: AGRIPINA MARIA DEL PILAR | H40: FEMENINO | I40: 23/06/1950 | J40: PERÚ | K40: LIMA | L40: LIMA | M40: MAGDALENA DEL MAR | N40: SENADOR | P40: ÚNICO NACIONAL | R40: https://mpesije.jne.gob.pe/apidocs/1c31e830-418b-4987-adc6-47f3007dd2bb.jpg | S40: https://mpesije.jne.gob.pe/apidocs/e75ecce3-6eb6-4315-b4a5-a3755c2dce0c.pdf | T40: =CONCATENATE(A40," - ",B40,".pdf") -> PARTIDO CIVICO OBRAS - 07250032.pdf | U40: =IF(I40="","",DATEDIF(DATE(VALUE(RIGHT(I40,4)),VALUE(MID(I40,4,2)),VALUE(LEFT(I40,2))),TODAY(),"Y")) -> 75 | V40: =IF(U40="","",IF(U40<30,"18-29",IF(U40<40,"30-39",IF(U40<50,"40-49",IF(U40<60,"50-59","60+"))))) -> 60+ | W40: =IF(UPPER(TRIM(J40))="PERU","PERÚ",UPPER(TRIM(J40))) -> PERÚ | X40: =UPPER(TRIM(H40)) -> FEMENINO | Y40: =UPPER(TRIM(K40)) -> LIMA | Z40: =UPPER(TRIM(P40)) -> ÚNICO NACIONAL
A41: PARTIDO CIVICO OBRAS | B41: 07412350 | C41: GAGO RODRIGUEZ, WALTER FRANCISCO | D41: 07412350 | E41: GAGO | F41: RODRIGUEZ | G41: WALTER FRANCISCO | H41: MASCULINO | I41: 13/07/1961 | J41: PERÚ | K41: LIMA | L41: CAÑETE | M41: SAN VICENTE DE CAÑETE | N41: SENADOR | P41: ÚNICO NACIONAL | R41: https://mpesije.jne.gob.pe/apidocs/7d624b9c-c411-46c2-9368-5f1280b8646b.jpg | S41: https://mpesije.jne.gob.pe/apidocs/75515f26-f0c4-4a79-9c09-d93ed7aae1bd.pdf | T41: =CONCATENATE(A41," - ",B41,".pdf") -> PARTIDO CIVICO OBRAS - 07412350.pdf | U41: =IF(I41="","",DATEDIF(DATE(VALUE(RIGHT(I41,4)),VALUE(MID(I41,4,2)),VALUE(LEFT(I41,2))),TODAY(),"Y")) -> 64 | V41: =IF(U41="","",IF(U41<30,"18-29",IF(U41<40,"30-39",IF(U41<50,"40-49",IF(U41<60,"50-59","60+"))))) -> 60+ | W41: =IF(UPPER(TRIM(J41))="PERU","PERÚ",UPPER(TRIM(J41))) -> PERÚ | X41: =UPPER(TRIM(H41)) -> MASCULINO | Y41: =UPPER(TRIM(K41)) -> LIMA | Z41: =UPPER(TRIM(P41)) -> ÚNICO NACIONAL
A42: PARTIDO CIVICO OBRAS | B42: 00422672 | C42: TICONA COHAILA, JUANA GUISELLA | D42: 00422672 | E42: TICONA | F42: COHAILA | G42: JUANA GUISELLA | H42: FEMENINO | I42: 30/05/1963 | J42: PERÚ | K42: TACNA | L42: TACNA | M42: TACNA | N42: SENADOR | P42: TACNA | R42: https://mpesije.jne.gob.pe/apidocs/35cb22aa-fee5-4341-b50c-2eaac0ddbb13.jpg | S42: https://mpesije.jne.gob.pe/apidocs/a3916658-d255-4bd2-b224-1059d32c8bbf.pdf | T42: =CONCATENATE(A42," - ",B42,".pdf") -> PARTIDO CIVICO OBRAS - 00422672.pdf | U42: =IF(I42="","",DATEDIF(DATE(VALUE(RIGHT(I42,4)),VALUE(MID(I42,4,2)),VALUE(LEFT(I42,2))),TODAY(),"Y")) -> 63 | V42: =IF(U42="","",IF(U42<30,"18-29",IF(U42<40,"30-39",IF(U42<50,"40-49",IF(U42<60,"50-59","60+"))))) -> 60+ | W42: =IF(UPPER(TRIM(J42))="PERU","PERÚ",UPPER(TRIM(J42))) -> PERÚ | X42: =UPPER(TRIM(H42)) -> FEMENINO | Y42: =UPPER(TRIM(K42)) -> TACNA | Z42: =UPPER(TRIM(P42)) -> TACNA
A43: PARTIDO DEL BUEN GOBIERNO | B43: 06519219 | C43: BONIFAZ CARMONA, NORA | D43: 06519219 | E43: BONIFAZ | F43: CARMONA | G43: NORA | H43: FEMENINO | I43: 08/06/1954 | J43: PERÚ | K43: LIMA | L43: LIMA | M43: LIMA | N43: SENADOR | P43: LIMA METROPOLITANA | R43: https://mpesije.jne.gob.pe/apidocs/f8a01e27-807f-4d43-a555-48f03cfe5baf.jpg | S43: https://mpesije.jne.gob.pe/apidocs/d092ca57-99b7-480c-bab3-4b7d3b8114ba.pdf | T43: =CONCATENATE(A43," - ",B43,".pdf") -> PARTIDO DEL BUEN GOBIERNO - 06519219.pdf | U43: =IF(I43="","",DATEDIF(DATE(VALUE(RIGHT(I43,4)),VALUE(MID(I43,4,2)),VALUE(LEFT(I43,2))),TODAY(),"Y")) -> 72 | V43: =IF(U43="","",IF(U43<30,"18-29",IF(U43<40,"30-39",IF(U43<50,"40-49",IF(U43<60,"50-59","60+"))))) -> 60+ | W43: =IF(UPPER(TRIM(J43))="PERU","PERÚ",UPPER(TRIM(J43))) -> PERÚ | X43: =UPPER(TRIM(H43)) -> FEMENINO | Y43: =UPPER(TRIM(K43)) -> LIMA | Z43: =UPPER(TRIM(P43)) -> LIMA METROPOLITANA
A44: PARTIDO DEL BUEN GOBIERNO | B44: 43360309 | C44: CABALLERO LEON, CARLOS DAVID | D44: 43360309 | E44: CABALLERO | F44: LEON | G44: CARLOS DAVID | H44: MASCULINO | I44: 03/05/1963 | J44: PERÚ | K44: LIMA | L44: LIMA | M44: LIMA | N44: SEGUNDO VICEPRESIDENTE DE LA REPÚBLICA | O44: SENADOR | P44: ÚNICO NACIONAL | R44: https://mpesije.jne.gob.pe/apidocs/22e7b027-0df4-461c-8fd9-1bc297a95caf.jpg | S44: https://mpesije.jne.gob.pe/apidocs/b7946182-ad32-409c-bb75-9ea7498fa803.pdf | T44: =CONCATENATE(A44," - ",B44,".pdf") -> PARTIDO DEL BUEN GOBIERNO - 43360309.pdf | U44: =IF(I44="","",DATEDIF(DATE(VALUE(RIGHT(I44,4)),VALUE(MID(I44,4,2)),VALUE(LEFT(I44,2))),TODAY(),"Y")) -> 63 | V44: =IF(U44="","",IF(U44<30,"18-29",IF(U44<40,"30-39",IF(U44<50,"40-49",IF(U44<60,"50-59","60+"))))) -> 60+ | W44: =IF(UPPER(TRIM(J44))="PERU","PERÚ",UPPER(TRIM(J44))) -> PERÚ | X44: =UPPER(TRIM(H44)) -> MASCULINO | Y44: =UPPER(TRIM(K44)) -> LIMA | Z44: =UPPER(TRIM(P44)) -> ÚNICO NACIONAL
A45: PARTIDO DEL BUEN GOBIERNO | B45: 07793210 | C45: FIGALLO RIVADENEYRA, FLAVIO FELIPE | D45: 07793210 | E45: FIGALLO | F45: RIVADENEYRA | G45: FLAVIO FELIPE | H45: MASCULINO | I45: 24/12/1953 | J45: PERÚ | K45: LIMA | L45: LIMA | M45: MIRAFLORES | N45: SENADOR | P45: ÚNICO NACIONAL | R45: https://mpesije.jne.gob.pe/apidocs/3e078903-65e7-4fe8-9c87-89be503223a7.jpg | S45: https://mpesije.jne.gob.pe/apidocs/bfbc620a-52a4-4ac5-8182-621d447b7fba.pdf | T45: =CONCATENATE(A45," - ",B45,".pdf") -> PARTIDO DEL BUEN GOBIERNO - 07793210.pdf | U45: =IF(I45="","",DATEDIF(DATE(VALUE(RIGHT(I45,4)),VALUE(MID(I45,4,2)),VALUE(LEFT(I45,2))),TODAY(),"Y")) -> 72 | V45: =IF(U45="","",IF(U45<30,"18-29",IF(U45<40,"30-39",IF(U45<50,"40-49",IF(U45<60,"50-59","60+"))))) -> 60+ | W45: =IF(UPPER(TRIM(J45))="PERU","PERÚ",UPPER(TRIM(J45))) -> PERÚ | X45: =UPPER(TRIM(H45)) -> MASCULINO | Y45: =UPPER(TRIM(K45)) -> LIMA | Z45: =UPPER(TRIM(P45)) -> ÚNICO NACIONAL
A46: PARTIDO DEL BUEN GOBIERNO | B46: 30762511 | C46: FLORES SUAREZ, JUVER NILSON | D46: 30762511 | E46: FLORES | F46: SUAREZ | G46: JUVER NILSON | H46: MASCULINO | I46: 05/04/1973 | J46: PERÚ | K46: AREQUIPA | L46: CAMANA | M46: CAMANA | N46: SENADOR | P46: AREQUIPA | R46: https://mpesije.jne.gob.pe/apidocs/9d17d4fc-7d1c-4e45-96ab-4361c6fe286a.jpg | S46: https://mpesije.jne.gob.pe/apidocs/4c33feea-65d4-4394-9edb-000badafb43b.pdf | T46: =CONCATENATE(A46," - ",B46,".pdf") -> PARTIDO DEL BUEN GOBIERNO - 30762511.pdf | U46: =IF(I46="","",DATEDIF(DATE(VALUE(RIGHT(I46,4)),VALUE(MID(I46,4,2)),VALUE(LEFT(I46,2))),TODAY(),"Y")) -> 53 | V46: =IF(U46="","",IF(U46<30,"18-29",IF(U46<40,"30-39",IF(U46<50,"40-49",IF(U46<60,"50-59","60+"))))) -> 50-59 | W46: =IF(UPPER(TRIM(J46))="PERU","PERÚ",UPPER(TRIM(J46))) -> PERÚ | X46: =UPPER(TRIM(H46)) -> MASCULINO | Y46: =UPPER(TRIM(K46)) -> AREQUIPA | Z46: =UPPER(TRIM(P46)) -> AREQUIPA
A47: PARTIDO DEL BUEN GOBIERNO | B47: 07619185 | C47: GAVIDIA RODRIGUEZ, JORGE OCTAVIO | D47: 07619185 | E47: GAVIDIA | F47: RODRIGUEZ | G47: JORGE OCTAVIO | H47: MASCULINO | I47: 16/06/1968 | J47: PERÚ | K47: LIMA | L47: LIMA | M47: MIRAFLORES | N47: SENADOR | P47: ÚNICO NACIONAL | Q47: Mayormente resido en: Bartolomé de las Casas 296, Santa Patricia, La Molina, Lima (Alquilado) | R47: https://mpesije.jne.gob.pe/apidocs/7348e9ca-1d86-470e-af99-1be833a166d3.jpg | S47: https://mpesije.jne.gob.pe/apidocs/38c9ab76-8a7b-4b09-8251-712162294305.pdf | T47: =CONCATENATE(A47," - ",B47,".pdf") -> PARTIDO DEL BUEN GOBIERNO - 07619185.pdf | U47: =IF(I47="","",DATEDIF(DATE(VALUE(RIGHT(I47,4)),VALUE(MID(I47,4,2)),VALUE(LEFT(I47,2))),TODAY(),"Y")) -> 57 | V47: =IF(U47="","",IF(U47<30,"18-29",IF(U47<40,"30-39",IF(U47<50,"40-49",IF(U47<60,"50-59","60+"))))) -> 50-59 | W47: =IF(UPPER(TRIM(J47))="PERU","PERÚ",UPPER(TRIM(J47))) -> PERÚ | X47: =UPPER(TRIM(H47)) -> MASCULINO | Y47: =UPPER(TRIM(K47)) -> LIMA | Z47: =UPPER(TRIM(P47)) -> ÚNICO NACIONAL
A48: PARTIDO DEL BUEN GOBIERNO | B48: 07231335 | C48: ITURREGUI BYRNE, PATRICIA MILAGROS | D48: 07231335 | E48: ITURREGUI | F48: BYRNE | G48: PATRICIA MILAGROS | H48: FEMENINO | I48: 18/05/1953 | J48: PERÚ | K48: LIMA | L48: LIMA | M48: LIMA | N48: SENADOR | P48: ÚNICO NACIONAL | R48: https://mpesije.jne.gob.pe/apidocs/1596b93e-f1f1-44e5-a76c-386c100a888d.jpg | S48: https://mpesije.jne.gob.pe/apidocs/70880c4c-58a3-4fcf-81e8-c7de76fa1446.pdf | T48: =CONCATENATE(A48," - ",B48,".pdf") -> PARTIDO DEL BUEN GOBIERNO - 07231335.pdf | U48: =IF(I48="","",DATEDIF(DATE(VALUE(RIGHT(I48,4)),VALUE(MID(I48,4,2)),VALUE(LEFT(I48,2))),TODAY(),"Y")) -> 73 | V48: =IF(U48="","",IF(U48<30,"18-29",IF(U48<40,"30-39",IF(U48<50,"40-49",IF(U48<60,"50-59","60+"))))) -> 60+ | W48: =IF(UPPER(TRIM(J48))="PERU","PERÚ",UPPER(TRIM(J48))) -> PERÚ | X48: =UPPER(TRIM(H48)) -> FEMENINO | Y48: =UPPER(TRIM(K48)) -> LIMA | Z48: =UPPER(TRIM(P48)) -> ÚNICO NACIONAL
A49: PARTIDO DEL BUEN GOBIERNO | B49: 06876967 | C49: MATUTE CHARUN, SUSANA FLOR DE MARIA | D49: 06876967 | E49: MATUTE | F49: CHARUN | G49: SUSANA FLOR DE MARIA | H49: FEMENINO | I49: 12/06/1965 | J49: PERÚ | K49: LIMA | L49: LIMA | M49: PUEBLO LIBRE | N49: PRIMER VICEPRESIDENTE DE LA REPÚBLICA | O49: SENADOR | P49: ÚNICO NACIONAL | R49: https://mpesije.jne.gob.pe/apidocs/63c487f6-0e92-45ec-8d58-5fed3a35e368.jpg | S49: https://mpesije.jne.gob.pe/apidocs/650515c4-438a-47e5-8f0f-1494a7716244.pdf | T49: =CONCATENATE(A49," - ",B49,".pdf") -> PARTIDO DEL BUEN GOBIERNO - 06876967.pdf | U49: =IF(I49="","",DATEDIF(DATE(VALUE(RIGHT(I49,4)),VALUE(MID(I49,4,2)),VALUE(LEFT(I49,2))),TODAY(),"Y")) -> 61 | V49: =IF(U49="","",IF(U49<30,"18-29",IF(U49<40,"30-39",IF(U49<50,"40-49",IF(U49<60,"50-59","60+"))))) -> 60+ | W49: =IF(UPPER(TRIM(J49))="PERU","PERÚ",UPPER(TRIM(J49))) -> PERÚ | X49: =UPPER(TRIM(H49)) -> FEMENINO | Y49: =UPPER(TRIM(K49)) -> LIMA | Z49: =UPPER(TRIM(P49)) -> ÚNICO NACIONAL
A50: RENOVACION POPULAR | B50: 08235876 | C50: ALCORTA SUERO, MARIA LOURDES PIA LUISA | D50: 08235876 | E50: ALCORTA | F50: SUERO | G50: MARIA LOURDES PIA LUISA | H50: FEMENINO | I50: 21/06/1951 | J50: PERÚ | K50: LIMA | L50: LIMA | M50: MIRAFLORES | N50: SENADOR | P50: ÚNICO NACIONAL | R50: https://mpesije.jne.gob.pe/apidocs/0a50619c-a4b3-4580-bdee-146c75827d2c.jpg | S50: https://mpesije.jne.gob.pe/apidocs/440ebb09-edfe-4ca7-9d2c-8659c6aff6f5.pdf | T50: =CONCATENATE(A50," - ",B50,".pdf") -> RENOVACION POPULAR - 08235876.pdf | U50: =IF(I50="","",DATEDIF(DATE(VALUE(RIGHT(I50,4)),VALUE(MID(I50,4,2)),VALUE(LEFT(I50,2))),TODAY(),"Y")) -> 74 | V50: =IF(U50="","",IF(U50<30,"18-29",IF(U50<40,"30-39",IF(U50<50,"40-49",IF(U50<60,"50-59","60+"))))) -> 60+ | W50: =IF(UPPER(TRIM(J50))="PERU","PERÚ",UPPER(TRIM(J50))) -> PERÚ | X50: =UPPER(TRIM(H50)) -> FEMENINO | Y50: =UPPER(TRIM(K50)) -> LIMA | Z50: =UPPER(TRIM(P50)) -> ÚNICO NACIONAL
A51: RENOVACION POPULAR | B51: 25799622 | C51: AMPUERO MEZA, KATHERINE MILAGROS | D51: 25799622 | E51: AMPUERO | F51: MEZA | G51: KATHERINE MILAGROS | H51: FEMENINO | I51: 05/11/1975 | J51: PERÚ | K51: AMAZONAS | L51: CHACHAPOYAS | M51: CHACHAPOYAS | N51: SENADOR | P51: ÚNICO NACIONAL | R51: https://mpesije.jne.gob.pe/apidocs/6574b5ec-9453-4117-8f95-80cf0bcb4371.jpg | S51: https://mpesije.jne.gob.pe/apidocs/f97f7d87-0cf7-4366-a4e3-c885d8aa1977.pdf | T51: =CONCATENATE(A51," - ",B51,".pdf") -> RENOVACION POPULAR - 25799622.pdf | U51: =IF(I51="","",DATEDIF(DATE(VALUE(RIGHT(I51,4)),VALUE(MID(I51,4,2)),VALUE(LEFT(I51,2))),TODAY(),"Y")) -> 50 | V51: =IF(U51="","",IF(U51<30,"18-29",IF(U51<40,"30-39",IF(U51<50,"40-49",IF(U51<60,"50-59","60+"))))) -> 50-59 | W51: =IF(UPPER(TRIM(J51))="PERU","PERÚ",UPPER(TRIM(J51))) -> PERÚ | X51: =UPPER(TRIM(H51)) -> FEMENINO | Y51: =UPPER(TRIM(K51)) -> AMAZONAS | Z51: =UPPER(TRIM(P51)) -> ÚNICO NACIONAL
A52: RENOVACION POPULAR | B52: 43285320 | C52: CALISTO GIAMPIETRI, FRANCISCO JOSE | D52: 43285320 | E52: CALISTO | F52: GIAMPIETRI | G52: FRANCISCO JOSE | H52: MASCULINO | I52: 28/02/1961 | J52: PERÚ | K52: CALLAO | L52: CALLAO | M52: BELLAVISTA | N52: SENADOR | P52: LIMA METROPOLITANA | R52: https://mpesije.jne.gob.pe/apidocs/552d520b-f83d-4e86-86c4-f55840c252be.jpg | S52: https://mpesije.jne.gob.pe/apidocs/321d680e-20b8-4049-94a9-a0a00b3fde03.pdf | T52: =CONCATENATE(A52," - ",B52,".pdf") -> RENOVACION POPULAR - 43285320.pdf | U52: =IF(I52="","",DATEDIF(DATE(VALUE(RIGHT(I52,4)),VALUE(MID(I52,4,2)),VALUE(LEFT(I52,2))),TODAY(),"Y")) -> 65 | V52: =IF(U52="","",IF(U52<30,"18-29",IF(U52<40,"30-39",IF(U52<50,"40-49",IF(U52<60,"50-59","60+"))))) -> 60+ | W52: =IF(UPPER(TRIM(J52))="PERU","PERÚ",UPPER(TRIM(J52))) -> PERÚ | X52: =UPPER(TRIM(H52)) -> MASCULINO | Y52: =UPPER(TRIM(K52)) -> CALLAO | Z52: =UPPER(TRIM(P52)) -> LIMA METROPOLITANA
A53: RENOVACION POPULAR | B53: 07852432 | C53: JAUREGUI MARTINEZ DE AGUAYO, MARIA DE LOS MILAGROS JACKELINE | D53: 07852432 | E53: JAUREGUI | F53: MARTINEZ DE AGUAYO | G53: MARIA DE LOS MILAGROS JACKELINE | H53: FEMENINO | I53: 16/06/1963 | J53: PERÚ | K53: JUNIN | L53: HUANCAYO | M53: HUANCAYO | N53: SENADOR | P53: LIMA METROPOLITANA | R53: https://mpesije.jne.gob.pe/apidocs/b0d9cd02-a849-4579-8091-2c6903eec61a.jpg | S53: https://mpesije.jne.gob.pe/apidocs/ae9a2ed0-e060-4adc-8ea5-81473a1d59a1.pdf | T53: =CONCATENATE(A53," - ",B53,".pdf") -> RENOVACION POPULAR - 07852432.pdf | U53: =IF(I53="","",DATEDIF(DATE(VALUE(RIGHT(I53,4)),VALUE(MID(I53,4,2)),VALUE(LEFT(I53,2))),TODAY(),"Y")) -> 62 | V53: =IF(U53="","",IF(U53<30,"18-29",IF(U53<40,"30-39",IF(U53<50,"40-49",IF(U53<60,"50-59","60+"))))) -> 60+ | W53: =IF(UPPER(TRIM(J53))="PERU","PERÚ",UPPER(TRIM(J53))) -> PERÚ | X53: =UPPER(TRIM(H53)) -> FEMENINO | Y53: =UPPER(TRIM(K53)) -> JUNIN | Z53: =UPPER(TRIM(P53)) -> LIMA METROPOLITANA
A54: RENOVACION POPULAR | B54: 07845838 | C54: LÓPEZ ALIAGA CAZORLA, RAFAEL BERNARDO | D54: 07845838 | E54: LÓPEZ ALIAGA | F54: CAZORLA | G54: RAFAEL BERNARDO | H54: MASCULINO | I54: 11/02/1961 | J54: PERÚ | K54: LIMA | L54: LIMA | M54: LIMA | N54: PRESIDENTE DE LA REPÚBLICA | O54: SENADOR | P54: ÚNICO NACIONAL | R54: https://mpesije.jne.gob.pe/apidocs/b2e00ae2-1e50-4ad3-a103-71fc7e4e8255.jpg | S54: https://mpesije.jne.gob.pe/apidocs/3d7498fe-7a54-4f7d-882e-c5cdfd2ba26b.pdf | T54: =CONCATENATE(A54," - ",B54,".pdf") -> RENOVACION POPULAR - 07845838.pdf | U54: =IF(I54="","",DATEDIF(DATE(VALUE(RIGHT(I54,4)),VALUE(MID(I54,4,2)),VALUE(LEFT(I54,2))),TODAY(),"Y")) -> 65 | V54: =IF(U54="","",IF(U54<30,"18-29",IF(U54<40,"30-39",IF(U54<50,"40-49",IF(U54<60,"50-59","60+"))))) -> 60+ | W54: =IF(UPPER(TRIM(J54))="PERU","PERÚ",UPPER(TRIM(J54))) -> PERÚ | X54: =UPPER(TRIM(H54)) -> MASCULINO | Y54: =UPPER(TRIM(K54)) -> LIMA | Z54: =UPPER(TRIM(P54)) -> ÚNICO NACIONAL
A55: RENOVACION POPULAR | B55: 01539305 | C55: MANCHA PINEDA, ESTANISLAO EDGAR | D55: 01539305 | E55: MANCHA | F55: PINEDA | G55: ESTANISLAO EDGAR | H55: MASCULINO | I55: 19/11/1973 | J55: PERÚ | K55: PUNO | L55: AZANGARO | M55: SAN ANTON | N55: SENADOR | P55: ÚNICO NACIONAL | R55: https://mpesije.jne.gob.pe/apidocs/278ecb43-645b-460c-82f0-b310cbb72289.jpg | S55: https://mpesije.jne.gob.pe/apidocs/cff4c882-00b3-4a6a-aca5-7bbc07ae3837.pdf | T55: =CONCATENATE(A55," - ",B55,".pdf") -> RENOVACION POPULAR - 01539305.pdf | U55: =IF(I55="","",DATEDIF(DATE(VALUE(RIGHT(I55,4)),VALUE(MID(I55,4,2)),VALUE(LEFT(I55,2))),TODAY(),"Y")) -> 52 | V55: =IF(U55="","",IF(U55<30,"18-29",IF(U55<40,"30-39",IF(U55<50,"40-49",IF(U55<60,"50-59","60+"))))) -> 50-59 | W55: =IF(UPPER(TRIM(J55))="PERU","PERÚ",UPPER(TRIM(J55))) -> PERÚ | X55: =UPPER(TRIM(H55)) -> MASCULINO | Y55: =UPPER(TRIM(K55)) -> PUNO | Z55: =UPPER(TRIM(P55)) -> ÚNICO NACIONAL
A56: RENOVACION POPULAR | B56: 45209282 | C56: MUÑANTE BARRIOS, ALEJANDRO | D56: 45209282 | E56: MUÑANTE | F56: BARRIOS | G56: ALEJANDRO | H56: MASCULINO | I56: 02/03/1987 | J56: PERÚ | K56: LORETO | L56: MAYNAS | M56: IQUITOS | N56: SENADOR | P56: ÚNICO NACIONAL | Q56: ES ACTUALMENTE CONGRESISTA. | R56: https://mpesije.jne.gob.pe/apidocs/bcf375ae-6a90-4f80-8ed3-37c2c43efbca.jpg | S56: https://mpesije.jne.gob.pe/apidocs/60f97c6b-ac8f-414a-b4f9-e45f6f680f17.pdf | T56: =CONCATENATE(A56," - ",B56,".pdf") -> RENOVACION POPULAR - 45209282.pdf | U56: =IF(I56="","",DATEDIF(DATE(VALUE(RIGHT(I56,4)),VALUE(MID(I56,4,2)),VALUE(LEFT(I56,2))),TODAY(),"Y")) -> 39 | V56: =IF(U56="","",IF(U56<30,"18-29",IF(U56<40,"30-39",IF(U56<50,"40-49",IF(U56<60,"50-59","60+"))))) -> 30-39 | W56: =IF(UPPER(TRIM(J56))="PERU","PERÚ",UPPER(TRIM(J56))) -> PERÚ | X56: =UPPER(TRIM(H56)) -> MASCULINO | Y56: =UPPER(TRIM(K56)) -> LORETO | Z56: =UPPER(TRIM(P56)) -> ÚNICO NACIONAL
A57: RENOVACION POPULAR | B57: 06504611 | C57: VELASQUEZ GARCIA, MIGUEL ANGEL | D57: 06504611 | E57: VELASQUEZ | F57: GARCIA | G57: MIGUEL ANGEL | H57: MASCULINO | I57: 05/01/1962 | J57: PERÚ | K57: LIMA | L57: LIMA | M57: JESUS MARIA | N57: SENADOR | P57: PERUANOS RESIDENTES EN EL EXTRANJERO | R57: https://mpesije.jne.gob.pe/apidocs/f526053a-32bd-4f15-b314-92c9603db466.jpg | S57: https://mpesije.jne.gob.pe/apidocs/10a7d2e3-71b6-48fe-adf1-e974a7119e3f.pdf | T57: =CONCATENATE(A57," - ",B57,".pdf") -> RENOVACION POPULAR - 06504611.pdf | U57: =IF(I57="","",DATEDIF(DATE(VALUE(RIGHT(I57,4)),VALUE(MID(I57,4,2)),VALUE(LEFT(I57,2))),TODAY(),"Y")) -> 64 | V57: =IF(U57="","",IF(U57<30,"18-29",IF(U57<40,"30-39",IF(U57<50,"40-49",IF(U57<60,"50-59","60+"))))) -> 60+ | W57: =IF(UPPER(TRIM(J57))="PERU","PERÚ",UPPER(TRIM(J57))) -> PERÚ | X57: =UPPER(TRIM(H57)) -> MASCULINO | Y57: =UPPER(TRIM(K57)) -> LIMA | Z57: =UPPER(TRIM(P57)) -> PERUANOS RESIDENTES EN EL EXTRANJERO
A58: FUERZA POPULAR | B58: 40433187 | C58: TORRES MORALES, MIGUEL ANGEL | D58: 40433187 | E58: TORRES | F58: MORALES | G58: MIGUEL ANGEL | H58: MASCULINO | I58: 18/02/1980 | J58: PERÚ | K58: LIMA | L58: LIMA | M58: LINCE | N58: SEGUNDO VICEPRESIDENTE DE LA REPÚBLICA | O58: SENADOR | P58: ÚNICO NACIONAL | R58: https://mpesije.jne.gob.pe/apidocs/789b7714-8633-4a59-a89b-7fab4646fef1.jpeg | S58: https://mpesije.jne.gob.pe/apidocs/99872797-b3bf-452e-939b-06d1cdeaa917.pdf | T58: =CONCATENATE(A58," - ",B58,".pdf") -> FUERZA POPULAR - 40433187.pdf | U58: =IF(I58="","",DATEDIF(DATE(VALUE(RIGHT(I58,4)),VALUE(MID(I58,4,2)),VALUE(LEFT(I58,2))),TODAY(),"Y")) -> 46 | V58: =IF(U58="","",IF(U58<30,"18-29",IF(U58<40,"30-39",IF(U58<50,"40-49",IF(U58<60,"50-59","60+"))))) -> 40-49 | W58: =IF(UPPER(TRIM(J58))="PERU","PERÚ",UPPER(TRIM(J58))) -> PERÚ | X58: =UPPER(TRIM(H58)) -> MASCULINO | Y58: =UPPER(TRIM(K58)) -> LIMA | Z58: =UPPER(TRIM(P58)) -> ÚNICO NACIONAL
A59: JUNTOS POR EL PERU | B59: 02044988 | C59: CHIPANA CHIPANA, JOSE MOISES | D59: 02044988 | E59: CHIPANA | F59: CHIPANA | G59: JOSE MOISES | H59: MASCULINO | I59: 29/08/1974 | J59: PERÚ | K59: PUNO | L59: HUANCANE | M59: HUANCANE | N59: SENADOR | P59: ÚNICO NACIONAL | T59: =CONCATENATE(A59," - ",B59,".pdf") -> JUNTOS POR EL PERU - 02044988.pdf | U59: =IF(I59="","",DATEDIF(DATE(VALUE(RIGHT(I59,4)),VALUE(MID(I59,4,2)),VALUE(LEFT(I59,2))),TODAY(),"Y")) -> 51 | V59: =IF(U59="","",IF(U59<30,"18-29",IF(U59<40,"30-39",IF(U59<50,"40-49",IF(U59<60,"50-59","60+"))))) -> 50-59 | W59: =IF(UPPER(TRIM(J59))="PERU","PERÚ",UPPER(TRIM(J59))) -> PERÚ | X59: =UPPER(TRIM(H59)) -> MASCULINO | Y59: =UPPER(TRIM(K59)) -> PUNO | Z59: =UPPER(TRIM(P59)) -> ÚNICO NACIONAL
A60: JUNTOS POR EL PERU | B60: 23271450 | C60: YAURI TUNQUE, JOAQUIN | D60: 23271450 | E60: YAURI | F60: TUNQUE | G60: JOAQUIN | H60: MASCULINO | I60: 16/08/1974 | J60: PERÚ | K60: HUANCAVELICA | L60: HUANCAVELICA | M60: HUANCAVELICA | N60: SENADOR | P60: ÚNICO NACIONAL | T60: =CONCATENATE(A60," - ",B60,".pdf") -> JUNTOS POR EL PERU - 23271450.pdf | U60: =IF(I60="","",DATEDIF(DATE(VALUE(RIGHT(I60,4)),VALUE(MID(I60,4,2)),VALUE(LEFT(I60,2))),TODAY(),"Y")) -> 51 | V60: =IF(U60="","",IF(U60<30,"18-29",IF(U60<40,"30-39",IF(U60<50,"40-49",IF(U60<60,"50-59","60+"))))) -> 50-59 | W60: =IF(UPPER(TRIM(J60))="PERU","PERÚ",UPPER(TRIM(J60))) -> PERÚ | X60: =UPPER(TRIM(H60)) -> MASCULINO | Y60: =UPPER(TRIM(K60)) -> HUANCAVELICA | Z60: =UPPER(TRIM(P60)) -> ÚNICO NACIONAL
A61: JUNTOS POR EL PERU | B61: 31010129 | C61: RAMOS HUILLCAS, ANDRES AVELINO | D61: 31010129 | E61: RAMOS | F61: HUILLCAS | G61: ANDRES AVELINO | H61: MASCULINO | I61: 10/11/1958 | J61: PERÚ | K61: APURIMAC | L61: ABANCAY | M61: PICHIRHUA | N61: SENADOR | P61: ÚNICO NACIONAL | T61: =CONCATENATE(A61," - ",B61,".pdf") -> JUNTOS POR EL PERU - 31010129.pdf | U61: =IF(I61="","",DATEDIF(DATE(VALUE(RIGHT(I61,4)),VALUE(MID(I61,4,2)),VALUE(LEFT(I61,2))),TODAY(),"Y")) -> 67 | V61: =IF(U61="","",IF(U61<30,"18-29",IF(U61<40,"30-39",IF(U61<50,"40-49",IF(U61<60,"50-59","60+"))))) -> 60+ | W61: =IF(UPPER(TRIM(J61))="PERU","PERÚ",UPPER(TRIM(J61))) -> PERÚ | X61: =UPPER(TRIM(H61)) -> MASCULINO | Y61: =UPPER(TRIM(K61)) -> APURIMAC | Z61: =UPPER(TRIM(P61)) -> ÚNICO NACIONAL
W62: =IF(UPPER(TRIM(J63))="PERU","PERÚ",UPPER(TRIM(J63)))
W63: =IF(UPPER(TRIM(J64))="PERU","PERÚ",UPPER(TRIM(J64)))
W64: =IF(UPPER(TRIM(J65))="PERU","PERÚ",UPPER(TRIM(J65)))
W65: =IF(UPPER(TRIM(J66))="PERU","PERÚ",UPPER(TRIM(J66)))
W66: =IF(UPPER(TRIM(J67))="PERU","PERÚ",UPPER(TRIM(J67)))
W67: =IF(UPPER(TRIM(J68))="PERU","PERÚ",UPPER(TRIM(J68)))
W68: =IF(UPPER(TRIM(J69))="PERU","PERÚ",UPPER(TRIM(J69)))
W69: =IF(UPPER(TRIM(J70))="PERU","PERÚ",UPPER(TRIM(J70)))
W70: =IF(UPPER(TRIM(J71))="PERU","PERÚ",UPPER(TRIM(J71)))
W71: =IF(UPPER(TRIM(J72))="PERU","PERÚ",UPPER(TRIM(J72)))
W72: =IF(UPPER(TRIM(J73))="PERU","PERÚ",UPPER(TRIM(J73)))
W73: =IF(UPPER(TRIM(J74))="PERU","PERÚ",UPPER(TRIM(J74)))
... W114: =IF(UPPER(TRIM(J115))="PERU","PERÚ",UPPER(TRIM(J115)))
W115: =IF(UPPER(TRIM(J58))="PERU","PERÚ",UPPER(TRIM(J58))) -> PERÚ

Sheet Pivot Table 2
A1: COUNTA of DNI_CANDIDATO | B1: SEXO_LIMPIO | F1: PARIDAD
A2: ORGANIZACION_POLITICA | B2: FEMENINO | C2: MASCULINO | D2: Total general | F2: % mujeres | G2: % hombres
A3: AHORA NACION - AN | B3: 2 | C3: 2 | D3: 4 | F3: =IFERROR(COUNTIFS('01 DATOS PERSONALES'!$A:$A,$A3,'01 DATOS PERSONALES'!$H:$H,"FEMENINO")/COUNTIF('01 DATOS PERSONALES'!$A:$A,$A3),"") -> 0.5 | G3: =IFERROR(COUNTIFS('01 DATOS PERSONALES'!$A:$A,$A3,'01 DATOS PERSONALES'!$H:$H,"MASCULINO")/COUNTIF('01 DATOS PERSONALES'!$A:$A,$A3),"") -> 0.5
A4: FUERZA POPULAR | B4: 5 | C4: 16 | D4: 21 | F4: =IFERROR(COUNTIFS('01 DATOS PERSONALES'!$A:$A,$A4,'01 DATOS PERSONALES'!$H:$H,"FEMENINO")/COUNTIF('01 DATOS PERSONALES'!$A:$A,$A4),"") -> 0.22727273 | G4: =IFERROR(COUNTIFS('01 DATOS PERSONALES'!$A:$A,$A4,'01 DATOS PERSONALES'!$H:$H,"MASCULINO")/COUNTIF('01 DATOS PERSONALES'!$A:$A,$A4),"") -> 0.77272727
A5: JUNTOS POR EL PERU | B5: 1 | C5: 10 | D5: 11 | F5: =IFERROR(COUNTIFS('01 DATOS PERSONALES'!$A:$A,$A5,'01 DATOS PERSONALES'!$H:$H,"FEMENINO")/COUNTIF('01 DATOS PERSONALES'!$A:$A,$A5),"") -> 0.071428571 | G5: =IFERROR(COUNTIFS('01 DATOS PERSONALES'!$A:$A,$A5,'01 DATOS PERSONALES'!$H:$H,"MASCULINO")/COUNTIF('01 DATOS PERSONALES'!$A:$A,$A5),"") -> 0.92857143
A6: PARTIDO CIVICO OBRAS | B6: 2 | C6: 3 | D6: 5 | F6: =IFERROR(COUNTIFS('01 DATOS PERSONALES'!$A:$A,$A6,'01 DATOS PERSONALES'!$H:$H,"FEMENINO")/COUNTIF('01 DATOS PERSONALES'!$A:$A,$A6),"") -> 0.4 | G6: =IFERROR(COUNTIFS('01 DATOS PERSONALES'!$A:$A,$A6,'01 DATOS PERSONALES'!$H:$H,"MASCULINO")/COUNTIF('01 DATOS PERSONALES'!$A:$A,$A6),"") -> 0.6
A7: PARTIDO DEL BUEN GOBIERNO | B7: 3 | C7: 4 | D7: 7 | F7: =IFERROR(COUNTIFS('01 DATOS PERSONALES'!$A:$A,$A7,'01 DATOS PERSONALES'!$H:$H,"FEMENINO")/COUNTIF('01 DATOS PERSONALES'!$A:$A,$A7),"") -> 0.42857143 | G7: =IFERROR(COUNTIFS('01 DATOS PERSONALES'!$A:$A,$A7,'01 DATOS PERSONALES'!$H:$H,"MASCULINO")/COUNTIF('01 DATOS PERSONALES'!$A:$A,$A7),"") -> 0.57142857
A8: RENOVACION POPULAR | B8: 3 | C8: 5 | D8: 8 | F8: =IFERROR(COUNTIFS('01 DATOS PERSONALES'!$A:$A,$A8,'01 DATOS PERSONALES'!$H:$H,"FEMENINO")/COUNTIF('01 DATOS PERSONALES'!$A:$A,$A8),"") -> 0.375 | G8: =IFERROR(COUNTIFS('01 DATOS PERSONALES'!$A:$A,$A8,'01 DATOS PERSONALES'!$H:$H,"MASCULINO")/COUNTIF('01 DATOS PERSONALES'!$A:$A,$A8),"") -> 0.625
A9: Total general | B9: 16 | C9: 40 | D9: 56 | F9: =IFERROR(COUNTIFS('01 DATOS PERSONALES'!$A:$A,$A9,'01 DATOS PERSONALES'!$H:$H,"FEMENINO")/COUNTIF('01 DATOS PERSONALES'!$A:$A,$A9),"") | G9: =IFERROR(COUNTIFS('01 DATOS PERSONALES'!$A:$A,$A9,'01 DATOS PERSONALES'!$H:$H,"MASCULINO")/COUNTIF('01 DATOS PERSONALES'!$A:$A,$A9),"")
F10: =IFERROR(COUNTIFS('01 DATOS PERSONALES'!$A:$A,$A10,'01 DATOS PERSONALES'!$H:$H,"FEMENINO")/COUNTIF('01 DATOS PERSONALES'!$A:$A,$A10),"") | G10: =IFERROR(COUNTIFS('01 DATOS PERSONALES'!$A:$A,$A10,'01 DATOS PERSONALES'!$H:$H,"MASCULINO")/COUNTIF('01 DATOS PERSONALES'!$A:$A,$A10),"")
F11: =IFERROR(COUNTIFS('01 DATOS PERSONALES'!$A:$A,$A11,'01 DATOS PERSONALES'!$H:$H,"FEMENINO")/COUNTIF('01 DATOS PERSONALES'!$A:$A,$A11),"") | G11: =IFERROR(COUNTIFS('01 DATOS PERSONALES'!$A:$A,$A11,'01 DATOS PERSONALES'!$H:$H,"MASCULINO")/COUNTIF('01 DATOS PERSONALES'!$A:$A,$A11),"")
A13: ORGANIZACION_POLITICA | B13: AVERAGE of EDAD | C13: MAX of EDAD | D13: MIN of EDAD
A14: AHORA NACION - AN | B14: 60.25 | C14: 75 | D14: 46
A15: FUERZA POPULAR | B15: 63.863636 | C15: 79 | D15: 46
A16: JUNTOS POR EL PERU | B16: 55.571429 | C16: 72 | D16: 41
A17: PARTIDO CIVICO OBRAS | B17: 66.2 | C17: 75 | D17: 63
A18: PARTIDO DEL BUEN GOBIERNO | B18: 64.428571 | C18: 73 | D18: 53
A19: RENOVACION POPULAR | B19: 58.875 | C19: 74 | D19: 39
A20: (en blanco)
A21: Total general | B21: 61.283333 | C21: 79 | D21: 39

Sheet RESUMEN_DP
A1: Total candidatos | B1: Mujeres | C1: Hombres | D1: Edad promedio | E1: Edad mediana | F1: Edad mínima | G1: Edad máxima
A2: =COUNTA('01 DATOS PERSONALES'!B2:B1000) -> 60 | B2: =COUNTIF('01 DATOS PERSONALES'!X2:Y1000,"FEMENINO") -> 16 | C2: =COUNTIF('01 DATOS PERSONALES'!X2:Y1000,"MASCULINO") -> 44 | D2: =AVERAGE('01 DATOS PERSONALES'!U2:U1000) -> 61.283333 | E2: =MEDIAN('01 DATOS PERSONALES'!U2:U1000) -> 63.5 | F2: =MIN('01 DATOS PERSONALES'!U2:U1000) -> 39 | G2: =MAX('01 DATOS PERSONALES'!U2:U1000) -> 79

Sheet 02 EXPERIENCIA LABORAL
A1: ORGANIZACION_POLITICA | B1: DNI_CANDIDATO | C1: CANDIDATO | D1: TIENE_EXPERIENCIA_LABORAL | E1: CENTRO_TRABAJO | F1: PROFESION_OCUPACION | G1: RUC | H1: DIRECCION | I1: AÑO_DESDE | J1: AÑO_HASTA | K1: PAIS | L1: DEPARTAMENTO | M1: PROVINCIA | N1: DISTRITO | O1: INFORMACION_ADICIONAL | P1: TRABAJO_CONGRESO
A2: AHORA NACION - AN | B2: 07755878 | C2: DELGADO ZEGARRA, JAIME RICARDO | D2: SI | E2: Congreso de la República | F2: Asesor | G2: 20161749126 | H2: Av. Abancay | I2: 2024 | J2: 2025 | K2: PERU | L2: LIMA | M2: LIMA | N2: LIMA | O2: Trabajé hasta el 28 de noviembre como asesor de la comisión de defensa del consumidor. | P2: =IFERROR(__xludf.DUMMYFUNCTION("IF(REGEXMATCH(UPPER(E2),""CONGRESO""),1,0)"),1) -> 1
A3: AHORA NACION - AN | B3: 07755878 | C3: DELGADO ZEGARRA, JAIME RICARDO | D3: SI | E3: Congreso de la República | F3: Asesor | G3: 20161749126 | H3: Av. Abancay | I3: 2020 | J3: 2020 | K3: PERU | L3: LIMA | M3: LIMA | N3: LIMA | P3: =IFERROR(__xludf.DUMMYFUNCTION("IF(REGEXMATCH(UPPER(E3),""CONGRESO""),1,0)"),1) -> 1
A4: AHORA NACION - AN | B4: 07755878 | C4: DELGADO ZEGARRA, JAIME RICARDO | D4: SI | E4: Congreso de la República | F4: Congresista | G4: 20161749126 | H4: Av. Abancay | I4: 2011 | J4: 2016 | K4: PERU | L4: LIMA | M4: LIMA | N4: LIMA | P4: =IFERROR(__xludf.DUMMYFUNCTION("IF(REGEXMATCH(UPPER(E4),""CONGRESO""),1,0)"),1) -> 1
A5: AHORA NACION - AN | B5: 07755878 | C5: DELGADO ZEGARRA, JAIME RICARDO | D5: SI | E5: Defensoría del Pueblo | F5: Asesor | H5: Jirón Ucayali 394 - 398 | I5: 2021 | J5: 2021 | K5: PERU | L5: LIMA | M5: LIMA | N5: LIMA | P5: =IFERROR(__xludf.DUMMYFUNCTION("IF(REGEXMATCH(UPPER(E5),""CONGRESO""),1,0)"),0) -> 0
A6: AHORA NACION - AN | B6: 25331980 | C6: LOPEZ CHAU NAVA, PABLO ALFONSO | D6: SI | E6: Universidad Nacional de Ingeniería | F6: Director de la Escuela de Ingeniería Económica | H6: Av. Tupac Amaru 210 | I6: 2017 | J6: 2019 | K6: PERU | L6: LIMA | M6: LIMA | N6: RIMAC | P6: =IFERROR(__xludf.DUMMYFUNCTION("IF(REGEXMATCH(UPPER(E6),""CONGRESO""),1,0)"),0) -> 0
A7: AHORA NACION - AN | B7: 25331980 | C7: LOPEZ CHAU NAVA, PABLO ALFONSO | D7: SI | E7: Universidad Nacional de Ingeniería | F7: Rector | H7: Av. Tupac Amaru 210 | I7: 2021 | J7: 2025 | K7: PERU | L7: LIMA | M7: LIMA | N7: RIMAC | P7: =IFERROR(__xludf.DUMMYFUNCTION("IF(REGEXMATCH(UPPER(E7),""CONGRESO""),1,0)"),0) -> 0
A8: AHORA NACION - AN | B8: 25331980 | C8: LOPEZ CHAU NAVA, PABLO ALFONSO | D8: SI | E8: Universidad Nacional de Ingeniería | F8: Profesor Principal | H8: Av. Tupac Amaru 210 | I8: 1990 | J8: 2025 | K8: PERU | L8: LIMA | M8: LIMA | N8: RIMAC | P8: =IFERROR(__xludf.DUMMYFUNCTION("IF(REGEXMATCH(UPPER(E8),""CONGRESO""),1,0)"),0) -> 0
A9: AHORA NACION - AN | B9: 40204874 | C9: LUQUE IBARRA, RUTH | D9: SI | E9: Derechos Humanos sin Fronteras | F9: Abogada - Directora Ejecutiva | G9: 20491238764 | H9: Barrio Profesional A-8 tercer piso | I9: 2013 | J9: 2016 | K9: PERU | L9: CUSCO | M9: CUSCO | N9: CUSCO | P9: =IFERROR(__xludf.DUMMYFUNCTION("IF(REGEXMATCH(UPPER(E9),""CONGRESO""),1,0)"),0) -> 0
A10: AHORA NACION - AN | B10: 40204874 | C10: LUQUE IBARRA, RUTH | D10: SI | E10: Congreso de la República | F10: Asesora | H10: Av. Abancay S/N | I10: 2016 | J10: 2021 | K10: PERU | L10: LIMA | M10: LIMA | N10: LIMA | P10: =IFERROR(__xludf.DUMMYFUNCTION("IF(REGEXMATCH(UPPER(E10),""CONGRESO""),1,0)"),1) -> 1
A11: AHORA NACION - AN | B11: 40204874 | C11: LUQUE IBARRA, RUTH | D11: SI | E11: Congreso de la República | F11: Congresista | H11: Av. Hospicio Ruiz Dávila Jr. Ancash 369 | I11: 2021 | J11: 2025 | K11: PERU | L11: LIMA | M11: LIMA | N11: LIMA | P11: =IFERROR(__xludf.DUMMYFUNCTION("IF(REGEXMATCH(UPPER(E11),""CONGRESO""),1,0)"),1) -> 1
A12: AHORA NACION - AN | B12: 26705695 | C12: VASQUEZ CHUQUILIN, MIRTHA ESTHER | D12: SI | E12: ONG Grufides | F12: Asesor legal | G12: 20453691536 | H12: Jr Cruz de Piedra No 441 | I12: 2023 | J12: 2025 | K12: PERU | L12: CAJAMARCA | M12: CAJAMARCA | N12: CAJAMARCA | P12: =IFERROR(__xludf.DUMMYFUNCTION("IF(REGEXMATCH(UPPER(E12),""CONGRESO""),1,0)"),0) -> 0
A13: AHORA NACION - AN | B13: 26705695 | C13: VASQUEZ CHUQUILIN, MIRTHA ESTHER | D13: SI | E13: Presidencia del Consejo de Ministros | F13: Presidenta del Consejo de Ministros | H13: Jirón Carabaya Cdra. 1 S/N | I13: 2021 | J13: 2022 | K13: PERU | L13: LIMA | M13: LIMA | N13: LIMA | O13: 07/10/2021 a 30/01/2022 | P13: =IFERROR(__xludf.DUMMYFUNCTION("IF(REGEXMATCH(UPPER(E13),""CONGRESO""),1,0)"),0) -> 0
A14: AHORA NACION - AN | B14: 26705695 | C14: VASQUEZ CHUQUILIN, MIRTHA ESTHER | D14: SI | E14: Universidad de Ciencias y Humanidades | F14: Docente | H14: Av. Universitaria 5175 | I14: 2023 | J14: 2025 | K14: PERU | L14: LIMA | M14: LIMA | N14: LOS OLIVOS | P14: =IFERROR(__xludf.DUMMYFUNCTION("IF(REGEXMATCH(UPPER(E14),""CONGRESO""),1,0)"),0) -> 0
A15: AHORA NACION - AN | B15: 26705695 | C15: VASQUEZ CHUQUILIN, MIRTHA ESTHER | D15: SI | E15: Pontificia Universidad Católica del Perú | F15: Docente | H15: Av. Universitaria 1801 | I15: 2022 | J15: 2023 | K15: PERU | L15: LIMA | M15: LIMA | N15: SAN MIGUEL | P15: =IFERROR(__xludf.DUMMYFUNCTION("IF(REGEXMATCH(UPPER(E15),""CONGRESO""),1,0)"),0) -> 0
A16: AHORA NACION - AN | B16: 26705695 | C16: VASQUEZ CHUQUILIN, MIRTHA ESTHER | D16: SI | E16: Congreso de la República | F16: Congresista de la República | H16: Plaza Bolívar S/N | I16: 2020 | J16: 2021 | K16: PERU | L16: LIMA | M16: LIMA | N16: LIMA | O16: 16/03/2020 a 27/07/2021 | P16: =IFERROR(__xludf.DUMMYFUNCTION("IF(REGEXMATCH(UPPER(E16),""CONGRESO""),1,0)"),1) -> 1
A17: FUERZA POPULAR | B17: 08236035 | C17: AGUINAGA RECUENCO, ALEJANDRO AURELIO | D17: SI | E17: CONGRESO DE LA REPÚBLICA | F17: CONGRESISTA | G17: 20161749126 | H17: JR. HUALLAGA 358 - LIMA | I17: 2021 | J17: 2025 | K17: PERU | L17: LIMA | M17: LIMA | N17: LIMA | O17: CONGRESISTA EN EJERCICIO HASTA EL AÑO 2026 | P17: =IFERROR(__xludf.DUMMYFUNCTION("IF(REGEXMATCH(UPPER(E17),""CONGRESO""),1,0)"),1) -> 1
A18: FUERZA POPULAR | B18: 08236035 | C18: AGUINAGA RECUENCO, ALEJANDRO AURELIO | D18: SI | E18: HOSPITAL NACIONAL ARZOBISPO LOAYZA | F18: MÉDICO ESPECIALISTA | G18: 20154996991 | H18: AV. ALFONSO UGARTE 848 | I18: 1986 | J18: 2020 | K18: PERU | L18: LIMA | M18: LIMA | N18: LIMA | O18: MÉDICO ESPECIALISTA NIVEL 5. | P18: =IFERROR(__xludf.DUMMYFUNCTION("IF(REGEXMATCH(UPPER(E18),""CONGRESO""),1,0)"),0) -> 0
A19: FUERZA POPULAR | B19: 08236035 | C19: AGUINAGA RECUENCO, ALEJANDRO AURELIO | D19: SI | E19: UNIVERSIDAD CIENTÍFICA DEL SUR | F19: DOCENTE | G19: 20421239275 | H19: CARRETERA PANAMERICANA SUR 19. | I19: 2019 | J19: 2020 | K19: PERU | L19: LIMA | M19: LIMA | N19: VILLA EL SALVADOR | P19: =IFERROR(__xludf.DUMMYFUNCTION("IF(REGEXMATCH(UPPER(E19),""CONGRESO""),1,0)"),0) -> 0
A20: FUERZA POPULAR | B20: 06717199 | C20: ARISTA ARBILDO, JOSE BERLEY | D20: SI | E20: Ministerio de Economía y Finanzas | F20: Ministro de Estado | G20: 20131370645 | H20: Jr. Junín 319, Cercado de Lima. | I20: 2024 | J20: 2025 | K20: PERU | L20: LIMA | M20: LIMA | N20: LIMA | P20: =IFERROR(__xludf.DUMMYFUNCTION("IF(REGEXMATCH(UPPER(E20),""CONGRESO""),1,0)"),0) -> 0
A21: FUERZA POPULAR | B21: 06717199 | C21: ARISTA ARBILDO, JOSE BERLEY | D21: SI | E21: Ministerio de Educación | F21: Consultor | G21: 20131370998 | H21: Calle Del Comercio 193 | I21: 2015 | J21: 2016 | K21: PERU | L21: LIMA | M21: LIMA | N21: SAN BORJA | P21: =IFERROR(__xludf.DUMMYFUNCTION("IF(REGEXMATCH(UPPER(E21),""CONGRESO""),1,0)"),0) -> 0
A22: FUERZA POPULAR | B22: 06717199 | C22: ARISTA ARBILDO, JOSE BERLEY | D22: SI | E22: Corporación Andina de Fomento | F22: Consultor | G22: 20508260581 | H22: Av. Canaval y Moreyra 380 | I22: 2018 | J22: 2021 | K22: PERU | L22: LIMA | M22: LIMA | N22: SAN ISIDRO | O22: Consultor externo. | P22: =IFERROR(__xludf.DUMMYFUNCTION("IF(REGEXMATCH(UPPER(E22),""CONGRESO""),1,0)"),0) -> 0
A23: FUERZA POPULAR | B23: 06717199 | C23: ARISTA ARBILDO, JOSE BERLEY | D23: SI | E23: Ministerio de Agricultura y Riego | F23: Ministro de Estado | G23: 20131372931 | H23: Jirón Cahuide 805 | I23: 2018 | J23: 2018 | K23: PERU | L23: LIMA | M23: LIMA | N23: JESUS MARIA | P23: =IFERROR(__xludf.DUMMYFUNCTION("IF(REGEXMATCH(UPPER(E23),""CONGRESO""),1,0)"),0) -> 0
A24: FUERZA POPULAR | B24: 06717199 | C24: ARISTA ARBILDO, JOSE BERLEY | D24: SI | E24: Ministerio de Economía y Finanzas | F24: Asesor | G24: 20131370645 | H24: Jr. Junín 319, Cercado de Lima. | I24: 2016 | J24: 2017 | K24: PERU | L24: LIMA | M24: LIMA | N24: LIMA | P24: =IFERROR(__xludf.DUMMYFUNCTION("IF(REGEXMATCH(UPPER(E24),""CONGRESO""),1,0)"),0) -> 0
A25: FUERZA POPULAR | B25: 10307948 | C25: ASTUDILLO SALCEDO, CESAR AUGUSTO | D25: SI | E25: Comando Conjunto de las FFAA | F25: Jefe | H25: Av. Arequipa / Av. Nicolas Corpancho, Santa Beatriz | I25: 2018 | J25: 2021 | K25: PERU | L25: LIMA | M25: LIMA | N25: LIMA | P25: =IFERROR(__xludf.DUMMYFUNCTION("IF(REGEXMATCH(UPPER(E25),""CONGRESO""),1,0)"),0) -> 0
A26: FUERZA POPULAR | B26: 10307948 | C26: ASTUDILLO SALCEDO, CESAR AUGUSTO | D26: SI | E26: Ejército del Perú | F26: Inspector | H26: Cuartel General del Ejército Peruano | I26: 2016 | J26: 2017 | K26: PERU | L26: LIMA | M26: LIMA | N26: SAN BORJA | P26: =IFERROR(__xludf.DUMMYFUNCTION("IF(REGEXMATCH(UPPER(E26),""CONGRESO""),1,0)"),0) -> 0
A27: FUERZA POPULAR | B27: 10307948 | C27: ASTUDILLO SALCEDO, CESAR AUGUSTO | D27: SI | E27: Ejército del Perú | F27: Comandante | H27: Cuartel del Ejército Peruano en Pichari | I27: 2014 | J27: 2015 | K27: PERU | L27: CUSCO | M27: LA CONVENCION | N27: PICHARI | P27: =IFERROR(__xludf.DUMMYFUNCTION("IF(REGEXMATCH(UPPER(E27),""CONGRESO""),1,0)"),0) -> 0
A28: FUERZA POPULAR | B28: 10307948 | C28: ASTUDILLO SALCEDO, CESAR AUGUSTO | D28: SI | E28: Ejército del Perú | F28: Comandante General | H28: Cuartel General del Ejército Peruano | I28: 2017 | J28: 2018 | K28: PERU | L28: LIMA | M28: LIMA | N28: SAN BORJA | P28: =IFERROR(__xludf.DUMMYFUNCTION("IF(REGEXMATCH(UPPER(E28),""CONGRESO""),1,0)"),0) -> 0
A29: FUERZA POPULAR | B29: 32971154 | C29: CHACON TRUJILLO, NILZA MERLY | D29: SI | E29: INVERSIONES GENERALES AMAT SAC | F29: Gerente General | H29: Av. Pardo #1380 | I29: 2006 | J29: 2016 | K29: PERU | L29: ANCASH | M29: SANTA | N29: CHIMBOTE | O29: La empresa se encuentra de baja conforme aparece en SUNAT | P29: =IFERROR(__xludf.DUMMYFUNCTION("IF(REGEXMATCH(UPPER(E29),""CONGRESO""),1,0)"),0) -> 0
A30: FUERZA POPULAR | B30: 32971154 | C30: CHACON TRUJILLO, NILZA MERLY | D30: SI | E30: Inversiones Generales ARIBET Corporation SAC. | F30: Gerente General | H30: Av. Pardo N° 1500 | I30: 2012 | J30: 2017 | K30: PERU | L30: ANCASH | M30: SANTA | N30: CHIMBOTE | O30: La empresa se encuentra de baja conforme aparece en SUNAT | P30: =IFERROR(__xludf.DUMMYFUNCTION("IF(REGEXMATCH(UPPER(E30),""CONGRESO""),1,0)"),0) -> 0
A31: FUERZA POPULAR | B31: 32971154 | C31: CHACON TRUJILLO, NILZA MERLY | D31: SI | E31: Congreso de la República | F31: Congresista de la República | H31: Plaza Bolívar, Av. Abancay s/n, en el Cercado de Lima | I31: 2021 | J31: 2025 | K31: PERU | L31: LIMA | M31: LIMA | N31: LIMA | O31: Actualmente se desempeña como congresista de la república por el periodo legislativo 2021-2026 | P31: =IFERROR(__xludf.DUMMYFUNCTION("IF(REGEXMATCH(UPPER(E31),""CONGRESO""),1,0)"),1) -> 1
A32: FUERZA POPULAR | B32: 32971154 | C32: CHACON TRUJILLO, NILZA MERLY | D32: SI | E32: BOTICA ROMA | F32: Director Técnico - Químico Farmaceútico | H32: Av. Alberto Reyes 123-124 | I32: 2012 | J32: 2021 | K32: PERU | L32: ANCASH | M32: HUARMEY | N32: HUARMEY | P32: =IFERROR(__xludf.DUMMYFUNCTION("IF(REGEXMATCH(UPPER(E32),""CONGRESO""),1,0)"),0) -> 0
A33: FUERZA POPULAR | B33: 32971154 | C33: CHACON TRUJILLO, NILZA MERLY | D33: SI | E33: CONSTRUREDES | F33: Conductor de vehículo | H33: Alameda Premio Real Mz D, Lt. 10 | I33: 2019 | J33: 2021 | K33: PERU | L33: LIMA | M33: LIMA | N33: CHORRILLOS | P33: =IFERROR(__xludf.DUMMYFUNCTION("IF(REGEXMATCH(UPPER(E33),""CONGRESO""),1,0)"),0) -> 0
A34: FUERZA POPULAR | B34: 07960843 | C34: CHAVEZ COSSIO, MARTHA GLADYS | D34: SI | E34: Congreso de la República | F34: Congresista de la República | H34: Av. Abancay - Plaza Bolivar S/N | I34: 2011 | J34: 2016 | K34: PERU | L34: LIMA | M34: LIMA | N34: LIMA | P34: =IFERROR(__xludf.DUMMYFUNCTION("IF(REGEXMATCH(UPPER(E34),""CONGRESO""),1,0)"),1) -> 1
A35: FUERZA POPULAR | B35: 07960843 | C35: CHAVEZ COSSIO, MARTHA GLADYS | D35: SI | E35: Congreso de la República | F35: Congresista de la República | H35: Av. Abancay - Plaza Bolivar S/N | I35: 2020 | J35: 2021 | K35: PERU | L35: LIMA | M35: LIMA | N35: LIMA | O35: Fui congresista en el Congreso Complementario. | P35: =IFERROR(__xludf.DUMMYFUNCTION("IF(REGEXMATCH(UPPER(E35),""CONGRESO""),1,0)"),1) -> 1
A36: FUERZA POPULAR | B36: 07960843 | C36: CHAVEZ COSSIO, MARTHA GLADYS | D36: SI | E36: Congreso de la República | F36: Asesor | H36: Av. Abancay - Plaza Bolivar S/N | I36: 2016 | J36: 2020 | K36: PERU | L36: LIMA | M36: LIMA | N36: LIMA | P36: =IFERROR(__xludf.DUMMYFUNCTION("IF(REGEXMATCH(UPPER(E36),""CONGRESO""),1,0)"),1) -> 1
A37: FUERZA POPULAR | B37: 07960843 | C37: CHAVEZ COSSIO, MARTHA GLADYS | D37: SI | E37: Universidad Privada San Juan Bautista | F37: Docente | H37: Av. San Luis 1923 | I37: 2007 | J37: 2019 | K37: PERU | L37: LIMA | M37: LIMA | N37: LIMA | O37: He sido docente a tiempo parcial en la Escuela de Derecho. | P37: =IFERROR(__xludf.DUMMYFUNCTION("IF(REGEXMATCH(UPPER(E37),""CONGRESO""),1,0)"),0) -> 0
A38: FUERZA POPULAR | B38: 07960843 | C38: CHAVEZ COSSIO, MARTHA GLADYS | D38: SI | E38: Congreso de la República | F38: Asesor | H38: Av. Abancay - Plaza Bolivar S/N | I38: 2021 | J38: 2025 | K38: PERU | L38: LIMA | M38: LIMA | N38: LIMA | O38: Continúo laborando hasta la actualidad. | P38: =IFERROR(__xludf.DUMMYFUNCTION("IF(REGEXMATCH(UPPER(E38),""CONGRESO""),1,0)"),1) -> 1
A39: FUERZA POPULAR | B39: 05227631 | C39: DEL AGUILA CARDENAS, JUAN CARLOS | D39: SI | E39: CONGRESO DE LA REPUBLICA | F39: CONGRESISTA | H39: PLAZA BOLIVAR - AV ABANCAY | I39: 2016 | J39: 2019 | K39: PERU | L39: LIMA | M39: LIMA | N39: LIMA | O39: EL PERIODO DE ELECCION FUE DEL 2016 AL 2021, PERO FUE INTERRUMPIDO POR EL CIERRE INCONSTITUCIONAL DEL CONGRESO EL 30 DE SETIEMBRE DE 2019 | P39: =IFERROR(__xludf.DUMMYFUNCTION("IF(REGEXMATCH(UPPER(E39),""CONGRESO""),1,0)"),1) -> 1
A40: FUERZA POPULAR | B40: 05227631 | C40: DEL AGUILA CARDENAS, JUAN CARLOS | D40: SI | E40: AMAZONIA PRODUCCIONES E.I.R.L | F40: TITULAR GERENTE | H40: CALLE ATLANTIDA 741-821 | I40: 2022 | J40: 2025 | K40: PERU | L40: LORETO | M40: MAYNAS | N40: IQUITOS | P40: =IFERROR(__xludf.DUMMYFUNCTION("IF(REGEXMATCH(UPPER(E40),""CONGRESO""),1,0)"),0) -> 0
A41: FUERZA POPULAR | B41: 05227631 | C41: DEL AGUILA CARDENAS, JUAN CARLOS | D41: SI | E41: MINISTERIO DE RELACIONES EXTERIORES | F41: ASESOR AD-HONOREM | H41: JR. LAMPA 545 | I41: 2020 | J41: 2020 | K41: PERU | L41: LIMA | M41: LIMA | N41: LIMA | P41: =IFERROR(__xludf.DUMMYFUNCTION("IF(REGEXMATCH(UPPER(E41),""CONGRESO""),1,0)"),0) -> 0
A42: FUERZA POPULAR | B42: 17896798 | C42: FLORES RUIZ, VICTOR SEFERINO | D42: SI | E42: CONGRESO DE LA REPUBLICA | F42: CONGRESISTA | G42: 20161749126 | H42: AV. ABANCAY S/N | I42: 2021 | J42: 2025 | K42: PERU | L42: LIMA | M42: LIMA | N42: LIMA | O42: HASTA LA ACTUALIDAD | P42: =IFERROR(__xludf.DUMMYFUNCTION("IF(REGEXMATCH(UPPER(E42),""CONGRESO""),1,0)"),1) -> 1
A43: FUERZA POPULAR | B43: 17896798 | C43: FLORES RUIZ, VICTOR SEFERINO | D43: SI | E43: FARMEDICA S.A.C. | F43: GERENTE GENERAL | G43: 20440481087 | H43: AV. PROLONGACIÓN UNIÓN 1570 - ANDRES RAZURI | I43: 2003 | J43: 2020 | K43: PERU | L43: LA LIBERTAD | M43: TRUJILLO | N43: TRUJILLO | P43: =IFERROR(__xludf.DUMMYFUNCTION("IF(REGEXMATCH(UPPER(E43),""CONGRESO""),1,0)"),0) -> 0
A44: FUERZA POPULAR | B44: 17896798 | C44: FLORES RUIZ, VICTOR SEFERINO | D44: SI | E44: CLINICA SALUD FARMEDICA S.A.C. | F44: GERENTE GENERAL | G44: 20477280022 | H44: AV. PROLONGACION UNION NRO. 1582 | I44: 2011 | J44: 2021 | K44: PERU | L44: LA LIBERTAD | M44: TRUJILLO | N44: TRUJILLO | P44: =IFERROR(__xludf.DUMMYFUNCTION("IF(REGEXMATCH(UPPER(E44),""CONGRESO""),1,0)"),0) -> 0
A45: FUERZA POPULAR | B45: 19994639 | C45: JIMENEZ HEREDIA, DAVID JULIO | D45: SI | E45: UNIVERSIDAD PRIVADA DE HUANCAYO FRANKLIN ROOSEVELT | F45: GERENTE GENERAL | G45: 20541310038 | H45: AV. GIRALDEZ 542 | I45: 2010 | J45: 2021 | K45: PERU | L45: JUNIN | M45: HUANCAYO | N45: HUANCAYO | P45: =IFERROR(__xludf.DUMMYFUNCTION("IF(REGEXMATCH(UPPER(E45),""CONGRESO""),1,0)"),0) -> 0
A46: FUERZA POPULAR | B46: 19994639 | C46: JIMENEZ HEREDIA, DAVID JULIO | D46: SI | E46: CONGRESO DE LA REPÚBLICA | F46: CONGRESISTA | G46: 20161749126 | H46: AV. ABANCAY S/N | I46: 2021 | J46: 2025 | K46: PERU | L46: LIMA | M46: LIMA | N46: LIMA | P46: =IFERROR(__xludf.DUMMYFUNCTION("IF(REGEXMATCH(UPPER(E46),""CONGRESO""),1,0)"),1) -> 1
A47: FUERZA POPULAR | B47: 07831436 | C47: JUAREZ GALLEGOS, CARMEN PATRICIA | D47: SI | E47: Congreso de la Republica del Perú | F47: Asesora del Congreso de la Republica | G47: 20161749126 | H47: Jr. Huallaga 358 | I47: 2013 | J47: 2015 | K47: PERU | L47: LIMA | M47: LIMA | N47: LIMA | P47: =IFERROR(__xludf.DUMMYFUNCTION("IF(REGEXMATCH(UPPER(E47),""CONGRESO""),1,0)"),1) -> 1
A48: FUERZA POPULAR | B48: 07831436 | C48: JUAREZ GALLEGOS, CARMEN PATRICIA | D48: SI | E48: Congreso de la Republica del Perú | F48: Congresista | G48: 20161749126 | H48: Av. Abancay | I48: 2021 | J48: 2025 | K48: PERU | L48: LIMA | M48: LIMA | N48: LIMA | O48: Mi periodo como congresista culmina en el 2026. | P48: =IFERROR(__xludf.DUMMYFUNCTION("IF(REGEXMATCH(UPPER(E48),""CONGRESO""),1,0)"),1) -> 1
A49: FUERZA POPULAR | B49: 07831436 | C49: JUAREZ GALLEGOS, CARMEN PATRICIA | D49: SI | E49: Abogada Independiente | F49: Abogada | G49: 10078314368 | H49: Prolongación Arenales Nro. 863 | I49: 2020 | J49: 2020 | K49: PERU | L49: LIMA | M49: LIMA | N49: MIRAFLORES | P49: =IFERROR(__xludf.DUMMYFUNCTION("IF(REGEXMATCH(UPPER(E49),""CONGRESO""),1,0)"),0) -> 0
A50: FUERZA POPULAR | B50: 07831436 | C50: JUAREZ GALLEGOS, CARMEN PATRICIA | D50: SI | E50: Municipalidad de Lima | F50: Regidora | G50: 20131380951 | H50: Jr. de la Unión Nro. 300 | I50: 2015 | J50: 2018 | K50: PERU | L50: LIMA | M50: LIMA | N50: LIMA | P50: =IFERROR(__xludf.DUMMYFUNCTION("IF(REGEXMATCH(UPPER(E50),""CONGRESO""),1,0)"),0) -> 0
A51: FUERZA POPULAR | B51: 07831436 | C51: JUAREZ GALLEGOS, CARMEN PATRICIA | D51: SI | E51: Municipalidad de Miraflores | F51: Secretaria General | G51: 20131377224 | H51: Av. Larco S/N | I51: 2019 | J51: 2019 | K51: PERU | L51: LIMA | M51: LIMA | N51: MIRAFLORES | P51: =IFERROR(__xludf.DUMMYFUNCTION("IF(REGEXMATCH(UPPER(E51),""CONGRESO""),1,0)"),0) -> 0
A52: FUERZA POPULAR | B52: 09884301 | C52: MELGAR VALDEZ, ELARD GALO | D52: SI | E52: Congreso de la República | F52: Congresista de la República | H52: Jr. Huallaga 358 | I52: 2016 | J52: 2019 | K52: PERU | L52: LIMA | M52: LIMA | N52: LIMA | P52: =IFERROR(__xludf.DUMMYFUNCTION("IF(REGEXMATCH(UPPER(E52),""CONGRESO""),1,0)"),1) -> 1
A53: FUERZA POPULAR | B53: 08266314 | C53: MESIA RAMIREZ, CARLOS FERNANDO | D53: SI | E53: Superintendencia Nacional de Educación Superior Universitaria - Sunedu | F53: Jefe de Asesoría Jurídica | H53: Calle Aldabas 337 | I53: 2023 | J53: 2025 | K53: PERU | L53: LIMA | M53: LIMA | N53: SANTIAGO DE SURCO | O53: Hasta la actualidad. | P53: =IFERROR(__xludf.DUMMYFUNCTION("IF(REGEXMATCH(UPPER(E53),""CONGRESO""),1,0)"),0) -> 0
A54: FUERZA POPULAR | B54: 08266314 | C54: MESIA RAMIREZ, CARLOS FERNANDO | D54: SI | E54: Congreso de la República | F54: Congresista de la República | H54: Av. Abancay - Plaza Bolivar S/N | I54: 2020 | J54: 2021 | K54: PERU | L54: LIMA | M54: LIMA | N54: LIMA | P54: =IFERROR(__xludf.DUMMYFUNCTION("IF(REGEXMATCH(UPPER(E54),""CONGRESO""),1,0)"),1) -> 1
A55: FUERZA POPULAR | B55: 08266314 | C55: MESIA RAMIREZ, CARLOS FERNANDO | D55: SI | E55: Carlos Mesía & Abogados S.A.C. | F55: Gerente General - Abogado | H55: Calle Los Médicos 176, dpto 301 - Los Alámos IV, Monterrico | I55: 2022 | J55: 2025 | K55: PERU | L55: LIMA | M55: LIMA | N55: SANTIAGO DE SURCO | O55: Hasta la actualidad. | P55: =IFERROR(__xludf.DUMMYFUNCTION("IF(REGEXMATCH(UPPER(E55),""CONGRESO""),1,0)"),0) -> 0
A56: FUERZA POPULAR | B56: 08266314 | C56: MESIA RAMIREZ, CARLOS FERNANDO | D56: SI | E56: Congreso de la República | F56: Asesor | H56: Av. Abancay - Plaza Bolivar S/N | I56: 2021 | J56: 2023 | K56: PERU | L56: LIMA | M56: LIMA | N56: LIMA | O56: Coordinador General de Asesores del Grupo Parlamentario Renovación Popular. | P56: =IFERROR(__xludf.DUMMYFUNCTION("IF(REGEXMATCH(UPPER(E56),""CONGRESO""),1,0)"),1) -> 1
A57: FUERZA POPULAR | B57: 08266314 | C57: MESIA RAMIREZ, CARLOS FERNANDO | D57: SI | E57: Universidad San Martín de Porres - USMP | F57: Docente universitario | H57: Av. Javier Prado Oeste 580 | I57: 2021 | J57: 2025 | K57: PERU | L57: LIMA | M57: LIMA | N57: SAN ISIDRO | O57: Hasta la actualidad. | P57: =IFERROR(__xludf.DUMMYFUNCTION("IF(REGEXMATCH(UPPER(E57),""CONGRESO""),1,0)"),0) -> 0
A58: FUERZA POPULAR | B58: 22974228 | C58: MIYASHIRO ARASHIRO, MARCO ENRIQUE | D58: SI | E58: CONGRESO DE LA REPUBLICA | F58: CONGRESISTA | G58: 20161749126 | H58: JR. HUALLAGA 358 | I58: 2016 | J58: 2019 | K58: PERU | L58: LIMA | M58: LIMA | N58: LIMA | O58: DESDE JULIO 2026 HASTA SETIEMBRE 2019 | P58: =IFERROR(__xludf.DUMMYFUNCTION("IF(REGEXMATCH(UPPER(E58),""CONGRESO""),1,0)"),1) -> 1
A59: FUERZA POPULAR | B59: 22974228 | C59: MIYASHIRO ARASHIRO, MARCO ENRIQUE | D59: SI | E59: GOBERNA ANALITICS SAC | F59: EXPOSITOR | G59: 20604038953 | H59: AV. MANUEL OLGUIN 321. INT.603 | I59: 2025 | J59: 2025 | K59: PERU | L59: LIMA | M59: LIMA | N59: LIMA | O59: HE DICTADO 5 CONFERENCIAS ESTE AÑO | P59: =IFERROR(__xludf.DUMMYFUNCTION("IF(REGEXMATCH(UPPER(E59),""CONGRESO""),1,0)"),0) -> 0
A60: FUERZA POPULAR | B60: 22974228 | C60: MIYASHIRO ARASHIRO, MARCO ENRIQUE | D60: SI | E60: CONGRESO DE LA REPUBLICA | F60: ASESOR | G60: 20161749126 | H60: AV. HUALLAGA 358 | I60: 2021 | J60: 2025 | K60: PERU | L60: LIMA | M60: LIMA | N60: LIMA | O60: DESDE AGOSTO 2021 HASTA LA ACTUALIDAD | P60: =IFERROR(__xludf.DUMMYFUNCTION("IF(REGEXMATCH(UPPER(E60),""CONGRESO""),1,0)"),1) -> 1
A61: FUERZA POPULAR | B61: 22974228 | C61: MIYASHIRO ARASHIRO, MARCO ENRIQUE | D61: SI | E61: MUNICIPALIDAD METROPOLITANA DE LIMA | F61: REGIDOR | H61: JR. CONDE SUPERUNDA 169. 3ER PISO | I61: 2015 | J61: 2015 | K61: PERU | L61: LIMA | M61: LIMA | N61: LIMA | O61: REGIDOR DESDE ENERO 2015 HASTA JULIO 2016 | P61: =IFERROR(__xludf.DUMMYFUNCTION("IF(REGEXMATCH(UPPER(E61),""CONGRESO""),1,0)"),0) -> 0
A62: FUERZA POPULAR | B62: 22974228 | C62: MIYASHIRO ARASHIRO, MARCO ENRIQUE | D62: SI | E62: COMPLEJO AGROINDUSTRIAL BETA SAC | F62: EXPOSITOR | H62: CALLE LEOPOLDO CARRILLO 160 | I62: 2025 | J62: 2025 | K62: PERU | L62: ICA | M62: CHINCHA | N62: CHINCHA ALTA | O62: REALIC|É EXPOSICIONES LOS DÍAS 5, 6, 7, 8 Y 13 DE NOVIEMBRE | P62: =IFERROR(__xludf.DUMMYFUNCTION("IF(REGEXMATCH(UPPER(E62),""CONGRESO""),1,0)"),0) -> 0
A63: FUERZA POPULAR | B63: 08911520 | C63: MOYANO DELGADO, MARTHA LUPE | D63: SI | E63: Municipalidad Metropolitana de Lima | F63: Regidora | G63: 20131380951 | H63: Jr. Conde de Superunda N° 141 | I63: 2019 | J63: 2021 | K63: PERU | L63: LIMA | M63: LIMA | N63: LIMA | P63: =IFERROR(__xludf.DUMMYFUNCTION("IF(REGEXMATCH(UPPER(E63),""CONGRESO""),1,0)"),0) -> 0
A64: FUERZA POPULAR | B64: 08911520 | C64: MOYANO DELGADO, MARTHA LUPE | D64: SI | E64: Ministerio de Trabajo y Promoción del Empleo | F64: Técnica en formalización | G64: 20124838010 | H64: Av. Salaverry 655 | I64: 2018 | J64: 2018 | K64: PERU | L64: LIMA | M64: LIMA | N64: JESUS MARIA | O64: Servicios por terceros. | P64: =IFERROR(__xludf.DUMMYFUNCTION("IF(REGEXMATCH(UPPER(E64),""CONGRESO""),1,0)"),0) -> 0
A65: FUERZA POPULAR | B65: 08911520 | C65: MOYANO DELGADO, MARTHA LUPE | D65: SI | E65: MUNICIPALIDAD DISTRITAL DE BREÑA | F65: GERENTE DE DESARROLLO HUMANO | H65: AV ARICA 500 | I65: 2016 | J65: 2017 | K65: PERU | L65: LIMA | M65: LIMA | N65: BRENA | P65: =IFERROR(__xludf.DUMMYFUNCTION("IF(REGEXMATCH(UPPER(E65),""CONGRESO""),1,0)"),0) -> 0
A66: FUERZA POPULAR | B66: 08911520 | C66: MOYANO DELGADO, MARTHA LUPE | D66: SI | E66: Congreso de la República | F66: Congresista | G66: 20161749126 | H66: Plaza de la Constitución, Av. Abancay s/n | I66: 2021 | J66: 2025 | K66: PERU | L66: LIMA | M66: LIMA | N66: LIMA | O66: El cargo de congresista es hasta julio 2026. | P66: =IFERROR(__xludf.DUMMYFUNCTION("IF(REGEXMATCH(UPPER(E66),""CONGRESO""),1,0)"),1) -> 1
A67: FUERZA POPULAR | B67: 17806760 | C67: NORIEGA REATEGUI, VICTOR MANUEL | D67: SI | E67: VICTOR MANUEL NORIEGA REATEGUI | F67: GINECOLOGO | G67: 10178067601 | H67: JR SAN MARTIN 271 | I67: 2019 | J67: 2025 | K67: PERU | L67: SAN MARTIN | M67: SAN MARTIN | N67: TARAPOTO | O67: CONSULTORIO MEDICO EN LA CLINICA SAN MARTIN | P67: =IFERROR(__xludf.DUMMYFUNCTION("IF(REGEXMATCH(UPPER(E67),""CONGRESO""),1,0)"),0) -> 0
A68: FUERZA POPULAR | B68: 17806760 | C68: NORIEGA REATEGUI, VICTOR MANUEL | D68: SI | E68: UNIDAD EJECUTORA HOSPITAL II-2 TARAPOTO | F68: GINECO-OBSTETRA | G68: 20494013453 | H68: Jr. Angel Delgado Morey Nro. 503 | I68: 2010 | J68: 2025 | K68: PERU | L68: SAN MARTIN | M68: SAN MARTIN | N68: TARAPOTO | O68: con interrupcion durante el periodo del ejercicio de gobernador regional del 2015 al 2018 | P68: =IFERROR(__xludf.DUMMYFUNCTION("IF(REGEXMATCH(UPPER(E68),""CONGRESO""),1,0)"),0) -> 0
A69: FUERZA POPULAR | B69: 17806760 | C69: NORIEGA REATEGUI, VICTOR MANUEL | D69: SI | E69: UNIVERSIDAD NACIONAL SAN MARTIN | F69: profesor auxiliar tiempo parcial | G69: 20160766191 | H69: jr amorarca 334 | I69: 2003 | J69: 2018 | K69: PERU | L69: SAN MARTIN | M69: SAN MARTIN | N69: MORALES | O69: renunciando el 2019, con interrupcion durante el periodo de gobernador regional 2015 al 2018 | P69: =IFERROR(__xludf.DUMMYFUNCTION("IF(REGEXMATCH(UPPER(E69),""CONGRESO""),1,0)"),0) -> 0
A70: FUERZA POPULAR | B70: 08234063 | C70: RODRICH ACKERMAN, JACQUES SALOMON | D70: SI | E70: Farenet | F70: Apoderado | H70: Calle Burgos N° 580 | I70: 2008 | J70: 2016 | K70: PERU | L70: LIMA | M70: LIMA | N70: SAN ISIDRO | O70: Farenet (grupo empresarial) | P70: =IFERROR(__xludf.DUMMYFUNCTION("IF(REGEXMATCH(UPPER(E70),""CONGRESO""),1,0)"),0) -> 0
A71: FUERZA POPULAR | B71: 08234063 | C71: RODRICH ACKERMAN, JACQUES SALOMON | D71: SI | E71: Marsala - Eureka Park | F71: Asesor | G71: 20604652201 | H71: Miguel Dasso 160, Piso 8 | I71: 2024 | J71: 2025 | K71: PERU | L71: LIMA | M71: LIMA | N71: SAN ISIDRO | O71: Prestando servicios en la actualidad. | P71: =IFERROR(__xludf.DUMMYFUNCTION("IF(REGEXMATCH(UPPER(E71),""CONGRESO""),1,0)"),0) -> 0
A72: FUERZA POPULAR | B72: 08234063 | C72: RODRICH ACKERMAN, JACQUES SALOMON | D72: SI | E72: Elección Inteligente Comercializadora S.A.C. | F72: Administrador | G72: 20608648667 | H72: Av. Javier Prado Este N° 1921 | I72: 2024 | J72: 2025 | K72: PERU | L72: LIMA | M72: LIMA | N72: SAN BORJA | O72: Prestando servicios en la actualidad. | P72: =IFERROR(__xludf.DUMMYFUNCTION("IF(REGEXMATCH(UPPER(E72),""CONGRESO""),1,0)"),0) -> 0
A73: FUERZA POPULAR | B73: 08234063 | C73: RODRICH ACKERMAN, JACQUES SALOMON | D73: SI | E73: Grupo Farenet | F73: Asesor | H73: Miguel Dasso 160, piso 08 | I73: 2017 | J73: 2025 | K73: PERU | L73: LIMA | M73: LIMA | N73: SAN ISIDRO | O73: Prestando servicios en la actualidad. | P73: =IFERROR(__xludf.DUMMYFUNCTION("IF(REGEXMATCH(UPPER(E73),""CONGRESO""),1,0)"),0) -> 0
A74: FUERZA POPULAR | B74: 07704730 | C74: ROSPIGLIOSI CAPURRO, FERNANDO MIGUEL | D74: SI | E74: Congreso de la República | F74: Congresista de la República | H74: Plaza Bolivar - Av. Abancay s/n | I74: 2023 | J74: 2025 | K74: PERU | L74: LIMA | M74: LIMA | N74: LIMA | O74: Hasta la actualidad. | P74: =IFERROR(__xludf.DUMMYFUNCTION("IF(REGEXMATCH(UPPER(E74),""CONGRESO""),1,0)"),1) -> 1
A75: FUERZA POPULAR | B75: 07704730 | C75: ROSPIGLIOSI CAPURRO, FERNANDO MIGUEL | D75: SI | E75: FRC CONSULTORES E.I.R.L. | F75: Gerente | G75: 20602717942 | H75: Calle Thomas Ramsay 516 | I75: 2019 | J75: 2023 | K75: PERU | L75: LIMA | M75: LIMA | N75: MAGDALENA DEL MAR | P75: =IFERROR(__xludf.DUMMYFUNCTION("IF(REGEXMATCH(UPPER(E75),""CONGRESO""),1,0)"),0) -> 0
A76: FUERZA POPULAR | B76: 10638205 | C76: SCHAEFER CUCULIZA, KARLA MELISSA | D76: SI | E76: OPERACIONES Y PROYECTOS INTEGRALES SAC | F76: ASESORAMIENTO EN GESTION PUBLICA Y PRIVADA | G76: 20517651096 | H76: AV PRIMAVERA 999, URB. CHACARILLA DEL ESTANQUE | I76: 2025 | J76: 2025 | K76: PERU | L76: LIMA | M76: LIMA | N76: SAN BORJA | P76: =IFERROR(__xludf.DUMMYFUNCTION("IF(REGEXMATCH(UPPER(E76),""CONGRESO""),1,0)"),0) -> 0
A77: FUERZA POPULAR | B77: 10638205 | C77: SCHAEFER CUCULIZA, KARLA MELISSA | D77: SI | E77: CLINICA SAN GABRIEL SAC | F77: ASESORIA | G77: 20505018509 | H77: AV LA MARINA 2955 | I77: 2022 | J77: 2024 | K77: PERU | L77: LIMA | M77: LIMA | N77: SAN MIGUEL | P77: =IFERROR(__xludf.DUMMYFUNCTION("IF(REGEXMATCH(UPPER(E77),""CONGRESO""),1,0)"),0) -> 0
A78: FUERZA POPULAR | B78: 10638205 | C78: SCHAEFER CUCULIZA, KARLA MELISSA | D78: SI | E78: CONGRESO DE LA REPUBLICA | F78: CONGRESISTA | G78: 20161749126 | H78: AV. ABANCAY S/N CERCADO | I78: 2016 | J78: 2019 | K78: PERU | L78: LIMA | M78: LIMA | N78: LIMA | P78: =IFERROR(__xludf.DUMMYFUNCTION("IF(REGEXMATCH(UPPER(E78),""CONGRESO""),1,0)"),1) -> 1
A79: FUERZA POPULAR | B79: 10638205 | C79: SCHAEFER CUCULIZA, KARLA MELISSA | D79: SI | E79: PURE LNG SAC | F79: ASESORIA | G79: 20603222408 | H79: CARRETERA PAITA- SULLANA KM 45 | I79: 2024 | J79: 2024 | K79: PERU | L79: PIURA | M79: PAITA | N79: COLAN | O79: ASESORIAS ESPORÁDICAS | P79: =IFERROR(__xludf.DUMMYFUNCTION("IF(REGEXMATCH(UPPER(E79),""CONGRESO""),1,0)"),0) -> 0
A80: FUERZA POPULAR | B80: 10638205 | C80: SCHAEFER CUCULIZA, KARLA MELISSA | D80: SI | E80: CONGRESO DE LA REPUBLICA | F80: CONGRESISTA | G80: 20161749126 | H80: AV. ABANCAY S/N CERCADO | I80: 2011 | J80: 2016 | K80: PERU | L80: LIMA | M80: LIMA | N80: LIMA | P80: =IFERROR(__xludf.DUMMYFUNCTION("IF(REGEXMATCH(UPPER(E80),""CONGRESO""),1,0)"),1) -> 1
A81: FUERZA POPULAR | B81: 16657841 | C81: TAPIA BERNAL, SEGUNDO LEOCADIO | D81: SI | E81: HOSPITAL NACIONAL ARZOBISPO LOAYZA | F81: MEDICO GINECOLOGO - OBSTETRA | H81: AV. ALFONSO UGARTE 848 | I81: 2004 | J81: 2025 | K81: PERU | L81: LIMA | M81: LIMA | N81: LIMA | O81: PRESTA LABORES HASTA LA ACTUALIDAD | P81: =IFERROR(__xludf.DUMMYFUNCTION("IF(REGEXMATCH(UPPER(E81),""CONGRESO""),1,0)"),0) -> 0
A82: FUERZA POPULAR | B82: 16657841 | C82: TAPIA BERNAL, SEGUNDO LEOCADIO | D82: SI | E82: UNIVERSIDAD DE SAN MARTIN DE PORRES | F82: DOCENTE | H82: ALAMEDA EL CORREGIDOR 1531 | I82: 2012 | J82: 2015 | K82: PERU | L82: LIMA | M82: LIMA | N82: LA MOLINA | O82: DOCENTE EN LA FACULTAD DE MEDICINA | P82: =IFERROR(__xludf.DUMMYFUNCTION("IF(REGEXMATCH(UPPER(E82),""CONGRESO""),1,0)"),0) -> 0
A83: FUERZA POPULAR | B83: 16657841 | C83: TAPIA BERNAL, SEGUNDO LEOCADIO | D83: SI | E83: CONGRESO DE LA REPUBLICA | F83: CONGRESISTA DE LA REPUBLICA | G83: 20161749126 | H83: PLAZA BOLIVAR S/N | I83: 2016 | J83: 2019 | K83: PERU | L83: LIMA | M83: LIMA | N83: LIMA | O83: CONGRESISTA PARA EL PERIODO 2016-2021, CONGRESO DISUELTO 2019 | P83: =IFERROR(__xludf.DUMMYFUNCTION("IF(REGEXMATCH(UPPER(E83),""CONGRESO""),1,0)"),1) -> 1
A84: FUERZA POPULAR | B84: 16657841 | C84: TAPIA BERNAL, SEGUNDO LEOCADIO | D84: SI | E84: UNIVERSIDAD NACIONAL FEDERICO VILLARREAL | F84: DOCENTE | H84: Jr. Río Chepén 290 - El Agustino | I84: 2020 | J84: 2025 | K84: PERU | L84: LIMA | M84: LIMA | N84: EL AGUSTINO | O84: DOCENTE EN LA FACULTAD DE MEDICINA HASTA LA ACTUALIDAD | P84: =IFERROR(__xludf.DUMMYFUNCTION("IF(REGEXMATCH(UPPER(E84),""CONGRESO""),1,0)"),0) -> 0
A85: FUERZA POPULAR | B85: 16657841 | C85: TAPIA BERNAL, SEGUNDO LEOCADIO | D85: SI | E85: CONGRESO DE LA REPUBLICA | F85: CONGRESISTA DE LA REPUBLICA | G85: 20161749126 | H85: PLAZA BOLIVAR S/N | I85: 2011 | J85: 2016 | K85: PERU | L85: LIMA | M85: LIMA | N85: LIMA | P85: =IFERROR(__xludf.DUMMYFUNCTION("IF(REGEXMATCH(UPPER(E85),""CONGRESO""),1,0)"),1) -> 1
A86: FUERZA POPULAR | B86: 21143880 | C86: VELASQUEZ PORTOCARRERO, JORGE | D86: SI | E86: JORGE VELASQUEZ PORTOCARRERO | F86: ABOGADO | G86: 17177218103 | H86: JR LIBERTAD 380 - TERCER PISO | I86: 2015 | J86: 2025 | K86: PERU | L86: UCAYALI | M86: CORONEL PORTILLO | N86: CALLERIA | O86: TRABAJO DE FORMA INDEPENDIENTE - HASTA LA ACTUALIDAD | P86: =IFERROR(__xludf.DUMMYFUNCTION("IF(REGEXMATCH(UPPER(E86),""CONGRESO""),1,0)"),0) -> 0
A87: FUERZA POPULAR | B87: 40242430 | C87: VENTURA ANGEL, HECTOR JOSE | D87: SI | E87: IE Sudamericano | F87: asesoría legal | H87: Mz. B1 Lt. 12 - Los Cipreses | I87: 2015 | J87: 2015 | K87: PERU | L87: LIMA | M87: LIMA | N87: SAN JUAN DE LURIGANCHO | O87: Desde 19.01.2015 hasta 17.09.2015. | P87: =IFERROR(__xludf.DUMMYFUNCTION("IF(REGEXMATCH(UPPER(E87),""CONGRESO""),1,0)"),0) -> 0
A88: FUERZA POPULAR | B88: 40242430 | C88: VENTURA ANGEL, HECTOR JOSE | D88: SI | E88: IE Sudamericano | F88: asesoría legal | H88: Mz. B- Lt.12 - Los Cipreses | I88: 2016 | J88: 2021 | K88: PERU | L88: LIMA | M88: LIMA | N88: SAN JUAN DE LURIGANCHO | O88: Del 08.08.2016 al 31.01.2021 y del 05.04.2021 al 30.06.2021 | P88: =IFERROR(__xludf.DUMMYFUNCTION("IF(REGEXMATCH(UPPER(E88),""CONGRESO""),1,0)"),0) -> 0
A89: FUERZA POPULAR | B89: 40242430 | C89: VENTURA ANGEL, HECTOR JOSE | D89: SI | E89: Congreso de la República | F89: Congresista de la República | H89: Jr. Huallaga 358 | I89: 2021 | J89: 2025 | K89: PERU | L89: LIMA | M89: LIMA | N89: LIMA | O89: Congresista en funciones hasta 2026 | P89: =IFERROR(__xludf.DUMMYFUNCTION("IF(REGEXMATCH(UPPER(E89),""CONGRESO""),1,0)"),1) -> 1
A90: FUERZA POPULAR | B90: 40242430 | C90: VENTURA ANGEL, HECTOR JOSE | D90: SI | E90: Congreso de la República | F90: asesor | H90: Jr. Huallaga 358 | I90: 2015 | J90: 2016 | K90: PERU | L90: LIMA | M90: LIMA | N90: LIMA | O90: Del 27.08.2015 al 31.10.2015 y del 12.11.2015 al 26.07.2016 | P90: =IFERROR(__xludf.DUMMYFUNCTION("IF(REGEXMATCH(UPPER(E90),""CONGRESO""),1,0)"),1) -> 1
A91: FUERZA POPULAR | B91: 21414172 | C91: YAMASHIRO ORE, RAFAEL GUSTAVO | D91: SI | E91: MUNICIPALIDAD METROPOLITANA DE LIMA | F91: REGIDOR | G91: 20131380951 | H91: JR. RUFINO TORRICO NRO.1178 CERCADO DE LIMA | I91: 2015 | J91: 2018 | K91: PERU | L91: LIMA | M91: LIMA | N91: LIMA | P91: =IFERROR(__xludf.DUMMYFUNCTION("IF(REGEXMATCH(UPPER(E91),""CONGRESO""),1,0)"),0) -> 0
A92: FUERZA POPULAR | B92: 21414172 | C92: YAMASHIRO ORE, RAFAEL GUSTAVO | D92: SI | E92: INVERSIONES EN TURISMO PALERMO S.R.L. | F92: GERENTE COMERCIAL | G92: 20609259541 | H92: AV. JOSÉ MATIAS MANZANILLA NRO.187 | I92: 2023 | J92: 2025 | K92: PERU | L92: ICA | M92: ICA | N92: ICA | O92: HASTA LA FECHA. | P92: =IFERROR(__xludf.DUMMYFUNCTION("IF(REGEXMATCH(UPPER(E92),""CONGRESO""),1,0)"),0) -> 0
A93: FUERZA POPULAR | B93: 21414172 | C93: YAMASHIRO ORE, RAFAEL GUSTAVO | D93: SI | E93: CONSILIUM S.A.C. | F93: GERENTE GENERAL | G93: 20548327025 | H93: CALLE SAN JOSE TOMASAL 829 INT. 104 | I93: 2013 | J93: 2025 | K93: PERU | L93: LIMA | M93: LIMA | N93: SANTIAGO DE SURCO | O93: HASTA LA FECHA. | P93: =IFERROR(__xludf.DUMMYFUNCTION("IF(REGEXMATCH(UPPER(E93),""CONGRESO""),1,0)"),0) -> 0
A94: FUERZA POPULAR | B94: 21414172 | C94: YAMASHIRO ORE, RAFAEL GUSTAVO | D94: SI | E94: POLLERÍAS EL PARADERO S.R.L. | F94: GERENTE MARKETING | G94: 20602606181 | H94: CALLE LIMA 139 | I94: 2022 | J94: 2025 | K94: PERU | L94: ICA | M94: ICA | N94: ICA | O94: HASTA LA FECHA. | P94: =IFERROR(__xludf.DUMMYFUNCTION("IF(REGEXMATCH(UPPER(E94),""CONGRESO""),1,0)"),0) -> 0
A95: JUNTOS POR EL PERU | B95: 22482738 | C95: ANDRES LUJAN, SERAFIN | D95: NO | P95: =IFERROR(__xludf.DUMMYFUNCTION("IF(REGEXMATCH(UPPER(E95),""CONGRESO""),1,0)"),0) -> 0
A96: JUNTOS POR EL PERU | B96: 21487528 | C96: ARMACANQUI MORALES, SAUL ANDRES | D96: SI | E96: RED DE SALUD - LIMA NORTE | F96: ENCARGADO DE ARCHIVO CENTRAL | H96: INDEPENDENCIA | I96: 2016 | J96: 2016 | K96: PERU | L96: LIMA | M96: LIMA | N96: INDEPENDENCIA | P96: =IFERROR(__xludf.DUMMYFUNCTION("IF(REGEXMATCH(UPPER(E96),""CONGRESO""),1,0)"),0) -> 0
A97: JUNTOS POR EL PERU | B97: 21487528 | C97: ARMACANQUI MORALES, SAUL ANDRES | D97: SI | E97: INDEPENDIENTE | F97: EDUCACIÓN PARTICULAR | H97: UCV 32 LOTE 18 ZONA B HUAYCAN | I97: 2024 | J97: 2025 | K97: PERU | L97: LIMA | M97: LIMA | N97: ATE | P97: =IFERROR(__xludf.DUMMYFUNCTION("IF(REGEXMATCH(UPPER(E97),""CONGRESO""),1,0)"),0) -> 0
A98: JUNTOS POR EL PERU | B98: 21487528 | C98: ARMACANQUI MORALES, SAUL ANDRES | D98: SI | E98: MUNICIPALIDAD DE LIMA METROPOLITANA - SISOL | F98: ENCARGADO DE CONTROL PATRIMONIAL Y ADMINISTRACION DE CENTROS DE SALUD | H98: LIMA | I98: 2011 | J98: 2015 | K98: PERU | L98: LIMA | M98: LIMA | N98: LIMA | P98: =IFERROR(__xludf.DUMMYFUNCTION("IF(REGEXMATCH(UPPER(E98),""CONGRESO""),1,0)"),0) -> 0
A99: JUNTOS POR EL PERU | B99: 21487528 | C99: ARMACANQUI MORALES, SAUL ANDRES | D99: SI | E99: CONGRESO DE LA REPUBLICA | F99: ASESOR | H99: AV. ABANCAY S/N | I99: 2021 | J99: 2024 | K99: PERU | L99: LIMA | M99: LIMA | N99: LIMA | O99: Despacho congresista Roberto Sánchez Palomino | P99: =IFERROR(__xludf.DUMMYFUNCTION("IF(REGEXMATCH(UPPER(E99),""CONGRESO""),1,0)"),1) -> 1
A100: JUNTOS POR EL PERU | B100: 21487528 | C100: ARMACANQUI MORALES, SAUL ANDRES | D100: SI | E100: UNICIENCIA | F100: PROFESOR PREUNIVERSITARIO | H100: LIMA | I100: 2017 | J100: 2019 | K100: PERU | L100: LIMA | M100: LIMA | N100: LIMA | P100: =IFERROR(__xludf.DUMMYFUNCTION("IF(REGEXMATCH(UPPER(E100),""CONGRESO""),1,0)"),0) -> 0
...

Sheet pivot_experiencia
A1: DNI_CANDIDATO | B1: TRABAJO ALGUNA VEZ EN CONGRESO | C1: REGISTROS CONGRESO
A2: 07755878 | B2: =IF(SUMIF('02 EXPERIENCIA LABORAL'!B:B,A2,'02 EXPERIENCIA LABORAL'!P:P)>0,1,0) -> 1 | C2: =SUMIF('02 EXPERIENCIA LABORAL'!B:B,A2,'02 EXPERIENCIA LABORAL'!P:P) -> 3
A3: 25331980 | B3: =IF(SUMIF('02 EXPERIENCIA LABORAL'!B:B,A3,'02 EXPERIENCIA LABORAL'!P:P)>0,1,0) -> 0 | C3: =SUMIF('02 EXPERIENCIA LABORAL'!B:B,A3,'02 EXPERIENCIA LABORAL'!P:P) -> 0
A4: 40204874 | B4: =IF(SUMIF('02 EXPERIENCIA LABORAL'!B:B,A4,'02 EXPERIENCIA LABORAL'!P:P)>0,1,0) -> 1 | C4: =SUMIF('02 EXPERIENCIA LABORAL'!B:B,A4,'02 EXPERIENCIA LABORAL'!P:P) -> 2
A5: 26705695 | B5: =IF(SUMIF('02 EXPERIENCIA LABORAL'!B:B,A5,'02 EXPERIENCIA LABORAL'!P:P)>0,1,0) -> 1 | C5: =SUMIF('02 EXPERIENCIA LABORAL'!B:B,A5,'02 EXPERIENCIA LABORAL'!P:P) -> 1
A6: 08236035 | B6: =IF(SUMIF('02 EXPERIENCIA LABORAL'!B:B,A6,'02 EXPERIENCIA LABORAL'!P:P)>0,1,0) -> 1 | C6: =SUMIF('02 EXPERIENCIA LABORAL'!B:B,A6,'02 EXPERIENCIA LABORAL'!P:P) -> 1
A7: 06717199 | B7: =IF(SUMIF('02 EXPERIENCIA LABORAL'!B:B,A7,'02 EXPERIENCIA LABORAL'!P:P)>0,1,0) -> 0 | C7: =SUMIF('02 EXPERIENCIA LABORAL'!B:B,A7,'02 EXPERIENCIA LABORAL'!P:P) -> 0
A8: 10307948 | B8: =IF(SUMIF('02 EXPERIENCIA LABORAL'!B:B,A8,'02 EXPERIENCIA LABORAL'!P:P)>0,1,0) -> 0 | C8: =SUMIF('02 EXPERIENCIA LABORAL'!B:B,A8,'02 EXPERIENCIA LABORAL'!P:P) -> 0
A9: 32971154 | B9: =IF(SUMIF('02 EXPERIENCIA LABORAL'!B:B,A9,'02 EXPERIENCIA LABORAL'!P:P)>0,1,0) -> 1 | C9: =SUMIF('02 EXPERIENCIA LABORAL'!B:B,A9,'02 EXPERIENCIA LABORAL'!P:P) -> 1
A10: 07960843 | B10: =IF(SUMIF('02 EXPERIENCIA LABORAL'!B:B,A10,'02 EXPERIENCIA LABORAL'!P:P)>0,1,0) -> 1 | C10: =SUMIF('02 EXPERIENCIA LABORAL'!B:B,A10,'02 EXPERIENCIA LABORAL'!P:P) -> 4
A11: 05227631 | B11: =IF(SUMIF('02 EXPERIENCIA LABORAL'!B:B,A11,'02 EXPERIENCIA LABORAL'!P:P)>0,1,0) -> 1 | C11: =SUMIF('02 EXPERIENCIA LABORAL'!B:B,A11,'02 EXPERIENCIA LABORAL'!P:P) -> 1
A12: 17896798 | B12: =IF(SUMIF('02 EXPERIENCIA LABORAL'!B:B,A12,'02 EXPERIENCIA LABORAL'!P:P)>0,1,0) -> 1 | C12: =SUMIF('02 EXPERIENCIA LABORAL'!B:B,A12,'02 EXPERIENCIA LABORAL'!P:P) -> 1
A13: 19994639 | B13: =IF(SUMIF('02 EXPERIENCIA LABORAL'!B:B,A13,'02 EXPERIENCIA LABORAL'!P:P)>0,1,0) -> 1 | C13: =SUMIF('02 EXPERIENCIA LABORAL'!B:B,A13,'02 EXPERIENCIA LABORAL'!P:P) -> 1
... A61: 31010129 | B61: =IF(SUMIF('02 EXPERIENCIA LABORAL'!B:B,A61,'02 EXPERIENCIA LABORAL'!P:P)>0,1,0) -> 0 | C61: =SUMIF('02 EXPERIENCIA LABORAL'!B:B,A61,'02 EXPERIENCIA LABORAL'!P:P) -> 0

Sheet 03 FORM ACADEM. - EDUC. BASICA
A1: ORGANIZACION_POLITICA | B1: DNI_CANDIDATO | C1: CANDIDATO | D1: TIENE_EDUCACION_BASICA | E1: EDUC_PRIMARIA | F1: EDUC_PRIMARIA_CONCLUIDA | G1: EDUC_SECUNDARIA | H1: EDUC_SECUNDARIA_CONCLUIDA
A2: AHORA NACION - AN | B2: 07755878 | C2: DELGADO ZEGARRA, JAIME RICARDO | D2: SI | E2: SI | F2: SI | G2: SI | H2: SI
A3: AHORA NACION - AN | B3: 25331980 | C3: LOPEZ CHAU NAVA, PABLO ALFONSO | D3: SI | E3: SI | F3: SI | G3: SI | H3: SI
A4: AHORA NACION - AN | B4: 25331980 | C4: LOPEZ CHAU NAVA, PABLO ALFONSO | D4: SI | E4: SI | F4: SI | G4: SI | H4: SI
A5: AHORA NACION - AN | B5: 40204874 | C5: LUQUE IBARRA, RUTH | D5: SI | E5: SI | F5: SI | G5: SI | H5: SI
A6: AHORA NACION - AN | B6: 26705695 | C6: VASQUEZ CHUQUILIN, MIRTHA ESTHER | D6: SI | E6: SI | F6: SI | G6: SI | H6: SI
A7: FUERZA POPULAR | B7: 08236035 | C7: AGUINAGA RECUENCO, ALEJANDRO AURELIO | D7: SI | E7: SI | F7: SI | G7: SI | H7: SI
A8: FUERZA POPULAR | B8: 06717199 | C8: ARISTA ARBILDO, JOSE BERLEY | D8: SI | E8: SI | F8: SI | G8: SI | H8: SI
A9: FUERZA POPULAR | B9: 10307948 | C9: ASTUDILLO SALCEDO, CESAR AUGUSTO | D9: SI | E9: SI | F9: SI | G9: SI | H9: SI
A10: FUERZA POPULAR | B10: 32971154 | C10: CHACON TRUJILLO, NILZA MERLY | D10: SI | E10: SI | F10: SI | G10: SI | H10: SI
A11: FUERZA POPULAR | B11: 07960843 | C11: CHAVEZ COSSIO, MARTHA GLADYS | D11: SI | E11: SI | F11: SI | G11: SI | H11: SI
A12: FUERZA POPULAR | B12: 05227631 | C12: DEL AGUILA CARDENAS, JUAN CARLOS | D12: SI | E12: SI | F12: SI | G12: SI | H12: SI
... A28: FUERZA POPULAR | B28: 21143880 | C28: VELASQUEZ PORTOCARRERO, JORGE | D28: SI | E28: SI | F28: SI | G28: SI | H28: SI
A29: FUERZA POPULAR | B29: 40242430 | C29: VENTURA ANGEL, HECTOR JOSE | D29: SI | E29: SI | G29: SI
A30: FUERZA POPULAR | B30: 21414172 | C30: YAMASHIRO ORE, RAFAEL GUSTAVO | D30: SI | E30: SI | F30: SI | G30: SI | H30: SI
A31: JUNTOS POR EL PERU | B31: 22482738 | C31: ANDRES LUJAN, SERAFIN | D31: SI | E31: SI | F31: SI | G31: SI | H31: SI
A32: JUNTOS POR EL PERU | B32: 21487528 | C32: ARMACANQUI MORALES, SAUL ANDRES | D32: SI | E32: SI | F32: SI | G32: SI | H32: SI
A33: JUNTOS POR EL PERU | B33: 27409088 | C33: CASTILLO TERRONES, JOSE MERCEDES | D33: SI | E33: SI | F33: No
A34: JUNTOS POR EL PERU | B34: 40669342 | C34: CCAHUANA AYMACHOQUE, HUGO ISAAC | D34: SI | E34: SI | F34: SI | G34: SI | H34: SI
A35: JUNTOS POR EL PERU | B35: 04647085 | C35: CUTIPA CCAMA, VICTOR RAUL | D35: SI | E35: SI | F35: SI | G35: SI | H35: SI
A36: JUNTOS POR EL PERU | B36: 21453924 | C36: MARAVI OLARTE, IBER ANTENOR | D36: SI | E36: SI | F36: SI | G36: SI | H36: SI
A37: JUNTOS POR EL PERU | B37: 10252335 | C37: MORALES RAMIREZ, EDYSON HUMBERTO | D37: SI | E37: SI | F37: SI | G37: SI | H37: SI
A38: JUNTOS POR EL PERU | B38: 40938678 | C38: OSORIO PALPAN, PERCY HERBERT | D38: SI | E38: SI | F38: SI | G38: SI | H38: SI
A39: JUNTOS POR EL PERU | B39: 29632775 | C39: QUITO SARMIENTO, BERNARDO JAIME | D39: SI | E39: SI | F39: SI | G39: SI | H39: SI
A40: JUNTOS POR EL PERU | B40: 42750152 | C40: ROBLES ARAUJO, SILVANA EMPERATRIZ | D40: SI | E40: SI | F40: SI | G40: SI | H40: SI
A41: JUNTOS POR EL PERU | B41: 23906812 | C41: VERANO SARAVIA, WILFREDO | D41: SI | E41: SI | F41: SI | G41: SI | H41: SI
A42: PARTIDO CIVICO OBRAS | B42: 07651031 | C42: ASTUCURI LAURA, ROGER MIGUEL | D42: SI | E42: SI | F42: SI | G42: SI | H42: SI
A43: PARTIDO CIVICO OBRAS | B43: 10063223 | C43: BARRAGAN COLOMA, DANIEL HUGO | D43: SI | E43: SI | F43: SI | G43: SI | H43: SI
A44: PARTIDO CIVICO OBRAS | B44: 10063223 | C44: BARRAGAN COLOMA, DANIEL HUGO | D44: SI | E44: SI | F44: SI | G44: SI | H44: SI
A45: PARTIDO CIVICO OBRAS | B45: 07250032 | C45: FLORES CORDOVA, AGRIPINA MARIA DEL PILAR | D45: SI | E45: SI | F45: SI | G45: SI | H45: SI
... A50: PARTIDO DEL BUEN GOBIERNO | B50: 43360309 | C50: CABALLERO LEON, CARLOS DAVID | D50: SI | E50: SI | F50: SI | G50: SI | H50: SI
A51: PARTIDO DEL BUEN GOBIERNO | B51: 07793210 | C51: FIGALLO RIVADENEYRA, FLAVIO FELIPE | D51: SI | G51: SI | H51: SI
A52: PARTIDO DEL BUEN GOBIERNO | B52: 30762511 | C52: FLORES SUAREZ, JUVER NILSON | D52: SI | E52: SI | F52: SI | G52: SI | H52: SI
A53: PARTIDO DEL BUEN GOBIERNO | B53: 07619185 | C53: GAVIDIA RODRIGUEZ, JORGE OCTAVIO | D53: SI | E53: SI | F53: SI | G53: SI | H53: SI
A54: PARTIDO DEL BUEN GOBIERNO | B54: 07231335 | C54: ITURREGUI BYRNE, PATRICIA MILAGROS | D54: NO
A55: PARTIDO DEL BUEN GOBIERNO | B55: 06876967 | C55: MATUTE CHARUN, SUSANA FLOR DE MARIA | D55: SI | E55: SI | F55: SI | G55: SI | H55: SI
A56: PARTIDO DEL BUEN GOBIERNO | B56: 06876967 | C56: MATUTE CHARUN, SUSANA FLOR DE MARIA | D56: SI | E56: SI | F56: SI | G56: SI | H56: SI
A57: RENOVACION POPULAR | B57: 08235876 | C57: ALCORTA SUERO, MARIA LOURDES PIA LUISA | D57: SI | E57: SI | F57: SI | G57: SI | H57: SI
A58: RENOVACION POPULAR | B58: 25799622 | C58: AMPUERO MEZA, KATHERINE MILAGROS | D58: SI | E58: SI | F58: SI | G58: SI | H58: SI
A59: RENOVACION POPULAR | B59: 43285320 | C59: CALISTO GIAMPIETRI, FRANCISCO JOSE | D59: SI | E59: SI | F59: SI | G59: SI | H59: SI
A60: RENOVACION POPULAR | B60: 07852432 | C60: JAUREGUI MARTINEZ DE AGUAYO, MARIA DE LOS MILAGROS JACKELINE | D60: SI | E60: SI | F60: SI | G60: SI | H60: SI
A61: RENOVACION POPULAR | B61: 07845838 | C61: LÓPEZ ALIAGA CAZORLA, RAFAEL BERNARDO | D61: SI | E61: SI | F61: SI | G61: SI | H61: SI
A62: RENOVACION POPULAR | B62: 07845838 | C62: LÓPEZ ALIAGA CAZORLA, RAFAEL BERNARDO | D62: SI | E62: SI | F62: SI | G62: SI | H62: SI
A63: RENOVACION POPULAR | B63: 01539305 | C63: MANCHA PINEDA, ESTANISLAO EDGAR | D63: SI | E63: SI | F63: SI | G63: SI | H63: SI
A64: RENOVACION POPULAR | B64: 45209282 | C64: MUÑANTE BARRIOS, ALEJANDRO | D64: SI | E64: SI | F64: SI | G64: SI | H64: SI
A65: RENOVACION POPULAR | B65: 06504611 | C65: VELASQUEZ GARCIA, MIGUEL ANGEL | D65: SI | E65: SI | F65: SI | G65: SI | H65: SI
A66: FUERZA POPULAR | B66: 40433187 | C66: TORRES MORALES, MIGUEL ANGEL | D66: SI | E66: SI | F66: SI | G66: SI | H66: SI
... A69: JUNTOS POR EL PERU | B69: 31010129 | C69: RAMOS HUILLCAS, ANDRES AVELINO | D69: SI | E69: SI | F69: SI | G69: SI | H69: SI

Sheet 03 FORM. ACADEM. - EDUC TECNICA
A1: ORGANIZACION_POLITICA | B1: DNI_CANDIDATO | C1: CANDIDATO | D1: TIENE_EDUC_TECNICO | E1: CENTRO_ESTUDIOS | F1: CARRERA | G1: CONCLUIDO | H1: INFORMACION_ADICIONAL
A2: AHORA NACION - AN | B2: 07755878 | C2: DELGADO ZEGARRA, JAIME RICARDO | D2: SI | E2: ITSPAE | F2: Administración de Empresas | G2: SI | H2: Título de bachiller profesional 1985
A3: AHORA NACION - AN | B3: 25331980 | C3: LOPEZ CHAU NAVA, PABLO ALFONSO | D3: NO
A4: AHORA NACION - AN | B4: 25331980 | C4: LOPEZ CHAU NAVA, PABLO ALFONSO | D4: NO
A5: AHORA NACION - AN | B5: 40204874 | C5: LUQUE IBARRA, RUTH | D5: NO
A6: AHORA NACION - AN | B6: 26705695 | C6: VASQUEZ CHUQUILIN, MIRTHA ESTHER | D6: NO
A7: FUERZA POPULAR | B7: 08236035 | C7: AGUINAGA RECUENCO, ALEJANDRO AURELIO | D7: NO
A8: FUERZA POPULAR | B8: 06717199 | C8: ARISTA ARBILDO, JOSE BERLEY | D8: NO
A9: FUERZA POPULAR | B9: 10307948 | C9: ASTUDILLO SALCEDO, CESAR AUGUSTO | D9: NO
A10: FUERZA POPULAR | B10: 32971154 | C10: CHACON TRUJILLO, NILZA MERLY | D10: SI | E10: I.S.T.N.e. Jose G. Salvador Lara | F10: Administración de Negocios Internacionales | G10: SI
A11: FUERZA POPULAR | B11: 07960843 | C11: CHAVEZ COSSIO, MARTHA GLADYS | D11: NO
A12: FUERZA POPULAR | B12: 05227631 | C12: DEL AGUILA CARDENAS, JUAN CARLOS | D12: NO
A13: FUERZA POPULAR | B13: 17896798 | C13: FLORES RUIZ, VICTOR SEFERINO | D13: NO
A14: FUERZA POPULAR | B14: 19994639 | C14: JIMENEZ HEREDIA, DAVID JULIO | D14: NO
A15: FUERZA POPULAR | B15: 07831436 | C15: JUAREZ GALLEGOS, CARMEN PATRICIA | D15: NO
A16: FUERZA POPULAR | B16: 09884301 | C16: MELGAR VALDEZ, ELARD GALO | D16: NO
A17: FUERZA POPULAR | B17: 08266314 | C17: MESIA RAMIREZ, CARLOS FERNANDO | D17: NO
A18: FUERZA POPULAR | B18: 22974228 | C18: MIYASHIRO ARASHIRO, MARCO ENRIQUE | D18: NO
A19: FUERZA POPULAR | B19: 08911520 | C19: MOYANO DELGADO, MARTHA LUPE | D19: NO
A20: FUERZA POPULAR | B20: 17806760 | C20: NORIEGA REATEGUI, VICTOR MANUEL | D20: NO
A21: FUERZA POPULAR | B21: 08234063 | C21: RODRICH ACKERMAN, JACQUES SALOMON | D21: NO
A22: FUERZA POPULAR | B22: 07704730 | C22: ROSPIGLIOSI CAPURRO, FERNANDO MIGUEL | D22: NO
A23: FUERZA POPULAR | B23: 10638205 | C23: SCHAEFER CUCULIZA, KARLA MELISSA | D23: SI | E23: IPAE | F23: ADMINISTRACION DE NEGOCIOS | G23: SI | H23: EL TÍTULO PROFESIONAL ES EN: ADMINISTRACIÓN DE NEGOCIOS CON MENCION EN COMERCIALIZACION
A24: FUERZA POPULAR | B24: 16657841 | C24: TAPIA BERNAL, SEGUNDO LEOCADIO | D24: NO
A25: FUERZA POPULAR | B25: 21143880 | C25: VELASQUEZ PORTOCARRERO, JORGE | D25: NO
A26: FUERZA POPULAR | B26: 40242430 | C26: VENTURA ANGEL, HECTOR JOSE | D26: NO
A27: FUERZA POPULAR | B27: 21414172 | C27: YAMASHIRO ORE, RAFAEL GUSTAVO | D27: NO
A28: JUNTOS POR EL PERU | B28: 22482738 | C28: ANDRES LUJAN, SERAFIN | D28: NO
A29: JUNTOS POR EL PERU | B29: 21487528 | C29: ARMACANQUI MORALES, SAUL ANDRES | D29: NO
A30: JUNTOS POR EL PERU | B30: 27409088 | C30: CASTILLO TERRONES, JOSE MERCEDES | D30: NO
A31: JUNTOS POR EL PERU | B31: 40669342 | C31: CCAHUANA AYMACHOQUE, HUGO ISAAC | D31: SI | E31: INSTITUTO JORGE BASADRE | F31: CONTABILIDAD | G31: NO
A32: JUNTOS POR EL PERU | B32: 04647085 | C32: CUTIPA CCAMA, VICTOR RAUL | D32: NO
A33: JUNTOS POR EL PERU | B33: 21453924 | C33: MARAVI OLARTE, IBER ANTENOR | D33: NO
A34: JUNTOS POR EL PERU | B34: 10252335 | C34: MORALES RAMIREZ, EDYSON HUMBERTO | D34: NO
A35: JUNTOS POR EL PERU | B35: 40938678 | C35: OSORIO PALPAN, PERCY HERBERT | D35: NO
A36: JUNTOS POR EL PERU | B36: 29632775 | C36: QUITO SARMIENTO, BERNARDO JAIME | D36: NO
A37: JUNTOS POR EL PERU | B37: 42750152 | C37: ROBLES ARAUJO, SILVANA EMPERATRIZ | D37: SI | E37: LA MERCED | F37: PROFESIONAL TÉCNICO EN ENFERMERÍA | G37: SI
A38: JUNTOS POR EL PERU | B38: 23906812 | C38: VERANO SARAVIA, WILFREDO | D38: NO
A39: PARTIDO CIVICO OBRAS | B39: 07651031 | C39: ASTUCURI LAURA, ROGER MIGUEL | D39: NO
A40: PARTIDO CIVICO OBRAS | B40: 10063223 | C40: BARRAGAN COLOMA, DANIEL HUGO | D40: NO
A41: PARTIDO CIVICO OBRAS | B41: 10063223 | C41: BARRAGAN COLOMA, DANIEL HUGO | D41: NO
A42: PARTIDO CIVICO OBRAS | B42: 07250032 | C42: FLORES CORDOVA, AGRIPINA MARIA DEL PILAR | D42: SI | E42: ESCUELA DE TURISMO DE LA UNIVERSIDAD NACIONAL MAYOR DE SAN MARCOS | F42: TECNICA DE TURISMO Y GUIA DE TURISMO | G42: SI | H42: ENTUR PERU - UNIVERSIDAD NACIONAL MAYOR DE SAN MARCOS
A43: PARTIDO CIVICO OBRAS | B43: 07412350 | C43: GAGO RODRIGUEZ, WALTER FRANCISCO | D43: NO
A44: PARTIDO CIVICO OBRAS | B44: 00422672 | C44: TICONA COHAILA, JUANA GUISELLA | D44: SI | E44: INSTITUTO SUPERIOR PUBLICO JOSE JIMENEZ BORJA | F44: PROFESORA DE EDUCACION PRIMARIA | G44: SI
A45: PARTIDO DEL BUEN GOBIERNO | B45: 06519219 | C45: BONIFAZ CARMONA, NORA | D45: NO
A46: PARTIDO DEL BUEN GOBIERNO | B46: 43360309 | C46: CABALLERO LEON, CARLOS DAVID | D46: NO
A47: PARTIDO DEL BUEN GOBIERNO | B47: 43360309 | C47: CABALLERO LEON, CARLOS DAVID | D47: NO
A48: PARTIDO DEL BUEN GOBIERNO | B48: 07793210 | C48: FIGALLO RIVADENEYRA, FLAVIO FELIPE | D48: NO
A49: PARTIDO DEL BUEN GOBIERNO | B49: 30762511 | C49: FLORES SUAREZ, JUVER NILSON | D49: NO
A50: PARTIDO DEL BUEN GOBIERNO | B50: 07619185 | C50: GAVIDIA RODRIGUEZ, JORGE OCTAVIO | D50: NO
A51: PARTIDO DEL BUEN GOBIERNO | B51: 07231335 | C51: ITURREGUI BYRNE, PATRICIA MILAGROS | D51: NO
A52: PARTIDO DEL BUEN GOBIERNO | B52: 06876967 | C52: MATUTE CHARUN, SUSANA FLOR DE MARIA | D52: NO
A53: PARTIDO DEL BUEN GOBIERNO | B53: 06876967 | C53: MATUTE CHARUN, SUSANA FLOR DE MARIA | D53: NO
A54: RENOVACION POPULAR | B54: 08235876 | C54: ALCORTA SUERO, MARIA LOURDES PIA LUISA | D54: NO
A55: RENOVACION POPULAR | B55: 25799622 | C55: AMPUERO MEZA, KATHERINE MILAGROS | D55: NO
A56: RENOVACION POPULAR | B56: 43285320 | C56: CALISTO GIAMPIETRI, FRANCISCO JOSE | D56: NO
... A64: JUNTOS POR EL PERU | B64: 02044988 | C64: CHIPANA CHIPANA, JOSE MOISES | D64: NO
A65: JUNTOS POR EL PERU | B65: 23271450 | C65: YAURI TUNQUE, JOAQUIN | D65: SI | E65: ISIP HUANCAVELICA | F65: COMPUTACION E INFORMATICA | G65: SI
A66: JUNTOS POR EL PERU | B66: 31010129 | C66: RAMOS HUILLCAS, ANDRES AVELINO | D66: NO

Sheet 03 FORM. ACADEM. - EDUC. NO UNI
A1: ORGANIZACION_POLITICA | B1: DNI_CANDIDATO | C1: CANDIDATO | D1: TIENE_EDUC_NO_UNIVERSITARIA | E1: EDUC_NO_UNIVERSITARIA | F1: CENTRO_ESTUDIOS | G1: CARRERA | H1: CONCLUIDO
A2: AHORA NACION - AN | B2: 07755878 | C2: DELGADO ZEGARRA, JAIME RICARDO | D2: SI | E2: NO
A3: AHORA NACION - AN | B3: 25331980 | C3: LOPEZ CHAU NAVA, PABLO ALFONSO | D3: NO
A4: AHORA NACION - AN | B4: 25331980 | C4: LOPEZ CHAU NAVA, PABLO ALFONSO | D4: NO
A5: AHORA NACION - AN | B5: 40204874 | C5: LUQUE IBARRA, RUTH | D5: NO
A6: AHORA NACION - AN | B6: 26705695 | C6: VASQUEZ CHUQUILIN, MIRTHA ESTHER | D6: NO
A7: FUERZA POPULAR | B7: 08236035 | C7: AGUINAGA RECUENCO, ALEJANDRO AURELIO | D7: NO
A8: FUERZA POPULAR | B8: 06717199 | C8: ARISTA ARBILDO, JOSE BERLEY | D8: NO
A9: FUERZA POPULAR | B9: 10307948 | C9: ASTUDILLO SALCEDO, CESAR AUGUSTO | D9: NO
A10: FUERZA POPULAR | B10: 32971154 | C10: CHACON TRUJILLO, NILZA MERLY | D10: SI | E10: NO
A11: FUERZA POPULAR | B11: 07960843 | C11: CHAVEZ COSSIO, MARTHA GLADYS | D11: NO
A12: FUERZA POPULAR | B12: 05227631 | C12: DEL AGUILA CARDENAS, JUAN CARLOS | D12: NO
A13: FUERZA POPULAR | B13: 17896798 | C13: FLORES RUIZ, VICTOR SEFERINO | D13: NO
A14: FUERZA POPULAR | B14: 19994639 | C14: JIMENEZ HEREDIA, DAVID JULIO | D14: NO
A15: FUERZA POPULAR | B15: 07831436 | C15: JUAREZ GALLEGOS, CARMEN PATRICIA | D15: NO
A16: FUERZA POPULAR | B16: 09884301 | C16: MELGAR VALDEZ, ELARD GALO | D16: NO
A17: FUERZA POPULAR | B17: 08266314 | C17: MESIA RAMIREZ, CARLOS FERNANDO | D17: NO
A18: FUERZA POPULAR | B18: 22974228 | C18: MIYASHIRO ARASHIRO, MARCO ENRIQUE | D18: NO
A19: FUERZA POPULAR | B19: 08911520 | C19: MOYANO DELGADO, MARTHA LUPE | D19: NO
A20: FUERZA POPULAR | B20: 17806760 | C20: NORIEGA REATEGUI, VICTOR MANUEL | D20: NO
A21: FUERZA POPULAR | B21: 08234063 | C21: RODRICH ACKERMAN, JACQUES SALOMON | D21: NO
A22: FUERZA POPULAR | B22: 07704730 | C22: ROSPIGLIOSI CAPURRO, FERNANDO MIGUEL | D22: NO
A23: FUERZA POPULAR | B23: 10638205 | C23: SCHAEFER CUCULIZA, KARLA MELISSA | D23: SI | E23: NO
A24: FUERZA POPULAR | B24: 16657841 | C24: TAPIA BERNAL, SEGUNDO LEOCADIO | D24: NO
A25: FUERZA POPULAR | B25: 21143880 | C25: VELASQUEZ PORTOCARRERO, JORGE | D25: NO
A26: FUERZA POPULAR | B26: 40242430 | C26: VENTURA ANGEL, HECTOR JOSE | D26: NO
A27: FUERZA POPULAR | B27: 21414172 | C27: YAMASHIRO ORE, RAFAEL GUSTAVO | D27: NO
A28: JUNTOS POR EL PERU | B28: 22482738 | C28: ANDRES LUJAN, SERAFIN | D28: NO
A29: JUNTOS POR EL PERU | B29: 21487528 | C29: ARMACANQUI MORALES, SAUL ANDRES | D29: NO
A30: JUNTOS POR EL PERU | B30: 27409088 | C30: CASTILLO TERRONES, JOSE MERCEDES | D30: NO
A31: JUNTOS POR EL PERU | B31: 40669342 | C31: CCAHUANA AYMACHOQUE, HUGO ISAAC | D31: SI | E31: SI | F31: INEI. ESCUELA NACIONAL DE ESTADISTICA E INFORMATICA | G31: ASISTENTE WINDOWS, OFFICE | H31: SI
A32: JUNTOS POR EL PERU | B32: 04647085 | C32: CUTIPA CCAMA, VICTOR RAUL | D32: NO
A33: JUNTOS POR EL PERU | B33: 21453924 | C33: MARAVI OLARTE, IBER ANTENOR | D33: NO
A34: JUNTOS POR EL PERU | B34: 10252335 | C34: MORALES RAMIREZ, EDYSON HUMBERTO | D34: NO
A35: JUNTOS POR EL PERU | B35: 40938678 | C35: OSORIO PALPAN, PERCY HERBERT | D35: NO
A36: JUNTOS POR EL PERU | B36: 29632775 | C36: QUITO SARMIENTO, BERNARDO JAIME | D36: NO
A37: JUNTOS POR EL PERU | B37: 42750152 | C37: ROBLES ARAUJO, SILVANA EMPERATRIZ | D37: SI | E37: NO
A38: JUNTOS POR EL PERU | B38: 23906812 | C38: VERANO SARAVIA, WILFREDO | D38: NO
A39: PARTIDO CIVICO OBRAS | B39: 07651031 | C39: ASTUCURI LAURA, ROGER MIGUEL | D39: NO
A40: PARTIDO CIVICO OBRAS | B40: 10063223 | C40: BARRAGAN COLOMA, DANIEL HUGO | D40: NO
A41: PARTIDO CIVICO OBRAS | B41: 10063223 | C41: BARRAGAN COLOMA, DANIEL HUGO | D41: NO
A42: PARTIDO CIVICO OBRAS | B42: 07250032 | C42: FLORES CORDOVA, AGRIPINA MARIA DEL PILAR | D42: SI | E42: NO
A43: PARTIDO CIVICO OBRAS | B43: 07412350 | C43: GAGO RODRIGUEZ, WALTER FRANCISCO | D43: NO
A44: PARTIDO CIVICO OBRAS | B44: 00422672 | C44: TICONA COHAILA, JUANA GUISELLA | D44: SI | E44: NO
A45: PARTIDO DEL BUEN GOBIERNO | B45: 06519219 | C45: BONIFAZ CARMONA, NORA | D45: NO
A46: PARTIDO DEL BUEN GOBIERNO | B46: 43360309 | C46: CABALLERO LEON, CARLOS DAVID | D46: SI | E46: NO
A47: PARTIDO DEL BUEN GOBIERNO | B47: 43360309 | C47: CABALLERO LEON, CARLOS DAVID | D47: SI | E47: NO
A48: PARTIDO DEL BUEN GOBIERNO | B48: 07793210 | C48: FIGALLO RIVADENEYRA, FLAVIO FELIPE | D48: NO
A49: PARTIDO DEL BUEN GOBIERNO | B49: 30762511 | C49: FLORES SUAREZ, JUVER NILSON | D49: NO
A50: PARTIDO DEL BUEN GOBIERNO | B50: 07619185 | C50: GAVIDIA RODRIGUEZ, JORGE OCTAVIO | D50: SI | E50: NO
A51: PARTIDO DEL BUEN GOBIERNO | B51: 07231335 | C51: ITURREGUI BYRNE, PATRICIA MILAGROS | D51: NO
A52: PARTIDO DEL BUEN GOBIERNO | B52: 06876967 | C52: MATUTE CHARUN, SUSANA FLOR DE MARIA | D52: NO
A53: PARTIDO DEL BUEN GOBIERNO | B53: 06876967 | C53: MATUTE CHARUN, SUSANA FLOR DE MARIA | D53: NO
A54: RENOVACION POPULAR | B54: 08235876 | C54: ALCORTA SUERO, MARIA LOURDES PIA LUISA | D54: NO
A55: RENOVACION POPULAR | B55: 25799622 | C55: AMPUERO MEZA, KATHERINE MILAGROS | D55: NO
A56: RENOVACION POPULAR | B56: 43285320 | C56: CALISTO GIAMPIETRI, FRANCISCO JOSE | D56: SI | E56: NO
A57: RENOVACION POPULAR | B57: 07852432 | C57: JAUREGUI MARTINEZ DE AGUAYO, MARIA DE LOS MILAGROS JACKELINE | D57: NO
A58: RENOVACION POPULAR | B58: 07845838 | C58: LÓPEZ ALIAGA CAZORLA, RAFAEL BERNARDO | D58: NO
A59: RENOVACION POPULAR | B59: 07845838 | C59: LÓPEZ ALIAGA CAZORLA, RAFAEL BERNARDO | D59: NO
A60: RENOVACION POPULAR | B60: 01539305 | C60: MANCHA PINEDA, ESTANISLAO EDGAR | D60: NO
A61: RENOVACION POPULAR | B61: 45209282 | C61: MUÑANTE BARRIOS, ALEJANDRO | D61: NO
A62: RENOVACION POPULAR | B62: 06504611 | C62: VELASQUEZ GARCIA, MIGUEL ANGEL | D62: NO
A63: FUERZA POPULAR | B63: 40433187 | C63: TORRES MORALES, MIGUEL ANGEL | D63: NO
A64: JUNTOS POR EL PERU | B64: 02044988 | C64: CHIPANA CHIPANA, JOSE MOISES | D64: SI | E64: SI | F64: ISPP JULIACA | G64: PROFESOR DE EDUCACIÓN SECUNDARIA | H64: SI
A65: JUNTOS POR EL PERU | B65: 23271450 | C65: YAURI TUNQUE, JOAQUIN | D65: NO
A66: JUNTOS POR EL PERU | B66: 31010129 | C66: RAMOS HUILLCAS, ANDRES AVELINO | D66: SI | E66: SI | F66: INSTITUTO SUPERIOR PEDAGOGICO LAS SALLE | G66: PROFESOR DE EDUCACION PRIMARIA | H66: SI

Sheet 03 FORM. ACADEM. - EDUC. UNIV
A1: ORGANIZACION_POLITICA | B1: DNI_CANDIDATO | C1: CANDIDATO | D1: TIENE_EDUC_UNIV | E1: EDUC_UNIV | F1: UNIVERSIDAD | G1: CARRERA | H1: CONCLUIDO | I1: EGRESADO | J1: INFORMACION_COMPLEMENTARIA
A2: AHORA NACION - AN | B2: 07755878 | C2: DELGADO ZEGARRA, JAIME RICARDO | D2: SI | E2: SI | F2: Universidad Nacional de San Agustín de Arequipa | G2: ABOGADO | H2: SI | I2: SI
A3: AHORA NACION - AN | B3: 07755878 | C3: DELGADO ZEGARRA, JAIME RICARDO | D3: SI | E3: SI | F3: Pontificia Universidad Católica del Perú | G3: TITULO DE SEGUNDA ESPECIALIDAD | H3: SI | I3: SI
A4: AHORA NACION - AN | B4: 07755878 | C4: DELGADO ZEGARRA, JAIME RICARDO | D4: SI | E4: SI | F4: Universidad Nacional de San Agustín de Arequipa | G4: BACHILLER EN DERECHO | H4: SI | I4: SI
A5: AHORA NACION - AN | B5: 25331980 | C5: LOPEZ CHAU NAVA, PABLO ALFONSO | D5: SI | E5: SI | F5: Universidad Nacional del Callao | G5: BACHILLER EN CIENCIAS ECONOMICAS | H5: SI | I5: SI
A6: AHORA NACION - AN | B6: 25331980 | C6: LOPEZ CHAU NAVA, PABLO ALFONSO | D6: SI | E6: SI | F6: Universidad Nacional del Callao | G6: ECONOMISTA | H6: SI | I6: SI | J6: Fecha de diploma: 12/06/1981
A7: AHORA NACION - AN | B7: 25331980 | C7: LOPEZ CHAU NAVA, PABLO ALFONSO | D7: SI | E7: SI | F7: Universidad Nacional del Callao | G7: BACHILLER EN CIENCIAS ECONOMICAS | H7: SI | I7: SI
A8: AHORA NACION - AN | B8: 25331980 | C8: LOPEZ CHAU NAVA, PABLO ALFONSO | D8: SI | E8: SI | F8: Universidad Nacional del Callao | G8: ECONOMISTA | H8: SI | I8: SI | J8: Fecha de diploma: 12/06/1981
A9: AHORA NACION - AN | B9: 40204874 | C9: LUQUE IBARRA, RUTH | D9: SI | E9: SI | F9: Universidad Nacional de San Antonio Abad del Cusco | G9: ABOGADA | H9: SI | I9: SI
A10: AHORA NACION - AN | B10: 40204874 | C10: LUQUE IBARRA, RUTH | D10: SI | E10: SI | F10: Universidad Nacional de San Antonio Abad del Cusco | G10: BACHILLER EN DERECHO Y CIENCIAS POLITICAS | H10: SI | I10: SI
A11: AHORA NACION - AN | B11: 26705695 | C11: VASQUEZ CHUQUILIN, MIRTHA ESTHER | D11: SI | E11: SI | F11: Universidad Nacional de Cajamarca | G11: ABOGADO | H11: SI | I11: SI
A12: AHORA NACION - AN | B12: 26705695 | C12: VASQUEZ CHUQUILIN, MIRTHA ESTHER | D12: SI | E12: SI | F12: Universidad Nacional de Cajamarca | G12: BACHILLER EN DERECHO | H12: SI | I12: SI
A13: FUERZA POPULAR | B13: 08236035 | C13: AGUINAGA RECUENCO, ALEJANDRO AURELIO | D13: SI | E13: SI | F13: Universidad Nacional Federico Villarreal | G13: BACHILLER EN MEDICINA | H13: SI | I13: SI
A14: FUERZA POPULAR | B14: 08236035 | C14: AGUINAGA RECUENCO, ALEJANDRO AURELIO | D14: SI | E14: SI | F14: Universidad Nacional Federico Villarreal | G14: MEDICO CIRUJANO | H14: SI | I14: SI | J14: AÑO DE OBTENCIÓN 1976
A15: FUERZA POPULAR | B15: 06717199 | C15: ARISTA ARBILDO, JOSE BERLEY | D15: SI | E15: SI | F15: Pontificia Universidad Católica del Perú | G15: BACHILLER EN CIENCIAS SOCIALES | H15: SI | I15: SI
A16: FUERZA POPULAR | B16: 10307948 | C16: ASTUDILLO SALCEDO, CESAR AUGUSTO | D16: SI | E16: SI | F16: Universidad Alas Peruanas S.A. | G16: BACHILLER EN INGENIERIA DE SISTEMAS E INFORMATICA | H16: SI | I16: SI
A17: FUERZA POPULAR | B17: 10307948 | C17: ASTUDILLO SALCEDO, CESAR AUGUSTO | D17: SI | E17: SI | F17: Universidad Alas Peruanas S.A. | G17: INGENIERO DE SISTEMAS E INFORMATICA | H17: SI | I17: SI
A18: FUERZA POPULAR | B18: 10307948 | C18: ASTUDILLO SALCEDO, CESAR AUGUSTO | D18: SI | E18: SI | F18: Escuela Militar de Chorrillos “Coronel Francisco Bolognesi” | G18: BACHILLER EN CIENCIAS MILITARES | H18: SI | I18: SI | J18: Egresé en el año 1983.
A19: FUERZA POPULAR | B19: 32971154 | C19: CHACON TRUJILLO, NILZA MERLY | D19: SI | E19: SI | F19: UNIVERSIDAD CESAR VALLEJO | G19: INGENIERÍA CIVIL | H19: NO
A20: FUERZA POPULAR | B20: 32971154 | C20: CHACON TRUJILLO, NILZA MERLY | D20: SI | E20: SI | F20: Universidad los Ángeles de Chimbote | G20: QUIMICO FARMACEUTICO | H20: SI | I20: SI
A21: FUERZA POPULAR | B21: 32971154 | C21: CHACON TRUJILLO, NILZA MERLY | D21: SI | E21: SI | F21: Universidad los Ángeles de Chimbote | G21: BACHILLER EN FARMACIA Y BIOQUIMICA | H21: SI | I21: SI
A22: FUERZA POPULAR | B22: 07960843 | C22: CHAVEZ COSSIO, MARTHA GLADYS | D22: SI | E22: SI | F22: Pontificia Universidad Católica del Perú | G22: ABOGADO | H22: SI | I22: SI | J22: Obtuve mi título de Abogada en 1983.
A23: FUERZA POPULAR | B23: 07960843 | C23: CHAVEZ COSSIO, MARTHA GLADYS | D23: SI | E23: SI | F23: Pontificia Universidad Católica del Perú | G23: BACHILLER EN DERECHO | H23: SI | I23: SI | J23: Obtuve mi grado de bachiller en 1981.
A24: FUERZA POPULAR | B24: 05227631 | C24: DEL AGUILA CARDENAS, JUAN CARLOS | D24: SI | E24: SI | F24: UNIVERSIDAD NACIONAL DE LA AMAZONÍA PERUANA | G24: ADMINISTRACIÓN | H24: NO
A25: FUERZA POPULAR | B25: 17896798 | C25: FLORES RUIZ, VICTOR SEFERINO | D25: SI | E25: SI | F25: Universidad Nacional de Trujillo | G25: BACHILLER EN FARMACIA Y BIOQUIMICA | H25: SI | I25: SI
A26: FUERZA POPULAR | B26: 17896798 | C26: FLORES RUIZ, VICTOR SEFERINO | D26: SI | E26: SI | F26: Universidad Nacional de Trujillo | G26: QUIMICO FARMACEUTICO | H26: SI | I26: SI
A27: FUERZA POPULAR | B27: 19994639 | C27: JIMENEZ HEREDIA, DAVID JULIO | D27: SI | E27: SI | F27: Universidad Peruana Los Andes | G27: ABOGADO | H27: SI | I27: SI
A28: FUERZA POPULAR | B28: 19994639 | C28: JIMENEZ HEREDIA, DAVID JULIO | D28: SI | E28: SI | F28: Universidad Nacional Federico Villarreal | G28: BACHILLER EN DERECHO | H28: SI | I28: SI
A29: FUERZA POPULAR | B29: 07831436 | C29: JUAREZ GALLEGOS, CARMEN PATRICIA | D29: SI | E29: SI | F29: Universidad Federico Villareal | G29: Bachiller en Derecho y Ciencias Políticas | H29: SI | I29: SI
A30: FUERZA POPULAR | B30: 07831436 | C30: JUAREZ GALLEGOS, CARMEN PATRICIA | D30: SI | E30: SI | F30: ESAN | G30: PROGRAMA DE GESTIÓN MUNICIPAL | H30: SI | I30: SI | J30: Diploma de especialista en Gestióon Municipal
A31: FUERZA POPULAR | B31: 09884301 | C31: MELGAR VALDEZ, ELARD GALO | D31: SI | E31: SI | F31: Universidad Inca Garcilaso de la Vega Asociación Civil | G31: BACHILLER EN DERECHO Y CIENCIAS POLITICAS | H31: SI | I31: SI
A32: FUERZA POPULAR | B32: 09884301 | C32: MELGAR VALDEZ, ELARD GALO | D32: SI | E32: SI | F32: Universidad Inca Garcilaso de la Vega Asociación Civil | G32: ABOGADO | H32: SI | I32: SI
A33: FUERZA POPULAR | B33: 08266314 | C33: MESIA RAMIREZ, CARLOS FERNANDO | D33: SI | E33: SI | F33: Universidad de San Martín de Porres | G33: BACHILLER EN DERECHO | H33: SI | I33: SI
A34: FUERZA POPULAR | B34: 08266314 | C34: MESIA RAMIREZ, CARLOS FERNANDO | D34: SI | E34: SI | F34: Universidad de San Martín de Porres | G34: ABOGADO | H34: SI | I34: SI
A35: FUERZA POPULAR | B35: 22974228 | C35: MIYASHIRO ARASHIRO, MARCO ENRIQUE | D35: SI | E35: SI | F35: Escuela de Oficiales de la Policía Nacional del Perú | G35: BACHILLER EN ADMINISTRACION Y CIENCIAS POLICIALES | H35: SI | I35: SI
A36: FUERZA POPULAR | B36: 22974228 | C36: MIYASHIRO ARASHIRO, MARCO ENRIQUE | D36: SI | E36: SI | F36: FAUSTINO SANCHEZ CARRION | G36: LICENCIADO EN ADMINISTRACIÓN | H36: SI | I36: SI
A37: FUERZA POPULAR | B37: 08911520 | C37: MOYANO DELGADO, MARTHA LUPE | D37: SI | E37: SI | F37: Universidad Privada Telesup S.A.C. | G37: BACHILLER EN DERECHO CORPORATIVO | H37: SI | I37: SI
A38: FUERZA POPULAR | B38: 17806760 | C38: NORIEGA REATEGUI, VICTOR MANUEL | D38: SI | E38: SI | F38: Universidad Nacional de Trujillo | G38: MEDICO CIRUJANO | H38: SI | I38: SI
A39: FUERZA POPULAR | B39: 17806760 | C39: NORIEGA REATEGUI, VICTOR MANUEL | D39: SI | E39: SI | F39: Universidad Nacional de Trujillo | G39: BACHILLER EN MEDICINA | H39: SI | I39: SI
A40: FUERZA POPULAR | B40: 08234063 | C40: RODRICH ACKERMAN, JACQUES SALOMON | D40: SI | E40: SI | F40: Pontificia Universidad Católica | G40: no obtuve título | H40: NO
A41: FUERZA POPULAR | B41: 08234063 | C41: RODRICH ACKERMAN, JACQUES SALOMON | D41: SI | E41: SI | F41: Universidad Hebrea de Jerusalén | G41: no obtuve título | H41: NO
A42: FUERZA POPULAR | B42: 07704730 | C42: ROSPIGLIOSI CAPURRO, FERNANDO MIGUEL | D42: SI | E42: SI | F42: Pontificia Universidad Católica del Perú | G42: BACHILLER EN CIENCIAS SOCIALES | H42: SI | I42: SI
A43: FUERZA POPULAR | B43: 10638205 | C43: SCHAEFER CUCULIZA, KARLA MELISSA | D43: NO
A44: FUERZA POPULAR | B44: 16657841 | C44: TAPIA BERNAL, SEGUNDO LEOCADIO | D44: SI | E44: SI | F44: Universidad Nacional Pedro Ruiz Gallo | G44: MEDICO CIRUJANO | H44: SI | I44: SI
A45: FUERZA POPULAR | B45: 16657841 | C45: TAPIA BERNAL, SEGUNDO LEOCADIO | D45: SI | E45: SI | F45: Universidad Nacional Pedro Ruiz Gallo | G45: BACHILLER EN MEDICINA HUMANA | H45: SI | I45: SI
A46: FUERZA POPULAR | B46: 16657841 | C46: TAPIA BERNAL, SEGUNDO LEOCADIO | D46: SI | E46: SI | F46: Universidad Peruana Cayetano Heredia | G46: ESPECIALISTA EN GINECOLOGIA Y OBSTETRICIA | H46: SI | I46: SI
A47: FUERZA POPULAR | B47: 21143880 | C47: VELASQUEZ PORTOCARRERO, JORGE | D47: SI | E47: SI | F47: Universidad de San Martín de Porres | G47: ABOGADA | H47: SI | I47: SI | J47: ESTA INFORMACION NO ES DEL CANDIDATO
A48: FUERZA POPULAR | B48: 21143880 | C48: VELASQUEZ PORTOCARRERO, JORGE | D48: SI | E48: SI | F48: Universidad de San Martín de Porres | G48: ABOGADO | H48: SI | I48: SI
A49: FUERZA POPULAR | B49: 21143880 | C49: VELASQUEZ PORTOCARRERO, JORGE | D49: SI | E49: SI | F49: Universidad de San Martín de Porres | G49: BACHILLER EN DERECHO | H49: SI | I49: SI
A50: FUERZA POPULAR | B50: 40242430 | C50: VENTURA ANGEL, HECTOR JOSE | D50: SI | E50: SI | F50: Universidad Privada "San Juan Bautista" | G50: ABOGADO | H50: SI | I50: SI | J50: Obtuvo el título el 07.11.2006
A51: FUERZA POPULAR | B51: 40242430 | C51: VENTURA ANGEL, HECTOR JOSE | D51: SI | E51: SI | F51: Universidad Privada "San Juan Bautista" | G51: BACHILLER EN DERECHO | H51: SI | I51: SI
A52: FUERZA POPULAR | B52: 21414172 | C52: YAMASHIRO ORE, RAFAEL GUSTAVO | D52: SI | E52: SI | F52: Universidad de Lima | G52: Bachiller en Ciencias Administrativas | H52: SI | I52: SI
A53: JUNTOS POR EL PERU | B53: 22482738 | C53: ANDRES LUJAN, SERAFIN | D53: NO
A54: JUNTOS POR EL PERU | B54: 21487528 | C54: ARMACANQUI MORALES, SAUL ANDRES | D54: SI | E54: SI | F54: Universidad Nacional San Luis Gonzaga | G54: ECONOMISTA | H54: SI | I54: SI
A55: JUNTOS POR EL PERU | B55: 21487528 | C55: ARMACANQUI MORALES, SAUL ANDRES | D55: SI | E55: SI | F55: Universidad Nacional San Luis Gonzaga | G55: BACHILLER EN ECONOMÍA | H55: SI | I55: SI
A56: JUNTOS POR EL PERU | B56: 27409088 | C56: CASTILLO TERRONES, JOSE MERCEDES | D56: NO
A57: JUNTOS POR EL PERU | B57: 40669342 | C57: CCAHUANA AYMACHOQUE, HUGO ISAAC | D57: SI | E57: SI | F57: Universidad Andina del Cusco | G57: BACHILLER EN DERECHO | H57: SI | I57: SI
A58: JUNTOS POR EL PERU | B58: 40669342 | C58: CCAHUANA AYMACHOQUE, HUGO ISAAC | D58: SI | E58: SI | F58: Universidad Alas Peruanas S.A. | G58: ABOGADO | H58: SI | I58: SI
A59: JUNTOS POR EL PERU | B59: 04647085 | C59: CUTIPA CCAMA, VICTOR RAUL | D59: SI | E59: SI | F59: Universidad Privada de Tacna | G59: BACHILLER EN DERECHO | H59: SI | I59: SI
A60: JUNTOS POR EL PERU | B60: 04647085 | C60: CUTIPA CCAMA, VICTOR RAUL | D60: SI | E60: SI | F60: Universidad Privada San Pedro | G60: ABOGADO | H60: SI | I60: SI
A61: JUNTOS POR EL PERU | B61: 21453924 | C61: MARAVI OLARTE, IBER ANTENOR | D61: SI | E61: SI | F61: Universidad Nacional San Luis Gonzaga de Ica | G61: ABOGADO | H61: SI | I61: SI
A62: JUNTOS POR EL PERU | B62: 21453924 | C62: MARAVI OLARTE, IBER ANTENOR | D62: SI | E62: SI | F62: Universidad Nacional San Luis Gonzaga de Ica | G62: LICENCIADO EN CIENCIAS DE LA EDUCACION | H62: SI | I62: SI
A63: JUNTOS POR EL PERU | B63: 10252335 | C63: MORALES RAMIREZ, EDYSON HUMBERTO | D63: SI | E63: SI | F63: Universidad Nacional de San Cristóbal de Huamanga | G63: BACHILLER EN CIENCIAS AGRICOLAS | H63: SI | I63: SI
A64: JUNTOS POR EL PERU | B64: 10252335 | C64: MORALES RAMIREZ, EDYSON HUMBERTO | D64: SI | E64: SI | F64: Universidad Nacional de San Cristóbal de Huamanga | G64: INGENIERO AGRONOMO | H64: SI | I64: SI
A65: JUNTOS POR EL PERU | B65: 40938678 | C65: OSORIO PALPAN, PERCY HERBERT | D65: SI | E65: SI | F65: Pontificia Universidad Católica del Perú | G65: BACHILLER EN CIENCIAS Y ARTES DE LA COMUNICACIÓN CON MENCIÓN EN COMUNICACIÓN PARA EL DESARROLLO | H65: SI | I65: SI
A66: JUNTOS POR EL PERU | B66: 29632775 | C66: QUITO SARMIENTO, BERNARDO JAIME | D66: SI | E66: SI | F66: Universidad José Carlos Mariátegui | G66: BACHILLER EN DERECHO | H66: SI | I66: SI
A67: JUNTOS POR EL PERU | B67: 29632775 | C67: QUITO SARMIENTO, BERNARDO JAIME | D67: SI | E67: SI | F67: UNIVERSIDAD NACIONAL DE SAN AGUSTIN | G67: DERECHO | H67: NO | J67: NO CULMINADO
A68: JUNTOS POR EL PERU | B68: 29632775 | C68: QUITO SARMIENTO, BERNARDO JAIME | D68: SI | E68: SI | F68: Universidad José Carlos Mariátegui | G68: ABOGADO | H68: SI | I68: SI
A69: JUNTOS POR EL PERU | B69: 42750152 | C69: ROBLES ARAUJO, SILVANA EMPERATRIZ | D69: SI | E69: SI | F69: Universidad Alas Peruanas S.A. | G69: CIRUJANO DENTISTA | H69: SI | I69: SI
A70: JUNTOS POR EL PERU | B70: 42750152 | C70: ROBLES ARAUJO, SILVANA EMPERATRIZ | D70: SI | E70: SI | F70: Universidad Alas Peruanas S.A. | G70: BACHILLER EN ESTOMATOLOGÍA | H70: SI | I70: SI
A71: JUNTOS POR EL PERU | B71: 42750152 | C71: ROBLES ARAUJO, SILVANA EMPERATRIZ | D71: SI | E71: SI | F71: FACULDADE UNICPO | G71: ESPECIALIZACIÓN EN ODONTOPEDIATRÍA (TÍTULO DE SEGUNDA ESPECIALIDAD PROFESIONAL) | H71: SI | I71: SI
A72: JUNTOS POR EL PERU | B72: 23906812 | C72: VERANO SARAVIA, WILFREDO | D72: SI | E72: SI | F72: UNIVERSIDAD NACIONAL SAN ANTONIO ABAD DEL CUSCO | G72: ECONOMIA | H72: NO
A73: PARTIDO CIVICO OBRAS | B73: 07651031 | C73: ASTUCURI LAURA, ROGER MIGUEL | D73: SI | E73: SI | F73: Universidad Nacional de San Cristóbal de Huamanga | G73: BACHILLER EN CIENCIAS AGRICOLAS | H73: SI | I73: SI
A74: PARTIDO CIVICO OBRAS | B74: 07651031 | C74: ASTUCURI LAURA, ROGER MIGUEL | D74: SI | E74: SI | F74: Universidad Nacional de San Cristóbal de Huamanga | G74: INGENIERO AGRONOMO | H74: SI | I74: SI
A75: PARTIDO CIVICO OBRAS | B75: 10063223 | C75: BARRAGAN COLOMA, DANIEL HUGO | D75: SI | E75: SI | F75: Escuela de Oficiales de la Fuerza Aérea del Perú | G75: BACHILLER EN CIENCIAS DE LA ADMINISTRACION AEROESPACIAL | H75: SI | I75: SI
A76: PARTIDO CIVICO OBRAS | B76: 10063223 | C76: BARRAGAN COLOMA, DANIEL HUGO | D76: SI | E76: SI | F76: Escuela de Oficiales de la Fuerza Aérea del Perú | G76: LICENCIADO EN CIENCIAS DE LA ADMINISTRACION AEROESPACIAL | H76: SI | I76: SI
A77: PARTIDO CIVICO OBRAS | B77: 10063223 | C77: BARRAGAN COLOMA, DANIEL HUGO | D77: SI | E77: SI | F77: Escuela de Oficiales de la Fuerza Aérea del Perú | G77: BACHILLER EN CIENCIAS DE LA ADMINISTRACION AEROESPACIAL | H77: SI | I77: SI
A78: PARTIDO CIVICO OBRAS | B78: 10063223 | C78: BARRAGAN COLOMA, DANIEL HUGO | D78: SI | E78: SI | F78: Escuela de Oficiales de la Fuerza Aérea del Perú | G78: LICENCIADO EN CIENCIAS DE LA ADMINISTRACION AEROESPACIAL | H78: SI | I78: SI
A79: PARTIDO CIVICO OBRAS | B79: 07250032 | C79: FLORES CORDOVA, AGRIPINA MARIA DEL PILAR | D79: NO
A80: PARTIDO CIVICO OBRAS | B80: 07412350 | C80: GAGO RODRIGUEZ, WALTER FRANCISCO | D80: SI | E80: SI | F80: UNIVERSIDAD INCA GARCILASO DE LA VEGA | G80: CIENCIAS ADMINISTRATIVAS Y CIENCIAS ECONÓMICAS | H80: NO | J80: CARRERA: CIENCIAS ECONÓMICAS (1981-2 - 2013-3)
A81: PARTIDO CIVICO OBRAS | B81: 07412350 | C81: GAGO RODRIGUEZ, WALTER FRANCISCO | D81: SI | E81: SI | F81: PONTIFICIA UNIVERSIDAD CATOLICA DEL PERÚ | G81: DERECHO | H81: NO | J81: CARRERA : DERECHO (2005-1 - 2010-1)
A82: PARTIDO CIVICO OBRAS | B82: 00422672 | C82: TICONA COHAILA, JUANA GUISELLA | D82: SI | E82: SI | F82: Universidad Nacional de San Agustín de Arequipa | G82: BACHILLER EN EDUCACION | H82: SI | I82: SI
A83: PARTIDO CIVICO OBRAS | B83: 00422672 | C83: TICONA COHAILA, JUANA GUISELLA | D83: SI | E83: SI | F83: Universidad Privada de Tacna | G83: LICENCIADA EN EDUCACION PRIMARIA | H83: SI | I83: SI
A84: PARTIDO DEL BUEN GOBIERNO | B84: 06519219 | C84: BONIFAZ CARMONA, NORA | D84: SI | E84: SI | F84: Pontificia Universidad Católica del Perú | G84: LICENCIADO EN SOCIOLOGÍA | H84: SI | I84: SI
A85: PARTIDO DEL BUEN GOBIERNO | B85: 43360309 | C85: CABALLERO LEON, CARLOS DAVID | D85: SI | E85: SI | F85: Escuela de Oficiales de la Fuerza Aérea del Perú | G85: BACHILLER EN CIENCIAS DE LA ADMINISTRACION AEROESPACIAL | H85: SI | I85: SI
A86: PARTIDO DEL BUEN GOBIERNO | B86: 43360309 | C86: CABALLERO LEON, CARLOS DAVID | D86: SI | E86: SI | F86: Escuela de Oficiales de la Fuerza Aérea del Perú | G86: LICENCIADO EN CIENCIAS DE LA ADMINISTRACION AEROESPACIAL | H86: SI | I86: SI
A87: PARTIDO DEL BUEN GOBIERNO | B87: 43360309 | C87: CABALLERO LEON, CARLOS DAVID | D87: SI | E87: SI | F87: Escuela de Oficiales de la Fuerza Aérea del Perú | G87: LICENCIADO EN CIENCIAS DE LA ADMINISTRACION AEROESPACIAL | H87: SI | I87: SI
A88: PARTIDO DEL BUEN GOBIERNO | B88: 43360309 | C88: CABALLERO LEON, CARLOS DAVID | D88: SI | E88: SI | F88: Escuela de Oficiales de la Fuerza Aérea del Perú | G88: BACHILLER EN CIENCIAS DE LA ADMINISTRACION AEROESPACIAL | H88: SI | I88: SI
A89: PARTIDO DEL BUEN GOBIERNO | B89: 07793210 | C89: FIGALLO RIVADENEYRA, FLAVIO FELIPE | D89: SI | E89: SI | F89: Pontificia Universidad Católica del Perú | G89: BACHILLER EN CIENCIAS SOCIALES | H89: SI | I89: SI
A90: PARTIDO DEL BUEN GOBIERNO | B90: 07793210 | C90: FIGALLO RIVADENEYRA, FLAVIO FELIPE | D90: SI | E90: SI | F90: Pontificia Universidad Católica del Perú | G90: LICENCIADO EN SOCIOLOGIA | H90: SI | I90: SI
A91: PARTIDO DEL BUEN GOBIERNO | B91: 30762511 | C91: FLORES SUAREZ, JUVER NILSON | D91: SI | E91: SI | F91: Universidad los Ángeles de Chimbote | G91: ABOGADO | H91: SI | I91: SI
A92: PARTIDO DEL BUEN GOBIERNO | B92: 30762511 | C92: FLORES SUAREZ, JUVER NILSON | D92: SI | E92: SI | F92: Universidad los Ángeles de Chimbote | G92: BACHILLER EN DERECHO Y CIENCIAS POLITICAS | H92: SI | I92: SI
A93: PARTIDO DEL BUEN GOBIERNO | B93: 07619185 | C93: GAVIDIA RODRIGUEZ, JORGE OCTAVIO | D93: SI | E93: SI | F93: Universidad Nacional Mayor de San Marcos | G93: BIOLOGO CON MENCION EN MICROBIOLOGIA Y PARASITOLOGIA | H93: SI | I93: SI
A94: PARTIDO DEL BUEN GOBIERNO | B94: 07619185 | C94: GAVIDIA RODRIGUEZ, JORGE OCTAVIO | D94: SI | E94: SI | F94: Universidad Nacional Mayor de San Marcos | G94: BACHILLER EN CIENCIAS BIOLOGICAS | H94: SI | I94: SI | J94: Ingresante 1986 con 13 años de estudios en pre-grado en las 5 menciones en Biología, al llevar cursos electivos.
A95: PARTIDO DEL BUEN GOBIERNO | B95: 07231335 | C95: ITURREGUI BYRNE, PATRICIA MILAGROS | D95: SI | E95: SI | F95: Pontificia Universidad Católica del Perú | G95: BACHILLER EN DERECHO | H95: SI | I95: SI
A96: PARTIDO DEL BUEN GOBIERNO | B96: 07231335 | C96: ITURREGUI BYRNE, PATRICIA MILAGROS | D96: SI | E96: SI | F96: Pontificia Universidad Católica del Perú | G96: ABOGADO | H96: SI | I96: SI
A97: PARTIDO DEL BUEN GOBIERNO | B97: 06876967 | C97: MATUTE CHARUN, SUSANA FLOR DE MARIA | D97: SI | E97: SI | F97: Universidad Nacional de Educación Enrique Guzmán y Valle | G97: BACHILLER EN EDUCACION | H97: SI | I97: SI
A98: PARTIDO DEL BUEN GOBIERNO | B98: 06876967 | C98: MATUTE CHARUN, SUSANA FLOR DE MARIA | D98: SI | E98: SI | F98: Universidad Nacional de Educación Enrique Guzmán y Valle | G98: LICENCIADO EN EDUCACION | H98: SI | I98: SI
A99: PARTIDO DEL BUEN GOBIERNO | B99: 06876967 | C99: MATUTE CHARUN, SUSANA FLOR DE MARIA | D99: SI | E99: SI | F99: Universidad Nacional de Educación Enrique Guzmán y Valle | G99: BACHILLER EN EDUCACION | H99: SI | I99: SI
A100: PARTIDO DEL BUEN GOBIERNO | B100: 06876967 | C100: MATUTE CHARUN, SUSANA FLOR DE MARIA | D100: SI | E100: SI | F100: Universidad Nacional de Educación Enrique Guzmán y Valle | G100: LICENCIADO EN EDUCACION | H100: SI | I100: SI
...

Sheet 03 FORM. ACADEM. - POSGRADO
A1: ORGANIZACION_POLITICA | B1: DNI_CANDIDATO | C1: CANDIDATO | D1: TIENE_POSGRADO | E1: POSGRADO | F1: CENTRO_ESTUDIOS | G1: ESPECIALIDAD_GRADO | H1: CONCLUIDO | I1: EGRESADO | J1: ES_MAESTRO | K1: ES_DOCTOR | L1: AÑO | M1: INFORMACION_COMPLEMENTARIA
A2: AHORA NACION - AN | B2: 07755878 | C2: DELGADO ZEGARRA, JAIME RICARDO | D2: SI | E2: SI | F2: Universidad Nacional Mayor de San Marcos | G2: MAGISTER EN POLITICAS Y PLANIFICACION EN SALUD | H2: SI | I2: SI | J2: SI | L2: 2021
A3: AHORA NACION - AN | B3: 25331980 | C3: LOPEZ CHAU NAVA, PABLO ALFONSO | D3: SI | E3: SI | F3: UNIVERSIDAD NACIONAL AUTÓNOMA DE MÉXICO | G3: GRADO DE MAESTRO EN ECONOMÍA | H3: SI | I3: SI | J3: SI | L3: 2002
A4: AHORA NACION - AN | B4: 25331980 | C4: LOPEZ CHAU NAVA, PABLO ALFONSO | D4: SI | E4: SI | F4: UNIVERSIDAD NACIONAL AUTÓNOMA DE MÉXICO | G4: GRADO DE DOCTOR EN ECONOMÍA | H4: SI | I4: SI | K4: SI | L4: 2005
A5: AHORA NACION - AN | B5: 25331980 | C5: LOPEZ CHAU NAVA, PABLO ALFONSO | D5: SI | E5: SI | F5: UNIVERSIDAD NACIONAL AUTÓNOMA DE MÉXICO | G5: GRADO DE DOCTOR EN ECONOMÍA | H5: SI | I5: SI | K5: SI | L5: 2005
A6: AHORA NACION - AN | B6: 25331980 | C6: LOPEZ CHAU NAVA, PABLO ALFONSO | D6: SI | E6: SI | F6: UNIVERSIDAD NACIONAL AUTÓNOMA DE MÉXICO | G6: GRADO DE MAESTRO EN ECONOMÍA | H6: SI | I6: SI | J6: SI | L6: 2002
A7: AHORA NACION - AN | B7: 40204874 | C7: LUQUE IBARRA, RUTH | D7: SI | E7: SI | F7: Pontificia Universidad Católica del Perú | G7: Maestría en Derechos Humanos | H7: SI | I7: NO | M7: En proceso de culminación de tesis
A8: AHORA NACION - AN | B8: 40204874 | C8: LUQUE IBARRA, RUTH | D8: SI | E8: SI | F8: Universidad Nacional San Antonio Abad del Cusco | G8: Maestría en Derecho Penal y Procesal Penal | H8: SI | I8: NO | M8: Culminé los estudios pero no me gradué.
A9: AHORA NACION - AN | B9: 26705695 | C9: VASQUEZ CHUQUILIN, MIRTHA ESTHER | D9: SI | E9: SI | F9: Universidad Internacional de Andalucía - España | G9: Derecho Ambiental | H9: SI | I9: NO
A10: AHORA NACION - AN | B10: 26705695 | C10: VASQUEZ CHUQUILIN, MIRTHA ESTHER | D10: SI | E10: SI | F10: Pontificia Universidad Católica del Perú | G10: MAGISTER EN GERENCIA SOCIAL | H10: SI | I10: SI | J10: SI
A11: FUERZA POPULAR | B11: 08236035 | C11: AGUINAGA RECUENCO, ALEJANDRO AURELIO | D11: SI | E11: SI | F11: UNMSM-UNIVERSIDAD NACIONAL MAYOR DE SAN MARCOS | G11: CIRUGIA GENERAL | H11: SI | I11: NO
A12: FUERZA POPULAR | B12: 06717199 | C12: ARISTA ARBILDO, JOSE BERLEY | D12: SI | E12: SI | F12: Universidad de California de los Angeles (USA) | G12: Maestro | H12: SI | I12: SI | J12: SI | L12: 1989 | M12: El grado es "Master of Arts".
A13: FUERZA POPULAR | B13: 10307948 | C13: ASTUDILLO SALCEDO, CESAR AUGUSTO | D13: SI | E13: SI | F13: Universidad Alas Peruanas S.A. | G13: MAESTRO EN ADMINISTRACION | H13: SI | I13: SI | J13: SI | L13: 2008
A14: FUERZA POPULAR | B14: 10307948 | C14: ASTUDILLO SALCEDO, CESAR AUGUSTO | D14: SI | E14: SI | F14: Escuela Superior de Guerra del Ejército | G14: MAESTRO EN CIENCIAS MILITARES | H14: SI | I14: SI | J14: SI | L14: 2015
A15: FUERZA POPULAR | B15: 10307948 | C15: ASTUDILLO SALCEDO, CESAR AUGUSTO | D15: SI | E15: SI | F15: Centro de Altos Estudios Nacionales - CAEN | G15: DOCTOR EN DESARROLLO Y SEGURIDAD ESTRATÉGICA | H15: SI | I15: SI | K15: SI | L15: 2024
A16: FUERZA POPULAR | B16: 32971154 | C16: CHACON TRUJILLO, NILZA MERLY | D16: SI | E16: SI | F16: UNIVERSIDAD TECNOLÓGICA DEL PERÚ - UTP | G16: MAESTRÍA EN GESTIÓN PÚBLICA | H16: NO
A17: FUERZA POPULAR | B17: 07960843 | C17: CHAVEZ COSSIO, MARTHA GLADYS | D17: SI | E17: SI | F17: PONTIFICIA UNIVERSIDAD CATOLICA DEL PERÚ | G17: MAESTRÍA EN DERECHO INTERNACIONAL ECONOMICO | H17: SI | I17: SI | J17: NO | K17: NO
A18: FUERZA POPULAR | B18: 07960843 | C18: CHAVEZ COSSIO, MARTHA GLADYS | D18: SI | E18: SI | F18: Universidad Privada San Juan Bautista | G18: Maestría en Derecho Constitucional y Gobierno | H18: SI | I18: SI | J18: NO | K18: NO
A19: FUERZA POPULAR | B19: 05227631 | C19: DEL AGUILA CARDENAS, JUAN CARLOS | D19: NO
A20: FUERZA POPULAR | B20: 17896798 | C20: FLORES RUIZ, VICTOR SEFERINO | D20: NO
A21: FUERZA POPULAR | B21: 19994639 | C21: JIMENEZ HEREDIA, DAVID JULIO | D21: SI | E21: SI | F21: Universidad de San Martín de Porres | G21: MAESTRO EN EDUCACIÓN CON MENCIÓN EN GESTIÓN UNIVERSITARIA | H21: SI | I21: SI | J21: SI | L21: 2024
A22: FUERZA POPULAR | B22: 07831436 | C22: JUAREZ GALLEGOS, CARMEN PATRICIA | D22: SI | E22: SI | F22: Universidad San MartÍn de Porres | G22: Maestría en Derecho Civil y Comercial | H22: SI | I22: SI | J22: NO | K22: NO | M22: Año de obtención 1994.
A23: FUERZA POPULAR | B23: 09884301 | C23: MELGAR VALDEZ, ELARD GALO | D23: NO
A24: FUERZA POPULAR | B24: 08266314 | C24: MESIA RAMIREZ, CARLOS FERNANDO | D24: SI | E24: SI | F24: Universidad Nacional Mayor de San Marcos | G24: DOCTOR EN DERECHO Y CIENCIA POLITICA | H24: SI | I24: SI | K24: SI | L24: 2016
A25: FUERZA POPULAR | B25: 08266314 | C25: MESIA RAMIREZ, CARLOS FERNANDO | D25: SI | E25: SI | F25: Pontificia Universidad Católica del Perú | G25: MAGISTER EN DERECHO. MENCION EN DERECHO CONSTITUCIONAL | H25: SI | I25: SI | J25: SI | M25: Año de obtención: 1997.
A26: FUERZA POPULAR | B26: 22974228 | C26: MIYASHIRO ARASHIRO, MARCO ENRIQUE | D26: NO
A27: FUERZA POPULAR | B27: 08911520 | C27: MOYANO DELGADO, MARTHA LUPE | D27: NO
A28: FUERZA POPULAR | B28: 17806760 | C28: NORIEGA REATEGUI, VICTOR MANUEL | D28: SI | E28: SI | F28: Universidad Privada César Vallejo | G28: MAGISTER EN DOCENCIA UNIVERSITARIA | H28: SI | I28: SI | J28: SI | L28: 2006
A29: FUERZA POPULAR | B29: 08234063 | C29: RODRICH ACKERMAN, JACQUES SALOMON | D29: NO
A30: FUERZA POPULAR | B30: 07704730 | C30: ROSPIGLIOSI CAPURRO, FERNANDO MIGUEL | D30: NO
A31: FUERZA POPULAR | B31: 10638205 | C31: SCHAEFER CUCULIZA, KARLA MELISSA | D31: NO
A32: FUERZA POPULAR | B32: 16657841 | C32: TAPIA BERNAL, SEGUNDO LEOCADIO | D32: SI | E32: SI | F32: UNIVERSIDAD INTERNACIONAL DE LA RIOJA | G32: TÍTULO OFICIAL DE MÁSTER UNIVERSITARIO EN COMUNICACIÓN Y MARKETING POLÍTICO (GRADO DE MAESTRO) | H32: SI | I32: SI | J32: SI | L32: 2022
A33: FUERZA POPULAR | B33: 16657841 | C33: TAPIA BERNAL, SEGUNDO LEOCADIO | D33: SI | E33: SI | F33: Universidad Nacional Mayor de San Marcos | G33: DOCTOR EN MEDICINA | H33: SI | I33: SI | K33: SI | L33: 2017 | M33: AÑO DEL DIPLOMA 2018
A34: FUERZA POPULAR | B34: 16657841 | C34: TAPIA BERNAL, SEGUNDO LEOCADIO | D34: SI | E34: SI | F34: Universidad Peruana Cayetano Heredia | G34: MAGISTER EN MEDICINA | H34: SI | I34: SI | J34: SI | L34: 2011
A35: FUERZA POPULAR | B35: 16657841 | C35: TAPIA BERNAL, SEGUNDO LEOCADIO | D35: SI | E35: SI | F35: Universidad Nacional Federico Villarreal | G35: MAESTRO EN DIRECCION Y ORGANIZACION DE HOSPITALES Y SERVICIOS DE SALUD | H35: SI | I35: SI | J35: SI | L35: 2011
A36: FUERZA POPULAR | B36: 21143880 | C36: VELASQUEZ PORTOCARRERO, JORGE | D36: SI | E36: SI | F36: UNIVERSIDAD SAN MARTÍN DE PORRES | G36: GESTION DE NEGOCIOS | H36: SI | I36: SI | J36: NO | K36: NO | M36: FALTA LA TESIS PARA OBTENER EL GRADO ACADEMICO
A37: FUERZA POPULAR | B37: 40242430 | C37: VENTURA ANGEL, HECTOR JOSE | D37: SI | E37: SI | F37: Universidad San Martín de Porres | G37: Maestria en Derecho Civil | H37: SI | I37: SI | J37: NO | K37: NO
A38: FUERZA POPULAR | B38: 40242430 | C38: VENTURA ANGEL, HECTOR JOSE | D38: SI | E38: SI | F38: Universidad Privada San Juan Bautista | G38: Maestria en Derecho, Gestión Parlamentaria y Sistemas Electorales. | H38: NO | M38: Estudios en curso
A39: FUERZA POPULAR | B39: 21414172 | C39: YAMASHIRO ORE, RAFAEL GUSTAVO | D39: SI | E39: SI | F39: UNIVERSIDAD NACIONAL SAN LUIS GONZAGA DE ICA | G39: ADMINISTRACIÓN - GESTIÓN PÚBLICA | H39: NO | M39: ESTUDIOS EN CURSO A LA FECHA.
A40: JUNTOS POR EL PERU | B40: 22482738 | C40: ANDRES LUJAN, SERAFIN | D40: NO
A41: JUNTOS POR EL PERU | B41: 21487528 | C41: ARMACANQUI MORALES, SAUL ANDRES | D41: SI | E41: SI | F41: UNIVERSIDAD NACIONAL FEDERICO VILLARREAL | G41: MAESTRIA DE ADMINISTRACION | H41: SI | I41: SI | J41: NO | K41: NO | M41: 2014
A42: JUNTOS POR EL PERU | B42: 27409088 | C42: CASTILLO TERRONES, JOSE MERCEDES | D42: NO
A43: JUNTOS POR EL PERU | B43: 40669342 | C43: CCAHUANA AYMACHOQUE, HUGO ISAAC | D43: SI | E43: SI | F43: CENTRO DE ALTOS ESTUDIOS NACIONALES - CAEN PERÚ | G43: MAESTRIA EN DESARROLLO Y DEFENSA NACIONAL | H43: SI | I43: SI | J43: NO | K43: NO
A44: JUNTOS POR EL PERU | B44: 04647085 | C44: CUTIPA CCAMA, VICTOR RAUL | D44: SI | E44: SI | F44: Universidad privada Jose Carlos Mariategui | G44: Maestría en Derecho Constitucional | H44: SI | I44: SI | J44: NO | K44: NO
A45: JUNTOS POR EL PERU | B45: 21453924 | C45: MARAVI OLARTE, IBER ANTENOR | D45: SI | E45: SI | F45: Universidad Nacional San Luis Gonzaga de Ica | G45: Maestria en Derecho con Mención en Ciencias Penales | H45: SI | I45: SI | J45: NO | K45: NO
A46: JUNTOS POR EL PERU | B46: 10252335 | C46: MORALES RAMIREZ, EDYSON HUMBERTO | D46: SI | E46: SI | F46: Universidad Nacional de San Cristóbal de Huamanga | G46: MAESTRO EN DOCENCIA UNIVERSITARIA | H46: SI | I46: SI | J46: SI | L46: 2023
A47: JUNTOS POR EL PERU | B47: 40938678 | C47: OSORIO PALPAN, PERCY HERBERT | D47: SI | E47: SI | F47: Universidad de san martin de porres | G47: maestria de solución de conflictos | H47: SI | I47: SI | J47: NO | K47: NO | M47: egresado en el 2024
A48: JUNTOS POR EL PERU | B48: 29632775 | C48: QUITO SARMIENTO, BERNARDO JAIME | D48: NO
A49: JUNTOS POR EL PERU | B49: 42750152 | C49: ROBLES ARAUJO, SILVANA EMPERATRIZ | D49: SI | E49: SI | F49: Universidad Nacional del Centro del Perú | G49: Maestra en Antropología Jurídica | H49: SI | I49: SI | J49: SI | L49: 2025
A50: JUNTOS POR EL PERU | B50: 23906812 | C50: VERANO SARAVIA, WILFREDO | D50: NO
A51: PARTIDO CIVICO OBRAS | B51: 07651031 | C51: ASTUCURI LAURA, ROGER MIGUEL | D51: SI | E51: SI | F51: Universidad Privada César Vallejo | G51: MAGISTER EN GESTION PUBLICA | H51: SI | I51: SI | J51: SI | L51: 2015
A52: PARTIDO CIVICO OBRAS | B52: 10063223 | C52: BARRAGAN COLOMA, DANIEL HUGO | D52: SI | E52: SI | F52: EPG-CENTRO DE ALTOS ESTUDIOS NACIONALES-CAEN | G52: CURSO ESPECIAL DE DESARROLLO Y DEFENSA NACIONAL– AÑO 1999 | H52: SI | I52: SI | J52: NO | K52: NO
A53: PARTIDO CIVICO OBRAS | B53: 10063223 | C53: BARRAGAN COLOMA, DANIEL HUGO | D53: SI | E53: SI | F53: EPG-CENTRO DE ALTOS ESTUDIOS NACIONALES-CAEN | G53: CURSO ESPECIAL DE DESARROLLO Y DEFENSA NACIONAL– AÑO 1999 | H53: SI | I53: SI | J53: NO | K53: NO
A54: PARTIDO CIVICO OBRAS | B54: 07250032 | C54: FLORES CORDOVA, AGRIPINA MARIA DEL PILAR | D54: NO
A55: PARTIDO CIVICO OBRAS | B55: 07412350 | C55: GAGO RODRIGUEZ, WALTER FRANCISCO | D55: NO
A56: PARTIDO CIVICO OBRAS | B56: 00422672 | C56: TICONA COHAILA, JUANA GUISELLA | D56: SI | E56: SI | F56: UNIVERSIDAD PRIVADA DE TACNA | G56: PSICOPEDAGOGIA | H56: SI | I56: SI | J56: NO | K56: NO
A57: PARTIDO DEL BUEN GOBIERNO | B57: 06519219 | C57: BONIFAZ CARMONA, NORA | D57: SI | E57: SI | F57: PUCP | G57: SOCIOLOGIA | H57: SI | I57: SI | J57: SI | L57: 1983 | M57: ESTUDIOS EN LA UNIVERSIDAD PARIS 1 CONVALIDADOS EN LA PUCP
A58: PARTIDO DEL BUEN GOBIERNO | B58: 06519219 | C58: BONIFAZ CARMONA, NORA | D58: SI | E58: SI | F58: Pontificia Universidad Católica del Perú | G58: MAGÍSTER EN SOCIOLOGÍA | H58: SI | I58: SI | J58: SI | L58: 1987
A59: PARTIDO DEL BUEN GOBIERNO | B59: 43360309 | C59: CABALLERO LEON, CARLOS DAVID | D59: SI | E59: SI | F59: INTER-AMERICAN DEFENSE COLLEGE | G59: GRADO DE MAGÍSTER EN CIENCIAS EN DEFENSA Y SEGURIDAD INTERAMERICANA (GRADO DE MAESTRO) | H59: SI | I59: SI | J59: SI | L59: 2016
A60: PARTIDO DEL BUEN GOBIERNO | B60: 43360309 | C60: CABALLERO LEON, CARLOS DAVID | D60: SI | E60: SI | F60: ACADEMIA NACIONAL DE ESTUDIOS POLÍTICOS Y ESTRATÉGICOS | G60: GRADO ACADÉMICO DE MAGÍSTER EN ESTUDIOS DE DEFENSA Y SEGURIDAD DE LAS AMÉRICAS (GRADO DE MAESTRO) | H60: SI | I60: SI | J60: SI | L60: 2019
A61: PARTIDO DEL BUEN GOBIERNO | B61: 43360309 | C61: CABALLERO LEON, CARLOS DAVID | D61: SI | E61: SI | F61: ECOLE NATIONALE SUPERIEURE D'INGENIEURS DE CONSTRUCTIONS AERONAUTIQUES | G61: DIPLOMA DE INGENIERO DE CONSTRUCCIONES AERONÁUTICAS (GRADO DE BACHILLER, TÍTULO PROFESIONAL Y GRADO DE MAESTRO) | H61: SI | I61: SI | J61: SI | L61: 2019
A62: PARTIDO DEL BUEN GOBIERNO | B62: 43360309 | C62: CABALLERO LEON, CARLOS DAVID | D62: SI | E62: SI | F62: INTER-AMERICAN DEFENSE COLLEGE | G62: GRADO DE MAGÍSTER EN CIENCIAS EN DEFENSA Y SEGURIDAD INTERAMERICANA (GRADO DE MAESTRO) | H62: SI | I62: SI | J62: SI | L62: 2016
A63: PARTIDO DEL BUEN GOBIERNO | B63: 43360309 | C63: CABALLERO LEON, CARLOS DAVID | D63: SI | E63: SI | F63: ACADEMIA NACIONAL DE ESTUDIOS POLÍTICOS Y ESTRATÉGICOS | G63: GRADO ACADÉMICO DE MAGÍSTER EN ESTUDIOS DE DEFENSA Y SEGURIDAD DE LAS AMÉRICAS (GRADO DE MAESTRO) | H63: SI | I63: SI | J63: SI | L63: 2019
A64: PARTIDO DEL BUEN GOBIERNO | B64: 43360309 | C64: CABALLERO LEON, CARLOS DAVID | D64: SI | E64: SI | F64: ECOLE NATIONALE SUPERIEURE D'INGENIEURS DE CONSTRUCTIONS AERONAUTIQUES | G64: DIPLOMA DE INGENIERO DE CONSTRUCCIONES AERONÁUTICAS (GRADO DE BACHILLER, TÍTULO PROFESIONAL Y GRADO DE MAESTRO) | H64: SI | I64: SI | J64: SI | L64: 2019
A65: PARTIDO DEL BUEN GOBIERNO | B65: 07793210 | C65: FIGALLO RIVADENEYRA, FLAVIO FELIPE | D65: SI | E65: SI | F65: Pontificia Universidad Católica del Perú | G65: MAGÍSTER EN POLÍTICA Y GESTIÓN UNIVERSITARIA | H65: SI | I65: SI | J65: SI | L65: 2019
A66: PARTIDO DEL BUEN GOBIERNO | B66: 30762511 | C66: FLORES SUAREZ, JUVER NILSON | D66: SI | E66: SI | F66: UNIVERSIDAD NACIONAL DE SAN AGUSTIN | G66: MAESTRIA EN DERECHO CONSTITUCIONAL | H66: SI | I66: NO
A67: PARTIDO DEL BUEN GOBIERNO | B67: 07619185 | C67: GAVIDIA RODRIGUEZ, JORGE OCTAVIO | D67: NO
A68: PARTIDO DEL BUEN GOBIERNO | B68: 07231335 | C68: ITURREGUI BYRNE, PATRICIA MILAGROS | D68: SI | E68: SI | F68: UNIVERSITY OF LONDON (THE SCHOOL OF ORIENTAL AND AFRICAN STUDIES) | G68: GRADO DE MÁSTER EN DERECHO CON ESPECIALIZACIÓN EN DERECHO AMBIENTAL (GRADO DE MAESTRO) | H68: SI | I68: SI | J68: SI | L68: 2018
A69: PARTIDO DEL BUEN GOBIERNO | B69: 06876967 | C69: MATUTE CHARUN, SUSANA FLOR DE MARIA | D69: SI | E69: SI | F69: Universidad Alas Peruanas S.A. | G69: MAESTRO EN CIENCIAS DE LA EDUCACION | H69: SI | I69: SI | J69: SI | L69: 2012
A70: PARTIDO DEL BUEN GOBIERNO | B70: 06876967 | C70: MATUTE CHARUN, SUSANA FLOR DE MARIA | D70: SI | E70: SI | F70: Universidad Alas Peruanas S.A. | G70: MAESTRO EN CIENCIAS DE LA EDUCACION | H70: SI | I70: SI | J70: SI | L70: 2012
A71: RENOVACION POPULAR | B71: 08235876 | C71: ALCORTA SUERO, MARIA LOURDES PIA LUISA | D71: NO
A72: RENOVACION POPULAR | B72: 25799622 | C72: AMPUERO MEZA, KATHERINE MILAGROS | D72: SI | E72: SI | F72: UNIVERSIDAD NACIONAL MAYOR DE SAN MARCOS | G72: CIENCIAS PENALES | H72: SI | I72: SI | J72: NO | K72: NO
A73: RENOVACION POPULAR | B73: 43285320 | C73: CALISTO GIAMPIETRI, FRANCISCO JOSE | D73: SI | E73: SI | F73: UNIVERSIDAD GARCILASO | G73: ADMINISTRACION DE LA EDUCACION | H73: SI | I73: SI | J73: NO | K73: NO | M73: Falta sustentar tesis
A74: RENOVACION POPULAR | B74: 43285320 | C74: CALISTO GIAMPIETRI, FRANCISCO JOSE | D74: SI | E74: SI | F74: CAEN | G74: ADMINISTRACION Y GESTION PUBLICA | H74: SI | I74: SI | J74: NO | K74: NO
A75: RENOVACION POPULAR | B75: 43285320 | C75: CALISTO GIAMPIETRI, FRANCISCO JOSE | D75: SI | E75: SI | F75: CAEN | G75: POLITICA Y ESTRATEGIA | H75: SI | I75: SI | J75: NO | K75: NO
A76: RENOVACION POPULAR | B76: 43285320 | C76: CALISTO GIAMPIETRI, FRANCISCO JOSE | D76: SI | E76: SI | F76: Centro de Altos Estudios Nacionales - CAEN | G76: MAESTRO EN DESARROLLO Y DEFENSA NACIONAL | H76: SI | I76: SI | J76: SI | L76: 2025
A77: RENOVACION POPULAR | B77: 07852432 | C77: JAUREGUI MARTINEZ DE AGUAYO, MARIA DE LOS MILAGROS JACKELINE | D77: NO
A78: RENOVACION POPULAR | B78: 07845838 | C78: LÓPEZ ALIAGA CAZORLA, RAFAEL BERNARDO | D78: SI | E78: SI | F78: Universidad del Pacífico | G78: MAGISTER EN ADMINISTRACION | H78: SI | I78: SI | J78: SI
A79: RENOVACION POPULAR | B79: 07845838 | C79: LÓPEZ ALIAGA CAZORLA, RAFAEL BERNARDO | D79: SI | E79: SI | F79: Universidad del Pacífico | G79: MAGISTER EN ADMINISTRACION | H79: SI | I79: SI | J79: SI
A80: RENOVACION POPULAR | B80: 01539305 | C80: MANCHA PINEDA, ESTANISLAO EDGAR | D80: SI | E80: SI | F80: Universidad Alas Peruanas S.A. | G80: DOCTOR EN CIENCIAS DE LA EDUCACION | H80: SI | I80: SI | K80: SI | L80: 2009
A81: RENOVACION POPULAR | B81: 01539305 | C81: MANCHA PINEDA, ESTANISLAO EDGAR | D81: SI | E81: SI | F81: Universidad Nacional del Altiplano | G81: MAGISTER SCIENTIAE EN CIENCIAS SOCIALES | H81: SI | I81: SI | J81: SI
A82: RENOVACION POPULAR | B82: 45209282 | C82: MUÑANTE BARRIOS, ALEJANDRO | D82: SI | E82: SI | F82: UNIVERSIDAD DE SAN MARTIN DE PORRES | G82: MAESTRIA | H82: SI | I82: SI | J82: NO | K82: NO | M82: EN PROCESO DE OBTENCIÓN DE GRADO DE MAGISTER, YA APROBÉ LA TESIS.
A83: RENOVACION POPULAR | B83: 06504611 | C83: VELASQUEZ GARCIA, MIGUEL ANGEL | D83: NO
A84: FUERZA POPULAR | B84: 40433187 | C84: TORRES MORALES, MIGUEL ANGEL | D84: SI | E84: SI | F84: Universidad de Piura | G84: MAGISTER EN GOBIERNO DE LAS ORGANIZACIONES | H84: SI | I84: SI | J84: SI | L84: 2020 | M84: Mi fecha de egreso es el 21/08/2020. Y, la obtención del título es el 29/01/21.
A85: JUNTOS POR EL PERU | B85: 02044988 | C85: CHIPANA CHIPANA, JOSE MOISES | D85: NO
A86: JUNTOS POR EL PERU | B86: 23271450 | C86: YAURI TUNQUE, JOAQUIN | D86: SI | E86: SI | F86: UNIVERSIDAD NACIONAL DE HUANCAVELICA | G86: GESTION PUBLICA | H86: SI | I86: SI | J86: NO | K86: NO | M86: NO CUENTO CON EL GRADO
A87: JUNTOS POR EL PERU | B87: 31010129 | C87: RAMOS HUILLCAS, ANDRES AVELINO | D87: NO

Sheet 03 FORM. ACADEM. - OTRO POSGRAD
A1: ORGANIZACION_POLITICA | B1: DNI_CANDIDATO | C1: CANDIDATO | D1: TIENE_OTRO_POSGRADO | E1: POSGRADO_OTRO | F1: CENTRO_ESTUDIOS | G1: ESPECIALIDAD | H1: CONCLUIDO | I1: EGRESADO | J1: GRADO | K1: AÑO | L1: INFORMACION_COMPLEMENTARIA
A2: AHORA NACION - AN | B2: 07755878 | C2: DELGADO ZEGARRA, JAIME RICARDO | D2: NO
A3: AHORA NACION - AN | B3: 25331980 | C3: LOPEZ CHAU NAVA, PABLO ALFONSO | D3: NO
A4: AHORA NACION - AN | B4: 25331980 | C4: LOPEZ CHAU NAVA, PABLO ALFONSO | D4: NO
A5: AHORA NACION - AN | B5: 40204874 | C5: LUQUE IBARRA, RUTH | D5: NO
A6: AHORA NACION - AN | B6: 26705695 | C6: VASQUEZ CHUQUILIN, MIRTHA ESTHER | D6: NO
A7: FUERZA POPULAR | B7: 08236035 | C7: AGUINAGA RECUENCO, ALEJANDRO AURELIO | D7: NO
A8: FUERZA POPULAR | B8: 06717199 | C8: ARISTA ARBILDO, JOSE BERLEY | D8: SI | E8: SI | F8: ESAN | G8: Construction Management | H8: SI | I8: SI | J8: - | K8: 2016 | L8: Es un diplomado.
A9: FUERZA POPULAR | B9: 10307948 | C9: ASTUDILLO SALCEDO, CESAR AUGUSTO | D9: NO
A10: FUERZA POPULAR | B10: 32971154 | C10: CHACON TRUJILLO, NILZA MERLY | D10: NO
A11: FUERZA POPULAR | B11: 07960843 | C11: CHAVEZ COSSIO, MARTHA GLADYS | D11: NO
A12: FUERZA POPULAR | B12: 05227631 | C12: DEL AGUILA CARDENAS, JUAN CARLOS | D12: NO
A13: FUERZA POPULAR | B13: 17896798 | C13: FLORES RUIZ, VICTOR SEFERINO | D13: NO
A14: FUERZA POPULAR | B14: 19994639 | C14: JIMENEZ HEREDIA, DAVID JULIO | D14: NO
A15: FUERZA POPULAR | B15: 07831436 | C15: JUAREZ GALLEGOS, CARMEN PATRICIA | D15: NO
A16: FUERZA POPULAR | B16: 09884301 | C16: MELGAR VALDEZ, ELARD GALO | D16: NO
A17: FUERZA POPULAR | B17: 08266314 | C17: MESIA RAMIREZ, CARLOS FERNANDO | D17: NO
A18: FUERZA POPULAR | B18: 22974228 | C18: MIYASHIRO ARASHIRO, MARCO ENRIQUE | D18: NO
A19: FUERZA POPULAR | B19: 08911520 | C19: MOYANO DELGADO, MARTHA LUPE | D19: NO | E19: SI
A20: FUERZA POPULAR | B20: 17806760 | C20: NORIEGA REATEGUI, VICTOR MANUEL | D20: SI | E20: SI | F20: UNIVERSIDAD NACIONAL DE TRUJILLO | G20: GINECO OBSTETRA | H20: SI | I20: SI | K20: 1994
A21: FUERZA POPULAR | B21: 08234063 | C21: RODRICH ACKERMAN, JACQUES SALOMON | D21: NO
A22: FUERZA POPULAR | B22: 07704730 | C22: ROSPIGLIOSI CAPURRO, FERNANDO MIGUEL | D22: NO
A23: FUERZA POPULAR | B23: 10638205 | C23: SCHAEFER CUCULIZA, KARLA MELISSA | D23: NO
A24: FUERZA POPULAR | B24: 16657841 | C24: TAPIA BERNAL, SEGUNDO LEOCADIO | D24: NO
A25: FUERZA POPULAR | B25: 21143880 | C25: VELASQUEZ PORTOCARRERO, JORGE | D25: NO
A26: FUERZA POPULAR | B26: 40242430 | C26: VENTURA ANGEL, HECTOR JOSE | D26: NO
A27: FUERZA POPULAR | B27: 21414172 | C27: YAMASHIRO ORE, RAFAEL GUSTAVO | D27: NO
A28: JUNTOS POR EL PERU | B28: 22482738 | C28: ANDRES LUJAN, SERAFIN | D28: NO
A29: JUNTOS POR EL PERU | B29: 21487528 | C29: ARMACANQUI MORALES, SAUL ANDRES | D29: NO
A30: JUNTOS POR EL PERU | B30: 27409088 | C30: CASTILLO TERRONES, JOSE MERCEDES | D30: NO
A31: JUNTOS POR EL PERU | B31: 40669342 | C31: CCAHUANA AYMACHOQUE, HUGO ISAAC | D31: SI | E31: SI | F31: UNIVERSIDAD SAN ANTONIO ABAD DEL CUSCO | G31: DERECHO CONSTITUCIONAL | H31: NO
A32: JUNTOS POR EL PERU | B32: 04647085 | C32: CUTIPA CCAMA, VICTOR RAUL | D32: NO
A33: JUNTOS POR EL PERU | B33: 21453924 | C33: MARAVI OLARTE, IBER ANTENOR | D33: NO
A34: JUNTOS POR EL PERU | B34: 10252335 | C34: MORALES RAMIREZ, EDYSON HUMBERTO | D34: NO
A35: JUNTOS POR EL PERU | B35: 40938678 | C35: OSORIO PALPAN, PERCY HERBERT | D35: NO
A36: JUNTOS POR EL PERU | B36: 29632775 | C36: QUITO SARMIENTO, BERNARDO JAIME | D36: NO
A37: JUNTOS POR EL PERU | B37: 42750152 | C37: ROBLES ARAUJO, SILVANA EMPERATRIZ | D37: SI | E37: SI | F37: Universidad Autónoma de Ica | G37: DOCTOR EN ADMINISTRACIÓN | H37: NO | L37: Inicio 2025
A38: JUNTOS POR EL PERU | B38: 23906812 | C38: VERANO SARAVIA, WILFREDO | D38: NO
A39: PARTIDO CIVICO OBRAS | B39: 07651031 | C39: ASTUCURI LAURA, ROGER MIGUEL | D39: SI | E39: SI | F39: UNIVERSIDAD NACIONAL AGRARIA LA MOLINA | G39: PRODUCCIÓN AGRICOLA | H39: SI | I39: NO
A40: PARTIDO CIVICO OBRAS | B40: 07651031 | C40: ASTUCURI LAURA, ROGER MIGUEL | D40: SI | E40: SI | F40: UNIVERSIDAD FEDERICO VILLARREAL | G40: MEDIO AMBIENTE Y DESARROLLO SOSTENIBLE | H40: SI | I40: NO
A41: PARTIDO CIVICO OBRAS | B41: 10063223 | C41: BARRAGAN COLOMA, DANIEL HUGO | D41: NO
A42: PARTIDO CIVICO OBRAS | B42: 10063223 | C42: BARRAGAN COLOMA, DANIEL HUGO | D42: NO
A43: PARTIDO CIVICO OBRAS | B43: 07250032 | C43: FLORES CORDOVA, AGRIPINA MARIA DEL PILAR | D43: NO
A44: PARTIDO CIVICO OBRAS | B44: 07412350 | C44: GAGO RODRIGUEZ, WALTER FRANCISCO | D44: NO
A45: PARTIDO CIVICO OBRAS | B45: 00422672 | C45: TICONA COHAILA, JUANA GUISELLA | D45: NO
A46: PARTIDO DEL BUEN GOBIERNO | B46: 06519219 | C46: BONIFAZ CARMONA, NORA | D46: SI | E46: SI | F46: UNIVERSIDAD PARIS 1 | G46: DESARROLLO AGRICOLA | H46: SI | I46: SI | J46: MAESTRIA | K46: 1982 | L46: NO LO INSCRIBI EN SUNEDU
A47: PARTIDO DEL BUEN GOBIERNO | B47: 43360309 | C47: CABALLERO LEON, CARLOS DAVID | D47: NO
A48: PARTIDO DEL BUEN GOBIERNO | B48: 43360309 | C48: CABALLERO LEON, CARLOS DAVID | D48: NO
A49: PARTIDO DEL BUEN GOBIERNO | B49: 07793210 | C49: FIGALLO RIVADENEYRA, FLAVIO FELIPE | D49: NO
A50: PARTIDO DEL BUEN GOBIERNO | B50: 30762511 | C50: FLORES SUAREZ, JUVER NILSON | D50: NO
A51: PARTIDO DEL BUEN GOBIERNO | B51: 07619185 | C51: GAVIDIA RODRIGUEZ, JORGE OCTAVIO | D51: NO
A52: PARTIDO DEL BUEN GOBIERNO | B52: 07231335 | C52: ITURREGUI BYRNE, PATRICIA MILAGROS | D52: NO
A53: PARTIDO DEL BUEN GOBIERNO | B53: 06876967 | C53: MATUTE CHARUN, SUSANA FLOR DE MARIA | D53: SI | E53: SI | F53: Universidad de Granada | G53: Segunda especialización en educación intercultural, economía y medio ambiente | H53: SI | I53: SI | J53: Segunda especialización | K53: 2016
A54: PARTIDO DEL BUEN GOBIERNO | B54: 06876967 | C54: MATUTE CHARUN, SUSANA FLOR DE MARIA | D54: SI | E54: SI | F54: Universidad de Granada | G54: Segunda especialización en educación intercultural, economía y medio ambiente | H54: SI | I54: SI | J54: Segunda especialización | K54: 2016
A55: RENOVACION POPULAR | B55: 08235876 | C55: ALCORTA SUERO, MARIA LOURDES PIA LUISA | D55: NO
A56: RENOVACION POPULAR | B56: 25799622 | C56: AMPUERO MEZA, KATHERINE MILAGROS | D56: SI | E56: SI | F56: UNIVERSIDAD DE SAN MARTIN DE PORRES | G56: DERECHO CIVIL Y COMERCIAL | H56: SI | I56: NO | L56: ESTUDIOS CONCLUIDOS EN EL 2006
A57: RENOVACION POPULAR | B57: 43285320 | C57: CALISTO GIAMPIETRI, FRANCISCO JOSE | D57: NO
A58: RENOVACION POPULAR | B58: 07852432 | C58: JAUREGUI MARTINEZ DE AGUAYO, MARIA DE LOS MILAGROS JACKELINE | D58: NO
A59: RENOVACION POPULAR | B59: 07845838 | C59: LÓPEZ ALIAGA CAZORLA, RAFAEL BERNARDO | D59: NO
A60: RENOVACION POPULAR | B60: 07845838 | C60: LÓPEZ ALIAGA CAZORLA, RAFAEL BERNARDO | D60: NO
A61: RENOVACION POPULAR | B61: 01539305 | C61: MANCHA PINEDA, ESTANISLAO EDGAR | D61: NO
A62: RENOVACION POPULAR | B62: 45209282 | C62: MUÑANTE BARRIOS, ALEJANDRO | D62: SI | E62: SI | F62: CENTRO DE ALTOS ESTUDIOS NACIONALES - CAEN | G62: DESARROLLO Y DEFENSA NACIONAL | H62: NO
A63: RENOVACION POPULAR | B63: 06504611 | C63: VELASQUEZ GARCIA, MIGUEL ANGEL | D63: NO
A64: FUERZA POPULAR | B64: 40433187 | C64: TORRES MORALES, MIGUEL ANGEL | D64: SI | E64: SI | F64: Universidad ESAN | G64: Responsabilidad Social | H64: SI | I64: SI | K64: 2012 | L64: Diploma en Responsabilidad Social (Tercer Programa de Alta Especializacion en Responsabilidad Social) 100 sesiones de una hora y treinta minutos cada una.
A65: JUNTOS POR EL PERU | B65: 02044988 | C65: CHIPANA CHIPANA, JOSE MOISES | D65: NO
A66: JUNTOS POR EL PERU | B66: 23271450 | C66: YAURI TUNQUE, JOAQUIN | D66: SI | E66: SI | F66: UNIVERSIDAD NACIONAL DEL CENTRO DEL PERU | G66: ADMINISTRACIÓN MENCION INFORMATICA PARA LA GESTION | H66: SI | I66: SI | L66: NO CUENTO CON EL GRADO
A67: JUNTOS POR EL PERU | B67: 31010129 | C67: RAMOS HUILLCAS, ANDRES AVELINO | D67: NO

Sheet 04 CARGO PARTIDARIO
A1: ORGANIZACION_POLITICA | B1: DNI_CANDIDATO | C1: CANDIDATO | D1: TIENE_CARGO_PARTIDARIO | E1: ORGANIZACION_POLITICA_CARGO | F1: CARGO_PARTIDARIO | G1: AÑO_DESDE | H1: AÑO_HASTA | I1: INFORMACION_COMPLEMENTARIA
A2: AHORA NACION - AN | B2: 07755878 | C2: DELGADO ZEGARRA, JAIME RICARDO | D2: NO
A3: AHORA NACION - AN | B3: 25331980 | C3: LOPEZ CHAU NAVA, PABLO ALFONSO | D3: SI | E3: AHORA NACION - AN | F3: FUNDADOR | G3: 2023 | H3: 0000
A4: AHORA NACION - AN | B4: 25331980 | C4: LOPEZ CHAU NAVA, PABLO ALFONSO | D4: SI | E4: ALIANZA ELECTORAL AHORA NACION | F4: PRESIDENTE | G4: 2025 | H4: 2025
A5: AHORA NACION - AN | B5: 25331980 | C5: LOPEZ CHAU NAVA, PABLO ALFONSO | D5: SI | E5: AHORA NACION - AN | F5: FUNDADOR | G5: 2023 | H5: 0000
A6: AHORA NACION - AN | B6: 25331980 | C6: LOPEZ CHAU NAVA, PABLO ALFONSO | D6: SI | E6: ALIANZA ELECTORAL AHORA NACION | F6: PRESIDENTE | G6: 2025 | H6: 2025
A7: AHORA NACION - AN | B7: 40204874 | C7: LUQUE IBARRA, RUTH | D7: SI | E7: NUEVO PERU, POR DEMOCRACIA, SOBERANIA Y JUSTICIA | F7: APODERADO LEGAL | G7: 2021 | H7: 2022
A8: AHORA NACION - AN | B8: 40204874 | C8: LUQUE IBARRA, RUTH | D8: SI | E8: NUEVO PERU, POR DEMOCRACIA, SOBERANIA Y JUSTICIA | F8: FUNDADOR | G8: 2021 | H8: 2022
A9: AHORA NACION - AN | B9: 26705695 | C9: VASQUEZ CHUQUILIN, MIRTHA ESTHER | D9: NO
A10: FUERZA POPULAR | B10: 08236035 | C10: AGUINAGA RECUENCO, ALEJANDRO AURELIO | D10: SI | E10: FUERZA POPULAR | F10: SECRETARÍA NACIONAL DEL GRUPO PARLAMENTARIO | G10: 2011 | H10: 2014
A11: FUERZA POPULAR | B11: 08236035 | C11: AGUINAGA RECUENCO, ALEJANDRO AURELIO | D11: SI | E11: FUERZA POPULAR | F11: FUNDADOR | G11: 2009 | H11: 0000 | I11: HASTA LA ACTUALIDAD
A12: FUERZA POPULAR | B12: 06717199 | C12: ARISTA ARBILDO, JOSE BERLEY | D12: SI | E12: ALIANZA REGIONAL JUNTOS POR AMAZONAS | F12: PRESIDENTE | G12: 2010 | H12: 2014 | I12: Fui militante, pero no tuve un cargo partidario.
A13: FUERZA POPULAR | B13: 10307948 | C13: ASTUDILLO SALCEDO, CESAR AUGUSTO | D13: NO
A14: FUERZA POPULAR | B14: 32971154 | C14: CHACON TRUJILLO, NILZA MERLY | D14: NO
A15: FUERZA POPULAR | B15: 07960843 | C15: CHAVEZ COSSIO, MARTHA GLADYS | D15: SI | E15: FUERZA POPULAR | F15: PERSONERO LEGAL TITULAR | G15: 2025 | H15: 2025
A16: FUERZA POPULAR | B16: 07960843 | C16: CHAVEZ COSSIO, MARTHA GLADYS | D16: SI | E16: FUERZA POPULAR | F16: REPRESENTANTE LEGAL | G16: 2025 | H16: 0000 | I16: Soy representante legal hasta la actualidad.
A17: FUERZA POPULAR | B17: 05227631 | C17: DEL AGUILA CARDENAS, JUAN CARLOS | D17: SI | E17: MI LORETO PARA TODOS | F17: VICE PRESIDENTE | G17: 2014 | H17: 2014 | I17: ALIANZA ELECTORAL DISUELTA
A18: FUERZA POPULAR | B18: 05227631 | C18: DEL AGUILA CARDENAS, JUAN CARLOS | D18: SI | E18: LORETO PARA TODOS | F18: APODERADO | G18: 2014 | H18: 2015 | I18: ORGANIZACIÓN POLÍTICA DISUELTA
A19: FUERZA POPULAR | B19: 17896798 | C19: FLORES RUIZ, VICTOR SEFERINO | D19: NO
A20: FUERZA POPULAR | B20: 19994639 | C20: JIMENEZ HEREDIA, DAVID JULIO | D20: NO
A21: FUERZA POPULAR | B21: 07831436 | C21: JUAREZ GALLEGOS, CARMEN PATRICIA | D21: SI | E21: FUERZA POPULAR | F21: SECRETARIO NACIONAL DEL GRUPO PARLAMENTARIO | G21: 2022 | H21: 2023
A22: FUERZA POPULAR | B22: 07831436 | C22: JUAREZ GALLEGOS, CARMEN PATRICIA | D22: SI | E22: FUERZA POPULAR | F22: SECRETARÍA NACIONAL DE GOBIERNOS SUBNACIONALES | G22: 2024 | H22: 0000 | I22: Hasta la actualidad.
A23: FUERZA POPULAR | B23: 09884301 | C23: MELGAR VALDEZ, ELARD GALO | D23: SI | E23: FUERZA POPULAR | F23: SECRETARÍA NACIONAL DE MOVILIZACIÓN | G23: 2018 | H23: 2019
A24: FUERZA POPULAR | B24: 09884301 | C24: MELGAR VALDEZ, ELARD GALO | D24: SI | E24: PARTIDO POLÍTICO FUERZA POPULAR | F24: SECRETARÍA NACIONAL DE MOVILIZACIÓN | G24: 2014 | H24: 2017
A25: FUERZA POPULAR | B25: 08266314 | C25: MESIA RAMIREZ, CARLOS FERNANDO | D25: NO
A26: FUERZA POPULAR | B26: 22974228 | C26: MIYASHIRO ARASHIRO, MARCO ENRIQUE | D26: SI | E26: FUERZA POPULAR | F26: SECRETARIA NACIONAL DE SEGURIDAD, ORDEN INTERNO Y DEFENSA NACIONAL | G26: 2018 | H26: 2020
A27: FUERZA POPULAR | B27: 08911520 | C27: MOYANO DELGADO, MARTHA LUPE | D27: SI | E27: AGRUPACION INDEPENDIENTE SI CUMPLE | F27: FUNDADOR | G27: 2004 | H27: 2010
A28: FUERZA POPULAR | B28: 08911520 | C28: MOYANO DELGADO, MARTHA LUPE | D28: SI | E28: AGRUPACION INDEPENDIENTE SI CUMPLE | F28: SECRETARÍA NACIONAL DE LA MUJER | G28: 2004 | H28: 2010
A29: FUERZA POPULAR | B29: 17806760 | C29: NORIEGA REATEGUI, VICTOR MANUEL | D29: NO
A30: FUERZA POPULAR | B30: 08234063 | C30: RODRICH ACKERMAN, JACQUES SALOMON | D30: NO
A31: FUERZA POPULAR | B31: 07704730 | C31: ROSPIGLIOSI CAPURRO, FERNANDO MIGUEL | D31: NO
A32: FUERZA POPULAR | B32: 10638205 | C32: SCHAEFER CUCULIZA, KARLA MELISSA | D32: SI | E32: FUERZA POPULAR | F32: SECRETARÍA NACIONAL DE POLÍTICAS SOCIALES | G32: 2014 | H32: 2017
A33: FUERZA POPULAR | B33: 16657841 | C33: TAPIA BERNAL, SEGUNDO LEOCADIO | D33: SI | E33: PARTIDO JUSTICIA NACIONAL | F33: MIEMBRO DE LA ASAMBLEA GENERAL | G33: 2004 | H33: 2007
A34: FUERZA POPULAR | B34: 21143880 | C34: VELASQUEZ PORTOCARRERO, JORGE | D34: SI | E34: INTEGRANDO UCAYALI | F34: PRESIDENTE FUNDADOR | G34: 2015 | H34: 2023
A35: FUERZA POPULAR | B35: 21143880 | C35: VELASQUEZ PORTOCARRERO, JORGE | D35: SI | E35: INTEGRANDO UCAYALI | F35: FUNDADOR | G35: 2015 | H35: 2023
A36: FUERZA POPULAR | B36: 40242430 | C36: VENTURA ANGEL, HECTOR JOSE | D36: SI | E36: ROCA FUERTE - SEGUNDA JERUSALEN | F36: FUNDADOR | G36: 2015 | H36: 2019
A37: FUERZA POPULAR | B37: 40242430 | C37: VENTURA ANGEL, HECTOR JOSE | D37: SI | E37: ROCA FUERTE - SEGUNDA JERUSALEN | F37: PERSONERO LEGAL TITULAR | G37: 2015 | H37: 2019
A38: FUERZA POPULAR | B38: 21414172 | C38: YAMASHIRO ORE, RAFAEL GUSTAVO | D38: SI | E38: PARTIDO POPULAR CRISTIANO - PPC | F38: VICEPRESIDENTE | G38: 2007 | H38: 2011
A39: FUERZA POPULAR | B39: 21414172 | C39: YAMASHIRO ORE, RAFAEL GUSTAVO | D39: SI | E39: PARTIDO POPULAR CRISTIANO - PPC | F39: SECRETARIO GENERAL NACIONAL | G39: 2011 | H39: 2017
A40: JUNTOS POR EL PERU | B40: 22482738 | C40: ANDRES LUJAN, SERAFIN | D40: NO
A41: JUNTOS POR EL PERU | B41: 21487528 | C41: ARMACANQUI MORALES, SAUL ANDRES | D41: SI | E41: JUNTOS POR EL PERU | F41: TESORERO SUPLENTE | G41: 2025 | H41: 0000
A42: JUNTOS POR EL PERU | B42: 21487528 | C42: ARMACANQUI MORALES, SAUL ANDRES | D42: SI | E42: JUNTOS POR EL PERU | F42: VOCALÍA POLÍTICA | G42: 2023 | H42: 0000
A43: JUNTOS POR EL PERU | B43: 27409088 | C43: CASTILLO TERRONES, JOSE MERCEDES | D43: NO
A44: JUNTOS POR EL PERU | B44: 40669342 | C44: CCAHUANA AYMACHOQUE, HUGO ISAAC | D44: SI | E44: RENOVACION POR EL DESARROLLO | F44: FUNDADOR | G44: 2006 | H44: 2011
A45: JUNTOS POR EL PERU | B45: 04647085 | C45: CUTIPA CCAMA, VICTOR RAUL | D45: SI | E45: FRENTE DE INTEGRACION REGIONAL MOQUEGUA EMPRENDEDORA FIRME | F45: SECRETARIO REGIONAL DE POLÍTICA | G45: 2010 | H45: 2017
A46: JUNTOS POR EL PERU | B46: 21453924 | C46: MARAVI OLARTE, IBER ANTENOR | D46: NO
A47: JUNTOS POR EL PERU | B47: 10252335 | C47: MORALES RAMIREZ, EDYSON HUMBERTO | D47: SI | E47: EL FRENTE AMPLIO POR JUSTICIA, VIDA Y LIBERTAD | F47: MIEMBRO DE LA COMISIÓN POLÍTICA NACIONAL | G47: 2017 | H47: 2020
A48: JUNTOS POR EL PERU | B48: 40938678 | C48: OSORIO PALPAN, PERCY HERBERT | D48: SI | E48: PARTIDO POLÍTICO PERU POSIBLE | F48: miembro de comite distrital de oxapampa | G48: 2005 | H48: 2008 | I48: Región Pasco
A49: JUNTOS POR EL PERU | B49: 29632775 | C49: QUITO SARMIENTO, BERNARDO JAIME | D49: SI | E49: PAUCARPATA EN MARCHA | F49: FUNDADOR | G49: 2017 | H49: 2018
A50: JUNTOS POR EL PERU | B50: 29632775 | C50: QUITO SARMIENTO, BERNARDO JAIME | D50: SI | E50: PAUCARPATA EN MARCHA | F50: PRESIDENTE | G50: 2017 | H50: 2018
A51: JUNTOS POR EL PERU | B51: 42750152 | C51: ROBLES ARAUJO, SILVANA EMPERATRIZ | D51: NO
A52: JUNTOS POR EL PERU | B52: 23906812 | C52: VERANO SARAVIA, WILFREDO | D52: SI | E52: JUNTOS POR EL PERU | F52: SECRETARÍA NACIONAL DE IDEOLOGÍA, DOCTRINA Y FORMACIÓN POLÍTICA | G52: 2023 | H52: 0000
A53: PARTIDO CIVICO OBRAS | B53: 07651031 | C53: ASTUCURI LAURA, ROGER MIGUEL | D53: NO
A54: PARTIDO CIVICO OBRAS | B54: 10063223 | C54: BARRAGAN COLOMA, DANIEL HUGO | D54: SI | E54: PARTIDO CIVICO OBRAS | F54: APODERADO | G54: 2022 | H54: 0000
A55: PARTIDO CIVICO OBRAS | B55: 10063223 | C55: BARRAGAN COLOMA, DANIEL HUGO | D55: SI | E55: PARTIDO CIVICO OBRAS | F55: SECRETARÍA GENERAL NACIONAL | G55: 2022 | H55: 0000
A56: PARTIDO CIVICO OBRAS | B56: 10063223 | C56: BARRAGAN COLOMA, DANIEL HUGO | D56: SI | E56: PARTIDO CIVICO OBRAS | F56: APODERADO | G56: 2022 | H56: 0000
A57: PARTIDO CIVICO OBRAS | B57: 10063223 | C57: BARRAGAN COLOMA, DANIEL HUGO | D57: SI | E57: PARTIDO CIVICO OBRAS | F57: SECRETARÍA GENERAL NACIONAL | G57: 2022 | H57: 0000
A58: PARTIDO CIVICO OBRAS | B58: 07250032 | C58: FLORES CORDOVA, AGRIPINA MARIA DEL PILAR | D58: SI | E58: PARTIDO CIVICO OBRAS | F58: FUNDADOR | G58: 2022 | H58: 0000
A59: PARTIDO CIVICO OBRAS | B59: 07412350 | C59: GAGO RODRIGUEZ, WALTER FRANCISCO | D59: NO
A60: PARTIDO CIVICO OBRAS | B60: 00422672 | C60: TICONA COHAILA, JUANA GUISELLA | D60: SI | E60: PARTIDO POLÍTICO PARTIDO CIVICO OBRAS | F60: SECRETARIA DE ACTAS | G60: 2023 | H60: 2025
A61: PARTIDO DEL BUEN GOBIERNO | B61: 06519219 | C61: BONIFAZ CARMONA, NORA | D61: SI | E61: PARTIDO DEL BUEN GOBIERNO | F61: SECRETARÍA DE LA COMISIÓN POLÍTICA CONSULTIVA | G61: 2024 | H61: 0000
A62: PARTIDO DEL BUEN GOBIERNO | B62: 06519219 | C62: BONIFAZ CARMONA, NORA | D62: SI | E62: PARTIDO DEL BUEN GOBIERNO | F62: FUNDADOR | G62: 2024 | H62: 0000
A63: PARTIDO DEL BUEN GOBIERNO | B63: 43360309 | C63: CABALLERO LEON, CARLOS DAVID | D63: SI | E63: PARTIDO DEL BUEN GOBIERNO | F63: TRIBUNAL NACIONAL DE ÉTICA Y DISCIPLINA - PRESIDENTE | G63: 2024 | H63: 2025
A64: PARTIDO DEL BUEN GOBIERNO | B64: 43360309 | C64: CABALLERO LEON, CARLOS DAVID | D64: SI | E64: PARTIDO DEL BUEN GOBIERNO | F64: TRIBUNAL NACIONAL DE ÉTICA Y DISCIPLINA - PRESIDENTE | G64: 2024 | H64: 2025
A65: PARTIDO DEL BUEN GOBIERNO | B65: 07793210 | C65: FIGALLO RIVADENEYRA, FLAVIO FELIPE | D65: SI | E65: PARTIDO DEL BUEN GOBIERNO | F65: SECRETARÍA DE PLAN DE GOBIERNO | G65: 2024 | H65: 0000
A66: PARTIDO DEL BUEN GOBIERNO | B66: 07793210 | C66: FIGALLO RIVADENEYRA, FLAVIO FELIPE | D66: SI | E66: PARTIDO DEL BUEN GOBIERNO | F66: FUNDADOR | G66: 2024 | H66: 0000
A67: PARTIDO DEL BUEN GOBIERNO | B67: 30762511 | C67: FLORES SUAREZ, JUVER NILSON | D67: NO
A68: PARTIDO DEL BUEN GOBIERNO | B68: 07619185 | C68: GAVIDIA RODRIGUEZ, JORGE OCTAVIO | D68: NO
A69: PARTIDO DEL BUEN GOBIERNO | B69: 07231335 | C69: ITURREGUI BYRNE, PATRICIA MILAGROS | D69: NO
A70: PARTIDO DEL BUEN GOBIERNO | B70: 06876967 | C70: MATUTE CHARUN, SUSANA FLOR DE MARIA | D70: NO
A71: PARTIDO DEL BUEN GOBIERNO | B71: 06876967 | C71: MATUTE CHARUN, SUSANA FLOR DE MARIA | D71: NO
A72: RENOVACION POPULAR | B72: 08235876 | C72: ALCORTA SUERO, MARIA LOURDES PIA LUISA | D72: SI | E72: PARTIDO POPULAR CRISTIANO - PPC | F72: OFICINAS NACIONALES DE APOYO | G72: 2003 | H72: 2007
A73: RENOVACION POPULAR | B73: 25799622 | C73: AMPUERO MEZA, KATHERINE MILAGROS | D73: NO
A74: RENOVACION POPULAR | B74: 43285320 | C74: CALISTO GIAMPIETRI, FRANCISCO JOSE | D74: SI | E74: MOVIMIENTO REGIONAL SOMOS CALLAO | F74: APODERADO | G74: 2021 | H74: 2022
A75: RENOVACION POPULAR | B75: 43285320 | C75: CALISTO GIAMPIETRI, FRANCISCO JOSE | D75: SI | E75: MOVIMIENTO REGIONAL SOMOS CALLAO | F75: FUNDADOR | G75: 2021 | H75: 2023
A76: RENOVACION POPULAR | B76: 07852432 | C76: JAUREGUI MARTINEZ DE AGUAYO, MARIA DE LOS MILAGROS JACKELINE | D76: SI | E76: PARTIDO POLÍTICO RENOVACION POPULAR | F76: CONGRESISTA | G76: 2021 | H76: 2025
A77: RENOVACION POPULAR | B77: 07845838 | C77: LÓPEZ ALIAGA CAZORLA, RAFAEL BERNARDO | D77: SI | E77: RENOVACION POPULAR | F77: PRESIDENTE | G77: 2025 | H77: 0000
A78: RENOVACION POPULAR | B78: 07845838 | C78: LÓPEZ ALIAGA CAZORLA, RAFAEL BERNARDO | D78: SI | E78: RENOVACION POPULAR | F78: REPRESENTANTE LEGAL | G78: 2019 | H78: 2022
A79: RENOVACION POPULAR | B79: 07845838 | C79: LÓPEZ ALIAGA CAZORLA, RAFAEL BERNARDO | D79: SI | E79: RENOVACION POPULAR | F79: PRESIDENTE | G79: 2025 | H79: 0000
A80: RENOVACION POPULAR | B80: 07845838 | C80: LÓPEZ ALIAGA CAZORLA, RAFAEL BERNARDO | D80: SI | E80: RENOVACION POPULAR | F80: REPRESENTANTE LEGAL | G80: 2019 | H80: 2022
A81: RENOVACION POPULAR | B81: 01539305 | C81: MANCHA PINEDA, ESTANISLAO EDGAR | D81: SI | E81: INTEGRACION FUERZA SAN ANTONINA | F81: PRESIDENTE | G81: 2006 | H81: 2006
A82: RENOVACION POPULAR | B82: 01539305 | C82: MANCHA PINEDA, ESTANISLAO EDGAR | D82: SI | E82: INTEGRACION FUERZA SAN ANTONINA | F82: FUNDADOR | G82: 2006 | H82: 2006
A83: RENOVACION POPULAR | B83: 45209282 | C83: MUÑANTE BARRIOS, ALEJANDRO | D83: NO
A84: RENOVACION POPULAR | B84: 06504611 | C84: VELASQUEZ GARCIA, MIGUEL ANGEL | D84: NO
A85: FUERZA POPULAR | B85: 40433187 | C85: TORRES MORALES, MIGUEL ANGEL | D85: SI | E85: FUERZA POPULAR | F85: APODERADO | G85: 2025 | H85: 0000 | I85: Hasta la actualidad. Adicional a ello, desde el 13/02/2024, ocupo el cargo de Sub Secretario General Nacional del partido político Fuerza Popular, el cual no figura en el sistema Declara.
A86: FUERZA POPULAR | B86: 40433187 | C86: TORRES MORALES, MIGUEL ANGEL | D86: SI | E86: FUERZA POPULAR | F86: SECRETARÍA NACIONAL DE EDUCACIÓN, ARTE, CULTURA, INNOVACIÓN Y TECNOLOGÍA | G86: 2018 | H86: 2020
A87: JUNTOS POR EL PERU | B87: 02044988 | C87: CHIPANA CHIPANA, JOSE MOISES | D87: NO
A88: JUNTOS POR EL PERU | B88: 23271450 | C88: YAURI TUNQUE, JOAQUIN | D88: SI | E88: PROYECTO INTEGRACIONISTA DE COMUNIDADES ORGANIZADAS | F88: FUNDADOR | G88: 2006 | H88: 2015
A89: JUNTOS POR EL PERU | B89: 23271450 | C89: YAURI TUNQUE, JOAQUIN | D89: SI | E89: PROYECTO INTEGRACIONISTA DE COMUNIDADES ORGANIZADAS | F89: PERSONERO TÉCNICO TITULAR | G89: 2006 | H89: 2015
A90: JUNTOS POR EL PERU | B90: 31010129 | C90: RAMOS HUILLCAS, ANDRES AVELINO | D90: NO

Sheet 04 CARGO ELECCION
A1: ORGANIZACION_POLITICA | B1: DNI_CANDIDATO | C1: CANDIDATO | D1: TINE_CARGO_ELECCION | E1: ORGANIZACION_POLITICA_CARGO | F1: AÑO_DESDE | G1: AÑO_HASTA | H1: CARGO_ELECCION | I1: INFORMACION_COMPLEMTARIA
A2: AHORA NACION - AN | B2: 07755878 | C2: DELGADO ZEGARRA, JAIME RICARDO | D2: SI | E2: GANA PERU | F2: 2011 | G2: 2016 | H2: CONGRESISTA DE LA REPÚBLICA
A3: AHORA NACION - AN | B3: 25331980 | C3: LOPEZ CHAU NAVA, PABLO ALFONSO | D3: NO
A4: AHORA NACION - AN | B4: 25331980 | C4: LOPEZ CHAU NAVA, PABLO ALFONSO | D4: NO
A5: AHORA NACION - AN | B5: 40204874 | C5: LUQUE IBARRA, RUTH | D5: SI | E5: JUNTOS POR EL PERU | F5: 2021 | G5: 2025 | H5: CONGRESISTA DE LA REPÚBLICA
A6: AHORA NACION - AN | B6: 26705695 | C6: VASQUEZ CHUQUILIN, MIRTHA ESTHER | D6: SI | E6: EL FRENTE AMPLIO POR JUSTICIA, VIDA Y LIBERTAD | F6: 2020 | G6: 2021 | H6: CONGRESISTA DE LA REPÚBLICA
A7: FUERZA POPULAR | B7: 08236035 | C7: AGUINAGA RECUENCO, ALEJANDRO AURELIO | D7: SI | E7: FUERZA 2011 | F7: 2011 | G7: 2016 | H7: CONGRESISTA DE LA REPÚBLICA
A8: FUERZA POPULAR | B8: 08236035 | C8: AGUINAGA RECUENCO, ALEJANDRO AURELIO | D8: SI | E8: ALIANZA POR EL FUTURO | F8: 2006 | G8: 2011 | H8: CONGRESISTA DE LA REPÚBLICA
A9: FUERZA POPULAR | B9: 06717199 | C9: ARISTA ARBILDO, JOSE BERLEY | D9: SI | E9: ALIANZA REGIONAL JUNTOS POR AMAZONAS | F9: 2011 | G9: 2014 | H9: GOBERNADOR REGIONAL
A10: FUERZA POPULAR | B10: 10307948 | C10: ASTUDILLO SALCEDO, CESAR AUGUSTO | D10: NO
A11: FUERZA POPULAR | B11: 32971154 | C11: CHACON TRUJILLO, NILZA MERLY | D11: SI | E11: FUERZA POPULAR | F11: 2021 | G11: 2025 | H11: CONGRESISTA DE LA REPÚBLICA | I11: A la fecha viene desempeñando funciones. Electa periodo 2021-2026.
A12: FUERZA POPULAR | B12: 07960843 | C12: CHAVEZ COSSIO, MARTHA GLADYS | D12: SI | E12: FUERZA POPULAR | F12: 2020 | G12: 2021 | H12: CONGRESISTA DE LA REPÚBLICA | I12: He sido congresista en el Congreso Complementario. El sistema también debería precisar que he sido congresista del 2011 al 2016 por el partido político "Fuerza 2011", actualmente Fuerza Popular.
A13: FUERZA POPULAR | B13: 07960843 | C13: CHAVEZ COSSIO, MARTHA GLADYS | D13: SI | E13: ALIANZA NUEVA MAYORIA - CAMBIO 90 | G13: 0000 | H13: CONGRESISTA CONSTITUYENTE | I13: He sido Congresista de la República por la organización Alianza Nueva Mayoría - Cambio 90 en el 2001-2006. Actualmente, el ROP precisa que la organización y mi persona tiene afiliación cancelada.
A14: FUERZA POPULAR | B14: 05227631 | C14: DEL AGUILA CARDENAS, JUAN CARLOS | D14: SI | E14: PARTIDO APRISTA PERUANO | F14: 2003 | G14: 2006 | H14: ALCALDE PROVINCIAL
A15: FUERZA POPULAR | B15: 05227631 | C15: DEL AGUILA CARDENAS, JUAN CARLOS | D15: SI | E15: FUERZA POPULAR | F15: 2016 | G15: 2021 | H15: CONGRESISTA DE LA REPÚBLICA | I15: PERIODO INTERRUMPIDO POR EL CIERRE INCONSTITUCIONAL DEL CONGRESO EN SETIEMBRE DEL 2019
A16: FUERZA POPULAR | B16: 17896798 | C16: FLORES RUIZ, VICTOR SEFERINO | D16: SI | E16: FUERZA POPULAR | F16: 2021 | G16: 2025 | H16: CONGRESISTA DE LA REPÚBLICA | I16: ACTUALMENTE VIENE EJERCIENDO FUNCIONES. PERIODO 2021-2026
A17: FUERZA POPULAR | B17: 19994639 | C17: JIMENEZ HEREDIA, DAVID JULIO | D17: SI | E17: FUERZA POPULAR | F17: 2021 | G17: 2025 | H17: CONGRESISTA DE LA REPÚBLICA
A18: FUERZA POPULAR | B18: 07831436 | C18: JUAREZ GALLEGOS, CARMEN PATRICIA | D18: SI | E18: SOLIDARIDAD NACIONAL | F18: 2015 | G18: 2018 | H18: REGIDOR PROVINCIAL
A19: FUERZA POPULAR | B19: 07831436 | C19: JUAREZ GALLEGOS, CARMEN PATRICIA | D19: SI | E19: FUERZA POPULAR | F19: 2021 | G19: 2025 | H19: CONGRESISTA DE LA REPÚBLICA | I19: Mi periodo como congresista culmina en el 2026.
A20: FUERZA POPULAR | B20: 09884301 | C20: MELGAR VALDEZ, ELARD GALO | D20: SI | E20: FUERZA 2011 | F20: 2011 | G20: 2016 | H20: CONGRESISTA DE LA REPÚBLICA
A21: FUERZA POPULAR | B21: 09884301 | C21: MELGAR VALDEZ, ELARD GALO | D21: SI | E21: FUERZA POPULAR | F21: 2016 | G21: 2021 | H21: CONGRESISTA DE LA REPÚBLICA | I21: HASTA EL SETIEMBRE 2019. POR DISOLUCIÓN DEL CONGRESO
A22: FUERZA POPULAR | B22: 08266314 | C22: MESIA RAMIREZ, CARLOS FERNANDO | D22: SI | E22: FUERZA POPULAR | F22: 2020 | G22: 2021 | H22: CONGRESISTA DE LA REPÚBLICA
A23: FUERZA POPULAR | B23: 22974228 | C23: MIYASHIRO ARASHIRO, MARCO ENRIQUE | D23: SI | E23: FUERZA POPULAR | F23: 2015 | G23: 2018 | H23: REGIDOR PROVINCIAL | I23: EL SISTEMA NO PERMITE ACTUALIZAR EL AÑO. EN JULIO DE 2016 ASUMÍ EL CARGO DE CONGRESITA DE LA REPÚBLICA
A24: FUERZA POPULAR | B24: 22974228 | C24: MIYASHIRO ARASHIRO, MARCO ENRIQUE | D24: SI | E24: FUERZA POPULAR | F24: 2016 | G24: 2021 | H24: CONGRESISTA DE LA REPÚBLICA | I24: EL SISTEMA NO PERMITE MODIFICAR EL AÑO. EL 30 DE SETIEMBRE SE DISOLVIÓ EL CONGRESO MEDIANTE DECRETO SUPREMO Nº 165-2019-PCM
A25: FUERZA POPULAR | B25: 08911520 | C25: MOYANO DELGADO, MARTHA LUPE | D25: SI | E25: ALIANZA POR EL FUTURO | F25: 2006 | G25: 2011 | H25: CONGRESISTA DE LA REPÚBLICA
A26: FUERZA POPULAR | B26: 08911520 | C26: MOYANO DELGADO, MARTHA LUPE | D26: SI | E26: ALIANZA ELECTORAL PERU 2000 | F26: 2000 | G26: 2001 | H26: CONGRESISTA DE LA REPÚBLICA
A27: FUERZA POPULAR | B27: 17806760 | C27: NORIEGA REATEGUI, VICTOR MANUEL | D27: SI | E27: FUERZA POPULAR | F27: 2015 | G27: 2018 | H27: GOBERNADOR REGIONAL
A28: FUERZA POPULAR | B28: 08234063 | C28: RODRICH ACKERMAN, JACQUES SALOMON | D28: SI | E28: PERU POSIBLE | F28: 2001 | G28: 2006 | H28: CONGRESISTA DE LA REPÚBLICA
A29: FUERZA POPULAR | B29: 07704730 | C29: ROSPIGLIOSI CAPURRO, FERNANDO MIGUEL | D29: SI | E29: PARTIDO POLÍTICO FUERZA POPULAR | F29: 2023 | G29: 2025 | H29: CONGRESISTA DE LA REPÚBLICA | I29: El periodo culmina en el 2026.
A30: FUERZA POPULAR | B30: 10638205 | C30: SCHAEFER CUCULIZA, KARLA MELISSA | D30: SI | E30: FUERZA POPULAR | F30: 2016 | G30: 2021 | H30: CONGRESISTA DE LA REPÚBLICA | I30: SE DEBE TENER EN CUENTA QUE FUI CONGRESISTA DESDE EL AÑO 2016 HASTA EL AÑO 2019, INTERRUMPIDO POR EL CIERRE DEL CONGRESO. EL SISTEMA DECLARA NO PERMITE EDITAR EL AÑO, POR ELLO SE REALIZA LA PRECISIÓN.
A31: FUERZA POPULAR | B31: 10638205 | C31: SCHAEFER CUCULIZA, KARLA MELISSA | D31: SI | E31: FUERZA 2011 | F31: 2011 | G31: 2016 | H31: CONGRESISTA DE LA REPÚBLICA
A32: FUERZA POPULAR | B32: 16657841 | C32: TAPIA BERNAL, SEGUNDO LEOCADIO | D32: SI | E32: FUERZA 2011 | F32: 2011 | G32: 2016 | H32: CONGRESISTA DE LA REPÚBLICA
A33: FUERZA POPULAR | B33: 16657841 | C33: TAPIA BERNAL, SEGUNDO LEOCADIO | D33: SI | E33: FUERZA POPULAR | F33: 2016 | G33: 2021 | H33: CONGRESISTA DE LA REPÚBLICA | I33: EJERCÍ FUNCIONES HASTA SETIEMBRE DEL 2019, CONGRESO DISUELTO
A34: FUERZA POPULAR | B34: 21143880 | C34: VELASQUEZ PORTOCARRERO, JORGE | D34: SI | E34: INTEGRANDO UCAYALI | F34: 2011 | G34: 2014 | H34: GOBERNADOR REGIONAL
A35: FUERZA POPULAR | B35: 21143880 | C35: VELASQUEZ PORTOCARRERO, JORGE | D35: SI | E35: INTEGRANDO UCAYALI | F35: 2007 | G35: 2010 | H35: GOBERNADOR REGIONAL
A36: FUERZA POPULAR | B36: 40242430 | C36: VENTURA ANGEL, HECTOR JOSE | D36: SI | E36: FUERZA POPULAR | F36: 2021 | G36: 2025 | H36: CONGRESISTA DE LA REPÚBLICA | I36: En ejercicio de funciones del periodo 2021-2026
A37: FUERZA POPULAR | B37: 21414172 | C37: YAMASHIRO ORE, RAFAEL GUSTAVO | D37: SI | E37: PARTIDO POPULAR CRISTIANO - PPC | F37: 2015 | G37: 2018 | H37: REGIDOR PROVINCIAL
A38: FUERZA POPULAR | B38: 21414172 | C38: YAMASHIRO ORE, RAFAEL GUSTAVO | D38: SI | E38: UNIDAD NACIONAL | F38: 2006 | G38: 2011 | H38: CONGRESISTA DE LA REPÚBLICA
A39: JUNTOS POR EL PERU | B39: 22482738 | C39: ANDRES LUJAN, SERAFIN | D39: NO
A40: JUNTOS POR EL PERU | B40: 21487528 | C40: ARMACANQUI MORALES, SAUL ANDRES | D40: NO
A41: JUNTOS POR EL PERU | B41: 27409088 | C41: CASTILLO TERRONES, JOSE MERCEDES | D41: NO
A42: JUNTOS POR EL PERU | B42: 40669342 | C42: CCAHUANA AYMACHOQUE, HUGO ISAAC | D42: NO
A43: JUNTOS POR EL PERU | B43: 04647085 | C43: CUTIPA CCAMA, VICTOR RAUL | D43: SI | E43: FRENTE DE INTEGRACION REGIONAL MOQUEGUA EMPRENDEDORA FIRME | F43: 2011 | G43: 2014 | H43: REGIDOR PROVINCIAL
A44: JUNTOS POR EL PERU | B44: 04647085 | C44: CUTIPA CCAMA, VICTOR RAUL | D44: SI | E44: PARTIDO POLITICO NACIONAL PERU LIBRE | F44: 2021 | G44: 2025 | H44: CONGRESISTA DE LA REPÚBLICA
A45: JUNTOS POR EL PERU | B45: 21453924 | C45: MARAVI OLARTE, IBER ANTENOR | D45: SI | E45: UNIDOS POR EL DESARROLLO DE AYACUCHO | F45: 2015 | G45: 2018 | H45: REGIDOR PROVINCIAL
A46: JUNTOS POR EL PERU | B46: 10252335 | C46: MORALES RAMIREZ, EDYSON HUMBERTO | D46: SI | E46: EL FRENTE AMPLIO POR JUSTICIA, VIDA Y LIBERTAD | F46: 2016 | G46: 2021 | H46: CONGRESISTA DE LA REPÚBLICA
A47: JUNTOS POR EL PERU | B47: 40938678 | C47: OSORIO PALPAN, PERCY HERBERT | D47: NO
A48: JUNTOS POR EL PERU | B48: 29632775 | C48: QUITO SARMIENTO, BERNARDO JAIME | D48: SI | E48: PARTIDO POLITICO NACIONAL PERU LIBRE | F48: 2021 | G48: 2025 | H48: CONGRESISTA DE LA REPÚBLICA
A49: JUNTOS POR EL PERU | B49: 42750152 | C49: ROBLES ARAUJO, SILVANA EMPERATRIZ | D49: SI | E49: PARTIDO POLITICO NACIONAL PERU LIBRE | F49: 2021 | G49: 2025 | H49: CONGRESISTA DE LA REPÚBLICA
A50: JUNTOS POR EL PERU | B50: 23906812 | C50: VERANO SARAVIA, WILFREDO | D50: NO
A51: PARTIDO CIVICO OBRAS | B51: 07651031 | C51: ASTUCURI LAURA, ROGER MIGUEL | D51: SI | E51: JUNTOS POR EL PERU | F51: 2022 | G51: 0000 | H51: REGIDOR DISTRITAL
A52: PARTIDO CIVICO OBRAS | B52: 07651031 | C52: ASTUCURI LAURA, ROGER MIGUEL | D52: SI | E52: PARTIDO NACIONALISTA PERUANO | F52: 2007 | G52: 2010 | H52: REGIDOR DISTRITAL
A53: PARTIDO CIVICO OBRAS | B53: 10063223 | C53: BARRAGAN COLOMA, DANIEL HUGO | D53: SI | E53: PARTIDO POLÍTICO UNION POR EL PERU | F53: 2021 | G53: 2021 | H53: SEGUNDO VICEPRESIDENTE DE LA REPÚBLICA
A54: PARTIDO CIVICO OBRAS | B54: 10063223 | C54: BARRAGAN COLOMA, DANIEL HUGO | D54: SI | E54: PARTIDO POLÍTICO UNION POR EL PERU | F54: 2021 | G54: 2021 | H54: SEGUNDO VICEPRESIDENTE DE LA REPÚBLICA
A55: PARTIDO CIVICO OBRAS | B55: 07250032 | C55: FLORES CORDOVA, AGRIPINA MARIA DEL PILAR | D55: NO
A56: PARTIDO CIVICO OBRAS | B56: 07412350 | C56: GAGO RODRIGUEZ, WALTER FRANCISCO | D56: NO
A57: PARTIDO CIVICO OBRAS | B57: 00422672 | C57: TICONA COHAILA, JUANA GUISELLA | D57: NO
A58: PARTIDO DEL BUEN GOBIERNO | B58: 06519219 | C58: BONIFAZ CARMONA, NORA | D58: SI | E58: MOVIMIENTO INDEPENDIENTE SOMOS PERU | F58: 1999 | G58: 2002 | H58: REGIDOR DISTRITAL
A59: PARTIDO DEL BUEN GOBIERNO | B59: 06519219 | C59: BONIFAZ CARMONA, NORA | D59: SI | E59: SOMOS LIMA | F59: 1996 | G59: 1998 | H59: REGIDOR DISTRITAL
A60: PARTIDO DEL BUEN GOBIERNO | B60: 43360309 | C60: CABALLERO LEON, CARLOS DAVID | D60: NO
A61: PARTIDO DEL BUEN GOBIERNO | B61: 43360309 | C61: CABALLERO LEON, CARLOS DAVID | D61: NO
A62: PARTIDO DEL BUEN GOBIERNO | B62: 07793210 | C62: FIGALLO RIVADENEYRA, FLAVIO FELIPE | D62: NO
A63: PARTIDO DEL BUEN GOBIERNO | B63: 30762511 | C63: FLORES SUAREZ, JUVER NILSON | D63: SI | E63: GANA PERU | F63: 2011 | G63: 2016
A64: PARTIDO DEL BUEN GOBIERNO | B64: 07619185 | C64: GAVIDIA RODRIGUEZ, JORGE OCTAVIO | D64: NO
A65: PARTIDO DEL BUEN GOBIERNO | B65: 07231335 | C65: ITURREGUI BYRNE, PATRICIA MILAGROS | D65: NO
A66: PARTIDO DEL BUEN GOBIERNO | B66: 06876967 | C66: MATUTE CHARUN, SUSANA FLOR DE MARIA | D66: NO
A67: PARTIDO DEL BUEN GOBIERNO | B67: 06876967 | C67: MATUTE CHARUN, SUSANA FLOR DE MARIA | D67: NO
A68: RENOVACION POPULAR | B68: 08235876 | C68: ALCORTA SUERO, MARIA LOURDES PIA LUISA | D68: SI | E68: UNIDAD NACIONAL | F68: 2006 | G68: 2011 | H68: CONGRESISTA DE LA REPÚBLICA
A69: RENOVACION POPULAR | B69: 08235876 | C69: ALCORTA SUERO, MARIA LOURDES PIA LUISA | D69: SI | E69: FUERZA POPULAR | F69: 2016 | G69: 2021 | H69: CONGRESISTA DE LA REPÚBLICA
A70: RENOVACION POPULAR | B70: 25799622 | C70: AMPUERO MEZA, KATHERINE MILAGROS | D70: NO
A71: RENOVACION POPULAR | B71: 43285320 | C71: CALISTO GIAMPIETRI, FRANCISCO JOSE | D71: NO
A72: RENOVACION POPULAR | B72: 07852432 | C72: JAUREGUI MARTINEZ DE AGUAYO, MARIA DE LOS MILAGROS JACKELINE | D72: SI | E72: RENOVACION POPULAR | F72: 2021 | G72: 2025 | H72: CONGRESISTA DE LA REPÚBLICA
A73: RENOVACION POPULAR | B73: 07845838 | C73: LÓPEZ ALIAGA CAZORLA, RAFAEL BERNARDO | D73: SI | E73: ALIANZA ELECTORAL UNIDAD NACIONAL | F73: 2007 | G73: 2010 | H73: REGIDOR PROVINCIAL
A74: RENOVACION POPULAR | B74: 07845838 | C74: LÓPEZ ALIAGA CAZORLA, RAFAEL BERNARDO | D74: SI | E74: ALIANZA ELECTORAL UNIDAD NACIONAL | F74: 2007 | G74: 2010 | H74: REGIDOR PROVINCIAL
A75: RENOVACION POPULAR | B75: 07845838 | C75: LÓPEZ ALIAGA CAZORLA, RAFAEL BERNARDO | D75: SI | E75: RENOVACION POPULAR | F75: 2022 | G75: 0000 | H75: ALCALDE PROVINCIAL | I75: Presenté mi renuncia al cargo de alcalde metropolitano de lima el día 13 de octubre del 2025.
A76: RENOVACION POPULAR | B76: 07845838 | C76: LÓPEZ ALIAGA CAZORLA, RAFAEL BERNARDO | D76: SI | E76: RENOVACION POPULAR | F76: 2022 | G76: 0000 | H76: ALCALDE PROVINCIAL | I76: Presenté mi renuncia al cargo de alcalde metropolitano de lima el día 13 de octubre del 2025.
A77: RENOVACION POPULAR | B77: 01539305 | C77: MANCHA PINEDA, ESTANISLAO EDGAR | D77: NO
A78: RENOVACION POPULAR | B78: 45209282 | C78: MUÑANTE BARRIOS, ALEJANDRO | D78: SI | E78: RENOVACION POPULAR | F78: 2021 | G78: 2025 | H78: CONGRESISTA DE LA REPÚBLICA
A79: RENOVACION POPULAR | B79: 06504611 | C79: VELASQUEZ GARCIA, MIGUEL ANGEL | D79: NO
A80: FUERZA POPULAR | B80: 40433187 | C80: TORRES MORALES, MIGUEL ANGEL | D80: SI | E80: FUERZA POPULAR | F80: 2016 | G80: 2021 | H80: CONGRESISTA DE LA REPÚBLICA | I80: El periodo parlamentario se dio del 2016 al 2020.
A81: JUNTOS POR EL PERU | B81: 02044988 | C81: CHIPANA CHIPANA, JOSE MOISES | D81: NO
A82: JUNTOS POR EL PERU | B82: 23271450 | C82: YAURI TUNQUE, JOAQUIN | D82: NO
A83: JUNTOS POR EL PERU | B83: 31010129 | C83: RAMOS HUILLCAS, ANDRES AVELINO | D83: NO

Sheet 05 SENTENCIA PENAL
A1: ORGANIZACION_POLITICA | B1: DNI_CANDIDATO | C1: CANDIDATO | D1: TIENE_SENTENCIA_PENAL | E1: EXPEDIENTE | F1: SENTENCIA | G1: ORGANO_JUDICIAL | H1: DELITO | I1: FALLO | J1: MODALIDAD | K1: OTRA_MODALIDAD | L1: CUMPLE_FALLO | M1: INFORMACION_COMPLEMENTARIA
A2: AHORA NACION - AN | B2: 07755878 | C2: DELGADO ZEGARRA, JAIME RICARDO | D2: NO
A3: AHORA NACION - AN | B3: 25331980 | C3: LOPEZ CHAU NAVA, PABLO ALFONSO | D3: NO
A4: AHORA NACION - AN | B4: 25331980 | C4: LOPEZ CHAU NAVA, PABLO ALFONSO | D4: NO
A5: AHORA NACION - AN | B5: 40204874 | C5: LUQUE IBARRA, RUTH | D5: NO
A6: AHORA NACION - AN | B6: 26705695 | C6: VASQUEZ CHUQUILIN, MIRTHA ESTHER | D6: NO
A7: FUERZA POPULAR | B7: 08236035 | C7: AGUINAGA RECUENCO, ALEJANDRO AURELIO | D7: NO
A8: FUERZA POPULAR | B8: 06717199 | C8: ARISTA ARBILDO, JOSE BERLEY | D8: NO
A9: FUERZA POPULAR | B9: 10307948 | C9: ASTUDILLO SALCEDO, CESAR AUGUSTO | D9: NO
A10: FUERZA POPULAR | B10: 32971154 | C10: CHACON TRUJILLO, NILZA MERLY | D10: NO
A11: FUERZA POPULAR | B11: 07960843 | C11: CHAVEZ COSSIO, MARTHA GLADYS | D11: NO
A12: FUERZA POPULAR | B12: 05227631 | C12: DEL AGUILA CARDENAS, JUAN CARLOS | D12: NO
A13: FUERZA POPULAR | B13: 17896798 | C13: FLORES RUIZ, VICTOR SEFERINO | D13: NO
... A24: FUERZA POPULAR | B24: 16657841 | C24: TAPIA BERNAL, SEGUNDO LEOCADIO | D24: NO
A25: FUERZA POPULAR | B25: 21143880 | C25: VELASQUEZ PORTOCARRERO, JORGE | D25: SI | E25: 055-1993 | F25: 22/07/1994 | G25: 2JP - PUCALLPA | H25: PELIGRO COMÚN Y OTRO | I25: RESERVA DEL FALLO | J25: RESERVA DE FALLO | L25: PENA CUMPLIDA | M25: REHABILITACIÓN 12-10-1998
A26: FUERZA POPULAR | B26: 40242430 | C26: VENTURA ANGEL, HECTOR JOSE | D26: NO
A27: FUERZA POPULAR | B27: 21414172 | C27: YAMASHIRO ORE, RAFAEL GUSTAVO | D27: NO
A28: JUNTOS POR EL PERU | B28: 22482738 | C28: ANDRES LUJAN, SERAFIN | D28: NO
A29: JUNTOS POR EL PERU | B29: 21487528 | C29: ARMACANQUI MORALES, SAUL ANDRES | D29: NO
A30: JUNTOS POR EL PERU | B30: 27409088 | C30: CASTILLO TERRONES, JOSE MERCEDES | D30: NO
A31: JUNTOS POR EL PERU | B31: 40669342 | C31: CCAHUANA AYMACHOQUE, HUGO ISAAC | D31: NO
A32: JUNTOS POR EL PERU | B32: 04647085 | C32: CUTIPA CCAMA, VICTOR RAUL | D32: NO
A33: JUNTOS POR EL PERU | B33: 21453924 | C33: MARAVI OLARTE, IBER ANTENOR | D33: NO
A34: JUNTOS POR EL PERU | B34: 10252335 | C34: MORALES RAMIREZ, EDYSON HUMBERTO | D34: NO
A35: JUNTOS POR EL PERU | B35: 40938678 | C35: OSORIO PALPAN, PERCY HERBERT | D35: SI | E35: 1212021 | F35: 07/03/2022 | G35: Juzgado Unipersonal de Oxapampa Selva Central | H35: Difamación | I35: Querella | J35: SUSPENDIDA | L35: PENA CUMPLIDA
A36: JUNTOS POR EL PERU | B36: 29632775 | C36: QUITO SARMIENTO, BERNARDO JAIME | D36: NO
A37: JUNTOS POR EL PERU | B37: 42750152 | C37: ROBLES ARAUJO, SILVANA EMPERATRIZ | D37: NO
A38: JUNTOS POR EL PERU | B38: 23906812 | C38: VERANO SARAVIA, WILFREDO | D38: NO
A39: PARTIDO CIVICO OBRAS | B39: 07651031 | C39: ASTUCURI LAURA, ROGER MIGUEL | D39: NO
A40: PARTIDO CIVICO OBRAS | B40: 10063223 | C40: BARRAGAN COLOMA, DANIEL HUGO | D40: NO
A41: PARTIDO CIVICO OBRAS | B41: 10063223 | C41: BARRAGAN COLOMA, DANIEL HUGO | D41: NO
A42: PARTIDO CIVICO OBRAS | B42: 07250032 | C42: FLORES CORDOVA, AGRIPINA MARIA DEL PILAR | D42: NO
A43: PARTIDO CIVICO OBRAS | B43: 07412350 | C43: GAGO RODRIGUEZ, WALTER FRANCISCO | D43: SI | E43: 98-536 | F43: 28/05/1999 | G43: 26 JUZGADO PENAL DE LIMA | H43: LIBRAMIENTO Y COBRO INDEBIDO | I43: 2 AÑOS | J43: OTRO | K43: FIJÁNDOSE PENA PRIVATIVA DE LIBERTAD CONDICIONAL | L43: PENA CUMPLIDA
A44: PARTIDO CIVICO OBRAS | B44: 07412350 | C44: GAGO RODRIGUEZ, WALTER FRANCISCO | D44: SI | E44: 311-98 | F44: 25/05/1999 | G44: 42 JUZGADO PENAL DE LIMA | H44: CONTRA LA CONFIANZA Y LA BUENA FE EN LOS NEGOCIOS | I44: 1 AÑO | J44: SUSPENDIDA | L44: PENA CUMPLIDA
A45: PARTIDO CIVICO OBRAS | B45: 00422672 | C45: TICONA COHAILA, JUANA GUISELLA | D45: NO
A46: PARTIDO DEL BUEN GOBIERNO | B46: 06519219 | C46: BONIFAZ CARMONA, NORA | D46: NO
A47: PARTIDO DEL BUEN GOBIERNO | B47: 43360309 | C47: CABALLERO LEON, CARLOS DAVID | D47: NO
A48: PARTIDO DEL BUEN GOBIERNO | B48: 43360309 | C48: CABALLERO LEON, CARLOS DAVID | D48: NO
A49: PARTIDO DEL BUEN GOBIERNO | B49: 07793210 | C49: FIGALLO RIVADENEYRA, FLAVIO FELIPE | D49: NO
A50: PARTIDO DEL BUEN GOBIERNO | B50: 30762511 | C50: FLORES SUAREZ, JUVER NILSON | D50: NO
A51: PARTIDO DEL BUEN GOBIERNO | B51: 07619185 | C51: GAVIDIA RODRIGUEZ, JORGE OCTAVIO | D51: SI | E51: 0 | F51: 07/02/2013 | G51: 0 | H51: 0 | I51: 0 | J51: SUSPENDIDA | L51: PENA CUMPLIDA | M51: 1. Causa penal prescrita. (privado en sociedad comercial) 2. Sentencia penal suspendida. (modalidad de estafa dentro de una sociedad privada)
A52: PARTIDO DEL BUEN GOBIERNO | B52: 07231335 | C52: ITURREGUI BYRNE, PATRICIA MILAGROS | D52: NO
A53: PARTIDO DEL BUEN GOBIERNO | B53: 06876967 | C53: MATUTE CHARUN, SUSANA FLOR DE MARIA | D53: NO
A54: PARTIDO DEL BUEN GOBIERNO | B54: 06876967 | C54: MATUTE CHARUN, SUSANA FLOR DE MARIA | D54: NO
A55: RENOVACION POPULAR | B55: 08235876 | C55: ALCORTA SUERO, MARIA LOURDES PIA LUISA | D55: NO
A56: RENOVACION POPULAR | B56: 25799622 | C56: AMPUERO MEZA, KATHERINE MILAGROS | D56: NO
A57: RENOVACION POPULAR | B57: 43285320 | C57: CALISTO GIAMPIETRI, FRANCISCO JOSE | D57: NO
A58: RENOVACION POPULAR | B58: 07852432 | C58: JAUREGUI MARTINEZ DE AGUAYO, MARIA DE LOS MILAGROS JACKELINE | D58: NO
A59: RENOVACION POPULAR | B59: 07845838 | C59: LÓPEZ ALIAGA CAZORLA, RAFAEL BERNARDO | D59: NO
A60: RENOVACION POPULAR | B60: 07845838 | C60: LÓPEZ ALIAGA CAZORLA, RAFAEL BERNARDO | D60: NO
A61: RENOVACION POPULAR | B61: 01539305 | C61: MANCHA PINEDA, ESTANISLAO EDGAR | D61: NO
A62: RENOVACION POPULAR | B62: 45209282 | C62: MUÑANTE BARRIOS, ALEJANDRO | D62: NO
A63: RENOVACION POPULAR | B63: 06504611 | C63: VELASQUEZ GARCIA, MIGUEL ANGEL | D63: NO
... A67: JUNTOS POR EL PERU | B67: 31010129 | C67: RAMOS HUILLCAS, ANDRES AVELINO | D67: NO

Sheet 06 SENTENCIA NO PENAL
A1: ORGANIZACION_POLITICA | B1: DNI_CANDIDATO | C1: CANDIDATO | D1: TIENE_SENTENCIA_NO_PENAL | E1: MATERIA | F1: EXPEDIENTE | G1: ORGANO_JURIDICO | H1: FALLO | I1: INFORMACION_COMPLEMENTARIA
A2: AHORA NACION - AN | B2: 07755878 | C2: DELGADO ZEGARRA, JAIME RICARDO | D2: NO
A3: AHORA NACION - AN | B3: 25331980 | C3: LOPEZ CHAU NAVA, PABLO ALFONSO | D3: NO
A4: AHORA NACION - AN | B4: 25331980 | C4: LOPEZ CHAU NAVA, PABLO ALFONSO | D4: NO
A5: AHORA NACION - AN | B5: 40204874 | C5: LUQUE IBARRA, RUTH | D5: NO
A6: AHORA NACION - AN | B6: 26705695 | C6: VASQUEZ CHUQUILIN, MIRTHA ESTHER | D6: NO
A7: FUERZA POPULAR | B7: 08236035 | C7: AGUINAGA RECUENCO, ALEJANDRO AURELIO | D7: NO
A8: FUERZA POPULAR | B8: 06717199 | C8: ARISTA ARBILDO, JOSE BERLEY | D8: NO
A9: FUERZA POPULAR | B9: 10307948 | C9: ASTUDILLO SALCEDO, CESAR AUGUSTO | D9: NO
A10: FUERZA POPULAR | B10: 32971154 | C10: CHACON TRUJILLO, NILZA MERLY | D10: NO
A11: FUERZA POPULAR | B11: 07960843 | C11: CHAVEZ COSSIO, MARTHA GLADYS | D11: NO
A12: FUERZA POPULAR | B12: 05227631 | C12: DEL AGUILA CARDENAS, JUAN CARLOS | D12: NO
A13: FUERZA POPULAR | B13: 17896798 | C13: FLORES RUIZ, VICTOR SEFERINO | D13: NO
... A16: FUERZA POPULAR | B16: 09884301 | C16: MELGAR VALDEZ, ELARD GALO | D16: NO
A17: FUERZA POPULAR | B17: 08266314 | C17: MESIA RAMIREZ, CARLOS FERNANDO | D17: SI | E17: FAMILIA / ALIMENTARIA | F17: 00193-2021-29-1809-JP-FC-05 | G17: Segundo Juzgado Paz Letrado Barranco y Miraflores | H17: Declara fundada la demanda de ejecución de acta de conciliación.
A18: FUERZA POPULAR | B18: 22974228 | C18: MIYASHIRO ARASHIRO, MARCO ENRIQUE | D18: NO
A19: FUERZA POPULAR | B19: 08911520 | C19: MOYANO DELGADO, MARTHA LUPE | D19: NO
A20: FUERZA POPULAR | B20: 17806760 | C20: NORIEGA REATEGUI, VICTOR MANUEL | D20: NO
A21: FUERZA POPULAR | B21: 08234063 | C21: RODRICH ACKERMAN, JACQUES SALOMON | D21: NO
A22: FUERZA POPULAR | B22: 07704730 | C22: ROSPIGLIOSI CAPURRO, FERNANDO MIGUEL | D22: NO
A23: FUERZA POPULAR | B23: 10638205 | C23: SCHAEFER CUCULIZA, KARLA MELISSA | D23: NO
A24: FUERZA POPULAR | B24: 16657841 | C24: TAPIA BERNAL, SEGUNDO LEOCADIO | D24: NO
A25: FUERZA POPULAR | B25: 21143880 | C25: VELASQUEZ PORTOCARRERO, JORGE | D25: SI | E25: FAMILIA / ALIMENTARIA | F25: 0207 | G25: PRIMER JUZGADO MIXTO - RIOJA - SAN MARTIN | H25: FUNDADA LA DEMANDA | I25: AÑO 2001 - SIN DEUDA PENDIENTE DE PAGO
A26: FUERZA POPULAR | B26: 40242430 | C26: VENTURA ANGEL, HECTOR JOSE | D26: NO
A27: FUERZA POPULAR | B27: 21414172 | C27: YAMASHIRO ORE, RAFAEL GUSTAVO | D27: NO
A28: JUNTOS POR EL PERU | B28: 22482738 | C28: ANDRES LUJAN, SERAFIN | D28: NO
A29: JUNTOS POR EL PERU | B29: 21487528 | C29: ARMACANQUI MORALES, SAUL ANDRES | D29: NO
A30: JUNTOS POR EL PERU | B30: 27409088 | C30: CASTILLO TERRONES, JOSE MERCEDES | D30: NO
A31: JUNTOS POR EL PERU | B31: 40669342 | C31: CCAHUANA AYMACHOQUE, HUGO ISAAC | D31: SI | E31: FAMILIA / ALIMENTARIA | F31: 5742018 | G31: JUZGADO PAZ LETRADO DE TAMBOPATA | H31: FUNDADA EN PARTE | I31: 574-2018
A32: JUNTOS POR EL PERU | B32: 04647085 | C32: CUTIPA CCAMA, VICTOR RAUL | D32: NO
A33: JUNTOS POR EL PERU | B33: 21453924 | C33: MARAVI OLARTE, IBER ANTENOR | D33: NO
A34: JUNTOS POR EL PERU | B34: 10252335 | C34: MORALES RAMIREZ, EDYSON HUMBERTO | D34: NO
A35: JUNTOS POR EL PERU | B35: 40938678 | C35: OSORIO PALPAN, PERCY HERBERT | D35: SI | E35: FAMILIA / ALIMENTARIA | F35: 00221-2021 | G35: Juzgado de Paz Letrado de Oxapampa | H35: Sentencia
A36: JUNTOS POR EL PERU | B36: 40938678 | C36: OSORIO PALPAN, PERCY HERBERT | D36: SI | E36: FAMILIA / ALIMENTARIA | F36: 00205-2025 | G36: Juzgado de Paz Letrado de Oxapampa | H36: Sentencia
A37: JUNTOS POR EL PERU | B37: 29632775 | C37: QUITO SARMIENTO, BERNARDO JAIME | D37: NO
A38: JUNTOS POR EL PERU | B38: 42750152 | C38: ROBLES ARAUJO, SILVANA EMPERATRIZ | D38: NO
A39: JUNTOS POR EL PERU | B39: 23906812 | C39: VERANO SARAVIA, WILFREDO | D39: NO
A40: PARTIDO CIVICO OBRAS | B40: 07651031 | C40: ASTUCURI LAURA, ROGER MIGUEL | D40: NO
A41: PARTIDO CIVICO OBRAS | B41: 10063223 | C41: BARRAGAN COLOMA, DANIEL HUGO | D41: NO
A42: PARTIDO CIVICO OBRAS | B42: 10063223 | C42: BARRAGAN COLOMA, DANIEL HUGO | D42: NO
A43: PARTIDO CIVICO OBRAS | B43: 07250032 | C43: FLORES CORDOVA, AGRIPINA MARIA DEL PILAR | D43: NO
A44: PARTIDO CIVICO OBRAS | B44: 07412350 | C44: GAGO RODRIGUEZ, WALTER FRANCISCO | D44: NO
A45: PARTIDO CIVICO OBRAS | B45: 00422672 | C45: TICONA COHAILA, JUANA GUISELLA | D45: NO
A46: PARTIDO DEL BUEN GOBIERNO | B46: 06519219 | C46: BONIFAZ CARMONA, NORA | D46: NO
A47: PARTIDO DEL BUEN GOBIERNO | B47: 43360309 | C47: CABALLERO LEON, CARLOS DAVID | D47: NO
A48: PARTIDO DEL BUEN GOBIERNO | B48: 43360309 | C48: CABALLERO LEON, CARLOS DAVID | D48: NO
... A50: PARTIDO DEL BUEN GOBIERNO | B50: 30762511 | C50: FLORES SUAREZ, JUVER NILSON | D50: NO
A51: PARTIDO DEL BUEN GOBIERNO | B51: 07619185 | C51: GAVIDIA RODRIGUEZ, JORGE OCTAVIO | D51: SI | E51: FAMILIA / ALIMENTARIA | F51: 0 | G51: 0 | H51: 0 | I51: Pago por alimentos
A52: PARTIDO DEL BUEN GOBIERNO | B52: 07231335 | C52: ITURREGUI BYRNE, PATRICIA MILAGROS | D52: NO
A53: PARTIDO DEL BUEN GOBIERNO | B53: 06876967 | C53: MATUTE CHARUN, SUSANA FLOR DE MARIA | D53: NO
A54: PARTIDO DEL BUEN GOBIERNO | B54: 06876967 | C54: MATUTE CHARUN, SUSANA FLOR DE MARIA | D54: NO
A55: RENOVACION POPULAR | B55: 08235876 | C55: ALCORTA SUERO, MARIA LOURDES PIA LUISA | D55: NO
A56: RENOVACION POPULAR | B56: 25799622 | C56: AMPUERO MEZA, KATHERINE MILAGROS | D56: NO
A57: RENOVACION POPULAR | B57: 43285320 | C57: CALISTO GIAMPIETRI, FRANCISCO JOSE | D57: NO
A58: RENOVACION POPULAR | B58: 07852432 | C58: JAUREGUI MARTINEZ DE AGUAYO, MARIA DE LOS MILAGROS JACKELINE | D58: NO
